Workbook

Sheet {HFM Defaults}
A2: Connection | B2: WSFN|HFM|HFM|ZAVALIVE|ZAVALIVE | C2: WSFN|HFM|HFM|ZAVALIVE|ZAVALIVE | D2: WSFN|HFM|HFM|ZAVALIVE|ZAVALIVE | E2: WSFN|HFM|HFM|ZAVALIVE|ZAVALIVE
A3: Scenario# | B3: ACTUAL | C3: ACTUAL | D3: ACTUAL | E3: ACTUAL
A4: Year#
A5: Period# | B5: [YEAR] | C5: [YEAR] | D5: [YEAR] | E5: [YEAR]
A6: View# | B6: <Scenario View> | C6: <Scenario View> | D6: <Scenario View> | E6: <Scenario View>
A7: Entity# | B7: [None] | C7: [None] | D7: [None] | E7: [None]
A8: Value# | B8: USD Total | C8: USD Total | D8: USD Total | E8: USD Total
A9: Account#
A10: ICP# | B10: [ICP Top] | C10: [ICP Top] | D10: [ICP Top] | E10: [ICP Top]
A11: Custom1# | B11: TotalC1 | C11: TotalC1 | D11: TotalC1 | E11: TotalC1
A12: Custom2# | B12: TotalC2 | C12: TotalC2 | D12: TotalC2 | E12: TotalC2
A13: Custom3# | B13: TotalC3 | C13: TotalC3 | D13: TotalC3 | E13: TotalC3
A14: Custom4# | B14: TotalC4 | C14: TotalC4 | D14: TotalC4 | E14: TotalC4
B15: TRAINING DATA ONLY - Zava Safety and all business names and numbers are fictitious. Layout mirrors a typical HFM / Cognos reporting pack.
B16: HFM entity name: | D16: GRANITE_DISP | G16: Current ME | J16: Next ME | N16: Period | O16: Month-end
B17: Current month-end period: | D17: P09 | G17: Jan | H17: Actual | J17: Jan | K17: Actual | N17: P01
B18: Next month-end period: | D18: P10 | G18: Feb | H18: Actual | J18: Feb | K18: Actual | N18: P02
B19: Current month-end date: | D19: 2026-09-30 | G19: Mar | H19: Actual | J19: Mar | K19: Actual | N19: P03
B20: Forecast reference for actual | D20: FCAST09 | G20: Apr | H20: Actual | J20: Apr | K20: Actual | N20: P04
B21: Next month-end date: | D21: 2026-10-31 | G21: May | H21: Actual | J21: May | K21: Actual | N21: P05
B22: Forecast reference for actual | D22: FCAST10 | G22: Jun | H22: Actual | J22: Jun | K22: Actual | N22: P06
G23: Jul | H23: Actual | J23: Jul | K23: Actual | N23: P07
G24: Aug | H24: Actual | J24: Aug | K24: Actual | N24: P08
B25: Current Period Estimate or Retrieve: | D25: Retrieve | G25: Sep | H25: FCAST09 | J25: Sep | K25: Actual | N25: P09
B26: Reported or Excl ACQ: | D26: Reported | G26: Oct | H26: FCAST09 | J26: Oct | K26: FCAST10 | N26: P10
G27: Nov | H27: FCAST09 | J27: Nov | K27: FCAST10 | N27: P11
G28: Dec | H28: FCAST09 | J28: Dec | K28: FCAST10 | N28: P12

Sheet Overview
B1: Granite Gloves - FCAST10 forecast file - instructions
B3: (1) Forecast
B4: 1 - On the {HFM Defaults} tab, confirm the entity name, the current month-end period and the next month-end period. Months that are closed show Actual; the month about to close shows the estimate.
B5: 2 - Refresh the workbook so closed months show Actuals and the remaining months show the previous forecast (FCAST09).
B6: 3 - FX changes for the current month and the forecast months are estimated automatically (see the Fx Changes block on the Forecast tab). Do not include FX in your operational adjustments.
B7: 4 - On the Adjustments tab, enter your best estimate of the operational change vs FCAST09 for the month about to close and any future months (yellow cells).
B8: 5 - Send the updated forecast file to Division Finance by end of day Friday before month-end close, unless told otherwise.
B9: Note - Make every forecast change on the Adjustments tab. Do not overwrite the Forecast tab; it is formula driven.
B10: Section 1: adjustments tied to individual events (new customer, changed contract, lost customer). Give every line a clear description - it is the only place the story of the change is captured.
B11: Section 2: general changes to Gross Margin % or Op Costs % of sales that are not tied to one event (for example employee turnover).
B12: Section 3: working capital adjustments.
B13: The Forecast tab shows Actuals for closed months plus FCAST09 for the remaining months, adds FX and your adjustments, and produces FCAST10. A variance section on the Forecast tab helps you sense-check the result.
... B18: TRAINING DATA ONLY - Zava Safety and all business names and numbers are fictitious. Layout mirrors a typical HFM / Cognos reporting pack.

Sheet Variances
A1: Current ME | B1: P09 | D1: Granite Gloves
A2: Next ME | B2: P10 | D2: TRAINING DATA ONLY - Zava Safety and all business names and numbers are fictitious. Layout mirrors a typical HFM / Cognos reporting pack.
C4: FCAST10
C5: Through Sep | F5: Rest of Year | I5: Full Year
B6: Favorable / (Unfavorable) | C6: Actual vs. FCAST09 | D6: Actual vs. Bud | E6: Actual vs. PY | F6: FCAST10 vs. FCAST09 | G6: FCAST10 vs. Bud | H6: FCAST10 vs. PY | I6: FCAST10 vs. FCAST09 | J6: FCAST10 vs. Bud | K6: FCAST10 vs. PY
B8: Sales | C8: ='Forecast'!BU28 -> -430 | D8: ='Forecast'!BV28 -> -2792.4 | E8: ='Forecast'!BW28 -> -1464.4 | F8: ='Forecast'!BY28 -> -750 | G8: ='Forecast'!BZ28 -> -1450.9 | H8: ='Forecast'!CA28 -> -1011.2 | I8: ='Forecast'!CC28 -> -1180 | J8: ='Forecast'!CD28 -> -4243.3 | K8: ='Forecast'!CE28 -> -2475.6
B10: Gross Margin | C10: ='Forecast'!BU29 -> -265 | D10: ='Forecast'!BV29 -> -1639.9 | E10: ='Forecast'!BW29 -> -1517.3 | F10: ='Forecast'!BY29 -> -260 | G10: ='Forecast'!BZ29 -> -712.2 | H10: ='Forecast'!CA29 -> -668.9 | I10: ='Forecast'!CC29 -> -525 | J10: ='Forecast'!CD29 -> -2352.1 | K10: ='Forecast'!CE29 -> -2186.2
B12: Op Costs | C12: ='Forecast'!BU30 -> 42 | D12: ='Forecast'!BV30 -> 254.5 | E12: ='Forecast'!BW30 -> 48.4 | F12: ='Forecast'!BY30 -> 132 | G12: ='Forecast'!BZ30 -> 219.7 | H12: ='Forecast'!CA30 -> 161.4 | I12: ='Forecast'!CC30 -> 174 | J12: ='Forecast'!CD30 -> 474.2 | K12: ='Forecast'!CE30 -> 209.8
B14: PBITA | C14: ='Forecast'!BU31 -> -223 | D14: ='Forecast'!BV31 -> -1385.4 | E14: ='Forecast'!BW31 -> -1468.9 | F14: ='Forecast'!BY31 -> -128 | G14: ='Forecast'!BZ31 -> -492.5 | H14: ='Forecast'!CA31 -> -507.5 | I14: ='Forecast'!CC31 -> -351 | J14: ='Forecast'!CD31 -> -1877.9 | K14: ='Forecast'!CE31 -> -1976.4
B17: Commentary (business controller):

Sheet Adjustments
A1: Index | C1: 21 | D1: 20 | E1: 22 | F1: 22 | G1: 20 | H1: 22 | I1: 22 | J1: 21 | K1: 21 | L1: 22 | M1: 19 | N1: 22 | O1: =SUM(C1:N1) -> 254
B2: Section 1: Adjustments tied to individual events (i.e., new customer, modified sales contract, new/lost customer):
B3: TRAINING DATA ONLY - Zava Safety and all business names and numbers are fictitious. Layout mirrors a typical HFM / Cognos reporting pack.
C4: January | D4: February | E4: March | F4: April | G4: May | H4: June | I4: July | J4: August | K4: September | L4: October | M4: November | N4: December | O4: Total Adj
B5: Sales
B6: Backorders due to inventory availability | C6: 0 | D6: 0 | E6: 0 | F6: 0 | G6: 0 | H6: 0 | I6: 0 | J6: 0 | K6: -250 | L6: -250 | M6: -200 | N6: 0 | O6: =SUM(C6:N6) -> -700
B7: Rebate true-up - buying group | C7: 0 | D7: 0 | E7: 0 | F7: 0 | G7: 0 | H7: 0 | I7: 0 | J7: 0 | K7: -180 | L7: 0 | M7: 0 | N7: 0 | O7: =SUM(C7:N7) -> -180
B8: Backorders due to inventory availability | C8: 0 | D8: 0 | E8: 0 | F8: 0 | G8: 0 | H8: 0 | I8: 0 | J8: 0 | K8: 0 | L8: 0 | M8: 0 | N8: -300 | O8: =SUM(C8:N8) -> -300
B9: Insert Adj. 4 | C9: 0 | D9: 0 | E9: 0 | F9: 0 | G9: 0 | H9: 0 | I9: 0 | J9: 0 | K9: 0 | L9: 0 | M9: 0 | N9: 0 | O9: =SUM(C9:N9) -> 0
B10: Insert Adj. 5 | C10: 0 | D10: 0 | E10: 0 | F10: 0 | G10: 0 | H10: 0 | I10: 0 | J10: 0 | K10: 0 | L10: 0 | M10: 0 | N10: 0 | O10: =SUM(C10:N10) -> 0
B11: Insert Adj. 6 | C11: 0 | D11: 0 | E11: 0 | F11: 0 | G11: 0 | H11: 0 | I11: 0 | J11: 0 | K11: 0 | L11: 0 | M11: 0 | N11: 0 | O11: =SUM(C11:N11) -> 0
B12: Insert Adj. 7 | C12: 0 | D12: 0 | E12: 0 | F12: 0 | G12: 0 | H12: 0 | I12: 0 | J12: 0 | K12: 0 | L12: 0 | M12: 0 | N12: 0 | O12: =SUM(C12:N12) -> 0
B13: Insert Adj. 8 | C13: 0 | D13: 0 | E13: 0 | F13: 0 | G13: 0 | H13: 0 | I13: 0 | J13: 0 | K13: 0 | L13: 0 | M13: 0 | N13: 0 | O13: =SUM(C13:N13) -> 0
B14: Total Sales | C14: =SUM(C6:C13) -> 0 | D14: =SUM(D6:D13) -> 0 | E14: =SUM(E6:E13) -> 0 | F14: =SUM(F6:F13) -> 0 | G14: =SUM(G6:G13) -> 0 | H14: =SUM(H6:H13) -> 0 | I14: =SUM(I6:I13) -> 0 | J14: =SUM(J6:J13) -> 0 | ... O14: =SUM(O6:O13) -> -1180
B16: Gross Margin (%)
B17: =B6 -> Backorders due to inventory availability | C17: =IFERROR(C28/C6,0) -> 0 | D17: =IFERROR(D28/D6,0) -> 0 | E17: =IFERROR(E28/E6,0) -> 0 | F17: =IFERROR(F28/F6,0) -> 0 | G17: =IFERROR(G28/G6,0) -> 0 | H17: =IFERROR(H28/H6,0) -> 0 | I17: =IFERROR(I28/I6,0) -> 0 | J17: =IFERROR(J28/J6,0) -> 0 | ... O17: =IFERROR(O28/O6,0) -> 0.3
B18: =B7 -> Rebate true-up - buying group | C18: =IFERROR(C29/C7,0) -> 0 | D18: =IFERROR(D29/D7,0) -> 0 | E18: =IFERROR(E29/E7,0) -> 0 | F18: =IFERROR(F29/F7,0) -> 0 | G18: =IFERROR(G29/G7,0) -> 0 | H18: =IFERROR(H29/H7,0) -> 0 | I18: =IFERROR(I29/I7,0) -> 0 | J18: =IFERROR(J29/J7,0) -> 0 | ... O18: =IFERROR(O29/O7,0) -> 1
B19: =B8 -> Backorders due to inventory availability | C19: =IFERROR(C30/C8,0) -> 0 | D19: =IFERROR(D30/D8,0) -> 0 | E19: =IFERROR(E30/E8,0) -> 0 | F19: =IFERROR(F30/F8,0) -> 0 | G19: =IFERROR(G30/G8,0) -> 0 | H19: =IFERROR(H30/H8,0) -> 0 | I19: =IFERROR(I30/I8,0) -> 0 | J19: =IFERROR(J30/J8,0) -> 0 | ... O19: =IFERROR(O30/O8,0) -> 0.3
B20: =B9 -> Insert Adj. 4 | C20: =IFERROR(C31/C9,0) -> 0 | D20: =IFERROR(D31/D9,0) -> 0 | E20: =IFERROR(E31/E9,0) -> 0 | F20: =IFERROR(F31/F9,0) -> 0 | G20: =IFERROR(G31/G9,0) -> 0 | H20: =IFERROR(H31/H9,0) -> 0 | I20: =IFERROR(I31/I9,0) -> 0 | J20: =IFERROR(J31/J9,0) -> 0 | ... O20: =IFERROR(O31/O9,0) -> 0
B21: =B10 -> Insert Adj. 5 | C21: =IFERROR(C32/C10,0) -> 0 | D21: =IFERROR(D32/D10,0) -> 0 | E21: =IFERROR(E32/E10,0) -> 0 | F21: =IFERROR(F32/F10,0) -> 0 | G21: =IFERROR(G32/G10,0) -> 0 | H21: =IFERROR(H32/H10,0) -> 0 | I21: =IFERROR(I32/I10,0) -> 0 | J21: =IFERROR(J32/J10,0) -> 0 | ... O21: =IFERROR(O32/O10,0) -> 0
B22: =B11 -> Insert Adj. 6 | C22: =IFERROR(C33/C11,0) -> 0 | D22: =IFERROR(D33/D11,0) -> 0 | E22: =IFERROR(E33/E11,0) -> 0 | F22: =IFERROR(F33/F11,0) -> 0 | G22: =IFERROR(G33/G11,0) -> 0 | H22: =IFERROR(H33/H11,0) -> 0 | I22: =IFERROR(I33/I11,0) -> 0 | J22: =IFERROR(J33/J11,0) -> 0 | ... O22: =IFERROR(O33/O11,0) -> 0
B23: =B12 -> Insert Adj. 7 | C23: =IFERROR(C34/C12,0) -> 0 | D23: =IFERROR(D34/D12,0) -> 0 | E23: =IFERROR(E34/E12,0) -> 0 | F23: =IFERROR(F34/F12,0) -> 0 | G23: =IFERROR(G34/G12,0) -> 0 | H23: =IFERROR(H34/H12,0) -> 0 | I23: =IFERROR(I34/I12,0) -> 0 | J23: =IFERROR(J34/J12,0) -> 0 | ... O23: =IFERROR(O34/O12,0) -> 0
B24: =B13 -> Insert Adj. 8 | C24: =IFERROR(C35/C13,0) -> 0 | D24: =IFERROR(D35/D13,0) -> 0 | E24: =IFERROR(E35/E13,0) -> 0 | F24: =IFERROR(F35/F13,0) -> 0 | G24: =IFERROR(G35/G13,0) -> 0 | H24: =IFERROR(H35/H13,0) -> 0 | I24: =IFERROR(I35/I13,0) -> 0 | J24: =IFERROR(J35/J13,0) -> 0 | ... O24: =IFERROR(O35/O13,0) -> 0
B25: Total Gross Margin (%) | C25: =IFERROR(C36/C14,0) -> 0 | D25: =IFERROR(D36/D14,0) -> 0 | E25: =IFERROR(E36/E14,0) -> 0 | F25: =IFERROR(F36/F14,0) -> 0 | G25: =IFERROR(G36/G14,0) -> 0 | H25: =IFERROR(H36/H14,0) -> 0 | I25: =IFERROR(I36/I14,0) -> 0 | J25: =IFERROR(J36/J14,0) -> 0 | ... O25: =IFERROR(O36/O14,0) -> 0.44491525
B27: Gross Margin ($)
B28: Backorders due to inventory availability | C28: 0 | D28: 0 | E28: 0 | F28: 0 | G28: 0 | H28: 0 | I28: 0 | J28: 0 | K28: -75 | L28: -75 | M28: -60 | N28: 0 | O28: =SUM(C28:N28) -> -210
B29: Rebate true-up - buying group | C29: 0 | D29: 0 | E29: 0 | F29: 0 | G29: 0 | H29: 0 | I29: 0 | J29: 0 | K29: -180 | L29: 0 | M29: 0 | N29: 0 | O29: =SUM(C29:N29) -> -180
B30: Container receipts timing - freight cost | C30: 0 | D30: 0 | E30: 0 | F30: 0 | G30: 0 | H30: 0 | I30: 0 | J30: 0 | K30: 0 | L30: -40 | M30: -30 | N30: -20 | O30: =SUM(C30:N30) -> -90
B31: Heat transfer decals | C31: 0 | D31: 0 | E31: 0 | F31: 0 | G31: 0 | H31: 0 | I31: 0 | J31: 0 | K31: -10 | L31: -12 | M31: -12 | N31: -11 | O31: =SUM(C31:N31) -> -45
B32: Insert Adj. 5 | C32: 0 | D32: 0 | E32: 0 | F32: 0 | G32: 0 | H32: 0 | I32: 0 | J32: 0 | K32: 0 | L32: 0 | M32: 0 | N32: 0 | O32: =SUM(C32:N32) -> 0
B33: Insert Adj. 6 | C33: 0 | D33: 0 | E33: 0 | F33: 0 | G33: 0 | H33: 0 | I33: 0 | J33: 0 | K33: 0 | L33: 0 | M33: 0 | N33: 0 | O33: =SUM(C33:N33) -> 0
B34: Insert Adj. 7 | C34: 0 | D34: 0 | E34: 0 | F34: 0 | G34: 0 | H34: 0 | I34: 0 | J34: 0 | K34: 0 | L34: 0 | M34: 0 | N34: 0 | O34: =SUM(C34:N34) -> 0
B35: Insert Adj. 8 | C35: 0 | D35: 0 | E35: 0 | F35: 0 | G35: 0 | H35: 0 | I35: 0 | J35: 0 | K35: 0 | L35: 0 | M35: 0 | N35: 0 | O35: =SUM(C35:N35) -> 0
B36: Total Gross Margin ($) | C36: =SUM(C28:C35) -> 0 | D36: =SUM(D28:D35) -> 0 | E36: =SUM(E28:E35) -> 0 | F36: =SUM(F28:F35) -> 0 | G36: =SUM(G28:G35) -> 0 | H36: =SUM(H28:H35) -> 0 | I36: =SUM(I28:I35) -> 0 | J36: =SUM(J28:J35) -> 0 | ... O36: =SUM(O28:O35) -> -525
B38: Op Costs (%)
B39: =B6 -> Backorders due to inventory availability | C39: =IFERROR(C50/C6,0) -> 0 | D39: =IFERROR(D50/D6,0) -> 0 | E39: =IFERROR(E50/E6,0) -> 0 | F39: =IFERROR(F50/F6,0) -> 0 | G39: =IFERROR(G50/G6,0) -> 0 | H39: =IFERROR(H50/H6,0) -> 0 | I39: =IFERROR(I50/I6,0) -> 0 | J39: =IFERROR(J50/J6,0) -> 0 | ... O39: =IFERROR(O50/O6,0) -> 0.085714286
B40: =B7 -> Rebate true-up - buying group | C40: =IFERROR(C51/C7,0) -> 0 | D40: =IFERROR(D51/D7,0) -> 0 | E40: =IFERROR(E51/E7,0) -> 0 | F40: =IFERROR(F51/F7,0) -> 0 | G40: =IFERROR(G51/G7,0) -> 0 | H40: =IFERROR(H51/H7,0) -> 0 | I40: =IFERROR(I51/I7,0) -> 0 | J40: =IFERROR(J51/J7,0) -> 0 | ... O40: =IFERROR(O51/O7,0) -> -0.26666667
B41: =B8 -> Backorders due to inventory availability | C41: =IFERROR(C52/C8,0) -> 0 | D41: =IFERROR(D52/D8,0) -> 0 | E41: =IFERROR(E52/E8,0) -> 0 | F41: =IFERROR(F52/F8,0) -> 0 | G41: =IFERROR(G52/G8,0) -> 0 | H41: =IFERROR(H52/H8,0) -> 0 | I41: =IFERROR(I52/I8,0) -> 0 | J41: =IFERROR(J52/J8,0) -> 0 | ... O41: =IFERROR(O52/O8,0) -> 0.12
B42: =B9 -> Insert Adj. 4 | C42: =IFERROR(C53/C9,0) -> 0 | D42: =IFERROR(D53/D9,0) -> 0 | E42: =IFERROR(E53/E9,0) -> 0 | F42: =IFERROR(F53/F9,0) -> 0 | G42: =IFERROR(G53/G9,0) -> 0 | H42: =IFERROR(H53/H9,0) -> 0 | I42: =IFERROR(I53/I9,0) -> 0 | J42: =IFERROR(J53/J9,0) -> 0 | ... O42: =IFERROR(O53/O9,0) -> 0
B43: =B10 -> Insert Adj. 5 | C43: =IFERROR(C54/C10,0) -> 0 | D43: =IFERROR(D54/D10,0) -> 0 | E43: =IFERROR(E54/E10,0) -> 0 | F43: =IFERROR(F54/F10,0) -> 0 | G43: =IFERROR(G54/G10,0) -> 0 | H43: =IFERROR(H54/H10,0) -> 0 | I43: =IFERROR(I54/I10,0) -> 0 | J43: =IFERROR(J54/J10,0) -> 0 | ... O43: =IFERROR(O54/O10,0) -> 0
B44: =B11 -> Insert Adj. 6 | C44: =IFERROR(C55/C11,0) -> 0 | D44: =IFERROR(D55/D11,0) -> 0 | E44: =IFERROR(E55/E11,0) -> 0 | F44: =IFERROR(F55/F11,0) -> 0 | G44: =IFERROR(G55/G11,0) -> 0 | H44: =IFERROR(H55/H11,0) -> 0 | I44: =IFERROR(I55/I11,0) -> 0 | J44: =IFERROR(J55/J11,0) -> 0 | ... O44: =IFERROR(O55/O11,0) -> 0
B45: =B12 -> Insert Adj. 7 | C45: =IFERROR(C56/C12,0) -> 0 | D45: =IFERROR(D56/D12,0) -> 0 | E45: =IFERROR(E56/E12,0) -> 0 | F45: =IFERROR(F56/F12,0) -> 0 | G45: =IFERROR(G56/G12,0) -> 0 | H45: =IFERROR(H56/H12,0) -> 0 | I45: =IFERROR(I56/I12,0) -> 0 | J45: =IFERROR(J56/J12,0) -> 0 | ... O45: =IFERROR(O56/O12,0) -> 0
B46: =B13 -> Insert Adj. 8 | C46: =IFERROR(C57/C13,0) -> 0 | D46: =IFERROR(D57/D13,0) -> 0 | E46: =IFERROR(E57/E13,0) -> 0 | F46: =IFERROR(F57/F13,0) -> 0 | G46: =IFERROR(G57/G13,0) -> 0 | H46: =IFERROR(H57/H13,0) -> 0 | I46: =IFERROR(I57/I13,0) -> 0 | J46: =IFERROR(J57/J13,0) -> 0 | ... O46: =IFERROR(O57/O13,0) -> 0
B47: Total Op Costs (%) | C47: =IFERROR(C58/C14,0) -> 0 | D47: =IFERROR(D58/D14,0) -> 0 | E47: =IFERROR(E58/E14,0) -> 0 | F47: =IFERROR(F58/F14,0) -> 0 | G47: =IFERROR(G58/G14,0) -> 0 | H47: =IFERROR(H58/H14,0) -> 0 | I47: =IFERROR(I58/I14,0) -> 0 | J47: =IFERROR(J58/J14,0) -> 0 | ... O47: =IFERROR(O58/O14,0) -> 0.14745763
B49: Op Costs ($)
B50: Backorders - variable cost savings | C50: 0 | D50: 0 | E50: 0 | F50: 0 | G50: 0 | H50: 0 | I50: 0 | J50: 0 | K50: -15 | L50: -15 | M50: -12 | N50: -18 | O50: =SUM(C50:N50) -> -60
B51: Temp labor - new distribution center | C51: 0 | D51: 0 | E51: 0 | F51: 0 | G51: 0 | H51: 0 | I51: 0 | J51: 0 | K51: 12 | L51: 12 | M51: 12 | N51: 12 | O51: =SUM(C51:N51) -> 48
B52: OT reduction | C52: 0 | D52: 0 | E52: 0 | F52: 0 | G52: 0 | H52: 0 | I52: 0 | J52: 0 | K52: -9 | L52: -9 | M52: -9 | N52: -9 | O52: =SUM(C52:N52) -> -36
B53: Headcount reduction / postpone hiring | C53: 0 | D53: 0 | E53: 0 | F53: 0 | G53: 0 | H53: 0 | I53: 0 | J53: 0 | K53: -24 | L53: -24 | M53: -24 | N53: -24 | O53: =SUM(C53:N53) -> -96
B54: Others | C54: 0 | D54: 0 | E54: 0 | F54: 0 | G54: 0 | H54: 0 | I54: 0 | J54: 0 | K54: -6 | L54: -8 | M54: -8 | N54: -8 | O54: =SUM(C54:N54) -> -30
B55: Insert Adj. 6 | C55: 0 | D55: 0 | E55: 0 | F55: 0 | G55: 0 | H55: 0 | I55: 0 | J55: 0 | K55: 0 | L55: 0 | M55: 0 | N55: 0 | O55: =SUM(C55:N55) -> 0
B56: Insert Adj. 7 | C56: 0 | D56: 0 | E56: 0 | F56: 0 | G56: 0 | H56: 0 | I56: 0 | J56: 0 | K56: 0 | L56: 0 | M56: 0 | N56: 0 | O56: =SUM(C56:N56) -> 0
B57: Insert Adj. 8 | C57: 0 | D57: 0 | E57: 0 | F57: 0 | G57: 0 | H57: 0 | I57: 0 | J57: 0 | K57: 0 | L57: 0 | M57: 0 | N57: 0 | O57: =SUM(C57:N57) -> 0
B58: Total Op Costs ($) | C58: =SUM(C50:C57) -> 0 | D58: =SUM(D50:D57) -> 0 | E58: =SUM(E50:E57) -> 0 | F58: =SUM(F50:F57) -> 0 | G58: =SUM(G50:G57) -> 0 | H58: =SUM(H50:H57) -> 0 | I58: =SUM(I50:I57) -> 0 | J58: =SUM(J50:J57) -> 0 | ... O58: =SUM(O50:O57) -> -174
B60: PBITA
B61: =B6 -> Backorders due to inventory availability | C61: =C28-C50 -> 0 | D61: =D28-D50 -> 0 | E61: =E28-E50 -> 0 | F61: =F28-F50 -> 0 | G61: =G28-G50 -> 0 | H61: =H28-H50 -> 0 | I61: =I28-I50 -> 0 | J61: =J28-J50 -> 0 | ... N61: =N28-N50 -> 18 | O61: =SUM(C61:N61) -> -150
B62: =B7 -> Rebate true-up - buying group | C62: =C29-C51 -> 0 | D62: =D29-D51 -> 0 | E62: =E29-E51 -> 0 | F62: =F29-F51 -> 0 | G62: =G29-G51 -> 0 | H62: =H29-H51 -> 0 | I62: =I29-I51 -> 0 | J62: =J29-J51 -> 0 | ... N62: =N29-N51 -> -12 | O62: =SUM(C62:N62) -> -228
B63: =B8 -> Backorders due to inventory availability | C63: =C30-C52 -> 0 | D63: =D30-D52 -> 0 | E63: =E30-E52 -> 0 | F63: =F30-F52 -> 0 | G63: =G30-G52 -> 0 | H63: =H30-H52 -> 0 | I63: =I30-I52 -> 0 | J63: =J30-J52 -> 0 | ... N63: =N30-N52 -> -11 | O63: =SUM(C63:N63) -> -54
B64: =B9 -> Insert Adj. 4 | C64: =C31-C53 -> 0 | D64: =D31-D53 -> 0 | E64: =E31-E53 -> 0 | F64: =F31-F53 -> 0 | G64: =G31-G53 -> 0 | H64: =H31-H53 -> 0 | I64: =I31-I53 -> 0 | J64: =J31-J53 -> 0 | ... N64: =N31-N53 -> 13 | O64: =SUM(C64:N64) -> 51
B65: =B10 -> Insert Adj. 5 | C65: =C32-C54 -> 0 | D65: =D32-D54 -> 0 | E65: =E32-E54 -> 0 | F65: =F32-F54 -> 0 | G65: =G32-G54 -> 0 | H65: =H32-H54 -> 0 | I65: =I32-I54 -> 0 | J65: =J32-J54 -> 0 | ... N65: =N32-N54 -> 8 | O65: =SUM(C65:N65) -> 30
B66: =B11 -> Insert Adj. 6 | C66: =C33-C55 -> 0 | D66: =D33-D55 -> 0 | E66: =E33-E55 -> 0 | F66: =F33-F55 -> 0 | G66: =G33-G55 -> 0 | H66: =H33-H55 -> 0 | I66: =I33-I55 -> 0 | J66: =J33-J55 -> 0 | ... N66: =N33-N55 -> 0 | O66: =SUM(C66:N66) -> 0
B67: =B12 -> Insert Adj. 7 | C67: =C34-C56 -> 0 | D67: =D34-D56 -> 0 | E67: =E34-E56 -> 0 | F67: =F34-F56 -> 0 | G67: =G34-G56 -> 0 | H67: =H34-H56 -> 0 | I67: =I34-I56 -> 0 | J67: =J34-J56 -> 0 | ... N67: =N34-N56 -> 0 | O67: =SUM(C67:N67) -> 0
B68: =B13 -> Insert Adj. 8 | C68: =C35-C57 -> 0 | D68: =D35-D57 -> 0 | E68: =E35-E57 -> 0 | F68: =F35-F57 -> 0 | G68: =G35-G57 -> 0 | H68: =H35-H57 -> 0 | I68: =I35-I57 -> 0 | J68: =J35-J57 -> 0 | ... N68: =N35-N57 -> 0 | O68: =SUM(C68:N68) -> 0
B69: Total PBITA | C69: =SUM(C61:C68) -> 0 | D69: =SUM(D61:D68) -> 0 | E69: =SUM(E61:E68) -> 0 | F69: =SUM(F61:F68) -> 0 | G69: =SUM(G61:G68) -> 0 | H69: =SUM(H61:H68) -> 0 | I69: =SUM(I61:I68) -> 0 | J69: =SUM(J61:J68) -> 0 | ... O69: =SUM(O61:O68) -> -351
B71: Section 2: General adjustments in Gross Margin or Opex % of Sales that are not tied to individual events (i.e., employee turnover):
C73: January | D73: February | E73: March | F73: April | G73: May | H73: June | I73: July | J73: August | K73: September | L73: October | M73: November | N73: December | O73: Total Adj
B74: Gross Margin
B75: Gross Margin - Previous FCAST | C75: ='Forecast'!C35 -> 0.28788407 | D75: ='Forecast'!D35 -> 0.28653611 | E75: ='Forecast'!E35 -> 0.28515886 | F75: ='Forecast'!F35 -> 0.28220881 | G75: ='Forecast'!G35 -> 0.2877414 | H75: ='Forecast'!H35 -> 0.28751972 | I75: ='Forecast'!I35 -> 0.28541904 | J75: ='Forecast'!J35 -> 0.28242086 | ... N75: ='Forecast'!N35 -> 0.28287016 | O75: N/A
B76: New Adjustments (%) | C76: None | D76: None | E76: None | F76: None | G76: None | H76: None | I76: None | J76: None | K76: None | L76: None | M76: None | N76: None
B77: New Adjustments ($) | C77: =IF(C76="None",0,((('Forecast'!C28*(C75+C76))-'Forecast'!C29))) -> 0 | D77: =IF(D76="None",0,((('Forecast'!D28*(D75+D76))-'Forecast'!D29))) -> 0 | E77: =IF(E76="None",0,((('Forecast'!E28*(E75+E76))-'Forecast'!E29))) -> 0 | F77: =IF(F76="None",0,((('Forecast'!F28*(F75+F76))-'Forecast'!F29))) -> 0 | G77: =IF(G76="None",0,((('Forecast'!G28*(G75+G76))-'Forecast'!G29))) -> 0 | H77: =IF(H76="None",0,((('Forecast'!H28*(H75+H76))-'Forecast'!H29))) -> 0 | I77: =IF(I76="None",0,((('Forecast'!I28*(I75+I76))-'Forecast'!I29))) -> 0 | J77: =IF(J76="None",0,((('Forecast'!J28*(J75+J76))-'Forecast'!J29))) -> 0 | ... N77: =IF(N76="None",0,((('Forecast'!N28*(N75+N76))-'Forecast'!N29))) -> 0 | O77: =SUM(C77:N77) -> 0
B78: Gross Margin - Current FCAST | C78: =SUM(C75:C76) -> 0.28788407 | D78: =SUM(D75:D76) -> 0.28653611 | E78: =SUM(E75:E76) -> 0.28515886 | F78: =SUM(F75:F76) -> 0.28220881 | G78: =SUM(G75:G76) -> 0.2877414 | H78: =SUM(H75:H76) -> 0.28751972 | I78: =SUM(I75:I76) -> 0.28541904 | J78: =SUM(J75:J76) -> 0.28242086 | ... N78: =SUM(N75:N76) -> 0.28287016 | O78: N/A
B81: Op Costs
B82: Op Costs - Previous FCAST | C82: ='Forecast'!C36 -> -0.21456536 | D82: ='Forecast'!D36 -> -0.21442961 | E82: ='Forecast'!E36 -> -0.21929859 | F82: ='Forecast'!F36 -> -0.21388006 | G82: ='Forecast'!G36 -> -0.2179086 | H82: ='Forecast'!H36 -> -0.21490273 | I82: ='Forecast'!I36 -> -0.21492226 | J82: ='Forecast'!J36 -> -0.24003823 | ... N82: ='Forecast'!N36 -> -0.21311445 | O82: N/A
B83: New Adjustments (%) | C83: None | D83: None | E83: None | F83: None | G83: None | H83: None | I83: None | J83: None | K83: None | L83: None | M83: None | N83: None
B84: New Adjustments ($) | C84: =-IF(C83="None",0,((('Forecast'!C28*-(C82+C83))-'Forecast'!C30))) -> 0 | D84: =-IF(D83="None",0,((('Forecast'!D28*-(D82+D83))-'Forecast'!D30))) -> 0 | E84: =-IF(E83="None",0,((('Forecast'!E28*-(E82+E83))-'Forecast'!E30))) -> 0 | F84: =-IF(F83="None",0,((('Forecast'!F28*-(F82+F83))-'Forecast'!F30))) -> 0 | G84: =-IF(G83="None",0,((('Forecast'!G28*-(G82+G83))-'Forecast'!G30))) -> 0 | H84: =-IF(H83="None",0,((('Forecast'!H28*-(H82+H83))-'Forecast'!H30))) -> 0 | I84: =-IF(I83="None",0,((('Forecast'!I28*-(I82+I83))-'Forecast'!I30))) -> 0 | J84: =-IF(J83="None",0,((('Forecast'!J28*-(J82+J83))-'Forecast'!J30))) -> 0 | ... N84: =-IF(N83="None",0,((('Forecast'!N28*-(N82+N83))-'Forecast'!N30))) -> 0 | O84: =SUM(C84:N84) -> 0
B85: Op Costs - Current FCAST | C85: =SUM(C82:C83) -> -0.21456536 | D85: =SUM(D82:D83) -> -0.21442961 | E85: =SUM(E82:E83) -> -0.21929859 | F85: =SUM(F82:F83) -> -0.21388006 | G85: =SUM(G82:G83) -> -0.2179086 | H85: =SUM(H82:H83) -> -0.21490273 | I85: =SUM(I82:I83) -> -0.21492226 | J85: =SUM(J82:J83) -> -0.24003823 | ... N85: =SUM(N82:N83) -> -0.21311445 | O85: N/A
B87: Section 3: Working Capital Adjustments
C89: January | D89: February | E89: March | F89: April | G89: May | H89: June | I89: July | J89: August | K89: September | L89: October | M89: November | N89: December | O89: Total Adj
A90: 2090 | B90: Net Inventory | C90: 0 | D90: 0 | E90: 0 | F90: 0 | G90: 0 | H90: 0 | I90: 0 | J90: 0 | K90: 400 | L90: 600 | M90: 300 | N90: 0
A91: 2135 | B91: Trade Receivables | C91: 0 | D91: 0 | E91: 0 | F91: 0 | G91: 0 | H91: 0 | I91: 0 | J91: 0 | K91: 0 | L91: 0 | M91: 0 | N91: 0
A92: 2175 | B92: Other Receivables | C92: 0 | D92: 0 | E92: 0 | F92: 0 | G92: 0 | H92: 0 | I92: 0 | J92: 0 | K92: 0 | L92: 0 | M92: 0 | N92: 0
A93: 2140 | B93: Trade Payables | C93: 0 | D93: 0 | E93: 0 | F93: 0 | G93: 0 | H93: 0 | I93: 0 | J93: 0 | K93: 0 | L93: 0 | M93: 0 | N93: 0
A94: 2180 | B94: Other Payables | C94: 0 | D94: 0 | E94: 0 | F94: 0 | G94: 0 | H94: 0 | I94: 0 | J94: 0 | K94: 0 | L94: 0 | M94: 0 | N94: 0
A95: 2185 | B95: Total Working Capital | C95: =SUM(C90:C94) -> 0 | D95: =SUM(D90:D94) -> 0 | E95: =SUM(E90:E94) -> 0 | F95: =SUM(F90:F94) -> 0 | G95: =SUM(G90:G94) -> 0 | H95: =SUM(H90:H94) -> 0 | I95: =SUM(I90:I94) -> 0 | J95: =SUM(J90:J94) -> 0 | ... N95: =SUM(N90:N94) -> 0
B97: NOTE: A positive number within the working capital adjustments section indicates a DR (i.e., increase to asset / decrease to liability). A negative number indicates a CR.

Sheet Forecast
C1: Actual | D1: Actual | E1: Actual | F1: Actual | G1: Actual | H1: Actual | I1: Actual | J1: Actual | K1: FCAST09 | L1: FCAST09 | M1: FCAST09 | N1: FCAST09
B2: Scenario# | C2: Actual | D2: Actual | E2: Actual | F2: Actual | G2: Actual | H2: Actual | I2: Actual | J2: Actual | K2: Actual | L2: Actual | M2: Actual | N2: Actual
B5: Year# | C5: 2026 | D5: 2026 | E5: 2026 | F5: 2026 | G5: 2026 | H5: 2026 | I5: 2026 | J5: 2026 | K5: 2026 | L5: 2026 | M5: 2026 | N5: 2026
B8: Period# | C8: P01 | D8: P02 | E8: P03 | F8: P04 | G8: P05 | H8: P06 | I8: P07 | J8: P08 | K8: P09 | L8: P10 | M8: P11 | N8: P12
B9: Account#
B10: ICP#
B11: Custom1# | C11: TotalC1 | D11: TotalC1 | E11: TotalC1 | F11: TotalC1 | G11: TotalC1 | H11: TotalC1 | I11: TotalC1 | J11: TotalC1 | K11: TotalC1 | L11: TotalC1 | M11: TotalC1 | N11: TotalC1
B12: Custom2# | C12: TotalC2 | D12: TotalC2 | E12: TotalC2 | F12: TotalC2 | G12: TotalC2 | H12: TotalC2 | I12: TotalC2 | J12: TotalC2 | K12: TotalC2 | L12: TotalC2 | M12: TotalC2 | N12: TotalC2
B13: Custom3#
B14: Custom4#
B18: View# | C18: Periodic | D18: Periodic | E18: Periodic | F18: Periodic | G18: Periodic | H18: Periodic | I18: Periodic | J18: Periodic | K18: Periodic | L18: Periodic | M18: Periodic | N18: Periodic
B19: Value# | C19: USD Total | D19: USD Total | E19: USD Total | F19: USD Total | G19: USD Total | H19: USD Total | I19: USD Total | J19: USD Total | K19: USD Total | L19: USD Total | M19: USD Total | N19: USD Total
B21: TRAINING DATA ONLY - Zava Safety and all business names and numbers are fictitious. Layout mirrors a typical HFM / Cognos reporting pack.
B22: GRANITE_DISP
B23: Granite Gloves | BU23: FCAST10 - Variance ($) - Favorable / (Unfavorable)
C24: FCAST09 as Reported | Q24: FCAST09 at New Fx Rates | AE24: Fx Changes | AS24: Operational Adjustments | BG24: FCAST10 | BU24: Through Sep | BY24: Rest of Year | CC24: Full Year
C25: Actual | D25: Actual | E25: Actual | F25: Actual | G25: Actual | H25: Actual | I25: Actual | J25: Actual | K25: FCAST09 | L25: FCAST09 | M25: FCAST09 | N25: FCAST09 | O25: Forecast | Q25: Actual | R25: Actual | S25: Actual | T25: Actual | U25: Actual | V25: Actual | W25: Actual | X25: Actual | Y25: FCAST09 | Z25: FCAST09 | AA25: FCAST09 | AB25: FCAST09 | AC25: Forecast | BG25: Actual | BH25: Actual | BI25: Actual | BJ25: Actual | BK25: Actual | BL25: Actual | BM25: Actual | BN25: Actual | BO25: Actual | BP25: FCAST10 | BQ25: FCAST10 | BR25: FCAST10 | BS25: Forecast
B26: Description: | C26: January | D26: February | E26: March | F26: April | G26: May | H26: June | I26: July | J26: August | K26: September | L26: October | M26: November | N26: December | O26: Full year | Q26: January | R26: February | S26: March | T26: April | U26: May | V26: June | W26: July | X26: August | Y26: September | Z26: October | AA26: November | AB26: December | AC26: Full year | AE26: January | AF26: February | AG26: March | AH26: April | AI26: May | AJ26: June | AK26: July | AL26: August | AM26: September | AN26: October | AO26: November | AP26: December | AQ26: Full year | AS26: January | AT26: February | AU26: March | AV26: April | AW26: May | AX26: June | AY26: July | AZ26: August | BA26: September | BB26: October | BC26: November | BD26: December | BE26: Full year | BG26: January | BH26: February | BI26: March | BJ26: April | BK26: May | BL26: June | BM26: July | BN26: August | BO26: September | BP26: October | BQ26: November | BR26: December | BS26: Full year | BU26: Actual vs. FCAST09 | BV26: Actual vs. Bud | BW26: Actual vs. PY | BY26: FCAST10 vs. FCAST09 | BZ26: FCAST10 vs. Bud | CA26: FCAST10 vs. PY | CC26: FCAST10 vs. FCAST09 | CD26: FCAST10 vs. Bud | CE26: FCAST10 vs. PY
B28: Sales | C28: 4878.7 | D28: 4815.1 | E28: 5092.6 | F28: 5599.4 | G28: 5017.7 | H28: 5325.2 | I28: 5274 | J28: 5127.1 | K28: 5095.3 | L28: 5441.6 | M28: 4915.5 | N28: 5354.4 | O28: =SUM(C28:N28) -> 61936.6 | Q28: 4878.7 | R28: 4815.1 | S28: 5092.6 | T28: 5599.4 | U28: 5017.7 | V28: 5325.2 | W28: 5274 | X28: 5127.1 | Y28: 5095.3 | Z28: 5441.6 | AA28: 4915.5 | AB28: 5354.4 | AC28: =SUM(Q28:AB28) -> 61936.6 | AE28: =Q28-C28 -> 0 | AF28: =R28-D28 -> 0 | AG28: =S28-E28 -> 0 | AH28: =T28-F28 -> 0 | AI28: =U28-G28 -> 0 | AJ28: =V28-H28 -> 0 | AK28: =W28-I28 -> 0 | AL28: =X28-J28 -> 0 | ... AP28: =AB28-N28 -> 0 | AQ28: =SUM(AE28:AP28) -> 0 | AS28: ='Adjustments'!C14 -> 0 | AT28: ='Adjustments'!D14 -> 0 | AU28: ='Adjustments'!E14 -> 0 | AV28: ='Adjustments'!F14 -> 0 | AW28: ='Adjustments'!G14 -> 0 | AX28: ='Adjustments'!H14 -> 0 | AY28: ='Adjustments'!I14 -> 0 | AZ28: ='Adjustments'!J14 -> 0 | ... BD28: ='Adjustments'!N14 -> -300 | BE28: =SUM(AS28:BD28) -> -1180 | BG28: =C28+AE28+AS28 -> 4878.7 | BH28: =D28+AF28+AT28 -> 4815.1 | BI28: =E28+AG28+AU28 -> 5092.6 | BJ28: =F28+AH28+AV28 -> 5599.4 | BK28: =G28+AI28+AW28 -> 5017.7 | BL28: =H28+AJ28+AX28 -> 5325.2 | BM28: =I28+AK28+AY28 -> 5274 | BN28: =J28+AL28+AZ28 -> 5127.1 | ... BR28: =N28+AP28+BD28 -> 5054.4 | BS28: =SUM(BG28:BR28) -> 60756.6 | BU28: =SUM(BG28:BO28)-SUM(C28:K28) -> -430 | BV28: =SUM(BG28:BO28)-SUM(C51:K51) -> -2792.4 | BW28: =SUM(BG28:BO28)-SUM(C64:K64) -> -1464.4 | BY28: =SUM(BP28:BR28)-SUM(L28:N28) -> -750 | BZ28: =SUM(BP28:BR28)-SUM(L51:N51) -> -1450.9 | CA28: =SUM(BP28:BR28)-SUM(L64:N64) -> -1011.2 | CC28: =BS28-O28 -> -1180 | CD28: =BS28-O51 -> -4243.3 | CE28: =BS28-O64 -> -2475.6
B29: Gross Margin | C29: 1404.5 | D29: 1379.7 | E29: 1452.2 | F29: 1580.2 | G29: 1443.8 | H29: 1531.1 | I29: 1505.3 | J29: 1448 | K29: 1456.5 | L29: 1543.4 | M29: 1413.4 | N29: 1514.6 | O29: =SUM(C29:N29) -> 17672.7 | Q29: 1404.5 | R29: 1379.7 | S29: 1452.2 | T29: 1580.2 | U29: 1443.8 | V29: 1531.1 | W29: 1505.3 | X29: 1448 | Y29: 1456.5 | Z29: 1543.4 | AA29: 1413.4 | AB29: 1514.6 | AC29: =SUM(Q29:AB29) -> 17672.7 | AE29: =Q29-C29 -> 0 | AF29: =R29-D29 -> 0 | AG29: =S29-E29 -> 0 | AH29: =T29-F29 -> 0 | AI29: =U29-G29 -> 0 | AJ29: =V29-H29 -> 0 | AK29: =W29-I29 -> 0 | AL29: =X29-J29 -> 0 | ... AP29: =AB29-N29 -> 0 | AQ29: =SUM(AE29:AP29) -> 0 | AS29: ='Adjustments'!C36+'Adjustments'!C77 -> 0 | AT29: ='Adjustments'!D36+'Adjustments'!D77 -> 0 | AU29: ='Adjustments'!E36+'Adjustments'!E77 -> 0 | AV29: ='Adjustments'!F36+'Adjustments'!F77 -> 0 | AW29: ='Adjustments'!G36+'Adjustments'!G77 -> 0 | AX29: ='Adjustments'!H36+'Adjustments'!H77 -> 0 | AY29: ='Adjustments'!I36+'Adjustments'!I77 -> 0 | AZ29: ='Adjustments'!J36+'Adjustments'!J77 -> 0 | ... BD29: ='Adjustments'!N36+'Adjustments'!N77 -> -31 | BE29: =SUM(AS29:BD29) -> -525 | BG29: =C29+AE29+AS29 -> 1404.5 | BH29: =D29+AF29+AT29 -> 1379.7 | BI29: =E29+AG29+AU29 -> 1452.2 | BJ29: =F29+AH29+AV29 -> 1580.2 | BK29: =G29+AI29+AW29 -> 1443.8 | BL29: =H29+AJ29+AX29 -> 1531.1 | BM29: =I29+AK29+AY29 -> 1505.3 | BN29: =J29+AL29+AZ29 -> 1448 | ... BR29: =N29+AP29+BD29 -> 1483.6 | BS29: =SUM(BG29:BR29) -> 17147.7 | BU29: =SUM(BG29:BO29)-SUM(C29:K29) -> -265 | BV29: =SUM(BG29:BO29)-SUM(C52:K52) -> -1639.9 | BW29: =SUM(BG29:BO29)-SUM(C65:K65) -> -1517.3 | BY29: =SUM(BP29:BR29)-SUM(L29:N29) -> -260 | BZ29: =SUM(BP29:BR29)-SUM(L52:N52) -> -712.2 | CA29: =SUM(BP29:BR29)-SUM(L65:N65) -> -668.9 | CC29: =BS29-O29 -> -525 | CD29: =BS29-O52 -> -2352.1 | CE29: =BS29-O65 -> -2186.2
B30: Op Costs | C30: -1046.8 | D30: -1032.5 | E30: -1116.8 | F30: -1197.6 | G30: -1093.4 | H30: -1144.4 | I30: -1133.5 | J30: -1230.7 | K30: -995.8 | L30: -1164.1 | M30: -1054.3 | N30: -1141.1 | O30: =SUM(C30:N30) -> -13351 | Q30: -1046.8 | R30: -1032.5 | S30: -1116.8 | T30: -1197.6 | U30: -1093.4 | V30: -1144.4 | W30: -1133.5 | X30: -1230.7 | Y30: -995.8 | Z30: -1164.1 | AA30: -1054.3 | AB30: -1141.1 | AC30: =SUM(Q30:AB30) -> -13351 | AE30: =Q30-C30 -> 0 | AF30: =R30-D30 -> 0 | AG30: =S30-E30 -> 0 | AH30: =T30-F30 -> 0 | AI30: =U30-G30 -> 0 | AJ30: =V30-H30 -> 0 | AK30: =W30-I30 -> 0 | AL30: =X30-J30 -> 0 | ... AP30: =AB30-N30 -> 0 | AQ30: =SUM(AE30:AP30) -> 0 | AS30: =-'Adjustments'!C58-'Adjustments'!C84 -> 0 | AT30: =-'Adjustments'!D58-'Adjustments'!D84 -> 0 | AU30: =-'Adjustments'!E58-'Adjustments'!E84 -> 0 | AV30: =-'Adjustments'!F58-'Adjustments'!F84 -> 0 | AW30: =-'Adjustments'!G58-'Adjustments'!G84 -> 0 | AX30: =-'Adjustments'!H58-'Adjustments'!H84 -> 0 | AY30: =-'Adjustments'!I58-'Adjustments'!I84 -> 0 | AZ30: =-'Adjustments'!J58-'Adjustments'!J84 -> 0 | ... BD30: =-'Adjustments'!N58-'Adjustments'!N84 -> 47 | BE30: =SUM(AS30:BD30) -> 174 | BG30: =C30+AE30+AS30 -> -1046.8 | BH30: =D30+AF30+AT30 -> -1032.5 | BI30: =E30+AG30+AU30 -> -1116.8 | BJ30: =F30+AH30+AV30 -> -1197.6 | BK30: =G30+AI30+AW30 -> -1093.4 | BL30: =H30+AJ30+AX30 -> -1144.4 | BM30: =I30+AK30+AY30 -> -1133.5 | BN30: =J30+AL30+AZ30 -> -1230.7 | ... BR30: =N30+AP30+BD30 -> -1094.1 | BS30: =SUM(BG30:BR30) -> -13177 | BU30: =SUM(BG30:BO30)-SUM(C30:K30) -> 42 | BV30: =SUM(BG30:BO30)-SUM(C53:K53) -> 254.5 | BW30: =SUM(BG30:BO30)-SUM(C66:K66) -> 48.4 | BY30: =SUM(BP30:BR30)-SUM(L30:N30) -> 132 | BZ30: =SUM(BP30:BR30)-SUM(L53:N53) -> 219.7 | CA30: =SUM(BP30:BR30)-SUM(L66:N66) -> 161.4 | CC30: =BS30-O30 -> 174 | CD30: =BS30-O53 -> 474.2 | CE30: =BS30-O66 -> 209.8
B31: PBITA | C31: =C29+C30 -> 357.7 | D31: =D29+D30 -> 347.2 | E31: =E29+E30 -> 335.4 | F31: =F29+F30 -> 382.6 | G31: =G29+G30 -> 350.4 | H31: =H29+H30 -> 386.7 | I31: =I29+I30 -> 371.8 | J31: =J29+J30 -> 217.3 | ... N31: =N29+N30 -> 373.5 | O31: =SUM(C31:N31) -> 4321.7 | Q31: =Q29+Q30 -> 357.7 | R31: =R29+R30 -> 347.2 | S31: =S29+S30 -> 335.4 | T31: =T29+T30 -> 382.6 | U31: =U29+U30 -> 350.4 | V31: =V29+V30 -> 386.7 | W31: =W29+W30 -> 371.8 | X31: =X29+X30 -> 217.3 | ... AB31: =AB29+AB30 -> 373.5 | AC31: =SUM(Q31:AB31) -> 4321.7 | AE31: =AE29+AE30 -> 0 | AF31: =AF29+AF30 -> 0 | AG31: =AG29+AG30 -> 0 | AH31: =AH29+AH30 -> 0 | AI31: =AI29+AI30 -> 0 | AJ31: =AJ29+AJ30 -> 0 | AK31: =AK29+AK30 -> 0 | AL31: =AL29+AL30 -> 0 | ... AP31: =AP29+AP30 -> 0 | AQ31: =SUM(AE31:AP31) -> 0 | AS31: =AS29+AS30 -> 0 | AT31: =AT29+AT30 -> 0 | AU31: =AU29+AU30 -> 0 | AV31: =AV29+AV30 -> 0 | AW31: =AW29+AW30 -> 0 | AX31: =AX29+AX30 -> 0 | AY31: =AY29+AY30 -> 0 | AZ31: =AZ29+AZ30 -> 0 | ... BD31: =BD29+BD30 -> 16 | BE31: =SUM(AS31:BD31) -> -351 | BG31: =BG29+BG30 -> 357.7 | BH31: =BH29+BH30 -> 347.2 | BI31: =BI29+BI30 -> 335.4 | BJ31: =BJ29+BJ30 -> 382.6 | BK31: =BK29+BK30 -> 350.4 | BL31: =BL29+BL30 -> 386.7 | BM31: =BM29+BM30 -> 371.8 | BN31: =BN29+BN30 -> 217.3 | ... BR31: =BR29+BR30 -> 389.5 | BS31: =SUM(BG31:BR31) -> 3970.7 | BU31: =SUM(BG31:BO31)-SUM(C31:K31) -> -223 | BV31: =SUM(BG31:BO31)-SUM(C54:K54) -> -1385.4 | BW31: =SUM(BG31:BO31)-SUM(C67:K67) -> -1468.9 | BY31: =SUM(BP31:BR31)-SUM(L31:N31) -> -128 | BZ31: =SUM(BP31:BR31)-SUM(L54:N54) -> -492.5 | CA31: =SUM(BP31:BR31)-SUM(L67:N67) -> -507.5 | CC31: =BS31-O31 -> -351 | CD31: =BS31-O54 -> -1877.9 | CE31: =BS31-O67 -> -1976.4
B35: GM % | C35: =IFERROR(C29/C28,0) -> 0.28788407 | D35: =IFERROR(D29/D28,0) -> 0.28653611 | E35: =IFERROR(E29/E28,0) -> 0.28515886 | F35: =IFERROR(F29/F28,0) -> 0.28220881 | G35: =IFERROR(G29/G28,0) -> 0.2877414 | H35: =IFERROR(H29/H28,0) -> 0.28751972 | I35: =IFERROR(I29/I28,0) -> 0.28541904 | J35: =IFERROR(J29/J28,0) -> 0.28242086 | ... O35: =IFERROR(O29/O28,0) -> 0.28533533 | Q35: =IFERROR(Q29/Q28,0) -> 0.28788407 | R35: =IFERROR(R29/R28,0) -> 0.28653611 | S35: =IFERROR(S29/S28,0) -> 0.28515886 | T35: =IFERROR(T29/T28,0) -> 0.28220881 | U35: =IFERROR(U29/U28,0) -> 0.2877414 | V35: =IFERROR(V29/V28,0) -> 0.28751972 | W35: =IFERROR(W29/W28,0) -> 0.28541904 | X35: =IFERROR(X29/X28,0) -> 0.28242086 | ... AC35: =IFERROR(AC29/AC28,0) -> 0.28533533 | AE35: =IFERROR(AE29/AE28,0) -> 0 | AF35: =IFERROR(AF29/AF28,0) -> 0 | AG35: =IFERROR(AG29/AG28,0) -> 0 | AH35: =IFERROR(AH29/AH28,0) -> 0 | AI35: =IFERROR(AI29/AI28,0) -> 0 | AJ35: =IFERROR(AJ29/AJ28,0) -> 0 | AK35: =IFERROR(AK29/AK28,0) -> 0 | AL35: =IFERROR(AL29/AL28,0) -> 0 | ... AQ35: =IFERROR(AQ29/AQ28,0) -> 0 | AS35: =IFERROR(AS29/AS28,0) -> 0 | AT35: =IFERROR(AT29/AT28,0) -> 0 | AU35: =IFERROR(AU29/AU28,0) -> 0 | AV35: =IFERROR(AV29/AV28,0) -> 0 | AW35: =IFERROR(AW29/AW28,0) -> 0 | AX35: =IFERROR(AX29/AX28,0) -> 0 | AY35: =IFERROR(AY29/AY28,0) -> 0 | AZ35: =IFERROR(AZ29/AZ28,0) -> 0 | ... BE35: =IFERROR(BE29/BE28,0) -> 0.44491525 | BG35: =IFERROR(BG29/BG28,0) -> 0.28788407 | BH35: =IFERROR(BH29/BH28,0) -> 0.28653611 | BI35: =IFERROR(BI29/BI28,0) -> 0.28515886 | BJ35: =IFERROR(BJ29/BJ28,0) -> 0.28220881 | BK35: =IFERROR(BK29/BK28,0) -> 0.2877414 | BL35: =IFERROR(BL29/BL28,0) -> 0.28751972 | BM35: =IFERROR(BM29/BM28,0) -> 0.28541904 | BN35: =IFERROR(BN29/BN28,0) -> 0.28242086 | ... BS35: =IFERROR(BS29/BS28,0) -> 0.282236
B36: Op Cost % | C36: =IFERROR(C30/C28,0) -> -0.21456536 | D36: =IFERROR(D30/D28,0) -> -0.21442961 | E36: =IFERROR(E30/E28,0) -> -0.21929859 | F36: =IFERROR(F30/F28,0) -> -0.21388006 | G36: =IFERROR(G30/G28,0) -> -0.2179086 | H36: =IFERROR(H30/H28,0) -> -0.21490273 | I36: =IFERROR(I30/I28,0) -> -0.21492226 | J36: =IFERROR(J30/J28,0) -> -0.24003823 | ... O36: =IFERROR(O30/O28,0) -> -0.21555914 | Q36: =IFERROR(Q30/Q28,0) -> -0.21456536 | R36: =IFERROR(R30/R28,0) -> -0.21442961 | S36: =IFERROR(S30/S28,0) -> -0.21929859 | T36: =IFERROR(T30/T28,0) -> -0.21388006 | U36: =IFERROR(U30/U28,0) -> -0.2179086 | V36: =IFERROR(V30/V28,0) -> -0.21490273 | W36: =IFERROR(W30/W28,0) -> -0.21492226 | X36: =IFERROR(X30/X28,0) -> -0.24003823 | ... AC36: =IFERROR(AC30/AC28,0) -> -0.21555914 | AE36: =IFERROR(AE30/AE28,0) -> 0 | AF36: =IFERROR(AF30/AF28,0) -> 0 | AG36: =IFERROR(AG30/AG28,0) -> 0 | AH36: =IFERROR(AH30/AH28,0) -> 0 | AI36: =IFERROR(AI30/AI28,0) -> 0 | AJ36: =IFERROR(AJ30/AJ28,0) -> 0 | AK36: =IFERROR(AK30/AK28,0) -> 0 | AL36: =IFERROR(AL30/AL28,0) -> 0 | ... AQ36: =IFERROR(AQ30/AQ28,0) -> 0 | AS36: =IFERROR(AS30/AS28,0) -> 0 | AT36: =IFERROR(AT30/AT28,0) -> 0 | AU36: =IFERROR(AU30/AU28,0) -> 0 | AV36: =IFERROR(AV30/AV28,0) -> 0 | AW36: =IFERROR(AW30/AW28,0) -> 0 | AX36: =IFERROR(AX30/AX28,0) -> 0 | AY36: =IFERROR(AY30/AY28,0) -> 0 | AZ36: =IFERROR(AZ30/AZ28,0) -> 0 | ... BE36: =IFERROR(BE30/BE28,0) -> -0.14745763 | BG36: =IFERROR(BG30/BG28,0) -> -0.21456536 | BH36: =IFERROR(BH30/BH28,0) -> -0.21442961 | BI36: =IFERROR(BI30/BI28,0) -> -0.21929859 | BJ36: =IFERROR(BJ30/BJ28,0) -> -0.21388006 | BK36: =IFERROR(BK30/BK28,0) -> -0.2179086 | BL36: =IFERROR(BL30/BL28,0) -> -0.21490273 | BM36: =IFERROR(BM30/BM28,0) -> -0.21492226 | BN36: =IFERROR(BN30/BN28,0) -> -0.24003823 | ... BS36: =IFERROR(BS30/BS28,0) -> -0.21688179
B37: PBITA % | C37: =IFERROR(C31/C28,0) -> 0.073318712 | D37: =IFERROR(D31/D28,0) -> 0.072106498 | E37: =IFERROR(E31/E28,0) -> 0.065860268 | F37: =IFERROR(F31/F28,0) -> 0.06832875 | G37: =IFERROR(G31/G28,0) -> 0.069832792 | H37: =IFERROR(H31/H28,0) -> 0.072616991 | I37: =IFERROR(I31/I28,0) -> 0.070496777 | J37: =IFERROR(J31/J28,0) -> 0.042382633 | ... O37: =IFERROR(O31/O28,0) -> 0.06977619 | Q37: =IFERROR(Q31/Q28,0) -> 0.073318712 | R37: =IFERROR(R31/R28,0) -> 0.072106498 | S37: =IFERROR(S31/S28,0) -> 0.065860268 | T37: =IFERROR(T31/T28,0) -> 0.06832875 | U37: =IFERROR(U31/U28,0) -> 0.069832792 | V37: =IFERROR(V31/V28,0) -> 0.072616991 | W37: =IFERROR(W31/W28,0) -> 0.070496777 | X37: =IFERROR(X31/X28,0) -> 0.042382633 | ... AC37: =IFERROR(AC31/AC28,0) -> 0.06977619 | AE37: =IFERROR(AE31/AE28,0) -> 0 | AF37: =IFERROR(AF31/AF28,0) -> 0 | AG37: =IFERROR(AG31/AG28,0) -> 0 | AH37: =IFERROR(AH31/AH28,0) -> 0 | AI37: =IFERROR(AI31/AI28,0) -> 0 | AJ37: =IFERROR(AJ31/AJ28,0) -> 0 | AK37: =IFERROR(AK31/AK28,0) -> 0 | AL37: =IFERROR(AL31/AL28,0) -> 0 | ... AQ37: =IFERROR(AQ31/AQ28,0) -> 0 | AS37: =IFERROR(AS31/AS28,0) -> 0 | AT37: =IFERROR(AT31/AT28,0) -> 0 | AU37: =IFERROR(AU31/AU28,0) -> 0 | AV37: =IFERROR(AV31/AV28,0) -> 0 | AW37: =IFERROR(AW31/AW28,0) -> 0 | AX37: =IFERROR(AX31/AX28,0) -> 0 | AY37: =IFERROR(AY31/AY28,0) -> 0 | AZ37: =IFERROR(AZ31/AZ28,0) -> 0 | ... BE37: =IFERROR(BE31/BE28,0) -> 0.29745763 | BG37: =IFERROR(BG31/BG28,0) -> 0.073318712 | BH37: =IFERROR(BH31/BH28,0) -> 0.072106498 | BI37: =IFERROR(BI31/BI28,0) -> 0.065860268 | BJ37: =IFERROR(BJ31/BJ28,0) -> 0.06832875 | BK37: =IFERROR(BK31/BK28,0) -> 0.069832792 | BL37: =IFERROR(BL31/BL28,0) -> 0.072616991 | BM37: =IFERROR(BM31/BM28,0) -> 0.070496777 | BN37: =IFERROR(BN31/BN28,0) -> 0.042382633 | ... BS37: =IFERROR(BS31/BS28,0) -> 0.065354217
B38: Sales/Day | C38: =IFERROR(C28/21,0) -> 232.31905 | D38: =IFERROR(D28/20,0) -> 240.755 | E38: =IFERROR(E28/22,0) -> 231.48182 | F38: =IFERROR(F28/22,0) -> 254.51818 | G38: =IFERROR(G28/20,0) -> 250.885 | H38: =IFERROR(H28/22,0) -> 242.05455 | I38: =IFERROR(I28/22,0) -> 239.72727 | J38: =IFERROR(J28/21,0) -> 244.14762 | K38: =IFERROR(K28/21,0) -> 242.63333 | L38: =IFERROR(L28/22,0) -> 247.34545 | M38: =IFERROR(M28/19,0) -> 258.71053 | N38: =IFERROR(N28/22,0) -> 243.38182 | O38: =IFERROR(O28/254,0) -> 243.84488 | Q38: =IFERROR(Q28/21,0) -> 232.31905 | R38: =IFERROR(R28/20,0) -> 240.755 | S38: =IFERROR(S28/22,0) -> 231.48182 | T38: =IFERROR(T28/22,0) -> 254.51818 | U38: =IFERROR(U28/20,0) -> 250.885 | V38: =IFERROR(V28/22,0) -> 242.05455 | W38: =IFERROR(W28/22,0) -> 239.72727 | X38: =IFERROR(X28/21,0) -> 244.14762 | Y38: =IFERROR(Y28/21,0) -> 242.63333 | Z38: =IFERROR(Z28/22,0) -> 247.34545 | AA38: =IFERROR(AA28/19,0) -> 258.71053 | AB38: =IFERROR(AB28/22,0) -> 243.38182 | AC38: =IFERROR(AC28/254,0) -> 243.84488 | AE38: =IFERROR(AE28/21,0) -> 0 | AF38: =IFERROR(AF28/20,0) -> 0 | AG38: =IFERROR(AG28/22,0) -> 0 | AH38: =IFERROR(AH28/22,0) -> 0 | AI38: =IFERROR(AI28/20,0) -> 0 | AJ38: =IFERROR(AJ28/22,0) -> 0 | AK38: =IFERROR(AK28/22,0) -> 0 | AL38: =IFERROR(AL28/21,0) -> 0 | AM38: =IFERROR(AM28/21,0) -> 0 | AN38: =IFERROR(AN28/22,0) -> 0 | AO38: =IFERROR(AO28/19,0) -> 0 | AP38: =IFERROR(AP28/22,0) -> 0 | AQ38: =IFERROR(AQ28/254,0) -> 0 | AS38: =IFERROR(AS28/21,0) -> 0 | AT38: =IFERROR(AT28/20,0) -> 0 | AU38: =IFERROR(AU28/22,0) -> 0 | AV38: =IFERROR(AV28/22,0) -> 0 | AW38: =IFERROR(AW28/20,0) -> 0 | AX38: =IFERROR(AX28/22,0) -> 0 | AY38: =IFERROR(AY28/22,0) -> 0 | AZ38: =IFERROR(AZ28/21,0) -> 0 | BA38: =IFERROR(BA28/21,0) -> -20.47619 | BB38: =IFERROR(BB28/22,0) -> -11.363636 | BC38: =IFERROR(BC28/19,0) -> -10.526316 | BD38: =IFERROR(BD28/22,0) -> -13.636364 | BE38: =IFERROR(BE28/254,0) -> -4.6456693 | BG38: =IFERROR(BG28/21,0) -> 232.31905 | BH38: =IFERROR(BH28/20,0) -> 240.755 | BI38: =IFERROR(BI28/22,0) -> 231.48182 | BJ38: =IFERROR(BJ28/22,0) -> 254.51818 | BK38: =IFERROR(BK28/20,0) -> 250.885 | BL38: =IFERROR(BL28/22,0) -> 242.05455 | BM38: =IFERROR(BM28/22,0) -> 239.72727 | BN38: =IFERROR(BN28/21,0) -> 244.14762 | BO38: =IFERROR(BO28/21,0) -> 222.15714 | BP38: =IFERROR(BP28/22,0) -> 235.98182 | BQ38: =IFERROR(BQ28/19,0) -> 248.18421 | BR38: =IFERROR(BR28/22,0) -> 229.74545 | BS38: =IFERROR(BS28/254,0) -> 239.19921
B40: Net Inventory | C40: 8938.2 | D40: 8677.6 | E40: 9094.9 | F40: 10143 | G40: 8777.8 | H40: 8884.8 | I40: 8549.7 | J40: 8121.8 | K40: 7734 | L40: 8363.2 | M40: 7509.9 | N40: 7719.4 | O40: =N40 -> 7719.4 | Q40: 8938.2 | R40: 8677.6 | S40: 9094.9 | T40: 10143 | U40: 8777.8 | V40: 8884.8 | W40: 8549.7 | X40: 8121.8 | Y40: 7734 | Z40: 8363.2 | AA40: 7509.9 | AB40: 7719.4 | AC40: =AB40 -> 7719.4 | AE40: =Q40-C40 -> 0 | AF40: =R40-D40 -> 0 | AG40: =S40-E40 -> 0 | AH40: =T40-F40 -> 0 | AI40: =U40-G40 -> 0 | AJ40: =V40-H40 -> 0 | AK40: =W40-I40 -> 0 | AL40: =X40-J40 -> 0 | ... AP40: =AB40-N40 -> 0 | AQ40: =AP40 -> 0 | AS40: ='Adjustments'!C90 -> 0 | AT40: ='Adjustments'!D90 -> 0 | AU40: ='Adjustments'!E90 -> 0 | AV40: ='Adjustments'!F90 -> 0 | AW40: ='Adjustments'!G90 -> 0 | AX40: ='Adjustments'!H90 -> 0 | AY40: ='Adjustments'!I90 -> 0 | AZ40: ='Adjustments'!J90 -> 0 | ... BD40: ='Adjustments'!N90 -> 0 | BE40: =BD40 -> 0 | BG40: =C40+AE40+AS40 -> 8938.2 | BH40: =D40+AF40+AT40 -> 8677.6 | BI40: =E40+AG40+AU40 -> 9094.9 | BJ40: =F40+AH40+AV40 -> 10143 | BK40: =G40+AI40+AW40 -> 8777.8 | BL40: =H40+AJ40+AX40 -> 8884.8 | BM40: =I40+AK40+AY40 -> 8549.7 | BN40: =J40+AL40+AZ40 -> 8121.8 | ... BR40: =N40+AP40+BD40 -> 7719.4 | BS40: =BR40 -> 7719.4
B41: Trade Receivables | C41: 7399.4 | D41: 7302.9 | E41: 7723.8 | F41: 8492.4 | G41: 7610.2 | H41: 8076.6 | I41: 7998.9 | J41: 7776.1 | K41: 7075.7 | L41: 7873.9 | M41: 7151.8 | N41: 7665.8 | O41: =N41 -> 7665.8 | Q41: 7399.4 | R41: 7302.9 | S41: 7723.8 | T41: 8492.4 | U41: 7610.2 | V41: 8076.6 | W41: 7998.9 | X41: 7776.1 | Y41: 7075.7 | Z41: 7873.9 | AA41: 7151.8 | AB41: 7665.8 | AC41: =AB41 -> 7665.8 | AE41: =Q41-C41 -> 0 | AF41: =R41-D41 -> 0 | AG41: =S41-E41 -> 0 | AH41: =T41-F41 -> 0 | AI41: =U41-G41 -> 0 | AJ41: =V41-H41 -> 0 | AK41: =W41-I41 -> 0 | AL41: =X41-J41 -> 0 | ... AP41: =AB41-N41 -> 0 | AQ41: =AP41 -> 0 | AS41: ='Adjustments'!C91 -> 0 | AT41: ='Adjustments'!D91 -> 0 | AU41: ='Adjustments'!E91 -> 0 | AV41: ='Adjustments'!F91 -> 0 | AW41: ='Adjustments'!G91 -> 0 | AX41: ='Adjustments'!H91 -> 0 | AY41: ='Adjustments'!I91 -> 0 | AZ41: ='Adjustments'!J91 -> 0 | ... BD41: ='Adjustments'!N91 -> 0 | BE41: =BD41 -> 0 | BG41: =C41+AE41+AS41 -> 7399.4 | BH41: =D41+AF41+AT41 -> 7302.9 | BI41: =E41+AG41+AU41 -> 7723.8 | BJ41: =F41+AH41+AV41 -> 8492.4 | BK41: =G41+AI41+AW41 -> 7610.2 | BL41: =H41+AJ41+AX41 -> 8076.6 | BM41: =I41+AK41+AY41 -> 7998.9 | BN41: =J41+AL41+AZ41 -> 7776.1 | ... BR41: =N41+AP41+BD41 -> 7665.8 | BS41: =BR41 -> 7665.8
B42: Other Receivables | C42: 73.2 | D42: 72.2 | E42: 76.4 | F42: 84 | G42: 75.3 | H42: 79.9 | I42: 79.1 | J42: 76.9 | K42: 70 | L42: 77.9 | M42: 70.7 | N42: 75.8 | O42: =N42 -> 75.8 | Q42: 73.2 | R42: 72.2 | S42: 76.4 | T42: 84 | U42: 75.3 | V42: 79.9 | W42: 79.1 | X42: 76.9 | Y42: 70 | Z42: 77.9 | AA42: 70.7 | AB42: 75.8 | AC42: =AB42 -> 75.8 | AE42: =Q42-C42 -> 0 | AF42: =R42-D42 -> 0 | AG42: =S42-E42 -> 0 | AH42: =T42-F42 -> 0 | AI42: =U42-G42 -> 0 | AJ42: =V42-H42 -> 0 | AK42: =W42-I42 -> 0 | AL42: =X42-J42 -> 0 | ... AP42: =AB42-N42 -> 0 | AQ42: =AP42 -> 0 | AS42: ='Adjustments'!C92 -> 0 | AT42: ='Adjustments'!D92 -> 0 | AU42: ='Adjustments'!E92 -> 0 | AV42: ='Adjustments'!F92 -> 0 | AW42: ='Adjustments'!G92 -> 0 | AX42: ='Adjustments'!H92 -> 0 | AY42: ='Adjustments'!I92 -> 0 | AZ42: ='Adjustments'!J92 -> 0 | ... BD42: ='Adjustments'!N92 -> 0 | BE42: =BD42 -> 0 | BG42: =C42+AE42+AS42 -> 73.2 | BH42: =D42+AF42+AT42 -> 72.2 | BI42: =E42+AG42+AU42 -> 76.4 | BJ42: =F42+AH42+AV42 -> 84 | BK42: =G42+AI42+AW42 -> 75.3 | BL42: =H42+AJ42+AX42 -> 79.9 | BM42: =I42+AK42+AY42 -> 79.1 | BN42: =J42+AL42+AZ42 -> 76.9 | ... BR42: =N42+AP42+BD42 -> 75.8 | BS42: =BR42 -> 75.8
B43: Trade Payables | C43: -4979.7 | D43: -4924.1 | E43: -5217.9 | F43: -5760.9 | G43: -5122.6 | H43: -5438.2 | I43: -5401.8 | J43: -5273.4 | K43: -4979.1 | L43: -5411.1 | M43: -4879.2 | N43: -5118.1 | O43: =N43 -> -5118.1 | Q43: -4979.7 | R43: -4924.1 | S43: -5217.9 | T43: -5760.9 | U43: -5122.6 | V43: -5438.2 | W43: -5401.8 | X43: -5273.4 | Y43: -4979.1 | Z43: -5411.1 | AA43: -4879.2 | AB43: -5118.1 | AC43: =AB43 -> -5118.1 | AE43: =Q43-C43 -> 0 | AF43: =R43-D43 -> 0 | AG43: =S43-E43 -> 0 | AH43: =T43-F43 -> 0 | AI43: =U43-G43 -> 0 | AJ43: =V43-H43 -> 0 | AK43: =W43-I43 -> 0 | AL43: =X43-J43 -> 0 | ... AP43: =AB43-N43 -> 0 | AQ43: =AP43 -> 0 | AS43: ='Adjustments'!C93 -> 0 | AT43: ='Adjustments'!D93 -> 0 | AU43: ='Adjustments'!E93 -> 0 | AV43: ='Adjustments'!F93 -> 0 | AW43: ='Adjustments'!G93 -> 0 | AX43: ='Adjustments'!H93 -> 0 | AY43: ='Adjustments'!I93 -> 0 | AZ43: ='Adjustments'!J93 -> 0 | ... BD43: ='Adjustments'!N93 -> 0 | BE43: =BD43 -> 0 | BG43: =C43+AE43+AS43 -> -4979.7 | BH43: =D43+AF43+AT43 -> -4924.1 | BI43: =E43+AG43+AU43 -> -5217.9 | BJ43: =F43+AH43+AV43 -> -5760.9 | BK43: =G43+AI43+AW43 -> -5122.6 | BL43: =H43+AJ43+AX43 -> -5438.2 | BM43: =I43+AK43+AY43 -> -5401.8 | BN43: =J43+AL43+AZ43 -> -5273.4 | ... BR43: =N43+AP43+BD43 -> -5118.1 | BS43: =BR43 -> -5118.1
B44: Other Payables | C44: -146.4 | D44: -144.5 | E44: -152.8 | F44: -168 | G44: -150.5 | H44: -159.8 | I44: -158.2 | J44: -153.8 | K44: -140 | L44: -155.7 | M44: -141.5 | N44: -151.6 | O44: =N44 -> -151.6 | Q44: -146.4 | R44: -144.5 | S44: -152.8 | T44: -168 | U44: -150.5 | V44: -159.8 | W44: -158.2 | X44: -153.8 | Y44: -140 | Z44: -155.7 | AA44: -141.5 | AB44: -151.6 | AC44: =AB44 -> -151.6 | AE44: =Q44-C44 -> 0 | AF44: =R44-D44 -> 0 | AG44: =S44-E44 -> 0 | AH44: =T44-F44 -> 0 | AI44: =U44-G44 -> 0 | AJ44: =V44-H44 -> 0 | AK44: =W44-I44 -> 0 | AL44: =X44-J44 -> 0 | ... AP44: =AB44-N44 -> 0 | AQ44: =AP44 -> 0 | AS44: ='Adjustments'!C94 -> 0 | AT44: ='Adjustments'!D94 -> 0 | AU44: ='Adjustments'!E94 -> 0 | AV44: ='Adjustments'!F94 -> 0 | AW44: ='Adjustments'!G94 -> 0 | AX44: ='Adjustments'!H94 -> 0 | AY44: ='Adjustments'!I94 -> 0 | AZ44: ='Adjustments'!J94 -> 0 | ... BD44: ='Adjustments'!N94 -> 0 | BE44: =BD44 -> 0 | BG44: =C44+AE44+AS44 -> -146.4 | BH44: =D44+AF44+AT44 -> -144.5 | BI44: =E44+AG44+AU44 -> -152.8 | BJ44: =F44+AH44+AV44 -> -168 | BK44: =G44+AI44+AW44 -> -150.5 | BL44: =H44+AJ44+AX44 -> -159.8 | BM44: =I44+AK44+AY44 -> -158.2 | BN44: =J44+AL44+AZ44 -> -153.8 | ... BR44: =N44+AP44+BD44 -> -151.6 | BS44: =BR44 -> -151.6
B45: Total working capital | C45: =SUM(C40:C44) -> 11284.7 | D45: =SUM(D40:D44) -> 10984.1 | E45: =SUM(E40:E44) -> 11524.4 | F45: =SUM(F40:F44) -> 12790.5 | G45: =SUM(G40:G44) -> 11190.2 | H45: =SUM(H40:H44) -> 11443.3 | I45: =SUM(I40:I44) -> 11067.7 | J45: =SUM(J40:J44) -> 10547.6 | ... N45: =SUM(N40:N44) -> 10191.3 | O45: =N45 -> 10191.3 | Q45: =SUM(Q40:Q44) -> 11284.7 | R45: =SUM(R40:R44) -> 10984.1 | S45: =SUM(S40:S44) -> 11524.4 | T45: =SUM(T40:T44) -> 12790.5 | U45: =SUM(U40:U44) -> 11190.2 | V45: =SUM(V40:V44) -> 11443.3 | W45: =SUM(W40:W44) -> 11067.7 | X45: =SUM(X40:X44) -> 10547.6 | ... AB45: =SUM(AB40:AB44) -> 10191.3 | AC45: =AB45 -> 10191.3 | AE45: =SUM(AE40:AE44) -> 0 | AF45: =SUM(AF40:AF44) -> 0 | AG45: =SUM(AG40:AG44) -> 0 | AH45: =SUM(AH40:AH44) -> 0 | AI45: =SUM(AI40:AI44) -> 0 | AJ45: =SUM(AJ40:AJ44) -> 0 | AK45: =SUM(AK40:AK44) -> 0 | AL45: =SUM(AL40:AL44) -> 0 | ... AP45: =SUM(AP40:AP44) -> 0 | AQ45: =AP45 -> 0 | AS45: =SUM(AS40:AS44) -> 0 | AT45: =SUM(AT40:AT44) -> 0 | AU45: =SUM(AU40:AU44) -> 0 | AV45: =SUM(AV40:AV44) -> 0 | AW45: =SUM(AW40:AW44) -> 0 | AX45: =SUM(AX40:AX44) -> 0 | AY45: =SUM(AY40:AY44) -> 0 | AZ45: =SUM(AZ40:AZ44) -> 0 | ... BD45: =SUM(BD40:BD44) -> 0 | BE45: =BD45 -> 0 | BG45: =SUM(BG40:BG44) -> 11284.7 | BH45: =SUM(BH40:BH44) -> 10984.1 | BI45: =SUM(BI40:BI44) -> 11524.4 | BJ45: =SUM(BJ40:BJ44) -> 12790.5 | BK45: =SUM(BK40:BK44) -> 11190.2 | BL45: =SUM(BL40:BL44) -> 11443.3 | BM45: =SUM(BM40:BM44) -> 11067.7 | BN45: =SUM(BN40:BN44) -> 10547.6 | ... BR45: =SUM(BR40:BR44) -> 10191.3 | BS45: =BR45 -> 10191.3
B46: Working capital/sales (monthly) | C46: =IFERROR(C45/(C28*12),0) -> 0.19275456 | D46: =IFERROR(D45/(D28*12),0) -> 0.19009816 | E46: =IFERROR(E45/(E28*12),0) -> 0.18858082 | F46: =IFERROR(F45/(F28*12),0) -> 0.19035522 | G46: =IFERROR(G45/(G28*12),0) -> 0.18584544 | H46: =IFERROR(H45/(H28*12),0) -> 0.17907465 | I46: =IFERROR(I45/(I28*12),0) -> 0.17487833 | J46: =IFERROR(J45/(J28*12),0) -> 0.17143544 | ... N46: =IFERROR(N45/(N28*12),0) -> 0.15861254 | Q46: =IFERROR(Q45/(Q28*12),0) -> 0.19275456 | R46: =IFERROR(R45/(R28*12),0) -> 0.19009816 | S46: =IFERROR(S45/(S28*12),0) -> 0.18858082 | T46: =IFERROR(T45/(T28*12),0) -> 0.19035522 | U46: =IFERROR(U45/(U28*12),0) -> 0.18584544 | V46: =IFERROR(V45/(V28*12),0) -> 0.17907465 | W46: =IFERROR(W45/(W28*12),0) -> 0.17487833 | X46: =IFERROR(X45/(X28*12),0) -> 0.17143544 | ... AB46: =IFERROR(AB45/(AB28*12),0) -> 0.15861254 | AE46: =IFERROR(AE45/(AE28*12),0) -> 0 | AF46: =IFERROR(AF45/(AF28*12),0) -> 0 | AG46: =IFERROR(AG45/(AG28*12),0) -> 0 | AH46: =IFERROR(AH45/(AH28*12),0) -> 0 | AI46: =IFERROR(AI45/(AI28*12),0) -> 0 | AJ46: =IFERROR(AJ45/(AJ28*12),0) -> 0 | AK46: =IFERROR(AK45/(AK28*12),0) -> 0 | AL46: =IFERROR(AL45/(AL28*12),0) -> 0 | ... AP46: =IFERROR(AP45/(AP28*12),0) -> 0 | AS46: =IFERROR(AS45/(AS28*12),0) -> 0 | AT46: =IFERROR(AT45/(AT28*12),0) -> 0 | AU46: =IFERROR(AU45/(AU28*12),0) -> 0 | AV46: =IFERROR(AV45/(AV28*12),0) -> 0 | AW46: =IFERROR(AW45/(AW28*12),0) -> 0 | AX46: =IFERROR(AX45/(AX28*12),0) -> 0 | AY46: =IFERROR(AY45/(AY28*12),0) -> 0 | AZ46: =IFERROR(AZ45/(AZ28*12),0) -> 0 | ... BD46: =IFERROR(BD45/(BD28*12),0) -> 0 | BG46: =IFERROR(BG45/(BG28*12),0) -> 0.19275456 | BH46: =IFERROR(BH45/(BH28*12),0) -> 0.19009816 | BI46: =IFERROR(BI45/(BI28*12),0) -> 0.18858082 | BJ46: =IFERROR(BJ45/(BJ28*12),0) -> 0.19035522 | BK46: =IFERROR(BK45/(BK28*12),0) -> 0.18584544 | BL46: =IFERROR(BL45/(BL28*12),0) -> 0.17907465 | BM46: =IFERROR(BM45/(BM28*12),0) -> 0.17487833 | BN46: =IFERROR(BN45/(BN28*12),0) -> 0.17143544 | ... BR46: =IFERROR(BR45/(BR28*12),0) -> 0.16802687
B49: Budget 2026
C50: January | D50: February | E50: March | F50: April | G50: May | H50: June | I50: July | J50: August | K50: September | L50: October | M50: November | N50: December | O50: Full year
B51: Sales | C51: 5145.9 | D51: 5037.5 | E51: 5416.6 | F51: 5849.9 | G51: 5308.4 | H51: 5579.2 | I51: 5525 | J51: 5416.7 | K51: 5308.3 | L51: 5687.4 | M51: 5145.8 | N51: 5579.2 | O51: =SUM(C51:N51) -> 64999.9
B52: Gross Margin | C52: 1543.8 | D52: 1511.3 | E52: 1624.9 | F52: 1754.9 | G52: 1592.6 | H52: 1673.7 | I52: 1657.5 | J52: 1625 | K52: 1592.5 | L52: 1706.3 | M52: 1543.7 | N52: 1673.6 | O52: =SUM(C52:N52) -> 19499.8
B53: Op Costs | C53: -1080.6 | D53: -1057.9 | E53: -1137.8 | F53: -1228.4 | G53: -1114.5 | H53: -1172.1 | I53: -1160.4 | J53: -1137.8 | K53: -1114.5 | L53: -1194.5 | M53: -1080.6 | N53: -1172.1 | O53: =SUM(C53:N53) -> -13651.2
B54: PBITA | C54: =C52+C53 -> 463.2 | D54: =D52+D53 -> 453.4 | E54: =E52+E53 -> 487.1 | F54: =F52+F53 -> 526.5 | G54: =G52+G53 -> 478.1 | H54: =H52+H53 -> 501.6 | I54: =I52+I53 -> 497.1 | J54: =J52+J53 -> 487.2 | ... N54: =N52+N53 -> 501.5 | O54: =SUM(C54:N54) -> 5848.6
B55: Net Inventory | C55: 9246.9 | D55: 8942 | E55: 9593.3 | F55: 10290.1 | G55: 9442.9 | H55: 9805.7 | I55: 9815.4 | J55: 9657.5 | K55: 9445.4 | L55: 10095.4 | M55: 9027.7 | N55: 9790.9 | O55: =N55 -> 9790.9
B56: Trade Receivables | C56: 7718.8 | D56: 7556.2 | E56: 8124.9 | F56: 8774.9 | G56: 7962.6 | H56: 8368.8 | I56: 8287.5 | J56: 8125.1 | K56: 7962.4 | L56: 8531.1 | M56: 7718.7 | N56: 8368.8 | O56: =N56 -> 8368.8
B57: Other Receivables | C57: 77.2 | D57: 75.6 | E57: 81.2 | F57: 87.7 | G57: 79.6 | H57: 83.7 | I57: 82.9 | J57: 81.3 | K57: 79.6 | L57: 85.3 | M57: 77.2 | N57: 83.7 | O57: =N57 -> 83.7
B58: Trade Payables | C58: -5042.9 | D58: -4936.7 | E58: -5308.4 | F58: -5733 | G58: -5202.1 | H58: -5467.7 | I58: -5414.5 | J58: -5308.4 | K58: -5202.1 | L58: -5573.5 | M58: -5042.9 | N58: -5467.8 | O58: =N58 -> -5467.8
B59: Other Payables | C59: -154.4 | D59: -151.1 | E59: -162.5 | F59: -175.5 | G59: -159.3 | H59: -167.4 | I59: -165.8 | J59: -162.5 | K59: -159.2 | L59: -170.6 | M59: -154.4 | N59: -167.4 | O59: =N59 -> -167.4
B60: Total working capital | C60: =SUM(C55:C59) -> 11845.6 | D60: =SUM(D55:D59) -> 11486 | E60: =SUM(E55:E59) -> 12328.5 | F60: =SUM(F55:F59) -> 13244.2 | G60: =SUM(G55:G59) -> 12123.7 | H60: =SUM(H55:H59) -> 12623.1 | I60: =SUM(I55:I59) -> 12605.5 | J60: =SUM(J55:J59) -> 12393 | ... N60: =SUM(N55:N59) -> 12608.2 | O60: =N60 -> 12608.2
B62: 2025 Actual
C63: January | D63: February | E63: March | F63: April | G63: May | H63: June | I63: July | J63: August | K63: September | L63: October | M63: November | N63: December | O63: Full year
B64: Sales | C64: 5026.5 | D64: 4931.5 | E64: 5216 | F64: 5758.2 | G64: 5054.5 | H64: 5461.9 | I64: 5399.4 | J64: 5188.1 | K64: 5223.4 | L64: 5444.6 | M64: 5021.7 | N64: 5506.4 | O64: =SUM(C64:N64) -> 63232.2
B65: Gross Margin | C65: 1544.4 | D65: 1517.7 | E65: 1594.6 | F65: 1761.5 | G65: 1553.8 | H65: 1660.5 | I65: 1640.1 | J65: 1601 | K65: 1580 | L65: 1641.8 | M65: 1545.5 | N65: 1693 | O65: =SUM(C65:N65) -> 19333.9
B66: Op Costs | C66: -1067.2 | D66: -1031.7 | E66: -1121.3 | F66: -1191.2 | G66: -1090.8 | H66: -1149.8 | I66: -1130.7 | J66: -1120.6 | K66: -1094.6 | L66: -1174.1 | M66: -1061.9 | N66: -1152.9 | O66: =SUM(C66:N66) -> -13386.8
B67: PBITA | C67: =C65+C66 -> 477.2 | D67: =D65+D66 -> 486 | E67: =E65+E66 -> 473.3 | F67: =F65+F66 -> 570.3 | G67: =G65+G66 -> 463 | H67: =H65+H66 -> 510.7 | I67: =I65+I66 -> 509.4 | J67: =J65+J66 -> 480.4 | ... N67: =N65+N66 -> 540.1 | O67: =SUM(C67:N67) -> 5947.1
B68: Net Inventory | C68: 9691 | D68: 9555.5 | E68: 10317.3 | F68: 11126.5 | G68: 9699.5 | H68: 10772.5 | I68: 10687.3 | J68: 10108.8 | K68: 10253.9 | L68: 10729.5 | M68: 9904.5 | N68: 10745.7 | O68: =N68 -> 10745.7
B69: Trade Receivables | C69: 7707.3 | D69: 7561.6 | E69: 7997.9 | F69: 8829.2 | G69: 7750.2 | H69: 8374.9 | I69: 8279.1 | J69: 7955.1 | K69: 8009.2 | L69: 8348.4 | M69: 7699.9 | N69: 8443.1 | O69: =N69 -> 8443.1
B70: Other Receivables | C70: 75.4 | D70: 74 | E70: 78.2 | F70: 86.4 | G70: 75.8 | H70: 81.9 | I70: 81 | J70: 77.8 | K70: 78.4 | L70: 81.7 | M70: 75.3 | N70: 82.6 | O70: =N70 -> 82.6
B71: Trade Payables | C71: -4758.9 | D71: -4665.5 | E71: -4949.2 | F71: -5462.2 | G71: -4784.3 | H71: -5195.2 | I71: -5137.7 | J71: -4902.4 | K71: -4979.3 | L71: -5197.2 | M71: -4750.8 | N71: -5211.6 | O71: =N71 -> -5211.6
B72: Other Payables | C72: -150.8 | D72: -147.9 | E72: -156.5 | F72: -172.7 | G72: -151.6 | H72: -163.9 | I72: -162 | J72: -155.6 | K72: -156.7 | L72: -163.3 | M72: -150.7 | N72: -165.2 | O72: =N72 -> -165.2
B73: Total working capital | C73: =SUM(C68:C72) -> 12564 | D73: =SUM(D68:D72) -> 12377.7 | E73: =SUM(E68:E72) -> 13287.7 | F73: =SUM(F68:F72) -> 14407.2 | G73: =SUM(G68:G72) -> 12589.6 | H73: =SUM(H68:H72) -> 13870.2 | I73: =SUM(I68:I72) -> 13747.7 | J73: =SUM(J68:J72) -> 13083.7 | ... N73: =SUM(N68:N72) -> 13894.6 | O73: =N73 -> 13894.6

Sheet Billing Days
A1: Billing Days & Daily Sales
A2: TRAINING DATA ONLY - Zava Safety and all business names and numbers are fictitious. Layout mirrors a typical HFM / Cognos reporting pack.
B4: January | C4: February | D4: March | E4: April | F4: May | G4: June | H4: July | I4: August | J4: September | K4: October | L4: November | M4: December | N4: Full Year
A5: Reported Sales - FCAST10 (Actual Jan-Sep) | B5: 4878.7 | C5: 4815.1 | D5: 5092.6 | E5: 5599.4 | F5: 5017.7 | G5: 5325.2 | H5: 5274 | I5: 5127.1 | J5: 4665.3 | K5: 5191.6 | L5: 4715.5 | M5: 5054.4 | N5: =SUM(B5:M5) -> 60756.6
A6: Days 2026 | B6: 21 | C6: 20 | D6: 22 | E6: 22 | F6: 20 | G6: 22 | H6: 22 | I6: 21 | J6: 21 | K6: 22 | L6: 19 | M6: 22 | N6: =SUM(B6:M6) -> 254
A7: Daily Reported Sales | B7: =B5/B6 -> 232.31905 | C7: =C5/C6 -> 240.755 | D7: =D5/D6 -> 231.48182 | E7: =E5/E6 -> 254.51818 | F7: =F5/F6 -> 250.885 | G7: =G5/G6 -> 242.05455 | H7: =H5/H6 -> 239.72727 | I7: =I5/I6 -> 244.14762 | ... N7: =N5/N6 -> 239.19921
A8: Budget Sales 2026 | B8: 5145.9 | C8: 5037.5 | D8: 5416.6 | E8: 5849.9 | F8: 5308.4 | G8: 5579.2 | H8: 5525 | I8: 5416.7 | J8: 5308.3 | K8: 5687.4 | L8: 5145.8 | M8: 5579.2 | N8: =SUM(B8:M8) -> 64999.9
A9: Daily Budget Sales | B9: =B8/B6 -> 245.04286 | C9: =C8/C6 -> 251.875 | D9: =D8/D6 -> 246.20909 | E9: =E8/E6 -> 265.90455 | F9: =F8/F6 -> 265.42 | G9: =G8/G6 -> 253.6 | H9: =H8/H6 -> 251.13636 | I9: =I8/I6 -> 257.9381 | ... N9: =N8/N6 -> 255.90512
A10: Reported Sales 2025 | B10: 5026.5 | C10: 4931.5 | D10: 5216 | E10: 5758.2 | F10: 5054.5 | G10: 5461.9 | H10: 5399.4 | I10: 5188.1 | J10: 5223.4 | K10: 5444.6 | L10: 5021.7 | M10: 5506.4 | N10: =SUM(B10:M10) -> 63232.2
A11: Days 2025 | B11: 22 | C11: 20 | D11: 21 | E11: 22 | F11: 21 | G11: 21 | H11: 22 | I11: 21 | J11: 21 | K11: 23 | L11: 18 | M11: 22 | N11: =SUM(B11:M11) -> 254
A12: Daily Reported Sales 2025 | B12: =B10/B11 -> 228.47727 | C12: =C10/C11 -> 246.575 | D12: =D10/D11 -> 248.38095 | E12: =E10/E11 -> 261.73636 | F12: =F10/F11 -> 240.69048 | G12: =G10/G11 -> 260.09048 | H12: =H10/H11 -> 245.42727 | I12: =I10/I11 -> 247.05238 | ... N12: =N10/N11 -> 248.94567

Sheet R&Os
B1: Risks and Opportunities NOT included in FCAST10
B2: TRAINING DATA ONLY - Zava Safety and all business names and numbers are fictitious. Layout mirrors a typical HFM / Cognos reporting pack.
B4: Likelihood | C4: Probability
B5: Low | C5: 0.25
B6: Medium | C6: 0.5
B7: High | C7: 0.75
B10: Business | C10: Type | D10: Description | E10: PBITA impact ($000) | F10: Likelihood | G10: Probability | H10: Weighted impact ($000) | I10: Timing
B11: Granite Gloves | C11: Risk | D11: Container receipts slip again into January | E11: -110 | F11: Medium | G11: =VLOOKUP(F11,$B$5:$C$7,2,FALSE) -> 0.5 | H11: =E11*G11 -> -55 | I11: Q4 2026
B12: Granite Gloves | C12: Opportunity | D12: Buying group rebate tier achieved | E12: 60 | F12: Low | G12: =VLOOKUP(F12,$B$5:$C$7,2,FALSE) -> 0.25 | H12: =E12*G12 -> 15 | I12: Q4 2026
D13: Net risks & opportunities | E13: =SUM(E11:E12) -> -50 | H13: =SUM(H11:H12) -> -40
