Workbook

Sheet {HFM Defaults}
A2: Connection | B2: WSFN|HFM|HFM|ZAVALIVE|ZAVALIVE | C2: WSFN|HFM|HFM|ZAVALIVE|ZAVALIVE | D2: WSFN|HFM|HFM|ZAVALIVE|ZAVALIVE | E2: WSFN|HFM|HFM|ZAVALIVE|ZAVALIVE
A3: Scenario# | B3: ACTUAL | C3: ACTUAL | D3: ACTUAL | E3: ACTUAL
A4: Year#
A5: Period# | B5: [YEAR] | C5: [YEAR] | D5: [YEAR] | E5: [YEAR]
A6: View# | B6: <Scenario View> | C6: <Scenario View> | D6: <Scenario View> | E6: <Scenario View>
A7: Entity# | B7: [None] | C7: [None] | D7: [None] | E7: [None]
A8: Value# | B8: USD Total | C8: USD Total | D8: USD Total | E8: USD Total
A9: Account#
A10: ICP# | B10: [ICP Top] | C10: [ICP Top] | D10: [ICP Top] | E10: [ICP Top]
A11: Custom1# | B11: TotalC1 | C11: TotalC1 | D11: TotalC1 | E11: TotalC1
A12: Custom2# | B12: TotalC2 | C12: TotalC2 | D12: TotalC2 | E12: TotalC2
A13: Custom3# | B13: TotalC3 | C13: TotalC3 | D13: TotalC3 | E13: TotalC3
A14: Custom4# | B14: TotalC4 | C14: TotalC4 | D14: TotalC4 | E14: TotalC4
B15: TRAINING DATA ONLY - Zava Safety and all business names and numbers are fictitious. Layout mirrors a typical HFM / Cognos reporting pack.
B16: HFM entity name: | D16: SAFECON_2DISP | G16: Current ME | J16: Next ME | N16: Period | O16: Month-end
B17: Current month-end period: | D17: P09 | G17: Jan | H17: Actual | J17: Jan | K17: Actual | N17: P01
B18: Next month-end period: | D18: P10 | G18: Feb | H18: Actual | J18: Feb | K18: Actual | N18: P02
B19: Current month-end date: | D19: 2026-09-30 | G19: Mar | H19: Actual | J19: Mar | K19: Actual | N19: P03
B20: Forecast reference for actual | D20: FCAST09 | G20: Apr | H20: Actual | J20: Apr | K20: Actual | N20: P04
B21: Next month-end date: | D21: 2026-10-31 | G21: May | H21: Actual | J21: May | K21: Actual | N21: P05
B22: Forecast reference for actual | D22: FCAST10 | G22: Jun | H22: Actual | J22: Jun | K22: Actual | N22: P06
G23: Jul | H23: Actual | J23: Jul | K23: Actual | N23: P07
G24: Aug | H24: Actual | J24: Aug | K24: Actual | N24: P08
B25: Current Period Estimate or Retrieve: | D25: Retrieve | G25: Sep | H25: FCAST09 | J25: Sep | K25: Actual | N25: P09
B26: Reported or Excl ACQ: | D26: Reported | G26: Oct | H26: FCAST09 | J26: Oct | K26: FCAST10 | N26: P10
G27: Nov | H27: FCAST09 | J27: Nov | K27: FCAST10 | N27: P11
G28: Dec | H28: FCAST09 | J28: Dec | K28: FCAST10 | N28: P12

Sheet Billing Days
A1: Billing Days & Daily Sales
A2: TRAINING DATA ONLY - Zava Safety and all business names and numbers are fictitious. Layout mirrors a typical HFM / Cognos reporting pack.
B4: January | C4: February | D4: March | E4: April | F4: May | G4: June | H4: July | I4: August | J4: September | K4: October | L4: November | M4: December | N4: Full Year
A5: Reported Sales - FCAST10 (Actual Jan-Sep) | B5: 49776.7 | C5: 49033.4 | D5: 52588.4 | E5: 56881.9 | F5: 51833.5 | G5: 54124.1 | H5: 53826.7 | I5: 52681.3 | J5: 53640.4 | K5: 54420.3 | L5: 50066 | M5: 55284.2 | N5: =SUM(B5:M5) -> 634156.9
A6: Days 2026 | B6: 21 | C6: 20 | D6: 22 | E6: 22 | F6: 20 | G6: 22 | H6: 22 | I6: 21 | J6: 21 | K6: 22 | L6: 19 | M6: 22 | N6: =SUM(B6:M6) -> 254
A7: Daily Reported Sales | B7: =B5/B6 -> 2370.319 | C7: =C5/C6 -> 2451.67 | D7: =D5/D6 -> 2390.3818 | E7: =E5/E6 -> 2585.5409 | F7: =F5/F6 -> 2591.675 | G7: =G5/G6 -> 2460.1864 | H7: =H5/H6 -> 2446.6682 | I7: =I5/I6 -> 2508.6333 | ... N7: =N5/N6 -> 2496.6807
A8: Budget Sales 2026 | B8: 49083 | C8: 48050 | D8: 51666.4 | E8: 55799.9 | F8: 50633.4 | G8: 53216.8 | H8: 52699.6 | I8: 51666.6 | J8: 50633.2 | K8: 54249.8 | L8: 49083.1 | M8: 53216.3 | N8: =SUM(B8:M8) -> 619998.1
A9: Daily Budget Sales | B9: =B8/B6 -> 2337.2857 | C9: =C8/C6 -> 2402.5 | D9: =D8/D6 -> 2348.4727 | E9: =E8/E6 -> 2536.3591 | F9: =F8/F6 -> 2531.67 | G9: =G8/G6 -> 2418.9455 | H9: =H8/H6 -> 2395.4364 | I9: =I8/I6 -> 2460.3143 | ... N9: =N8/N6 -> 2440.9374
A10: Reported Sales 2025 | B10: 46990.7 | C10: 45717.1 | D10: 49328.6 | E10: 53313.8 | F10: 48140.4 | G10: 50828.2 | H10: 50581.7 | I10: 48966.9 | J10: 48517.7 | K10: 51865.9 | L10: 46746 | M10: 50915.4 | N10: =SUM(B10:M10) -> 591912.4
A11: Days 2025 | B11: 22 | C11: 20 | D11: 21 | E11: 22 | F11: 21 | G11: 21 | H11: 22 | I11: 21 | J11: 21 | K11: 23 | L11: 18 | M11: 22 | N11: =SUM(B11:M11) -> 254
A12: Daily Reported Sales 2025 | B12: =B10/B11 -> 2135.9409 | C12: =C10/C11 -> 2285.855 | D12: =D10/D11 -> 2348.981 | E12: =E10/E11 -> 2423.3545 | F12: =F10/F11 -> 2292.4 | G12: =G10/G11 -> 2420.3905 | H12: =H10/H11 -> 2299.1682 | I12: =I10/I11 -> 2331.7571 | ... N12: =N10/N11 -> 2330.3638

Sheet Variances Summary
A1: Current ME | B1: P09 | D1: Variances Summary by Business - FCAST10
A2: Next ME | B2: P10 | D2: TRAINING DATA ONLY - Zava Safety and all business names and numbers are fictitious. Layout mirrors a typical HFM / Cognos reporting pack.
C4: FCAST10
C5: Through Sep | F5: Rest of Year | I5: Full Year
B6: Favorable / (Unfavorable) | C6: Actual vs. FCAST09 | D6: Actual vs. Bud | E6: Actual vs. PY | F6: FCAST10 vs. FCAST09 | G6: FCAST10 vs. Bud | H6: FCAST10 vs. PY | I6: FCAST10 vs. FCAST09 | J6: FCAST10 vs. Bud | K6: FCAST10 vs. PY
B8: Sales
B9: Alder Gloves | C9: =Alder!BU28 -> 0 | D9: =Alder!BV28 -> 4321.5 | E9: =Alder!BW28 -> 9085.9 | F9: =Alder!BY28 -> -600 | G9: =Alder!BZ28 -> 890 | H9: =Alder!CA28 -> 2526.4 | I9: =Alder!CC28 -> -600 | J9: =Alder!CD28 -> 5211.5 | K9: =Alder!CE28 -> 11612.3
B10: Beacon Hi-Vis | C10: =Beacon!BU28 -> 150 | D10: =Beacon!BV28 -> 3250.8 | E10: =Beacon!BW28 -> 6179 | F10: =Beacon!BY28 -> 750 | G10: =Beacon!BZ28 -> 2417 | H10: =Beacon!CA28 -> 3639.3 | I10: =Beacon!CC28 -> 900 | J10: =Beacon!CD28 -> 5667.8 | K10: =Beacon!CE28 -> 9818.3
B11: Cobalt Eyewear | C11: =Cobalt!BU28 -> 30 | D11: =Cobalt!BV28 -> -114.6 | E11: =Cobalt!BW28 -> 1556.2 | F11: =Cobalt!BY28 -> 120 | G11: =Cobalt!BZ28 -> 5.5 | H11: =Cobalt!CA28 -> 598.8 | I11: =Cobalt!CC28 -> 150 | J11: =Cobalt!CD28 -> -109.1 | K11: =Cobalt!CE28 -> 2155
B12: Delta Welding Supply | C12: =Delta!BU28 -> 0 | D12: =Delta!BV28 -> -664 | E12: =Delta!BW28 -> 386.8 | F12: =Delta!BY28 -> 0 | G12: =Delta!BZ28 -> -260.6 | H12: =Delta!CA28 -> 8.4 | I12: =Delta!CC28 -> 0 | J12: =Delta!CD28 -> -924.6 | K12: =Delta!CE28 -> 395.2
B13: Ember Workwear | C13: =Ember!BU28 -> -260 | D13: =Ember!BV28 -> -1538.3 | E13: =Ember!BW28 -> -177 | F13: =Ember!BY28 -> -240 | G13: =Ember!BZ28 -> -978.4 | H13: =Ember!CA28 -> -640.3 | I13: =Ember!CC28 -> -500 | J13: =Ember!CD28 -> -2516.7 | K13: =Ember!CE28 -> -817.3
B14: Falcon Hand Protection | C14: =Falcon!BU28 -> 300 | D14: =Falcon!BV28 -> 5882 | E14: =Falcon!BW28 -> 9896.4 | F14: =Falcon!BY28 -> 900 | G14: =Falcon!BZ28 -> 3410.6 | H14: =Falcon!CA28 -> 4812.9 | I14: =Falcon!CC28 -> 1200 | J14: =Falcon!CD28 -> 9292.6 | K14: =Falcon!CE28 -> 14709.3
B15: Granite Gloves | C15: =Granite!BU28 -> -430 | D15: =Granite!BV28 -> -2792.4 | E15: =Granite!BW28 -> -1464.4 | F15: =Granite!BY28 -> -750 | G15: =Granite!BZ28 -> -1450.9 | H15: =Granite!CA28 -> -1011.2 | I15: =Granite!CC28 -> -1180 | J15: =Granite!CD28 -> -4243.3 | K15: =Granite!CE28 -> -2475.6
B16: Hollis Rainwear | C16: =Hollis!BU28 -> 1655 | D16: =Hollis!BV28 -> 2592.5 | E16: =Hollis!BW28 -> 6538.4 | F16: =Hollis!BY28 -> -1235 | G16: =Hollis!BZ28 -> -811.9 | H16: =Hollis!CA28 -> 308.9 | I16: =Hollis!CC28 -> 420 | J16: =Hollis!CD28 -> 1780.6 | K16: =Hollis!CE28 -> 6847.3
B17: Safety Region (regional office) | C17: =SAFEREG!BU28 -> 0 | D17: =SAFEREG!BV28 -> 0 | E17: =SAFEREG!BW28 -> 0 | F17: =SAFEREG!BY28 -> 0 | G17: =SAFEREG!BZ28 -> 0 | H17: =SAFEREG!CA28 -> 0 | I17: =SAFEREG!CC28 -> 0 | J17: =SAFEREG!CD28 -> 0 | K17: =SAFEREG!CE28 -> 0
B18: Total Zava Safety | C18: =SUM(C9:C17) -> 1445 | D18: =SUM(D9:D17) -> 10937.5 | E18: =SUM(E9:E17) -> 32001.3 | F18: =SUM(F9:F17) -> -1055 | G18: =SUM(G9:G17) -> 3221.3 | H18: =SUM(H9:H17) -> 10243.2 | I18: =SUM(I9:I17) -> 390 | J18: =SUM(J9:J17) -> 14158.8 | K18: =SUM(K9:K17) -> 42244.5
B20: Gross Margin
B21: Alder Gloves | C21: =Alder!BU29 -> -160 | D21: =Alder!BV29 -> -475.7 | E21: =Alder!BW29 -> 123.5 | F21: =Alder!BY29 -> -420 | G21: =Alder!BZ29 -> -1101 | H21: =Alder!CA29 -> -909.6 | I21: =Alder!CC29 -> -580 | J21: =Alder!CD29 -> -1576.7 | K21: =Alder!CE29 -> -786.1
B22: Beacon Hi-Vis | C22: =Beacon!BU29 -> 60 | D22: =Beacon!BV29 -> 2370.9 | E22: =Beacon!BW29 -> 3866.8 | F22: =Beacon!BY29 -> 290 | G22: =Beacon!BZ29 -> 1301.7 | H22: =Beacon!CA29 -> 1877.3 | I22: =Beacon!CC29 -> 350 | J22: =Beacon!CD29 -> 3672.6 | K22: =Beacon!CE29 -> 5744.1
B23: Cobalt Eyewear | C23: =Cobalt!BU29 -> -162 | D23: =Cobalt!BV29 -> -598.4 | E23: =Cobalt!BW29 -> 253.6 | F23: =Cobalt!BY29 -> -648 | G23: =Cobalt!BZ29 -> -833.5 | H23: =Cobalt!CA29 -> -575.4 | I23: =Cobalt!CC29 -> -810 | J23: =Cobalt!CD29 -> -1431.9 | K23: =Cobalt!CE29 -> -321.8
B24: Delta Welding Supply | C24: =Delta!BU29 -> 0 | D24: =Delta!BV29 -> -209.7 | E24: =Delta!BW29 -> 72.2 | F24: =Delta!BY29 -> 0 | G24: =Delta!BZ29 -> -94.7 | H24: =Delta!CA29 -> -5.2 | I24: =Delta!CC29 -> 0 | J24: =Delta!CD29 -> -304.4 | K24: =Delta!CE29 -> 67
B25: Ember Workwear | C25: =Ember!BU29 -> -83 | D25: =Ember!BV29 -> -633 | E25: =Ember!BW29 -> -140.5 | F25: =Ember!BY29 -> -77 | G25: =Ember!BZ29 -> -363.5 | H25: =Ember!CA29 -> -238.1 | I25: =Ember!CC29 -> -160 | J25: =Ember!CD29 -> -996.5 | K25: =Ember!CE29 -> -378.6
B26: Falcon Hand Protection | C26: =Falcon!BU29 -> 120 | D26: =Falcon!BV29 -> 3096.1 | E26: =Falcon!BW29 -> 4787.3 | F26: =Falcon!BY29 -> 360 | G26: =Falcon!BZ29 -> 1607.6 | H26: =Falcon!CA29 -> 2147.9 | I26: =Falcon!CC29 -> 480 | J26: =Falcon!CD29 -> 4703.7 | K26: =Falcon!CE29 -> 6935.2
B27: Granite Gloves | C27: =Granite!BU29 -> -265 | D27: =Granite!BV29 -> -1639.9 | E27: =Granite!BW29 -> -1517.3 | F27: =Granite!BY29 -> -260 | G27: =Granite!BZ29 -> -712.2 | H27: =Granite!CA29 -> -668.9 | I27: =Granite!CC29 -> -525 | J27: =Granite!CD29 -> -2352.1 | K27: =Granite!CE29 -> -2186.2
B28: Hollis Rainwear | C28: =Hollis!BU29 -> 242 | D28: =Hollis!BV29 -> 207.5 | E28: =Hollis!BW29 -> 1310 | F28: =Hollis!BY29 -> 6 | G28: =Hollis!BZ29 -> 50 | H28: =Hollis!CA29 -> 357.9 | I28: =Hollis!CC29 -> 248 | J28: =Hollis!CD29 -> 257.5 | K28: =Hollis!CE29 -> 1667.9
B29: Safety Region (regional office) | C29: =SAFEREG!BU29 -> 0 | D29: =SAFEREG!BV29 -> 0 | E29: =SAFEREG!BW29 -> 0 | F29: =SAFEREG!BY29 -> 0 | G29: =SAFEREG!BZ29 -> 0 | H29: =SAFEREG!CA29 -> 0 | I29: =SAFEREG!CC29 -> 0 | J29: =SAFEREG!CD29 -> 0 | K29: =SAFEREG!CE29 -> 0
B30: Total Zava Safety | C30: =SUM(C21:C29) -> -248 | D30: =SUM(D21:D29) -> 2117.8 | E30: =SUM(E21:E29) -> 8755.6 | F30: =SUM(F21:F29) -> -749 | G30: =SUM(G21:G29) -> -145.6 | H30: =SUM(H21:H29) -> 1985.9 | I30: =SUM(I21:I29) -> -997 | J30: =SUM(J21:J29) -> 1972.2 | K30: =SUM(K21:K29) -> 10741.5
B32: Op Costs
B33: Alder Gloves | C33: =Alder!BU30 -> 240 | D33: =Alder!BV30 -> -174.7 | E33: =Alder!BW30 -> -899.6 | F33: =Alder!BY30 -> 60 | G33: =Alder!BZ30 -> -77.2 | H33: =Alder!CA30 -> -330.8 | I33: =Alder!CC30 -> 300 | J33: =Alder!CD30 -> -251.9 | K33: =Alder!CE30 -> -1230.4
B34: Beacon Hi-Vis | C34: =Beacon!BU30 -> -76 | D34: =Beacon!BV30 -> -434.8 | E34: =Beacon!BW30 -> -863.9 | F34: =Beacon!BY30 -> -30 | G34: =Beacon!BZ30 -> -233 | H34: =Beacon!CA30 -> -364.9 | I34: =Beacon!CC30 -> -106 | J34: =Beacon!CD30 -> -667.8 | K34: =Beacon!CE30 -> -1228.8
B35: Cobalt Eyewear | C35: =Cobalt!BU30 -> 6 | D35: =Cobalt!BV30 -> -85.3 | E35: =Cobalt!BW30 -> -285 | F35: =Cobalt!BY30 -> -36 | G35: =Cobalt!BZ30 -> -30 | H35: =Cobalt!CA30 -> -101.5 | I35: =Cobalt!CC30 -> -30 | J35: =Cobalt!CD30 -> -115.3 | K35: =Cobalt!CE30 -> -386.5
B36: Delta Welding Supply | C36: =Delta!BU30 -> 0 | D36: =Delta!BV30 -> 78.5 | E36: =Delta!BW30 -> -53.8 | F36: =Delta!BY30 -> 0 | G36: =Delta!BZ30 -> 33.1 | H36: =Delta!CA30 -> -9.8 | I36: =Delta!CC30 -> 0 | J36: =Delta!CD30 -> 111.6 | K36: =Delta!CE30 -> -63.6
B37: Ember Workwear | C37: =Ember!BU30 -> 10 | D37: =Ember!BV30 -> 173.1 | E37: =Ember!BW30 -> 13.3 | F37: =Ember!BY30 -> 30 | G37: =Ember!BZ30 -> 105.3 | H37: =Ember!CA30 -> 48 | I37: =Ember!CC30 -> 40 | J37: =Ember!CD30 -> 278.4 | K37: =Ember!CE30 -> 61.3
B38: Falcon Hand Protection | C38: =Falcon!BU30 -> -110 | D38: =Falcon!BV30 -> -662.9 | E38: =Falcon!BW30 -> -1166.4 | F38: =Falcon!BY30 -> -40 | G38: =Falcon!BZ30 -> -283.2 | H38: =Falcon!CA30 -> -466.9 | I38: =Falcon!CC30 -> -150 | J38: =Falcon!CD30 -> -946.1 | K38: =Falcon!CE30 -> -1633.3
B39: Granite Gloves | C39: =Granite!BU30 -> 42 | D39: =Granite!BV30 -> 254.5 | E39: =Granite!BW30 -> 48.4 | F39: =Granite!BY30 -> 132 | G39: =Granite!BZ30 -> 219.7 | H39: =Granite!CA30 -> 161.4 | I39: =Granite!CC30 -> 174 | J39: =Granite!CD30 -> 474.2 | K39: =Granite!CE30 -> 209.8
B40: Hollis Rainwear | C40: =Hollis!BU30 -> 39 | D40: =Hollis!BV30 -> 215.7 | E40: =Hollis!BW30 -> -267.2 | F40: =Hollis!BY30 -> 507 | G40: =Hollis!BZ30 -> 635.3 | H40: =Hollis!CA30 -> 463.6 | I40: =Hollis!CC30 -> 546 | J40: =Hollis!CD30 -> 851 | K40: =Hollis!CE30 -> 196.4
B41: Safety Region (regional office) | C41: =SAFEREG!BU30 -> 0 | D41: =SAFEREG!BV30 -> 1.8 | E41: =SAFEREG!BW30 -> -94.8 | F41: =SAFEREG!BY30 -> 0 | G41: =SAFEREG!BZ30 -> 2.8 | H41: =SAFEREG!CA30 -> -36.8 | I41: =SAFEREG!CC30 -> 0 | J41: =SAFEREG!CD30 -> 4.6 | K41: =SAFEREG!CE30 -> -131.6
B42: Total Zava Safety | C42: =SUM(C33:C41) -> 151 | D42: =SUM(D33:D41) -> -634.1 | E42: =SUM(E33:E41) -> -3569 | F42: =SUM(F33:F41) -> 623 | G42: =SUM(G33:G41) -> 372.8 | H42: =SUM(H33:H41) -> -637.7 | I42: =SUM(I33:I41) -> 774 | J42: =SUM(J33:J41) -> -261.3 | K42: =SUM(K33:K41) -> -4206.7
B44: PBITA
B45: Alder Gloves | C45: =Alder!BU31 -> 80 | D45: =Alder!BV31 -> -650.4 | E45: =Alder!BW31 -> -776.1 | F45: =Alder!BY31 -> -360 | G45: =Alder!BZ31 -> -1178.2 | H45: =Alder!CA31 -> -1240.4 | I45: =Alder!CC31 -> -280 | J45: =Alder!CD31 -> -1828.6 | K45: =Alder!CE31 -> -2016.5
B46: Beacon Hi-Vis | C46: =Beacon!BU31 -> -16 | D46: =Beacon!BV31 -> 1936.1 | E46: =Beacon!BW31 -> 3002.9 | F46: =Beacon!BY31 -> 260 | G46: =Beacon!BZ31 -> 1068.7 | H46: =Beacon!CA31 -> 1512.4 | I46: =Beacon!CC31 -> 244 | J46: =Beacon!CD31 -> 3004.8 | K46: =Beacon!CE31 -> 4515.3
B47: Cobalt Eyewear | C47: =Cobalt!BU31 -> -156 | D47: =Cobalt!BV31 -> -683.7 | E47: =Cobalt!BW31 -> -31.4 | F47: =Cobalt!BY31 -> -684 | G47: =Cobalt!BZ31 -> -863.5 | H47: =Cobalt!CA31 -> -676.9 | I47: =Cobalt!CC31 -> -840 | J47: =Cobalt!CD31 -> -1547.2 | K47: =Cobalt!CE31 -> -708.3
B48: Delta Welding Supply | C48: =Delta!BU31 -> 0 | D48: =Delta!BV31 -> -131.2 | E48: =Delta!BW31 -> 18.4 | F48: =Delta!BY31 -> 0 | G48: =Delta!BZ31 -> -61.6 | H48: =Delta!CA31 -> -15 | I48: =Delta!CC31 -> 0 | J48: =Delta!CD31 -> -192.8 | K48: =Delta!CE31 -> 3.4
B49: Ember Workwear | C49: =Ember!BU31 -> -73 | D49: =Ember!BV31 -> -459.9 | E49: =Ember!BW31 -> -127.2 | F49: =Ember!BY31 -> -47 | G49: =Ember!BZ31 -> -258.2 | H49: =Ember!CA31 -> -190.1 | I49: =Ember!CC31 -> -120 | J49: =Ember!CD31 -> -718.1 | K49: =Ember!CE31 -> -317.3
B50: Falcon Hand Protection | C50: =Falcon!BU31 -> 10 | D50: =Falcon!BV31 -> 2433.2 | E50: =Falcon!BW31 -> 3620.9 | F50: =Falcon!BY31 -> 320 | G50: =Falcon!BZ31 -> 1324.4 | H50: =Falcon!CA31 -> 1681 | I50: =Falcon!CC31 -> 330 | J50: =Falcon!CD31 -> 3757.6 | K50: =Falcon!CE31 -> 5301.9
B51: Granite Gloves | C51: =Granite!BU31 -> -223 | D51: =Granite!BV31 -> -1385.4 | E51: =Granite!BW31 -> -1468.9 | F51: =Granite!BY31 -> -128 | G51: =Granite!BZ31 -> -492.5 | H51: =Granite!CA31 -> -507.5 | I51: =Granite!CC31 -> -351 | J51: =Granite!CD31 -> -1877.9 | K51: =Granite!CE31 -> -1976.4
B52: Hollis Rainwear | C52: =Hollis!BU31 -> 281 | D52: =Hollis!BV31 -> 423.2 | E52: =Hollis!BW31 -> 1042.8 | F52: =Hollis!BY31 -> 513 | G52: =Hollis!BZ31 -> 685.3 | H52: =Hollis!CA31 -> 821.5 | I52: =Hollis!CC31 -> 794 | J52: =Hollis!CD31 -> 1108.5 | K52: =Hollis!CE31 -> 1864.3
B53: Safety Region (regional office) | C53: =SAFEREG!BU31 -> 0 | D53: =SAFEREG!BV31 -> 1.8 | E53: =SAFEREG!BW31 -> -94.8 | F53: =SAFEREG!BY31 -> 0 | G53: =SAFEREG!BZ31 -> 2.8 | H53: =SAFEREG!CA31 -> -36.8 | I53: =SAFEREG!CC31 -> 0 | J53: =SAFEREG!CD31 -> 4.6 | K53: =SAFEREG!CE31 -> -131.6
B54: Total Zava Safety | C54: =SUM(C45:C53) -> -97 | D54: =SUM(D45:D53) -> 1483.7 | E54: =SUM(E45:E53) -> 5186.6 | F54: =SUM(F45:F53) -> -126 | G54: =SUM(G45:G53) -> 227.2 | H54: =SUM(H45:H53) -> 1348.2 | I54: =SUM(I45:I53) -> -223 | J54: =SUM(J45:J53) -> 1710.9 | K54: =SUM(K45:K53) -> 6534.8

Sheet Exec Smry Safety
A1: Index | B1: Division | C1: Zava Safety
D2: TRAINING DATA ONLY - Zava Safety and all business names and numbers are fictitious. Layout mirrors a typical HFM / Cognos reporting pack.
F3: FCAST09 | I3: FCAST10 vs. FCAST09 | O3: FCAST10
F4: FY26 | I4: September | L4: Rest of Year | O4: FY26 | R4: Check vs. sum of businesses
D7: Sales | F7: =Safety!O28 -> 633766.9 | I7: =Safety!BO28-Safety!K28 -> 1445 | L7: =SUM(Safety!BP28:BR28)-SUM(Safety!L28:N28) -> -1055 | O7: =Safety!BS28 -> 634156.9 | R7: =ROUND(O7-(Alder!BS28+Beacon!BS28+Cobalt!BS28+Delta!BS28+Ember!BS28+Falcon!BS28+Granite!BS28+Hollis!BS28+SAFEREG!BS28),1) -> 0
D9: Gross Margin | F9: =Safety!O29 -> 197718.7 | I9: =Safety!BO29-Safety!K29 -> -85.92 | L9: =SUM(Safety!BP29:BR29)-SUM(Safety!L29:N29) -> -100.76 | O9: =Safety!BS29 -> 197532.02 | R9: =ROUND(O9-(Alder!BS29+Beacon!BS29+Cobalt!BS29+Delta!BS29+Ember!BS29+Falcon!BS29+Granite!BS29+Hollis!BS29+SAFEREG!BS29),1) -> 810.3
D10: % / Leverage | F10: =IFERROR(F9/F7,0) -> 0.31197385 | I10: =IFERROR(I9/I7,0) -> -0.059460208 | L10: =IFERROR(L9/L7,0) -> 0.095507109 | O10: =IFERROR(O9/O7,0) -> 0.31148761
D12: Op Costs | F12: =Safety!O30 -> -135761.7 | I12: =Safety!BO30-Safety!K30 -> 151 | L12: =SUM(Safety!BP30:BR30)-SUM(Safety!L30:N30) -> 623 | O12: =Safety!BS30 -> -134987.7 | R12: =ROUND(O12-(Alder!BS30+Beacon!BS30+Cobalt!BS30+Delta!BS30+Ember!BS30+Falcon!BS30+Granite!BS30+Hollis!BS30+SAFEREG!BS30),1) -> 0
D13: % / Leverage | F13: =IFERROR(F12/F7,0) -> -0.21421393 | I13: =IFERROR(I12/I7,0) -> 0.10449827 | L13: =IFERROR(L12/L7,0) -> -0.59052133 | O13: =IFERROR(O12/O7,0) -> -0.21286168
D15: PBITA | F15: =Safety!O31 -> 61957 | I15: =Safety!BO31-Safety!K31 -> 65.08 | L15: =SUM(Safety!BP31:BR31)-SUM(Safety!L31:N31) -> 522.24 | O15: =Safety!BS31 -> 62544.32 | R15: =ROUND(O15-(Alder!BS31+Beacon!BS31+Cobalt!BS31+Delta!BS31+Ember!BS31+Falcon!BS31+Granite!BS31+Hollis!BS31+SAFEREG!BS31),1) -> 810.3
D16: % / Leverage | F16: =IFERROR(F15/F7,0) -> 0.097759918 | I16: =IFERROR(I15/I7,0) -> 0.045038062 | L16: =IFERROR(L15/L7,0) -> -0.49501422 | O16: =IFERROR(O15/O7,0) -> 0.098625939
F18: Budget | I18: FCAST10 vs. Budget | L18: Actual | O18: FCAST10 vs. FY25
F19: FY26 | L19: FY25
C22: Sales | F22: =Safety!O51 -> 619998.1 | I22: =O7-F22 -> 14158.8 | L22: =Safety!O64 -> 591912.4 | O22: =O7-L22 -> 42244.5
C24: Gross Margin | F24: =Safety!O52 -> 194749.5 | I24: =O9-F24 -> 2782.52 | L24: =Safety!O65 -> 185980.2 | O24: =O9-L24 -> 11551.82
C25: % | F25: =IFERROR(F24/F22,0) -> 0.31411306 | L25: =IFERROR(L24/L22,0) -> 0.31420224
C27: Op Costs | F27: =Safety!O53 -> -134726.4 | I27: =O12-F27 -> -261.3 | L27: =Safety!O66 -> -130781 | O27: =O12-L27 -> -4206.7
C28: % | F28: =IFERROR(F27/F22,0) -> -0.21730131 | L28: =IFERROR(L27/L22,0) -> -0.22094655
C30: PBITA | F30: =Safety!O54 -> 60023.1 | I30: =O15-F30 -> 2521.22 | L30: =Safety!O67 -> 55199.2 | O30: =O15-L30 -> 7345.12
C31: % | F31: =IFERROR(F30/F22,0) -> 0.096811748 | L31: =IFERROR(L30/L22,0) -> 0.093255691

Sheet Safety-Var
A1: Current ME | B1: P09 | D1: Zava Safety - Consolidated
A2: Next ME | B2: P10 | D2: TRAINING DATA ONLY - Zava Safety and all business names and numbers are fictitious. Layout mirrors a typical HFM / Cognos reporting pack.
C4: FCAST10
C5: Through Sep | F5: Rest of Year | I5: Full Year
B6: Favorable / (Unfavorable) | C6: Actual vs. FCAST09 | D6: Actual vs. Bud | E6: Actual vs. PY | F6: FCAST10 vs. FCAST09 | G6: FCAST10 vs. Bud | H6: FCAST10 vs. PY | I6: FCAST10 vs. FCAST09 | J6: FCAST10 vs. Bud | K6: FCAST10 vs. PY
B8: Sales | C8: =Safety!BU28 -> 1445 | D8: =Safety!BV28 -> 10937.5 | E8: =Safety!BW28 -> 32001.3 | F8: =Safety!BY28 -> -1055 | G8: =Safety!BZ28 -> 3221.3 | H8: =Safety!CA28 -> 10243.2 | I8: =Safety!CC28 -> 390 | J8: =Safety!CD28 -> 14158.8 | K8: =Safety!CE28 -> 42244.5
B10: Gross Margin | C10: =Safety!BU29 -> -85.92 | D10: =Safety!BV29 -> 2279.88 | E10: =Safety!BW29 -> 8917.68 | F10: =Safety!BY29 -> -100.76 | G10: =Safety!BZ29 -> 502.64 | H10: =Safety!CA29 -> 2634.14 | I10: =Safety!CC29 -> -186.68 | J10: =Safety!CD29 -> 2782.52 | K10: =Safety!CE29 -> 11551.82
B12: Op Costs | C12: =Safety!BU30 -> 151 | D12: =Safety!BV30 -> -634.1 | E12: =Safety!BW30 -> -3569 | F12: =Safety!BY30 -> 623 | G12: =Safety!BZ30 -> 372.8 | H12: =Safety!CA30 -> -637.7 | I12: =Safety!CC30 -> 774 | J12: =Safety!CD30 -> -261.3 | K12: =Safety!CE30 -> -4206.7
B14: PBITA | C14: =Safety!BU31 -> 65.08 | D14: =Safety!BV31 -> 1645.78 | E14: =Safety!BW31 -> 5348.68 | F14: =Safety!BY31 -> 522.24 | G14: =Safety!BZ31 -> 875.44 | H14: =Safety!CA31 -> 1996.44 | I14: =Safety!CC31 -> 587.32 | J14: =Safety!CD31 -> 2521.22 | K14: =Safety!CE31 -> 7345.12
B17: Commentary (business controller):

Sheet Safety-Adj
A1: Index | C1: 46053 | D1: 46081 | E1: 46112 | F1: 46142 | G1: 46173 | H1: 46203 | I1: 46234 | J1: 46265 | K1: 46295 | L1: 46326 | M1: 46356 | N1: 46387
B2: Section 1: Adjustments tied to individual events (i.e., new customer, modified sales contract, new/lost customer):
B3: TRAINING DATA ONLY - Zava Safety and all business names and numbers are fictitious. Layout mirrors a typical HFM / Cognos reporting pack.
C4: January | D4: February | E4: March | F4: April | G4: May | H4: June | I4: July | J4: August | K4: September | L4: October | M4: November | N4: December | O4: Total Adjustments | Q4: YTG
B5: Sales
B6: Alder Gloves | C6: ='Alder-Adj'!C$14 -> 0 | D6: ='Alder-Adj'!D$14 -> 0 | E6: ='Alder-Adj'!E$14 -> 0 | F6: ='Alder-Adj'!F$14 -> 0 | G6: ='Alder-Adj'!G$14 -> 0 | H6: ='Alder-Adj'!H$14 -> 0 | I6: ='Alder-Adj'!I$14 -> 0 | J6: ='Alder-Adj'!J$14 -> 0 | ... N6: ='Alder-Adj'!N$14 -> -200 | O6: =SUM(C6:N6) -> -600 | Q6: =SUM(L6:N6) -> -600
B7: Beacon Hi-Vis | C7: ='Beacon-Adj'!C$14 -> 0 | D7: ='Beacon-Adj'!D$14 -> 0 | E7: ='Beacon-Adj'!E$14 -> 0 | F7: ='Beacon-Adj'!F$14 -> 0 | G7: ='Beacon-Adj'!G$14 -> 0 | H7: ='Beacon-Adj'!H$14 -> 0 | I7: ='Beacon-Adj'!I$14 -> 0 | J7: ='Beacon-Adj'!J$14 -> 0 | ... N7: ='Beacon-Adj'!N$14 -> 200 | O7: =SUM(C7:N7) -> 900 | Q7: =SUM(L7:N7) -> 750
B8: Cobalt Eyewear | C8: ='Cobalt-Adj'!C$14 -> 0 | D8: ='Cobalt-Adj'!D$14 -> 0 | E8: ='Cobalt-Adj'!E$14 -> 0 | F8: ='Cobalt-Adj'!F$14 -> 0 | G8: ='Cobalt-Adj'!G$14 -> 0 | H8: ='Cobalt-Adj'!H$14 -> 0 | I8: ='Cobalt-Adj'!I$14 -> 0 | J8: ='Cobalt-Adj'!J$14 -> 0 | ... N8: ='Cobalt-Adj'!N$14 -> 40 | O8: =SUM(C8:N8) -> 150 | Q8: =SUM(L8:N8) -> 120
B9: Delta Welding Supply | C9: ='Delta-Adj'!C$14 -> 0 | D9: ='Delta-Adj'!D$14 -> 0 | E9: ='Delta-Adj'!E$14 -> 0 | F9: ='Delta-Adj'!F$14 -> 0 | G9: ='Delta-Adj'!G$14 -> 0 | H9: ='Delta-Adj'!H$14 -> 0 | I9: ='Delta-Adj'!I$14 -> 0 | J9: ='Delta-Adj'!J$14 -> 0 | ... N9: ='Delta-Adj'!N$14 -> 0 | O9: =SUM(C9:N9) -> 0 | Q9: =SUM(L9:N9) -> 0
B10: Ember Workwear | C10: ='Ember-Adj'!C$14 -> 0 | D10: ='Ember-Adj'!D$14 -> 0 | E10: ='Ember-Adj'!E$14 -> 0 | F10: ='Ember-Adj'!F$14 -> 0 | G10: ='Ember-Adj'!G$14 -> 0 | H10: ='Ember-Adj'!H$14 -> 0 | I10: ='Ember-Adj'!I$14 -> 0 | J10: ='Ember-Adj'!J$14 -> 0 | ... N10: ='Ember-Adj'!N$14 -> 0 | O10: =SUM(C10:N10) -> -500 | Q10: =SUM(L10:N10) -> -240
B11: Falcon Hand Protection | C11: ='Falcon-Adj'!C$14 -> 0 | D11: ='Falcon-Adj'!D$14 -> 0 | E11: ='Falcon-Adj'!E$14 -> 0 | F11: ='Falcon-Adj'!F$14 -> 0 | G11: ='Falcon-Adj'!G$14 -> 0 | H11: ='Falcon-Adj'!H$14 -> 0 | I11: ='Falcon-Adj'!I$14 -> 0 | J11: ='Falcon-Adj'!J$14 -> 0 | ... N11: ='Falcon-Adj'!N$14 -> 300 | O11: =SUM(C11:N11) -> 1200 | Q11: =SUM(L11:N11) -> 900
B12: Granite Gloves | C12: ='Granite-Adj'!C$14 -> 0 | D12: ='Granite-Adj'!D$14 -> 0 | E12: ='Granite-Adj'!E$14 -> 0 | F12: ='Granite-Adj'!F$14 -> 0 | G12: ='Granite-Adj'!G$14 -> 0 | H12: ='Granite-Adj'!H$14 -> 0 | I12: ='Granite-Adj'!I$14 -> 0 | J12: ='Granite-Adj'!J$14 -> 0 | ... N12: ='Granite-Adj'!N$14 -> -300 | O12: =SUM(C12:N12) -> -1180 | Q12: =SUM(L12:N12) -> -750
B13: Hollis Rainwear | C13: ='Hollis-Adj'!C$14 -> 0 | D13: ='Hollis-Adj'!D$14 -> 0 | E13: ='Hollis-Adj'!E$14 -> 0 | F13: ='Hollis-Adj'!F$14 -> 0 | G13: ='Hollis-Adj'!G$14 -> 0 | H13: ='Hollis-Adj'!H$14 -> 0 | I13: ='Hollis-Adj'!I$14 -> 0 | J13: ='Hollis-Adj'!J$14 -> 0 | ... N13: ='Hollis-Adj'!N$14 -> 300 | O13: =SUM(C13:N13) -> 600 | Q13: =SUM(L13:N13) -> -1100
B14: SAFEREG | C14: ='SAFEREG-Adj'!C$14 -> 0 | D14: ='SAFEREG-Adj'!D$14 -> 0 | E14: ='SAFEREG-Adj'!E$14 -> 0 | F14: ='SAFEREG-Adj'!F$14 -> 0 | G14: ='SAFEREG-Adj'!G$14 -> 0 | H14: ='SAFEREG-Adj'!H$14 -> 0 | I14: ='SAFEREG-Adj'!I$14 -> 0 | J14: ='SAFEREG-Adj'!J$14 -> 0 | ... N14: ='SAFEREG-Adj'!N$14 -> 0 | O14: =SUM(C14:N14) -> 0 | Q14: =SUM(L14:N14) -> 0
B15: Total Sales | C15: =SUM(C6:C14) -> 0 | D15: =SUM(D6:D14) -> 0 | E15: =SUM(E6:E14) -> 0 | F15: =SUM(F6:F14) -> 0 | G15: =SUM(G6:G14) -> 0 | H15: =SUM(H6:H14) -> 0 | I15: =SUM(I6:I14) -> 0 | J15: =SUM(J6:J14) -> 0 | ... O15: =SUM(O6:O14) -> 570 | Q15: =SUM(L15:N15) -> -920
B17: Gross Margin (%)
B18: Alder Gloves | C18: =IFERROR(C30/C6,"-") -> - | D18: =IFERROR(D30/D6,"-") -> - | E18: =IFERROR(E30/E6,"-") -> - | F18: =IFERROR(F30/F6,"-") -> - | G18: =IFERROR(G30/G6,"-") -> - | H18: =IFERROR(H30/H6,"-") -> - | I18: =IFERROR(I30/I6,"-") -> - | J18: =IFERROR(J30/J6,"-") -> - | ... O18: =IFERROR(O30/O6,"-") -> 0.96666667
B19: Beacon Hi-Vis | C19: =IFERROR(C31/C7,"-") -> - | D19: =IFERROR(D31/D7,"-") -> - | E19: =IFERROR(E31/E7,"-") -> - | F19: =IFERROR(F31/F7,"-") -> - | G19: =IFERROR(G31/G7,"-") -> - | H19: =IFERROR(H31/H7,"-") -> - | I19: =IFERROR(I31/I7,"-") -> - | J19: =IFERROR(J31/J7,"-") -> - | ... O19: =IFERROR(O31/O7,"-") -> 0.38888889
B20: Cobalt Eyewear | C20: =IFERROR(C32/C8,"-") -> - | D20: =IFERROR(D32/D8,"-") -> - | E20: =IFERROR(E32/E8,"-") -> - | F20: =IFERROR(F32/F8,"-") -> - | G20: =IFERROR(G32/G8,"-") -> - | H20: =IFERROR(H32/H8,"-") -> - | I20: =IFERROR(I32/I8,"-") -> - | J20: =IFERROR(J32/J8,"-") -> - | ... O20: =IFERROR(O32/O8,"-") -> 0.0021333333
B21: Delta Welding Supply | C21: =IFERROR(C33/C9,"-") -> - | D21: =IFERROR(D33/D9,"-") -> - | E21: =IFERROR(E33/E9,"-") -> - | F21: =IFERROR(F33/F9,"-") -> - | G21: =IFERROR(G33/G9,"-") -> - | H21: =IFERROR(H33/H9,"-") -> - | I21: =IFERROR(I33/I9,"-") -> - | J21: =IFERROR(J33/J9,"-") -> - | ... O21: =IFERROR(O33/O9,"-") -> -
B22: Ember Workwear | C22: =IFERROR(C34/C10,"-") -> - | D22: =IFERROR(D34/D10,"-") -> - | E22: =IFERROR(E34/E10,"-") -> - | F22: =IFERROR(F34/F10,"-") -> - | G22: =IFERROR(G34/G10,"-") -> - | H22: =IFERROR(H34/H10,"-") -> - | I22: =IFERROR(I34/I10,"-") -> - | J22: =IFERROR(J34/J10,"-") -> - | ... O22: =IFERROR(O34/O10,"-") -> 0.32
B23: Falcon Hand Protection | C23: =IFERROR(C35/C11,"-") -> - | D23: =IFERROR(D35/D11,"-") -> - | E23: =IFERROR(E35/E11,"-") -> - | F23: =IFERROR(F35/F11,"-") -> - | G23: =IFERROR(G35/G11,"-") -> - | H23: =IFERROR(H35/H11,"-") -> - | I23: =IFERROR(I35/I11,"-") -> - | J23: =IFERROR(J35/J11,"-") -> - | ... O23: =IFERROR(O35/O11,"-") -> 0.4
B24: Granite Gloves | C24: =IFERROR(C36/C12,"-") -> - | D24: =IFERROR(D36/D12,"-") -> - | E24: =IFERROR(E36/E12,"-") -> - | F24: =IFERROR(F36/F12,"-") -> - | G24: =IFERROR(G36/G12,"-") -> - | H24: =IFERROR(H36/H12,"-") -> - | I24: =IFERROR(I36/I12,"-") -> - | J24: =IFERROR(J36/J12,"-") -> - | ... O24: =IFERROR(O36/O12,"-") -> 0.44491525
B25: Hollis Rainwear | C25: =IFERROR(C37/C13,"-") -> - | D25: =IFERROR(D37/D13,"-") -> - | E25: =IFERROR(E37/E13,"-") -> - | F25: =IFERROR(F37/F13,"-") -> - | G25: =IFERROR(G37/G13,"-") -> - | H25: =IFERROR(H37/H13,"-") -> - | I25: =IFERROR(I37/I13,"-") -> - | J25: =IFERROR(J37/J13,"-") -> - | ... O25: =IFERROR(O37/O13,"-") -> 0.5
B26: SAFEREG | C26: =IFERROR(C38/C14,"-") -> - | D26: =IFERROR(D38/D14,"-") -> - | E26: =IFERROR(E38/E14,"-") -> - | F26: =IFERROR(F38/F14,"-") -> - | G26: =IFERROR(G38/G14,"-") -> - | H26: =IFERROR(H38/H14,"-") -> - | I26: =IFERROR(I38/I14,"-") -> - | J26: =IFERROR(J38/J14,"-") -> - | ... O26: =IFERROR(O38/O14,"-") -> -
B27: Total Gross Margin (%) | C27: =IFERROR(C39/C15,"-") -> - | D27: =IFERROR(D39/D15,"-") -> - | E27: =IFERROR(E39/E15,"-") -> - | F27: =IFERROR(F39/F15,"-") -> - | G27: =IFERROR(G39/G15,"-") -> - | H27: =IFERROR(H39/H15,"-") -> - | I27: =IFERROR(I39/I15,"-") -> - | J27: =IFERROR(J39/J15,"-") -> - | ... O27: =IFERROR(O39/O15,"-") -> -0.2362807
B29: Gross Margin ($)
B30: Alder Gloves | C30: ='Alder-Adj'!C$36 -> 0 | D30: ='Alder-Adj'!D$36 -> 0 | E30: ='Alder-Adj'!E$36 -> 0 | F30: ='Alder-Adj'!F$36 -> 0 | G30: ='Alder-Adj'!G$36 -> 0 | H30: ='Alder-Adj'!H$36 -> 0 | I30: ='Alder-Adj'!I$36 -> 0 | J30: ='Alder-Adj'!J$36 -> 0 | ... N30: ='Alder-Adj'!N$36 -> -140 | O30: =SUM(C30:N30) -> -580 | Q30: =SUM(L30:N30) -> -420
B31: Beacon Hi-Vis | C31: ='Beacon-Adj'!C$36 -> 0 | D31: ='Beacon-Adj'!D$36 -> 0 | E31: ='Beacon-Adj'!E$36 -> 0 | F31: ='Beacon-Adj'!F$36 -> 0 | G31: ='Beacon-Adj'!G$36 -> 0 | H31: ='Beacon-Adj'!H$36 -> 0 | I31: ='Beacon-Adj'!I$36 -> 0 | J31: ='Beacon-Adj'!J$36 -> 0 | ... N31: ='Beacon-Adj'!N$36 -> 80 | O31: =SUM(C31:N31) -> 350 | Q31: =SUM(L31:N31) -> 290
B32: Cobalt Eyewear | C32: ='Cobalt-Adj'!C$39 -> 0 | D32: ='Cobalt-Adj'!D$39 -> 0 | E32: ='Cobalt-Adj'!E$39 -> 0 | H32: ='Cobalt-Adj'!H$39 -> 0 | I32: ='Cobalt-Adj'!I$39 -> 0 | J32: ='Cobalt-Adj'!J$39 -> 0 | K32: ='Cobalt-Adj'!K$39 -> 0.08 | L32: ='Cobalt-Adj'!L$39 -> 0.08 | M32: ='Cobalt-Adj'!M$39 -> 0.08 | N32: ='Cobalt-Adj'!N$39 -> 0.08 | O32: =SUM(C32:N32) -> 0.32 | Q32: =SUM(L32:N32) -> 0.24
B33: Delta Welding Supply | C33: ='Delta-Adj'!C$36 -> 0 | D33: ='Delta-Adj'!D$36 -> 0 | E33: ='Delta-Adj'!E$36 -> 0 | F33: ='Delta-Adj'!F$36 -> 0 | G33: ='Delta-Adj'!G$36 -> 0 | H33: ='Delta-Adj'!H$36 -> 0 | I33: ='Delta-Adj'!I$36 -> 0 | J33: ='Delta-Adj'!J$36 -> 0 | ... N33: ='Delta-Adj'!N$36 -> 0 | O33: =SUM(C33:N33) -> 0 | Q33: =SUM(L33:N33) -> 0
B34: Ember Workwear | C34: ='Ember-Adj'!C$36 -> 0 | D34: ='Ember-Adj'!D$36 -> 0 | E34: ='Ember-Adj'!E$36 -> 0 | F34: ='Ember-Adj'!F$36 -> 0 | G34: ='Ember-Adj'!G$36 -> 0 | H34: ='Ember-Adj'!H$36 -> 0 | I34: ='Ember-Adj'!I$36 -> 0 | J34: ='Ember-Adj'!J$36 -> 0 | ... N34: ='Ember-Adj'!N$36 -> 0 | O34: =SUM(C34:N34) -> -160 | Q34: =SUM(L34:N34) -> -77
B35: Falcon Hand Protection | C35: ='Falcon-Adj'!C$36 -> 0 | D35: ='Falcon-Adj'!D$36 -> 0 | E35: ='Falcon-Adj'!E$36 -> 0 | F35: ='Falcon-Adj'!F$36 -> 0 | G35: ='Falcon-Adj'!G$36 -> 0 | H35: ='Falcon-Adj'!H$36 -> 0 | I35: ='Falcon-Adj'!I$36 -> 0 | J35: ='Falcon-Adj'!J$36 -> 0 | ... N35: ='Falcon-Adj'!N$36 -> 120 | O35: =SUM(C35:N35) -> 480 | Q35: =SUM(L35:N35) -> 360
B36: Granite Gloves | C36: ='Granite-Adj'!C$36 -> 0 | D36: ='Granite-Adj'!D$36 -> 0 | E36: ='Granite-Adj'!E$36 -> 0 | F36: ='Granite-Adj'!F$36 -> 0 | G36: ='Granite-Adj'!G$36 -> 0 | H36: ='Granite-Adj'!H$36 -> 0 | I36: ='Granite-Adj'!I$36 -> 0 | J36: ='Granite-Adj'!J$36 -> 0 | ... N36: ='Granite-Adj'!N$36 -> -31 | O36: =SUM(C36:N36) -> -525 | Q36: =SUM(L36:N36) -> -260
B37: Hollis Rainwear | C37: ='Hollis-Adj'!C$36 -> 0 | D37: ='Hollis-Adj'!D$36 -> 0 | E37: ='Hollis-Adj'!E$36 -> 0 | F37: ='Hollis-Adj'!F$36 -> 0 | G37: ='Hollis-Adj'!G$36 -> 0 | H37: ='Hollis-Adj'!H$36 -> 0 | I37: ='Hollis-Adj'!I$36 -> 0 | J37: ='Hollis-Adj'!J$36 -> 0 | ... N37: ='Hollis-Adj'!N$36 -> 210 | O37: =SUM(C37:N37) -> 300 | Q37: =SUM(L37:N37) -> 45
B38: SAFEREG | C38: ='SAFEREG-Adj'!C$36 -> 0 | D38: ='SAFEREG-Adj'!D$36 -> 0 | E38: ='SAFEREG-Adj'!E$36 -> 0 | F38: ='SAFEREG-Adj'!F$36 -> 0 | G38: ='SAFEREG-Adj'!G$36 -> 0 | H38: ='SAFEREG-Adj'!H$36 -> 0 | I38: ='SAFEREG-Adj'!I$36 -> 0 | J38: ='SAFEREG-Adj'!J$36 -> 0 | ... N38: ='SAFEREG-Adj'!N$36 -> 0 | O38: =SUM(C38:N38) -> 0 | Q38: =SUM(L38:N38) -> 0
B39: Total Gross Margin ($) | C39: =SUM(C30:C38) -> 0 | D39: =SUM(D30:D38) -> 0 | E39: =SUM(E30:E38) -> 0 | F39: =SUM(F30:F38) -> 0 | G39: =SUM(G30:G38) -> 0 | H39: =SUM(H30:H38) -> 0 | I39: =SUM(I30:I38) -> 0 | J39: =SUM(J30:J38) -> 0 | ... O39: =SUM(O30:O38) -> -134.68 | Q39: =SUM(L39:N39) -> -61.76
B41: Op Costs (%)
B42: Alder Gloves | C42: =IFERROR(C54/C6,"-") -> - | D42: =IFERROR(D54/D6,"-") -> - | E42: =IFERROR(E54/E6,"-") -> - | F42: =IFERROR(F54/F6,"-") -> - | G42: =IFERROR(G54/G6,"-") -> - | H42: =IFERROR(H54/H6,"-") -> - | I42: =IFERROR(I54/I6,"-") -> - | J42: =IFERROR(J54/J6,"-") -> - | ... O42: =IFERROR(O54/O6,"-") -> 0.5
B43: Beacon Hi-Vis | C43: =IFERROR(C55/C7,"-") -> - | D43: =IFERROR(D55/D7,"-") -> - | E43: =IFERROR(E55/E7,"-") -> - | F43: =IFERROR(F55/F7,"-") -> - | G43: =IFERROR(G55/G7,"-") -> - | H43: =IFERROR(H55/H7,"-") -> - | I43: =IFERROR(I55/I7,"-") -> - | J43: =IFERROR(J55/J7,"-") -> - | ... O43: =IFERROR(O55/O7,"-") -> 0.11777778
B44: Cobalt Eyewear | C44: =IFERROR(C56/C8,"-") -> - | D44: =IFERROR(D56/D8,"-") -> - | E44: =IFERROR(E56/E8,"-") -> - | F44: =IFERROR(F56/F8,"-") -> - | G44: =IFERROR(G56/G8,"-") -> - | H44: =IFERROR(H56/H8,"-") -> - | I44: =IFERROR(I56/I8,"-") -> - | J44: =IFERROR(J56/J8,"-") -> - | ... O44: =IFERROR(O56/O8,"-") -> 0.2
B45: Delta Welding Supply | C45: =IFERROR(C57/C9,"-") -> - | D45: =IFERROR(D57/D9,"-") -> - | E45: =IFERROR(E57/E9,"-") -> - | F45: =IFERROR(F57/F9,"-") -> - | G45: =IFERROR(G57/G9,"-") -> - | H45: =IFERROR(H57/H9,"-") -> - | I45: =IFERROR(I57/I9,"-") -> - | J45: =IFERROR(J57/J9,"-") -> - | ... O45: =IFERROR(O57/O9,"-") -> -
B46: Ember Workwear | C46: =IFERROR(C58/C10,"-") -> - | D46: =IFERROR(D58/D10,"-") -> - | E46: =IFERROR(E58/E10,"-") -> - | F46: =IFERROR(F58/F10,"-") -> - | G46: =IFERROR(G58/G10,"-") -> - | H46: =IFERROR(H58/H10,"-") -> - | I46: =IFERROR(I58/I10,"-") -> - | J46: =IFERROR(J58/J10,"-") -> - | ... O46: =IFERROR(O58/O10,"-") -> 0.08
B47: Falcon Hand Protection | C47: =IFERROR(C59/C11,"-") -> - | D47: =IFERROR(D59/D11,"-") -> - | E47: =IFERROR(E59/E11,"-") -> - | F47: =IFERROR(F59/F11,"-") -> - | G47: =IFERROR(G59/G11,"-") -> - | H47: =IFERROR(H59/H11,"-") -> - | I47: =IFERROR(I59/I11,"-") -> - | J47: =IFERROR(J59/J11,"-") -> - | ... O47: =IFERROR(O59/O11,"-") -> 0.125
B48: Granite Gloves | C48: =IFERROR(C60/C12,"-") -> - | D48: =IFERROR(D60/D12,"-") -> - | E48: =IFERROR(E60/E12,"-") -> - | F48: =IFERROR(F60/F12,"-") -> - | G48: =IFERROR(G60/G12,"-") -> - | H48: =IFERROR(H60/H12,"-") -> - | I48: =IFERROR(I60/I12,"-") -> - | J48: =IFERROR(J60/J12,"-") -> - | ... O48: =IFERROR(O60/O12,"-") -> 0.14745763
B49: Hollis Rainwear | C49: =IFERROR(C61/C13,"-") -> - | D49: =IFERROR(D61/D13,"-") -> - | E49: =IFERROR(E61/E13,"-") -> - | F49: =IFERROR(F61/F13,"-") -> - | G49: =IFERROR(G61/G13,"-") -> - | H49: =IFERROR(H61/H13,"-") -> - | I49: =IFERROR(I61/I13,"-") -> - | J49: =IFERROR(J61/J13,"-") -> - | ... O49: =IFERROR(O61/O13,"-") -> -0.85
B50: SAFEREG | C50: =IFERROR(C62/C14,"-") -> - | D50: =IFERROR(D62/D14,"-") -> - | E50: =IFERROR(E62/E14,"-") -> - | F50: =IFERROR(F62/F14,"-") -> - | G50: =IFERROR(G62/G14,"-") -> - | H50: =IFERROR(H62/H14,"-") -> - | I50: =IFERROR(I62/I14,"-") -> - | J50: =IFERROR(J62/J14,"-") -> - | ... O50: =IFERROR(O62/O14,"-") -> -
B51: Total Op Costs (%) | C51: =IFERROR(C63/C15,"-") -> - | D51: =IFERROR(D63/D15,"-") -> - | E51: =IFERROR(E63/E15,"-") -> - | F51: =IFERROR(F63/F15,"-") -> - | G51: =IFERROR(G63/G15,"-") -> - | H51: =IFERROR(H63/H15,"-") -> - | I51: =IFERROR(I63/I15,"-") -> - | J51: =IFERROR(J63/J15,"-") -> - | ... O51: =IFERROR(O63/O15,"-") -> -1.2947368
B53: Op Costs ($)
B54: Alder Gloves | C54: ='Alder-Adj'!C$58 -> 0 | D54: ='Alder-Adj'!D$58 -> 0 | E54: ='Alder-Adj'!E$58 -> 0 | F54: ='Alder-Adj'!F$58 -> 0 | G54: ='Alder-Adj'!G$58 -> 0 | H54: ='Alder-Adj'!H$58 -> 0 | I54: ='Alder-Adj'!I$58 -> 0 | J54: ='Alder-Adj'!J$58 -> 0 | ... N54: ='Alder-Adj'!N$58 -> -20 | O54: =SUM(C54:N54) -> -300 | Q54: =SUM(L54:N54) -> -60
B55: Beacon Hi-Vis | C55: ='Beacon-Adj'!C$58 -> 0 | D55: ='Beacon-Adj'!D$58 -> 0 | E55: ='Beacon-Adj'!E$58 -> 0 | F55: ='Beacon-Adj'!F$58 -> 0 | G55: ='Beacon-Adj'!G$58 -> 0 | H55: ='Beacon-Adj'!H$58 -> 0 | I55: ='Beacon-Adj'!I$58 -> 0 | J55: ='Beacon-Adj'!J$58 -> 0 | ... N55: ='Beacon-Adj'!N$58 -> 8 | O55: =SUM(C55:N55) -> 106 | Q55: =SUM(L55:N55) -> 30
B56: Cobalt Eyewear | C56: ='Cobalt-Adj'!C$58 -> 0 | D56: ='Cobalt-Adj'!D$58 -> 0 | E56: ='Cobalt-Adj'!E$58 -> 0 | F56: ='Cobalt-Adj'!F$58 -> 0 | G56: ='Cobalt-Adj'!G$58 -> 0 | H56: ='Cobalt-Adj'!H$58 -> 0 | I56: ='Cobalt-Adj'!I$58 -> 0 | J56: ='Cobalt-Adj'!J$58 -> 0 | ... N56: ='Cobalt-Adj'!N$58 -> 12 | O56: =SUM(C56:N56) -> 30 | Q56: =SUM(L56:N56) -> 36
B57: Delta Welding Supply | C57: ='Delta-Adj'!C$58 -> 0 | D57: ='Delta-Adj'!D$58 -> 0 | E57: ='Delta-Adj'!E$58 -> 0 | F57: ='Delta-Adj'!F$58 -> 0 | G57: ='Delta-Adj'!G$58 -> 0 | H57: ='Delta-Adj'!H$58 -> 0 | I57: ='Delta-Adj'!I$58 -> 0 | J57: ='Delta-Adj'!J$58 -> 0 | ... N57: ='Delta-Adj'!N$58 -> 0 | O57: =SUM(C57:N57) -> 0 | Q57: =SUM(L57:N57) -> 0
B58: Ember Workwear | C58: ='Ember-Adj'!C$58 -> 0 | D58: ='Ember-Adj'!D$58 -> 0 | E58: ='Ember-Adj'!E$58 -> 0 | F58: ='Ember-Adj'!F$58 -> 0 | G58: ='Ember-Adj'!G$58 -> 0 | H58: ='Ember-Adj'!H$58 -> 0 | I58: ='Ember-Adj'!I$58 -> 0 | J58: ='Ember-Adj'!J$58 -> 0 | ... N58: ='Ember-Adj'!N$58 -> -10 | O58: =SUM(C58:N58) -> -40 | Q58: =SUM(L58:N58) -> -30
B59: Falcon Hand Protection | C59: ='Falcon-Adj'!C$58 -> 0 | D59: ='Falcon-Adj'!D$58 -> 0 | E59: ='Falcon-Adj'!E$58 -> 0 | F59: ='Falcon-Adj'!F$58 -> 0 | G59: ='Falcon-Adj'!G$58 -> 0 | H59: ='Falcon-Adj'!H$58 -> 0 | I59: ='Falcon-Adj'!I$58 -> 0 | J59: ='Falcon-Adj'!J$58 -> 0 | ... N59: ='Falcon-Adj'!N$58 -> 10 | O59: =SUM(C59:N59) -> 150 | Q59: =SUM(L59:N59) -> 40
B60: Granite Gloves | C60: ='Granite-Adj'!C$58 -> 0 | D60: ='Granite-Adj'!D$58 -> 0 | E60: ='Granite-Adj'!E$58 -> 0 | F60: ='Granite-Adj'!F$58 -> 0 | G60: ='Granite-Adj'!G$58 -> 0 | H60: ='Granite-Adj'!H$58 -> 0 | I60: ='Granite-Adj'!I$58 -> 0 | J60: ='Granite-Adj'!J$58 -> 0 | ... N60: ='Granite-Adj'!N$58 -> -47 | O60: =SUM(C60:N60) -> -174 | Q60: =SUM(L60:N60) -> -132
B61: Hollis Rainwear | C61: ='Hollis-Adj'!C$58 -> 0 | D61: ='Hollis-Adj'!D$58 -> 0 | E61: ='Hollis-Adj'!E$58 -> 0 | F61: ='Hollis-Adj'!F$58 -> 0 | G61: ='Hollis-Adj'!G$58 -> 0 | H61: ='Hollis-Adj'!H$58 -> 0 | I61: ='Hollis-Adj'!I$58 -> 0 | J61: ='Hollis-Adj'!J$58 -> 0 | ... N61: ='Hollis-Adj'!N$58 -> -180 | O61: =SUM(C61:N61) -> -510 | Q61: =SUM(L61:N61) -> -480
B62: SAFEREG | C62: ='SAFEREG-Adj'!C$58 -> 0 | D62: ='SAFEREG-Adj'!D$58 -> 0 | E62: ='SAFEREG-Adj'!E$58 -> 0 | F62: ='SAFEREG-Adj'!F$58 -> 0 | G62: ='SAFEREG-Adj'!G$58 -> 0 | H62: ='SAFEREG-Adj'!H$58 -> 0 | I62: ='SAFEREG-Adj'!I$58 -> 0 | J62: ='SAFEREG-Adj'!J$58 -> 0 | ... N62: ='SAFEREG-Adj'!N$58 -> 0 | O62: =SUM(C62:N62) -> 0 | Q62: =SUM(L62:N62) -> 0
B63: Total Op Costs ($) | C63: =SUM(C54:C62) -> 0 | D63: =SUM(D54:D62) -> 0 | E63: =SUM(E54:E62) -> 0 | F63: =SUM(F54:F62) -> 0 | G63: =SUM(G54:G62) -> 0 | H63: =SUM(H54:H62) -> 0 | I63: =SUM(I54:I62) -> 0 | J63: =SUM(J54:J62) -> 0 | ... O63: =SUM(O54:O62) -> -738 | Q63: =SUM(L63:N63) -> -596
B65: PBITA
B66: Alder Gloves | C66: =C30-C54 -> 0 | D66: =D30-D54 -> 0 | E66: =E30-E54 -> 0 | F66: =F30-F54 -> 0 | G66: =G30-G54 -> 0 | H66: =H30-H54 -> 0 | I66: =I30-I54 -> 0 | J66: =J30-J54 -> 0 | ... N66: =N30-N54 -> -120 | O66: =SUM(C66:N66) -> -280 | Q66: =SUM(L66:N66) -> -360
B67: Beacon Hi-Vis | C67: =C31-C55 -> 0 | D67: =D31-D55 -> 0 | E67: =E31-E55 -> 0 | F67: =F31-F55 -> 0 | G67: =G31-G55 -> 0 | H67: =H31-H55 -> 0 | I67: =I31-I55 -> 0 | J67: =J31-J55 -> 0 | ... N67: =N31-N55 -> 72 | O67: =SUM(C67:N67) -> 244 | Q67: =SUM(L67:N67) -> 260
B68: Cobalt Eyewear | C68: =C32-C56 -> 0 | D68: =D32-D56 -> 0 | E68: =E32-E56 -> 0 | F68: =F32-F56 -> 0 | G68: =G32-G56 -> 0 | H68: =H32-H56 -> 0 | I68: =I32-I56 -> 0 | J68: =J32-J56 -> 0 | ... N68: =N32-N56 -> -11.92 | O68: =SUM(C68:N68) -> -29.68 | Q68: =SUM(L68:N68) -> -35.76
B69: Delta Welding Supply | C69: =C33-C57 -> 0 | D69: =D33-D57 -> 0 | E69: =E33-E57 -> 0 | F69: =F33-F57 -> 0 | G69: =G33-G57 -> 0 | H69: =H33-H57 -> 0 | I69: =I33-I57 -> 0 | J69: =J33-J57 -> 0 | ... N69: =N33-N57 -> 0 | O69: =SUM(C69:N69) -> 0 | Q69: =SUM(L69:N69) -> 0
B70: Ember Workwear | C70: =C34-C58 -> 0 | D70: =D34-D58 -> 0 | E70: =E34-E58 -> 0 | F70: =F34-F58 -> 0 | G70: =G34-G58 -> 0 | H70: =H34-H58 -> 0 | I70: =I34-I58 -> 0 | J70: =J34-J58 -> 0 | ... N70: =N34-N58 -> 10 | O70: =SUM(C70:N70) -> -120 | Q70: =SUM(L70:N70) -> -47
B71: Falcon Hand Protection | C71: =C35-C59 -> 0 | D71: =D35-D59 -> 0 | E71: =E35-E59 -> 0 | F71: =F35-F59 -> 0 | G71: =G35-G59 -> 0 | H71: =H35-H59 -> 0 | I71: =I35-I59 -> 0 | J71: =J35-J59 -> 0 | ... N71: =N35-N59 -> 110 | O71: =SUM(C71:N71) -> 330 | Q71: =SUM(L71:N71) -> 320
B72: Granite Gloves | C72: =C36-C60 -> 0 | D72: =D36-D60 -> 0 | E72: =E36-E60 -> 0 | F72: =F36-F60 -> 0 | G72: =G36-G60 -> 0 | H72: =H36-H60 -> 0 | I72: =I36-I60 -> 0 | J72: =J36-J60 -> 0 | ... N72: =N36-N60 -> 16 | O72: =SUM(C72:N72) -> -351 | Q72: =SUM(L72:N72) -> -128
B73: Hollis Rainwear | C73: =C37-C61 -> 0 | D73: =D37-D61 -> 0 | E73: =E37-E61 -> 0 | F73: =F37-F61 -> 0 | G73: =G37-G61 -> 0 | H73: =H37-H61 -> 0 | I73: =I37-I61 -> 0 | J73: =J37-J61 -> 0 | ... N73: =N37-N61 -> 390 | O73: =SUM(C73:N73) -> 810 | Q73: =SUM(L73:N73) -> 525
B74: SAFEREG | C74: =C38-C62 -> 0 | D74: =D38-D62 -> 0 | E74: =E38-E62 -> 0 | F74: =F38-F62 -> 0 | G74: =G38-G62 -> 0 | H74: =H38-H62 -> 0 | I74: =I38-I62 -> 0 | J74: =J38-J62 -> 0 | ... N74: =N38-N62 -> 0 | O74: =SUM(C74:N74) -> 0 | Q74: =SUM(L74:N74) -> 0
B75: Total PBITA | C75: =SUM(C66:C74) -> 0 | D75: =SUM(D66:D74) -> 0 | E75: =SUM(E66:E74) -> 0 | F75: =SUM(F66:F74) -> 0 | G75: =SUM(G66:G74) -> 0 | H75: =SUM(H66:H74) -> 0 | I75: =SUM(I66:I74) -> 0 | J75: =SUM(J66:J74) -> 0 | ... O75: =SUM(O66:O74) -> 603.32 | Q75: =SUM(L75:N75) -> 534.24
B77: Section 2: General adjustments in Gross Margin or Opex % of Sales that are not tied to individual events (i.e., employee turnover):
C79: January | D79: February | E79: March | F79: April | G79: May | H79: June | I79: July | J79: August | K79: September | L79: October | M79: November | N79: December | O79: Total
B80: Gross Margin
B81: Gross Margin - Previous FCAST | C81: =Safety!C35 -> 0.31612381 | D81: =Safety!D35 -> 0.3149853 | E81: =Safety!E35 -> 0.31445908 | F81: =Safety!F35 -> 0.31538328 | G81: =Safety!G35 -> 0.31534818 | H81: =Safety!H35 -> 0.31013541 | I81: =Safety!I35 -> 0.30982951 | J81: =Safety!J35 -> 0.30938682 | ... N81: =Safety!N35 -> 0.30930255
B82: New Adjustments (%) | C82: None | D82: None | E82: None | F82: None | G82: None | H82: None | I82: None | J82: None | K82: None | L82: None | M82: None | N82: None
B83: New Adjustments ($) | C83: =IF(C82="None",0,(((Safety!C28*('Safety-Adj'!C81+'Safety-Adj'!C82))-Safety!C29))) -> 0 | D83: =IF(D82="None",0,(((Safety!D28*('Safety-Adj'!D81+'Safety-Adj'!D82))-Safety!D29))) -> 0 | E83: =IF(E82="None",0,(((Safety!E28*('Safety-Adj'!E81+'Safety-Adj'!E82))-Safety!E29))) -> 0 | F83: =IF(F82="None",0,(((Safety!F28*('Safety-Adj'!F81+'Safety-Adj'!F82))-Safety!F29))) -> 0 | G83: =IF(G82="None",0,(((Safety!G28*('Safety-Adj'!G81+'Safety-Adj'!G82))-Safety!G29))) -> 0 | H83: =IF(H82="None",0,(((Safety!H28*('Safety-Adj'!H81+'Safety-Adj'!H82))-Safety!H29))) -> 0 | I83: =IF(I82="None",0,(((Safety!I28*('Safety-Adj'!I81+'Safety-Adj'!I82))-Safety!I29))) -> 0 | J83: =IF(J82="None",0,(((Safety!J28*('Safety-Adj'!J81+'Safety-Adj'!J82))-Safety!J29))) -> 0 | ... N83: =IF(N82="None",0,(((Safety!N28*('Safety-Adj'!N81+'Safety-Adj'!N82))-Safety!N29))) -> 0
B84: Gross Margin - Current FCAST | C84: =SUM(C81:C82) -> 0.31612381 | D84: =SUM(D81:D82) -> 0.3149853 | E84: =SUM(E81:E82) -> 0.31445908 | F84: =SUM(F81:F82) -> 0.31538328 | G84: =SUM(G81:G82) -> 0.31534818 | H84: =SUM(H81:H82) -> 0.31013541 | I84: =SUM(I81:I82) -> 0.30982951 | J84: =SUM(J81:J82) -> 0.30938682 | ... N84: =SUM(N81:N82) -> 0.30930255
B86: Op Costs
B87: Op Costs - Previous FCAST | C87: =Safety!C36 -> -0.21573547 | D87: =Safety!D36 -> -0.21492085 | E87: =Safety!E36 -> -0.21497136 | F87: =Safety!F36 -> -0.21416303 | G87: =Safety!G36 -> -0.21463725 | H87: =Safety!H36 -> -0.21443313 | I87: =Safety!I36 -> -0.21377866 | J87: =Safety!J36 -> -0.21631585 | ... N87: =Safety!N36 -> -0.212018
B88: New Adjustments (%) | C88: None | D88: None | E88: None | F88: None | G88: None | H88: None | I88: None | J88: None | K88: None | L88: None | M88: None | N88: None
B89: New Adjustments ($) | C89: =-IF(C88="None",0,(((Safety!C28*-('Safety-Adj'!C87+'Safety-Adj'!C88))-Safety!C30))) -> 0 | D89: =-IF(D88="None",0,(((Safety!D28*-('Safety-Adj'!D87+'Safety-Adj'!D88))-Safety!D30))) -> 0 | E89: =-IF(E88="None",0,(((Safety!E28*-('Safety-Adj'!E87+'Safety-Adj'!E88))-Safety!E30))) -> 0 | F89: =-IF(F88="None",0,(((Safety!F28*-('Safety-Adj'!F87+'Safety-Adj'!F88))-Safety!F30))) -> 0 | G89: =-IF(G88="None",0,(((Safety!G28*-('Safety-Adj'!G87+'Safety-Adj'!G88))-Safety!G30))) -> 0 | H89: =-IF(H88="None",0,(((Safety!H28*-('Safety-Adj'!H87+'Safety-Adj'!H88))-Safety!H30))) -> 0 | I89: =-IF(I88="None",0,(((Safety!I28*-('Safety-Adj'!I87+'Safety-Adj'!I88))-Safety!I30))) -> 0 | J89: =-IF(J88="None",0,(((Safety!J28*-('Safety-Adj'!J87+'Safety-Adj'!J88))-Safety!J30))) -> 0 | ... N89: =-IF(N88="None",0,(((Safety!N28*-('Safety-Adj'!N87+'Safety-Adj'!N88))-Safety!N30))) -> 0
B90: Op Costs - Current FCAST | C90: =SUM(C87:C88) -> -0.21573547 | D90: =SUM(D87:D88) -> -0.21492085 | E90: =SUM(E87:E88) -> -0.21497136 | F90: =SUM(F87:F88) -> -0.21416303 | G90: =SUM(G87:G88) -> -0.21463725 | H90: =SUM(H87:H88) -> -0.21443313 | I90: =SUM(I87:I88) -> -0.21377866 | J90: =SUM(J87:J88) -> -0.21631585 | ... N90: =SUM(N87:N88) -> -0.212018
B92: Section 3: Working Capital Adjustments
C94: January | D94: February | E94: March | F94: April | G94: May | H94: June | I94: July | J94: August | K94: September | L94: October | M94: November | N94: December
A95: 2090 | B95: Net Inventory | C95: ='Alder-Adj'!C90+'Beacon-Adj'!C90+'Cobalt-Adj'!C90+'Delta-Adj'!C90+'Ember-Adj'!C90+'Falcon-Adj'!C90+'Granite-Adj'!C90+'Hollis-Adj'!C90+'SAFEREG-Adj'!C90 -> 0 | D95: ='Alder-Adj'!D90+'Beacon-Adj'!D90+'Cobalt-Adj'!D90+'Delta-Adj'!D90+'Ember-Adj'!D90+'Falcon-Adj'!D90+'Granite-Adj'!D90+'Hollis-Adj'!D90+'SAFEREG-Adj'!D90 -> 0 | E95: ='Alder-Adj'!E90+'Beacon-Adj'!E90+'Cobalt-Adj'!E90+'Delta-Adj'!E90+'Ember-Adj'!E90+'Falcon-Adj'!E90+'Granite-Adj'!E90+'Hollis-Adj'!E90+'SAFEREG-Adj'!E90 -> 0 | F95: ='Alder-Adj'!F90+'Beacon-Adj'!F90+'Cobalt-Adj'!F90+'Delta-Adj'!F90+'Ember-Adj'!F90+'Falcon-Adj'!F90+'Granite-Adj'!F90+'Hollis-Adj'!F90+'SAFEREG-Adj'!F90 -> 0 | G95: ='Alder-Adj'!G90+'Beacon-Adj'!G90+'Cobalt-Adj'!G90+'Delta-Adj'!G90+'Ember-Adj'!G90+'Falcon-Adj'!G90+'Granite-Adj'!G90+'Hollis-Adj'!G90+'SAFEREG-Adj'!G90 -> 0 | H95: ='Alder-Adj'!H90+'Beacon-Adj'!H90+'Cobalt-Adj'!H90+'Delta-Adj'!H90+'Ember-Adj'!H90+'Falcon-Adj'!H90+'Granite-Adj'!H90+'Hollis-Adj'!H90+'SAFEREG-Adj'!H90 -> 0 | I95: ='Alder-Adj'!I90+'Beacon-Adj'!I90+'Cobalt-Adj'!I90+'Delta-Adj'!I90+'Ember-Adj'!I90+'Falcon-Adj'!I90+'Granite-Adj'!I90+'Hollis-Adj'!I90+'SAFEREG-Adj'!I90 -> 0 | J95: ='Alder-Adj'!J90+'Beacon-Adj'!J90+'Cobalt-Adj'!J90+'Delta-Adj'!J90+'Ember-Adj'!J90+'Falcon-Adj'!J90+'Granite-Adj'!J90+'Hollis-Adj'!J90+'SAFEREG-Adj'!J90 -> 0 | ... N95: ='Alder-Adj'!N90+'Beacon-Adj'!N90+'Cobalt-Adj'!N90+'Delta-Adj'!N90+'Ember-Adj'!N90+'Falcon-Adj'!N90+'Granite-Adj'!N90+'Hollis-Adj'!N90+'SAFEREG-Adj'!N90 -> -4000
A96: 2135 | B96: Trade Receivables | C96: ='Alder-Adj'!C91+'Beacon-Adj'!C91+'Cobalt-Adj'!C91+'Delta-Adj'!C91+'Ember-Adj'!C91+'Falcon-Adj'!C91+'Granite-Adj'!C91+'Hollis-Adj'!C91+'SAFEREG-Adj'!C91 -> 0 | D96: ='Alder-Adj'!D91+'Beacon-Adj'!D91+'Cobalt-Adj'!D91+'Delta-Adj'!D91+'Ember-Adj'!D91+'Falcon-Adj'!D91+'Granite-Adj'!D91+'Hollis-Adj'!D91+'SAFEREG-Adj'!D91 -> 0 | E96: ='Alder-Adj'!E91+'Beacon-Adj'!E91+'Cobalt-Adj'!E91+'Delta-Adj'!E91+'Ember-Adj'!E91+'Falcon-Adj'!E91+'Granite-Adj'!E91+'Hollis-Adj'!E91+'SAFEREG-Adj'!E91 -> 0 | F96: ='Alder-Adj'!F91+'Beacon-Adj'!F91+'Cobalt-Adj'!F91+'Delta-Adj'!F91+'Ember-Adj'!F91+'Falcon-Adj'!F91+'Granite-Adj'!F91+'Hollis-Adj'!F91+'SAFEREG-Adj'!F91 -> 0 | G96: ='Alder-Adj'!G91+'Beacon-Adj'!G91+'Cobalt-Adj'!G91+'Delta-Adj'!G91+'Ember-Adj'!G91+'Falcon-Adj'!G91+'Granite-Adj'!G91+'Hollis-Adj'!G91+'SAFEREG-Adj'!G91 -> 0 | H96: ='Alder-Adj'!H91+'Beacon-Adj'!H91+'Cobalt-Adj'!H91+'Delta-Adj'!H91+'Ember-Adj'!H91+'Falcon-Adj'!H91+'Granite-Adj'!H91+'Hollis-Adj'!H91+'SAFEREG-Adj'!H91 -> 0 | I96: ='Alder-Adj'!I91+'Beacon-Adj'!I91+'Cobalt-Adj'!I91+'Delta-Adj'!I91+'Ember-Adj'!I91+'Falcon-Adj'!I91+'Granite-Adj'!I91+'Hollis-Adj'!I91+'SAFEREG-Adj'!I91 -> 0 | J96: ='Alder-Adj'!J91+'Beacon-Adj'!J91+'Cobalt-Adj'!J91+'Delta-Adj'!J91+'Ember-Adj'!J91+'Falcon-Adj'!J91+'Granite-Adj'!J91+'Hollis-Adj'!J91+'SAFEREG-Adj'!J91 -> 0 | ... N96: ='Alder-Adj'!N91+'Beacon-Adj'!N91+'Cobalt-Adj'!N91+'Delta-Adj'!N91+'Ember-Adj'!N91+'Falcon-Adj'!N91+'Granite-Adj'!N91+'Hollis-Adj'!N91+'SAFEREG-Adj'!N91 -> 0
A97: 2175 | B97: Other Receivables | C97: ='Alder-Adj'!C92+'Beacon-Adj'!C92+'Cobalt-Adj'!C92+'Delta-Adj'!C92+'Ember-Adj'!C92+'Falcon-Adj'!C92+'Granite-Adj'!C92+'Hollis-Adj'!C92+'SAFEREG-Adj'!C92 -> 0 | D97: ='Alder-Adj'!D92+'Beacon-Adj'!D92+'Cobalt-Adj'!D92+'Delta-Adj'!D92+'Ember-Adj'!D92+'Falcon-Adj'!D92+'Granite-Adj'!D92+'Hollis-Adj'!D92+'SAFEREG-Adj'!D92 -> 0 | E97: ='Alder-Adj'!E92+'Beacon-Adj'!E92+'Cobalt-Adj'!E92+'Delta-Adj'!E92+'Ember-Adj'!E92+'Falcon-Adj'!E92+'Granite-Adj'!E92+'Hollis-Adj'!E92+'SAFEREG-Adj'!E92 -> 0 | F97: ='Alder-Adj'!F92+'Beacon-Adj'!F92+'Cobalt-Adj'!F92+'Delta-Adj'!F92+'Ember-Adj'!F92+'Falcon-Adj'!F92+'Granite-Adj'!F92+'Hollis-Adj'!F92+'SAFEREG-Adj'!F92 -> 0 | G97: ='Alder-Adj'!G92+'Beacon-Adj'!G92+'Cobalt-Adj'!G92+'Delta-Adj'!G92+'Ember-Adj'!G92+'Falcon-Adj'!G92+'Granite-Adj'!G92+'Hollis-Adj'!G92+'SAFEREG-Adj'!G92 -> 0 | H97: ='Alder-Adj'!H92+'Beacon-Adj'!H92+'Cobalt-Adj'!H92+'Delta-Adj'!H92+'Ember-Adj'!H92+'Falcon-Adj'!H92+'Granite-Adj'!H92+'Hollis-Adj'!H92+'SAFEREG-Adj'!H92 -> 0 | I97: ='Alder-Adj'!I92+'Beacon-Adj'!I92+'Cobalt-Adj'!I92+'Delta-Adj'!I92+'Ember-Adj'!I92+'Falcon-Adj'!I92+'Granite-Adj'!I92+'Hollis-Adj'!I92+'SAFEREG-Adj'!I92 -> 0 | J97: ='Alder-Adj'!J92+'Beacon-Adj'!J92+'Cobalt-Adj'!J92+'Delta-Adj'!J92+'Ember-Adj'!J92+'Falcon-Adj'!J92+'Granite-Adj'!J92+'Hollis-Adj'!J92+'SAFEREG-Adj'!J92 -> 0 | ... N97: ='Alder-Adj'!N92+'Beacon-Adj'!N92+'Cobalt-Adj'!N92+'Delta-Adj'!N92+'Ember-Adj'!N92+'Falcon-Adj'!N92+'Granite-Adj'!N92+'Hollis-Adj'!N92+'SAFEREG-Adj'!N92 -> 0
A98: 2140 | B98: Trade Payables | C98: ='Alder-Adj'!C93+'Beacon-Adj'!C93+'Cobalt-Adj'!C93+'Delta-Adj'!C93+'Ember-Adj'!C93+'Falcon-Adj'!C93+'Granite-Adj'!C93+'Hollis-Adj'!C93+'SAFEREG-Adj'!C93 -> 0 | D98: ='Alder-Adj'!D93+'Beacon-Adj'!D93+'Cobalt-Adj'!D93+'Delta-Adj'!D93+'Ember-Adj'!D93+'Falcon-Adj'!D93+'Granite-Adj'!D93+'Hollis-Adj'!D93+'SAFEREG-Adj'!D93 -> 0 | E98: ='Alder-Adj'!E93+'Beacon-Adj'!E93+'Cobalt-Adj'!E93+'Delta-Adj'!E93+'Ember-Adj'!E93+'Falcon-Adj'!E93+'Granite-Adj'!E93+'Hollis-Adj'!E93+'SAFEREG-Adj'!E93 -> 0 | F98: ='Alder-Adj'!F93+'Beacon-Adj'!F93+'Cobalt-Adj'!F93+'Delta-Adj'!F93+'Ember-Adj'!F93+'Falcon-Adj'!F93+'Granite-Adj'!F93+'Hollis-Adj'!F93+'SAFEREG-Adj'!F93 -> 0 | G98: ='Alder-Adj'!G93+'Beacon-Adj'!G93+'Cobalt-Adj'!G93+'Delta-Adj'!G93+'Ember-Adj'!G93+'Falcon-Adj'!G93+'Granite-Adj'!G93+'Hollis-Adj'!G93+'SAFEREG-Adj'!G93 -> 0 | H98: ='Alder-Adj'!H93+'Beacon-Adj'!H93+'Cobalt-Adj'!H93+'Delta-Adj'!H93+'Ember-Adj'!H93+'Falcon-Adj'!H93+'Granite-Adj'!H93+'Hollis-Adj'!H93+'SAFEREG-Adj'!H93 -> 0 | I98: ='Alder-Adj'!I93+'Beacon-Adj'!I93+'Cobalt-Adj'!I93+'Delta-Adj'!I93+'Ember-Adj'!I93+'Falcon-Adj'!I93+'Granite-Adj'!I93+'Hollis-Adj'!I93+'SAFEREG-Adj'!I93 -> 0 | J98: ='Alder-Adj'!J93+'Beacon-Adj'!J93+'Cobalt-Adj'!J93+'Delta-Adj'!J93+'Ember-Adj'!J93+'Falcon-Adj'!J93+'Granite-Adj'!J93+'Hollis-Adj'!J93+'SAFEREG-Adj'!J93 -> 0 | ... N98: ='Alder-Adj'!N93+'Beacon-Adj'!N93+'Cobalt-Adj'!N93+'Delta-Adj'!N93+'Ember-Adj'!N93+'Falcon-Adj'!N93+'Granite-Adj'!N93+'Hollis-Adj'!N93+'SAFEREG-Adj'!N93 -> 0
A99: 2180 | B99: Other Payables | C99: ='Alder-Adj'!C94+'Beacon-Adj'!C94+'Cobalt-Adj'!C94+'Delta-Adj'!C94+'Ember-Adj'!C94+'Falcon-Adj'!C94+'Granite-Adj'!C94+'Hollis-Adj'!C94+'SAFEREG-Adj'!C94 -> 0 | D99: ='Alder-Adj'!D94+'Beacon-Adj'!D94+'Cobalt-Adj'!D94+'Delta-Adj'!D94+'Ember-Adj'!D94+'Falcon-Adj'!D94+'Granite-Adj'!D94+'Hollis-Adj'!D94+'SAFEREG-Adj'!D94 -> 0 | E99: ='Alder-Adj'!E94+'Beacon-Adj'!E94+'Cobalt-Adj'!E94+'Delta-Adj'!E94+'Ember-Adj'!E94+'Falcon-Adj'!E94+'Granite-Adj'!E94+'Hollis-Adj'!E94+'SAFEREG-Adj'!E94 -> 0 | F99: ='Alder-Adj'!F94+'Beacon-Adj'!F94+'Cobalt-Adj'!F94+'Delta-Adj'!F94+'Ember-Adj'!F94+'Falcon-Adj'!F94+'Granite-Adj'!F94+'Hollis-Adj'!F94+'SAFEREG-Adj'!F94 -> 0 | G99: ='Alder-Adj'!G94+'Beacon-Adj'!G94+'Cobalt-Adj'!G94+'Delta-Adj'!G94+'Ember-Adj'!G94+'Falcon-Adj'!G94+'Granite-Adj'!G94+'Hollis-Adj'!G94+'SAFEREG-Adj'!G94 -> 0 | H99: ='Alder-Adj'!H94+'Beacon-Adj'!H94+'Cobalt-Adj'!H94+'Delta-Adj'!H94+'Ember-Adj'!H94+'Falcon-Adj'!H94+'Granite-Adj'!H94+'Hollis-Adj'!H94+'SAFEREG-Adj'!H94 -> 0 | I99: ='Alder-Adj'!I94+'Beacon-Adj'!I94+'Cobalt-Adj'!I94+'Delta-Adj'!I94+'Ember-Adj'!I94+'Falcon-Adj'!I94+'Granite-Adj'!I94+'Hollis-Adj'!I94+'SAFEREG-Adj'!I94 -> 0 | J99: ='Alder-Adj'!J94+'Beacon-Adj'!J94+'Cobalt-Adj'!J94+'Delta-Adj'!J94+'Ember-Adj'!J94+'Falcon-Adj'!J94+'Granite-Adj'!J94+'Hollis-Adj'!J94+'SAFEREG-Adj'!J94 -> 0 | ... N99: ='Alder-Adj'!N94+'Beacon-Adj'!N94+'Cobalt-Adj'!N94+'Delta-Adj'!N94+'Ember-Adj'!N94+'Falcon-Adj'!N94+'Granite-Adj'!N94+'Hollis-Adj'!N94+'SAFEREG-Adj'!N94 -> 0
A100: 2185 | B100: Total Working Capital | C100: =SUM(C95:C99) -> 0 | D100: =SUM(D95:D99) -> 0 | E100: =SUM(E95:E99) -> 0 | F100: =SUM(F95:F99) -> 0 | G100: =SUM(G95:G99) -> 0 | H100: =SUM(H95:H99) -> 0 | I100: =SUM(I95:I99) -> 0 | J100: =SUM(J95:J99) -> 0 | ... N100: =SUM(N95:N99) -> -4000

Sheet Safety
C1: Actual | D1: Actual | E1: Actual | F1: Actual | G1: Actual | H1: Actual | I1: Actual | J1: Actual | K1: FCAST09 | L1: FCAST09 | M1: FCAST09 | N1: FCAST09
B2: Scenario# | C2: Actual | D2: Actual | E2: Actual | F2: Actual | G2: Actual | H2: Actual | I2: Actual | J2: Actual | K2: Actual | L2: Actual | M2: Actual | N2: Actual
B5: Year# | C5: 2026 | D5: 2026 | E5: 2026 | F5: 2026 | G5: 2026 | H5: 2026 | I5: 2026 | J5: 2026 | K5: 2026 | L5: 2026 | M5: 2026 | N5: 2026
B8: Period# | C8: P01 | D8: P02 | E8: P03 | F8: P04 | G8: P05 | H8: P06 | I8: P07 | J8: P08 | K8: P09 | L8: P10 | M8: P11 | N8: P12
B9: Account#
B10: ICP#
B11: Custom1# | C11: TotalC1 | D11: TotalC1 | E11: TotalC1 | F11: TotalC1 | G11: TotalC1 | H11: TotalC1 | I11: TotalC1 | J11: TotalC1 | K11: TotalC1 | L11: TotalC1 | M11: TotalC1 | N11: TotalC1
B12: Custom2# | C12: TotalC2 | D12: TotalC2 | E12: TotalC2 | F12: TotalC2 | G12: TotalC2 | H12: TotalC2 | I12: TotalC2 | J12: TotalC2 | K12: TotalC2 | L12: TotalC2 | M12: TotalC2 | N12: TotalC2
B13: Custom3#
B14: Custom4#
B18: View# | C18: Periodic | D18: Periodic | E18: Periodic | F18: Periodic | G18: Periodic | H18: Periodic | I18: Periodic | J18: Periodic | K18: Periodic | L18: Periodic | M18: Periodic | N18: Periodic
B19: Value# | C19: USD Total | D19: USD Total | E19: USD Total | F19: USD Total | G19: USD Total | H19: USD Total | I19: USD Total | J19: USD Total | K19: USD Total | L19: USD Total | M19: USD Total | N19: USD Total
B21: TRAINING DATA ONLY - Zava Safety and all business names and numbers are fictitious. Layout mirrors a typical HFM / Cognos reporting pack.
B22: SAFECON_2DISP
B23: Zava Safety - Consolidated | BU23: FCAST10 - Variance ($) - Favorable / (Unfavorable)
C24: FCAST09 as Reported | Q24: FCAST09 at New Fx Rates | AE24: Fx Changes | AS24: Operational Adjustments | BG24: FCAST10 | BU24: Through Sep | BY24: Rest of Year | CC24: Full Year
C25: Actual | D25: Actual | E25: Actual | F25: Actual | G25: Actual | H25: Actual | I25: Actual | J25: Actual | K25: FCAST09 | L25: FCAST09 | M25: FCAST09 | N25: FCAST09 | O25: Forecast | Q25: Actual | R25: Actual | S25: Actual | T25: Actual | U25: Actual | V25: Actual | W25: Actual | X25: Actual | Y25: FCAST09 | Z25: FCAST09 | AA25: FCAST09 | AB25: FCAST09 | AC25: Forecast | BG25: Actual | BH25: Actual | BI25: Actual | BJ25: Actual | BK25: Actual | BL25: Actual | BM25: Actual | BN25: Actual | BO25: Actual | BP25: FCAST10 | BQ25: FCAST10 | BR25: FCAST10 | BS25: Forecast
B26: Description: | C26: January | D26: February | E26: March | F26: April | G26: May | H26: June | I26: July | J26: August | K26: September | L26: October | M26: November | N26: December | O26: Full year | Q26: January | R26: February | S26: March | T26: April | U26: May | V26: June | W26: July | X26: August | Y26: September | Z26: October | AA26: November | AB26: December | AC26: Full year | AE26: January | AF26: February | AG26: March | AH26: April | AI26: May | AJ26: June | AK26: July | AL26: August | AM26: September | AN26: October | AO26: November | AP26: December | AQ26: Full year | AS26: January | AT26: February | AU26: March | AV26: April | AW26: May | AX26: June | AY26: July | AZ26: August | BA26: September | BB26: October | BC26: November | BD26: December | BE26: Full year | BG26: January | BH26: February | BI26: March | BJ26: April | BK26: May | BL26: June | BM26: July | BN26: August | BO26: September | BP26: October | BQ26: November | BR26: December | BS26: Full year | BU26: Actual vs. FCAST09 | BV26: Actual vs. Bud | BW26: Actual vs. PY | BY26: FCAST10 vs. FCAST09 | BZ26: FCAST10 vs. Bud | CA26: FCAST10 vs. PY | CC26: FCAST10 vs. FCAST09 | CD26: FCAST10 vs. Bud | CE26: FCAST10 vs. PY
B28: Sales | C28: =Alder!C28+Beacon!C28+Cobalt!C28+Delta!C28+Ember!C28+Falcon!C28+Granite!C28+Hollis!C28+SAFEREG!C28 -> 49776.7 | D28: =Alder!D28+Beacon!D28+Cobalt!D28+Delta!D28+Ember!D28+Falcon!D28+Granite!D28+Hollis!D28+SAFEREG!D28 -> 49033.4 | E28: =Alder!E28+Beacon!E28+Cobalt!E28+Delta!E28+Ember!E28+Falcon!E28+Granite!E28+Hollis!E28+SAFEREG!E28 -> 52588.4 | F28: =Alder!F28+Beacon!F28+Cobalt!F28+Delta!F28+Ember!F28+Falcon!F28+Granite!F28+Hollis!F28+SAFEREG!F28 -> 56881.9 | G28: =Alder!G28+Beacon!G28+Cobalt!G28+Delta!G28+Ember!G28+Falcon!G28+Granite!G28+Hollis!G28+SAFEREG!G28 -> 51833.5 | H28: =Alder!H28+Beacon!H28+Cobalt!H28+Delta!H28+Ember!H28+Falcon!H28+Granite!H28+Hollis!H28+SAFEREG!H28 -> 54124.1 | I28: =Alder!I28+Beacon!I28+Cobalt!I28+Delta!I28+Ember!I28+Falcon!I28+Granite!I28+Hollis!I28+SAFEREG!I28 -> 53826.7 | J28: =Alder!J28+Beacon!J28+Cobalt!J28+Delta!J28+Ember!J28+Falcon!J28+Granite!J28+Hollis!J28+SAFEREG!J28 -> 52681.3 | ... N28: =Alder!N28+Beacon!N28+Cobalt!N28+Delta!N28+Ember!N28+Falcon!N28+Granite!N28+Hollis!N28+SAFEREG!N28 -> 54989.2 | O28: =SUM(C28:N28) -> 633766.9 | Q28: =Alder!Q28+Beacon!Q28+Cobalt!Q28+Delta!Q28+Ember!Q28+Falcon!Q28+Granite!Q28+Hollis!Q28+SAFEREG!Q28 -> 49776.7 | R28: =Alder!R28+Beacon!R28+Cobalt!R28+Delta!R28+Ember!R28+Falcon!R28+Granite!R28+Hollis!R28+SAFEREG!R28 -> 49033.4 | S28: =Alder!S28+Beacon!S28+Cobalt!S28+Delta!S28+Ember!S28+Falcon!S28+Granite!S28+Hollis!S28+SAFEREG!S28 -> 52588.4 | T28: =Alder!T28+Beacon!T28+Cobalt!T28+Delta!T28+Ember!T28+Falcon!T28+Granite!T28+Hollis!T28+SAFEREG!T28 -> 56881.9 | U28: =Alder!U28+Beacon!U28+Cobalt!U28+Delta!U28+Ember!U28+Falcon!U28+Granite!U28+Hollis!U28+SAFEREG!U28 -> 51833.5 | V28: =Alder!V28+Beacon!V28+Cobalt!V28+Delta!V28+Ember!V28+Falcon!V28+Granite!V28+Hollis!V28+SAFEREG!V28 -> 54124.1 | W28: =Alder!W28+Beacon!W28+Cobalt!W28+Delta!W28+Ember!W28+Falcon!W28+Granite!W28+Hollis!W28+SAFEREG!W28 -> 53826.7 | X28: =Alder!X28+Beacon!X28+Cobalt!X28+Delta!X28+Ember!X28+Falcon!X28+Granite!X28+Hollis!X28+SAFEREG!X28 -> 52681.3 | ... AB28: =Alder!AB28+Beacon!AB28+Cobalt!AB28+Delta!AB28+Ember!AB28+Falcon!AB28+Granite!AB28+Hollis!AB28+SAFEREG!AB28 -> 54944.2 | AC28: =SUM(Q28:AB28) -> 633586.9 | AE28: =Q28-C28 -> 0 | AF28: =R28-D28 -> 0 | AG28: =S28-E28 -> 0 | AH28: =T28-F28 -> 0 | AI28: =U28-G28 -> 0 | AJ28: =V28-H28 -> 0 | AK28: =W28-I28 -> 0 | AL28: =X28-J28 -> 0 | ... AP28: =AB28-N28 -> -45 | AQ28: =SUM(AE28:AP28) -> -180 | AS28: ='Safety-Adj'!C15 -> 0 | AT28: ='Safety-Adj'!D15 -> 0 | AU28: ='Safety-Adj'!E15 -> 0 | AV28: ='Safety-Adj'!F15 -> 0 | AW28: ='Safety-Adj'!G15 -> 0 | AX28: ='Safety-Adj'!H15 -> 0 | AY28: ='Safety-Adj'!I15 -> 0 | AZ28: ='Safety-Adj'!J15 -> 0 | ... BD28: ='Safety-Adj'!N15 -> 340 | BE28: =SUM(AS28:BD28) -> 570 | BG28: =C28+AE28+AS28 -> 49776.7 | BH28: =D28+AF28+AT28 -> 49033.4 | BI28: =E28+AG28+AU28 -> 52588.4 | BJ28: =F28+AH28+AV28 -> 56881.9 | BK28: =G28+AI28+AW28 -> 51833.5 | BL28: =H28+AJ28+AX28 -> 54124.1 | BM28: =I28+AK28+AY28 -> 53826.7 | BN28: =J28+AL28+AZ28 -> 52681.3 | ... BR28: =N28+AP28+BD28 -> 55284.2 | BS28: =SUM(BG28:BR28) -> 634156.9 | BU28: =SUM(BG28:BO28)-SUM(C28:K28) -> 1445 | BV28: =SUM(BG28:BO28)-SUM(C51:K51) -> 10937.5 | BW28: =SUM(BG28:BO28)-SUM(C64:K64) -> 32001.3 | BY28: =SUM(BP28:BR28)-SUM(L28:N28) -> -1055 | BZ28: =SUM(BP28:BR28)-SUM(L51:N51) -> 3221.3 | CA28: =SUM(BP28:BR28)-SUM(L64:N64) -> 10243.2 | CC28: =BS28-O28 -> 390 | CD28: =BS28-O51 -> 14158.8 | CE28: =BS28-O64 -> 42244.5
B29: Gross Margin | C29: =Alder!C29+Beacon!C29+Cobalt!C29+Delta!C29+Ember!C29+Falcon!C29+Granite!C29+Hollis!C29+SAFEREG!C29 -> 15735.6 | D29: =Alder!D29+Beacon!D29+Cobalt!D29+Delta!D29+Ember!D29+Falcon!D29+Granite!D29+Hollis!D29+SAFEREG!D29 -> 15444.8 | E29: =Alder!E29+Beacon!E29+Cobalt!E29+Delta!E29+Ember!E29+Falcon!E29+Granite!E29+Hollis!E29+SAFEREG!E29 -> 16536.9 | F29: =Alder!F29+Beacon!F29+Cobalt!F29+Delta!F29+Ember!F29+Falcon!F29+Granite!F29+Hollis!F29+SAFEREG!F29 -> 17939.6 | G29: =Alder!G29+Beacon!G29+Cobalt!G29+Delta!G29+Ember!G29+Falcon!G29+Granite!G29+Hollis!G29+SAFEREG!G29 -> 16345.6 | H29: =Alder!H29+Beacon!H29+Cobalt!H29+Delta!H29+Ember!H29+Falcon!H29+Granite!H29+Hollis!H29+SAFEREG!H29 -> 16785.8 | I29: =Alder!I29+Beacon!I29+Cobalt!I29+Delta!I29+Ember!I29+Falcon!I29+Granite!I29+Hollis!I29+SAFEREG!I29 -> 16677.1 | J29: =Alder!J29+Beacon!J29+Cobalt!J29+Delta!J29+Ember!J29+Falcon!J29+Granite!J29+Hollis!J29+SAFEREG!J29 -> 16298.9 | ... N29: =Alder!N29+Beacon!N29+Cobalt!N29+Delta!N29+Ember!N29+Falcon!N29+Granite!N29+Hollis!N29+SAFEREG!N29 -> 17008.3 | O29: =SUM(C29:N29) -> 197718.7 | Q29: =Alder!Q29+Beacon!Q29+Cobalt!Q29+Delta!Q29+Ember!Q29+Falcon!Q29+Granite!Q29+Hollis!Q29+SAFEREG!Q29 -> 15735.6 | R29: =Alder!R29+Beacon!R29+Cobalt!R29+Delta!R29+Ember!R29+Falcon!R29+Granite!R29+Hollis!R29+SAFEREG!R29 -> 15444.8 | S29: =Alder!S29+Beacon!S29+Cobalt!S29+Delta!S29+Ember!S29+Falcon!S29+Granite!S29+Hollis!S29+SAFEREG!S29 -> 16536.9 | T29: =Alder!T29+Beacon!T29+Cobalt!T29+Delta!T29+Ember!T29+Falcon!T29+Granite!T29+Hollis!T29+SAFEREG!T29 -> 17939.6 | U29: =Alder!U29+Beacon!U29+Cobalt!U29+Delta!U29+Ember!U29+Falcon!U29+Granite!U29+Hollis!U29+SAFEREG!U29 -> 16345.6 | V29: =Alder!V29+Beacon!V29+Cobalt!V29+Delta!V29+Ember!V29+Falcon!V29+Granite!V29+Hollis!V29+SAFEREG!V29 -> 16785.8 | W29: =Alder!W29+Beacon!W29+Cobalt!W29+Delta!W29+Ember!W29+Falcon!W29+Granite!W29+Hollis!W29+SAFEREG!W29 -> 16677.1 | X29: =Alder!X29+Beacon!X29+Cobalt!X29+Delta!X29+Ember!X29+Falcon!X29+Granite!X29+Hollis!X29+SAFEREG!X29 -> 16298.9 | ... AB29: =Alder!AB29+Beacon!AB29+Cobalt!AB29+Delta!AB29+Ember!AB29+Falcon!AB29+Granite!AB29+Hollis!AB29+SAFEREG!AB29 -> 16995.3 | AC29: =SUM(Q29:AB29) -> 197666.7 | AE29: =Q29-C29 -> 0 | AF29: =R29-D29 -> 0 | AG29: =S29-E29 -> 0 | AH29: =T29-F29 -> 0 | AI29: =U29-G29 -> 0 | AJ29: =V29-H29 -> 0 | AK29: =W29-I29 -> 0 | AL29: =X29-J29 -> 0 | ... AP29: =AB29-N29 -> -13 | AQ29: =SUM(AE29:AP29) -> -52 | AS29: ='Safety-Adj'!C39+'Safety-Adj'!C83 -> 0 | AT29: ='Safety-Adj'!D39+'Safety-Adj'!D83 -> 0 | AU29: ='Safety-Adj'!E39+'Safety-Adj'!E83 -> 0 | AV29: ='Safety-Adj'!F39+'Safety-Adj'!F83 -> 0 | AW29: ='Safety-Adj'!G39+'Safety-Adj'!G83 -> 0 | AX29: ='Safety-Adj'!H39+'Safety-Adj'!H83 -> 0 | AY29: ='Safety-Adj'!I39+'Safety-Adj'!I83 -> 0 | AZ29: ='Safety-Adj'!J39+'Safety-Adj'!J83 -> 0 | ... BD29: ='Safety-Adj'!N39+'Safety-Adj'!N83 -> 239.08 | BE29: =SUM(AS29:BD29) -> -134.68 | BG29: =C29+AE29+AS29 -> 15735.6 | BH29: =D29+AF29+AT29 -> 15444.8 | BI29: =E29+AG29+AU29 -> 16536.9 | BJ29: =F29+AH29+AV29 -> 17939.6 | BK29: =G29+AI29+AW29 -> 16345.6 | BL29: =H29+AJ29+AX29 -> 16785.8 | BM29: =I29+AK29+AY29 -> 16677.1 | BN29: =J29+AL29+AZ29 -> 16298.9 | ... BR29: =N29+AP29+BD29 -> 17234.38 | BS29: =SUM(BG29:BR29) -> 197532.02 | BU29: =SUM(BG29:BO29)-SUM(C29:K29) -> -85.92 | BV29: =SUM(BG29:BO29)-SUM(C52:K52) -> 2279.88 | BW29: =SUM(BG29:BO29)-SUM(C65:K65) -> 8917.68 | BY29: =SUM(BP29:BR29)-SUM(L29:N29) -> -100.76 | BZ29: =SUM(BP29:BR29)-SUM(L52:N52) -> 502.64 | CA29: =SUM(BP29:BR29)-SUM(L65:N65) -> 2634.14 | CC29: =BS29-O29 -> -186.68 | CD29: =BS29-O52 -> 2782.52 | CE29: =BS29-O65 -> 11551.82
B30: Op Costs | C30: =Alder!C30+Beacon!C30+Cobalt!C30+Delta!C30+Ember!C30+Falcon!C30+Granite!C30+Hollis!C30+SAFEREG!C30 -> -10738.6 | D30: =Alder!D30+Beacon!D30+Cobalt!D30+Delta!D30+Ember!D30+Falcon!D30+Granite!D30+Hollis!D30+SAFEREG!D30 -> -10538.3 | E30: =Alder!E30+Beacon!E30+Cobalt!E30+Delta!E30+Ember!E30+Falcon!E30+Granite!E30+Hollis!E30+SAFEREG!E30 -> -11305 | F30: =Alder!F30+Beacon!F30+Cobalt!F30+Delta!F30+Ember!F30+Falcon!F30+Granite!F30+Hollis!F30+SAFEREG!F30 -> -12182 | G30: =Alder!G30+Beacon!G30+Cobalt!G30+Delta!G30+Ember!G30+Falcon!G30+Granite!G30+Hollis!G30+SAFEREG!G30 -> -11125.4 | H30: =Alder!H30+Beacon!H30+Cobalt!H30+Delta!H30+Ember!H30+Falcon!H30+Granite!H30+Hollis!H30+SAFEREG!H30 -> -11606 | I30: =Alder!I30+Beacon!I30+Cobalt!I30+Delta!I30+Ember!I30+Falcon!I30+Granite!I30+Hollis!I30+SAFEREG!I30 -> -11507 | J30: =Alder!J30+Beacon!J30+Cobalt!J30+Delta!J30+Ember!J30+Falcon!J30+Granite!J30+Hollis!J30+SAFEREG!J30 -> -11395.8 | ... N30: =Alder!N30+Beacon!N30+Cobalt!N30+Delta!N30+Ember!N30+Falcon!N30+Granite!N30+Hollis!N30+SAFEREG!N30 -> -11658.7 | O30: =SUM(C30:N30) -> -135761.7 | Q30: =Alder!Q30+Beacon!Q30+Cobalt!Q30+Delta!Q30+Ember!Q30+Falcon!Q30+Granite!Q30+Hollis!Q30+SAFEREG!Q30 -> -10738.6 | R30: =Alder!R30+Beacon!R30+Cobalt!R30+Delta!R30+Ember!R30+Falcon!R30+Granite!R30+Hollis!R30+SAFEREG!R30 -> -10538.3 | S30: =Alder!S30+Beacon!S30+Cobalt!S30+Delta!S30+Ember!S30+Falcon!S30+Granite!S30+Hollis!S30+SAFEREG!S30 -> -11305 | T30: =Alder!T30+Beacon!T30+Cobalt!T30+Delta!T30+Ember!T30+Falcon!T30+Granite!T30+Hollis!T30+SAFEREG!T30 -> -12182 | U30: =Alder!U30+Beacon!U30+Cobalt!U30+Delta!U30+Ember!U30+Falcon!U30+Granite!U30+Hollis!U30+SAFEREG!U30 -> -11125.4 | V30: =Alder!V30+Beacon!V30+Cobalt!V30+Delta!V30+Ember!V30+Falcon!V30+Granite!V30+Hollis!V30+SAFEREG!V30 -> -11606 | W30: =Alder!W30+Beacon!W30+Cobalt!W30+Delta!W30+Ember!W30+Falcon!W30+Granite!W30+Hollis!W30+SAFEREG!W30 -> -11507 | X30: =Alder!X30+Beacon!X30+Cobalt!X30+Delta!X30+Ember!X30+Falcon!X30+Granite!X30+Hollis!X30+SAFEREG!X30 -> -11395.8 | ... AB30: =Alder!AB30+Beacon!AB30+Cobalt!AB30+Delta!AB30+Ember!AB30+Falcon!AB30+Granite!AB30+Hollis!AB30+SAFEREG!AB30 -> -11649.7 | AC30: =SUM(Q30:AB30) -> -135725.7 | AE30: =Q30-C30 -> 0 | AF30: =R30-D30 -> 0 | AG30: =S30-E30 -> 0 | AH30: =T30-F30 -> 0 | AI30: =U30-G30 -> 0 | AJ30: =V30-H30 -> 0 | AK30: =W30-I30 -> 0 | AL30: =X30-J30 -> 0 | ... AP30: =AB30-N30 -> 9 | AQ30: =SUM(AE30:AP30) -> 36 | AS30: =-'Safety-Adj'!C63-'Safety-Adj'!C89 -> 0 | AT30: =-'Safety-Adj'!D63-'Safety-Adj'!D89 -> 0 | AU30: =-'Safety-Adj'!E63-'Safety-Adj'!E89 -> 0 | AV30: =-'Safety-Adj'!F63-'Safety-Adj'!F89 -> 0 | AW30: =-'Safety-Adj'!G63-'Safety-Adj'!G89 -> 0 | AX30: =-'Safety-Adj'!H63-'Safety-Adj'!H89 -> 0 | AY30: =-'Safety-Adj'!I63-'Safety-Adj'!I89 -> 0 | AZ30: =-'Safety-Adj'!J63-'Safety-Adj'!J89 -> 0 | ... BD30: =-'Safety-Adj'!N63-'Safety-Adj'!N89 -> 227 | BE30: =SUM(AS30:BD30) -> 738 | BG30: =C30+AE30+AS30 -> -10738.6 | BH30: =D30+AF30+AT30 -> -10538.3 | BI30: =E30+AG30+AU30 -> -11305 | BJ30: =F30+AH30+AV30 -> -12182 | BK30: =G30+AI30+AW30 -> -11125.4 | BL30: =H30+AJ30+AX30 -> -11606 | BM30: =I30+AK30+AY30 -> -11507 | BN30: =J30+AL30+AZ30 -> -11395.8 | ... BR30: =N30+AP30+BD30 -> -11422.7 | BS30: =SUM(BG30:BR30) -> -134987.7 | BU30: =SUM(BG30:BO30)-SUM(C30:K30) -> 151 | BV30: =SUM(BG30:BO30)-SUM(C53:K53) -> -634.1 | BW30: =SUM(BG30:BO30)-SUM(C66:K66) -> -3569 | BY30: =SUM(BP30:BR30)-SUM(L30:N30) -> 623 | BZ30: =SUM(BP30:BR30)-SUM(L53:N53) -> 372.8 | CA30: =SUM(BP30:BR30)-SUM(L66:N66) -> -637.7 | CC30: =BS30-O30 -> 774 | CD30: =BS30-O53 -> -261.3 | CE30: =BS30-O66 -> -4206.7
B31: PBITA | C31: =C29+C30 -> 4997 | D31: =D29+D30 -> 4906.5 | E31: =E29+E30 -> 5231.9 | F31: =F29+F30 -> 5757.6 | G31: =G29+G30 -> 5220.2 | H31: =H29+H30 -> 5179.8 | I31: =I29+I30 -> 5170.1 | J31: =J29+J30 -> 4903.1 | ... N31: =N29+N30 -> 5349.6 | O31: =SUM(C31:N31) -> 61957 | Q31: =Q29+Q30 -> 4997 | R31: =R29+R30 -> 4906.5 | S31: =S29+S30 -> 5231.9 | T31: =T29+T30 -> 5757.6 | U31: =U29+U30 -> 5220.2 | V31: =V29+V30 -> 5179.8 | W31: =W29+W30 -> 5170.1 | X31: =X29+X30 -> 4903.1 | ... AB31: =AB29+AB30 -> 5345.6 | AC31: =SUM(Q31:AB31) -> 61941 | AE31: =AE29+AE30 -> 0 | AF31: =AF29+AF30 -> 0 | AG31: =AG29+AG30 -> 0 | AH31: =AH29+AH30 -> 0 | AI31: =AI29+AI30 -> 0 | AJ31: =AJ29+AJ30 -> 0 | AK31: =AK29+AK30 -> 0 | AL31: =AL29+AL30 -> 0 | ... AP31: =AP29+AP30 -> -4 | AQ31: =SUM(AE31:AP31) -> -16 | AS31: =AS29+AS30 -> 0 | AT31: =AT29+AT30 -> 0 | AU31: =AU29+AU30 -> 0 | AV31: =AV29+AV30 -> 0 | AW31: =AW29+AW30 -> 0 | AX31: =AX29+AX30 -> 0 | AY31: =AY29+AY30 -> 0 | AZ31: =AZ29+AZ30 -> 0 | ... BD31: =BD29+BD30 -> 466.08 | BE31: =SUM(AS31:BD31) -> 603.32 | BG31: =BG29+BG30 -> 4997 | BH31: =BH29+BH30 -> 4906.5 | BI31: =BI29+BI30 -> 5231.9 | BJ31: =BJ29+BJ30 -> 5757.6 | BK31: =BK29+BK30 -> 5220.2 | BL31: =BL29+BL30 -> 5179.8 | BM31: =BM29+BM30 -> 5170.1 | BN31: =BN29+BN30 -> 4903.1 | ... BR31: =BR29+BR30 -> 5811.68 | BS31: =SUM(BG31:BR31) -> 62544.32 | BU31: =SUM(BG31:BO31)-SUM(C31:K31) -> 65.08 | BV31: =SUM(BG31:BO31)-SUM(C54:K54) -> 1645.78 | BW31: =SUM(BG31:BO31)-SUM(C67:K67) -> 5348.68 | BY31: =SUM(BP31:BR31)-SUM(L31:N31) -> 522.24 | BZ31: =SUM(BP31:BR31)-SUM(L54:N54) -> 875.44 | CA31: =SUM(BP31:BR31)-SUM(L67:N67) -> 1996.44 | CC31: =BS31-O31 -> 587.32 | CD31: =BS31-O54 -> 2521.22 | CE31: =BS31-O67 -> 7345.12
B35: GM % | C35: =IFERROR(C29/C28,0) -> 0.31612381 | D35: =IFERROR(D29/D28,0) -> 0.3149853 | E35: =IFERROR(E29/E28,0) -> 0.31445908 | F35: =IFERROR(F29/F28,0) -> 0.31538328 | G35: =IFERROR(G29/G28,0) -> 0.31534818 | H35: =IFERROR(H29/H28,0) -> 0.31013541 | I35: =IFERROR(I29/I28,0) -> 0.30982951 | J35: =IFERROR(J29/J28,0) -> 0.30938682 | ... O35: =IFERROR(O29/O28,0) -> 0.31197385 | Q35: =IFERROR(Q29/Q28,0) -> 0.31612381 | R35: =IFERROR(R29/R28,0) -> 0.3149853 | S35: =IFERROR(S29/S28,0) -> 0.31445908 | T35: =IFERROR(T29/T28,0) -> 0.31538328 | U35: =IFERROR(U29/U28,0) -> 0.31534818 | V35: =IFERROR(V29/V28,0) -> 0.31013541 | W35: =IFERROR(W29/W28,0) -> 0.30982951 | X35: =IFERROR(X29/X28,0) -> 0.30938682 | ... AC35: =IFERROR(AC29/AC28,0) -> 0.31198041 | AE35: =IFERROR(AE29/AE28,0) -> 0 | AF35: =IFERROR(AF29/AF28,0) -> 0 | AG35: =IFERROR(AG29/AG28,0) -> 0 | AH35: =IFERROR(AH29/AH28,0) -> 0 | AI35: =IFERROR(AI29/AI28,0) -> 0 | AJ35: =IFERROR(AJ29/AJ28,0) -> 0 | AK35: =IFERROR(AK29/AK28,0) -> 0 | AL35: =IFERROR(AL29/AL28,0) -> 0 | ... AQ35: =IFERROR(AQ29/AQ28,0) -> 0.28888889 | AS35: =IFERROR(AS29/AS28,0) -> 0 | AT35: =IFERROR(AT29/AT28,0) -> 0 | AU35: =IFERROR(AU29/AU28,0) -> 0 | AV35: =IFERROR(AV29/AV28,0) -> 0 | AW35: =IFERROR(AW29/AW28,0) -> 0 | AX35: =IFERROR(AX29/AX28,0) -> 0 | AY35: =IFERROR(AY29/AY28,0) -> 0 | AZ35: =IFERROR(AZ29/AZ28,0) -> 0 | ... BE35: =IFERROR(BE29/BE28,0) -> -0.2362807 | BG35: =IFERROR(BG29/BG28,0) -> 0.31612381 | BH35: =IFERROR(BH29/BH28,0) -> 0.3149853 | BI35: =IFERROR(BI29/BI28,0) -> 0.31445908 | BJ35: =IFERROR(BJ29/BJ28,0) -> 0.31538328 | BK35: =IFERROR(BK29/BK28,0) -> 0.31534818 | BL35: =IFERROR(BL29/BL28,0) -> 0.31013541 | BM35: =IFERROR(BM29/BM28,0) -> 0.30982951 | BN35: =IFERROR(BN29/BN28,0) -> 0.30938682 | ... BS35: =IFERROR(BS29/BS28,0) -> 0.31148761
B36: Op Cost % | C36: =IFERROR(C30/C28,0) -> -0.21573547 | D36: =IFERROR(D30/D28,0) -> -0.21492085 | E36: =IFERROR(E30/E28,0) -> -0.21497136 | F36: =IFERROR(F30/F28,0) -> -0.21416303 | G36: =IFERROR(G30/G28,0) -> -0.21463725 | H36: =IFERROR(H30/H28,0) -> -0.21443313 | I36: =IFERROR(I30/I28,0) -> -0.21377866 | J36: =IFERROR(J30/J28,0) -> -0.21631585 | ... O36: =IFERROR(O30/O28,0) -> -0.21421393 | Q36: =IFERROR(Q30/Q28,0) -> -0.21573547 | R36: =IFERROR(R30/R28,0) -> -0.21492085 | S36: =IFERROR(S30/S28,0) -> -0.21497136 | T36: =IFERROR(T30/T28,0) -> -0.21416303 | U36: =IFERROR(U30/U28,0) -> -0.21463725 | V36: =IFERROR(V30/V28,0) -> -0.21443313 | W36: =IFERROR(W30/W28,0) -> -0.21377866 | X36: =IFERROR(X30/X28,0) -> -0.21631585 | ... AC36: =IFERROR(AC30/AC28,0) -> -0.21421797 | AE36: =IFERROR(AE30/AE28,0) -> 0 | AF36: =IFERROR(AF30/AF28,0) -> 0 | AG36: =IFERROR(AG30/AG28,0) -> 0 | AH36: =IFERROR(AH30/AH28,0) -> 0 | AI36: =IFERROR(AI30/AI28,0) -> 0 | AJ36: =IFERROR(AJ30/AJ28,0) -> 0 | AK36: =IFERROR(AK30/AK28,0) -> 0 | AL36: =IFERROR(AL30/AL28,0) -> 0 | ... AQ36: =IFERROR(AQ30/AQ28,0) -> -0.2 | AS36: =IFERROR(AS30/AS28,0) -> 0 | AT36: =IFERROR(AT30/AT28,0) -> 0 | AU36: =IFERROR(AU30/AU28,0) -> 0 | AV36: =IFERROR(AV30/AV28,0) -> 0 | AW36: =IFERROR(AW30/AW28,0) -> 0 | AX36: =IFERROR(AX30/AX28,0) -> 0 | AY36: =IFERROR(AY30/AY28,0) -> 0 | AZ36: =IFERROR(AZ30/AZ28,0) -> 0 | ... BE36: =IFERROR(BE30/BE28,0) -> 1.2947368 | BG36: =IFERROR(BG30/BG28,0) -> -0.21573547 | BH36: =IFERROR(BH30/BH28,0) -> -0.21492085 | BI36: =IFERROR(BI30/BI28,0) -> -0.21497136 | BJ36: =IFERROR(BJ30/BJ28,0) -> -0.21416303 | BK36: =IFERROR(BK30/BK28,0) -> -0.21463725 | BL36: =IFERROR(BL30/BL28,0) -> -0.21443313 | BM36: =IFERROR(BM30/BM28,0) -> -0.21377866 | BN36: =IFERROR(BN30/BN28,0) -> -0.21631585 | ... BS36: =IFERROR(BS30/BS28,0) -> -0.21286168
B37: PBITA % | C37: =IFERROR(C31/C28,0) -> 0.10038833 | D37: =IFERROR(D31/D28,0) -> 0.10006445 | E37: =IFERROR(E31/E28,0) -> 0.09948772 | F37: =IFERROR(F31/F28,0) -> 0.10122025 | G37: =IFERROR(G31/G28,0) -> 0.10071093 | H37: =IFERROR(H31/H28,0) -> 0.095702284 | I37: =IFERROR(I31/I28,0) -> 0.096050845 | J37: =IFERROR(J31/J28,0) -> 0.093070976 | ... O37: =IFERROR(O31/O28,0) -> 0.097759918 | Q37: =IFERROR(Q31/Q28,0) -> 0.10038833 | R37: =IFERROR(R31/R28,0) -> 0.10006445 | S37: =IFERROR(S31/S28,0) -> 0.09948772 | T37: =IFERROR(T31/T28,0) -> 0.10122025 | U37: =IFERROR(U31/U28,0) -> 0.10071093 | V37: =IFERROR(V31/V28,0) -> 0.095702284 | W37: =IFERROR(W31/W28,0) -> 0.096050845 | X37: =IFERROR(X31/X28,0) -> 0.093070976 | ... AC37: =IFERROR(AC31/AC28,0) -> 0.097762438 | AE37: =IFERROR(AE31/AE28,0) -> 0 | AF37: =IFERROR(AF31/AF28,0) -> 0 | AG37: =IFERROR(AG31/AG28,0) -> 0 | AH37: =IFERROR(AH31/AH28,0) -> 0 | AI37: =IFERROR(AI31/AI28,0) -> 0 | AJ37: =IFERROR(AJ31/AJ28,0) -> 0 | AK37: =IFERROR(AK31/AK28,0) -> 0 | AL37: =IFERROR(AL31/AL28,0) -> 0 | ... AQ37: =IFERROR(AQ31/AQ28,0) -> 0.088888889 | AS37: =IFERROR(AS31/AS28,0) -> 0 | AT37: =IFERROR(AT31/AT28,0) -> 0 | AU37: =IFERROR(AU31/AU28,0) -> 0 | AV37: =IFERROR(AV31/AV28,0) -> 0 | AW37: =IFERROR(AW31/AW28,0) -> 0 | AX37: =IFERROR(AX31/AX28,0) -> 0 | AY37: =IFERROR(AY31/AY28,0) -> 0 | AZ37: =IFERROR(AZ31/AZ28,0) -> 0 | ... BE37: =IFERROR(BE31/BE28,0) -> 1.0584561 | BG37: =IFERROR(BG31/BG28,0) -> 0.10038833 | BH37: =IFERROR(BH31/BH28,0) -> 0.10006445 | BI37: =IFERROR(BI31/BI28,0) -> 0.09948772 | BJ37: =IFERROR(BJ31/BJ28,0) -> 0.10122025 | BK37: =IFERROR(BK31/BK28,0) -> 0.10071093 | BL37: =IFERROR(BL31/BL28,0) -> 0.095702284 | BM37: =IFERROR(BM31/BM28,0) -> 0.096050845 | BN37: =IFERROR(BN31/BN28,0) -> 0.093070976 | ... BS37: =IFERROR(BS31/BS28,0) -> 0.098625939
B38: Sales/Day | C38: =IFERROR(C28/21,0) -> 2370.319 | D38: =IFERROR(D28/20,0) -> 2451.67 | E38: =IFERROR(E28/22,0) -> 2390.3818 | F38: =IFERROR(F28/22,0) -> 2585.5409 | G38: =IFERROR(G28/20,0) -> 2591.675 | H38: =IFERROR(H28/22,0) -> 2460.1864 | I38: =IFERROR(I28/22,0) -> 2446.6682 | J38: =IFERROR(J28/21,0) -> 2508.6333 | K38: =IFERROR(K28/21,0) -> 2485.4952 | L38: =IFERROR(L28/22,0) -> 2522.9682 | M38: =IFERROR(M28/19,0) -> 2649 | N38: =IFERROR(N28/22,0) -> 2499.5091 | O38: =IFERROR(O28/254,0) -> 2495.1453 | Q38: =IFERROR(Q28/21,0) -> 2370.319 | R38: =IFERROR(R28/20,0) -> 2451.67 | S38: =IFERROR(S28/22,0) -> 2390.3818 | T38: =IFERROR(T28/22,0) -> 2585.5409 | U38: =IFERROR(U28/20,0) -> 2591.675 | V38: =IFERROR(V28/22,0) -> 2460.1864 | W38: =IFERROR(W28/22,0) -> 2446.6682 | X38: =IFERROR(X28/21,0) -> 2508.6333 | Y38: =IFERROR(Y28/21,0) -> 2483.3524 | Z38: =IFERROR(Z28/22,0) -> 2520.9227 | AA38: =IFERROR(AA28/19,0) -> 2646.6316 | AB38: =IFERROR(AB28/22,0) -> 2497.4636 | AC38: =IFERROR(AC28/254,0) -> 2494.4366 | AE38: =IFERROR(AE28/21,0) -> 0 | AF38: =IFERROR(AF28/20,0) -> 0 | AG38: =IFERROR(AG28/22,0) -> 0 | AH38: =IFERROR(AH28/22,0) -> 0 | AI38: =IFERROR(AI28/20,0) -> 0 | AJ38: =IFERROR(AJ28/22,0) -> 0 | AK38: =IFERROR(AK28/22,0) -> 0 | AL38: =IFERROR(AL28/21,0) -> 0 | AM38: =IFERROR(AM28/21,0) -> -2.1428571 | AN38: =IFERROR(AN28/22,0) -> -2.0454545 | AO38: =IFERROR(AO28/19,0) -> -2.3684211 | AP38: =IFERROR(AP28/22,0) -> -2.0454545 | AQ38: =IFERROR(AQ28/254,0) -> -0.70866142 | AS38: =IFERROR(AS28/21,0) -> 0 | AT38: =IFERROR(AT28/20,0) -> 0 | AU38: =IFERROR(AU28/22,0) -> 0 | AV38: =IFERROR(AV28/22,0) -> 0 | AW38: =IFERROR(AW28/20,0) -> 0 | AX38: =IFERROR(AX28/22,0) -> 0 | AY38: =IFERROR(AY28/22,0) -> 0 | AZ38: =IFERROR(AZ28/21,0) -> 0 | BA38: =IFERROR(BA28/21,0) -> 70.952381 | BB38: =IFERROR(BB28/22,0) -> -47.272727 | BC38: =IFERROR(BC28/19,0) -> -11.578947 | BD38: =IFERROR(BD28/22,0) -> 15.454545 | BE38: =IFERROR(BE28/254,0) -> 2.2440945 | BG38: =IFERROR(BG28/21,0) -> 2370.319 | BH38: =IFERROR(BH28/20,0) -> 2451.67 | BI38: =IFERROR(BI28/22,0) -> 2390.3818 | BJ38: =IFERROR(BJ28/22,0) -> 2585.5409 | BK38: =IFERROR(BK28/20,0) -> 2591.675 | BL38: =IFERROR(BL28/22,0) -> 2460.1864 | BM38: =IFERROR(BM28/22,0) -> 2446.6682 | BN38: =IFERROR(BN28/21,0) -> 2508.6333 | BO38: =IFERROR(BO28/21,0) -> 2554.3048 | BP38: =IFERROR(BP28/22,0) -> 2473.65 | BQ38: =IFERROR(BQ28/19,0) -> 2635.0526 | BR38: =IFERROR(BR28/22,0) -> 2512.9182 | BS38: =IFERROR(BS28/254,0) -> 2496.6807
B40: Net Inventory | C40: =Alder!C40+Beacon!C40+Cobalt!C40+Delta!C40+Ember!C40+Falcon!C40+Granite!C40+Hollis!C40+SAFEREG!C40 -> 85813.1 | D40: =Alder!D40+Beacon!D40+Cobalt!D40+Delta!D40+Ember!D40+Falcon!D40+Granite!D40+Hollis!D40+SAFEREG!D40 -> 85188.2 | E40: =Alder!E40+Beacon!E40+Cobalt!E40+Delta!E40+Ember!E40+Falcon!E40+Granite!E40+Hollis!E40+SAFEREG!E40 -> 90743.6 | F40: =Alder!F40+Beacon!F40+Cobalt!F40+Delta!F40+Ember!F40+Falcon!F40+Granite!F40+Hollis!F40+SAFEREG!F40 -> 98182 | G40: =Alder!G40+Beacon!G40+Cobalt!G40+Delta!G40+Ember!G40+Falcon!G40+Granite!G40+Hollis!G40+SAFEREG!G40 -> 87470.4 | H40: =Alder!H40+Beacon!H40+Cobalt!H40+Delta!H40+Ember!H40+Falcon!H40+Granite!H40+Hollis!H40+SAFEREG!H40 -> 88474.9 | I40: =Alder!I40+Beacon!I40+Cobalt!I40+Delta!I40+Ember!I40+Falcon!I40+Granite!I40+Hollis!I40+SAFEREG!I40 -> 86267.1 | J40: =Alder!J40+Beacon!J40+Cobalt!J40+Delta!J40+Ember!J40+Falcon!J40+Granite!J40+Hollis!J40+SAFEREG!J40 -> 81103.4 | ... N40: =Alder!N40+Beacon!N40+Cobalt!N40+Delta!N40+Ember!N40+Falcon!N40+Granite!N40+Hollis!N40+SAFEREG!N40 -> 84145.9 | O40: =N40 -> 84145.9 | Q40: =Alder!Q40+Beacon!Q40+Cobalt!Q40+Delta!Q40+Ember!Q40+Falcon!Q40+Granite!Q40+Hollis!Q40+SAFEREG!Q40 -> 85813.1 | R40: =Alder!R40+Beacon!R40+Cobalt!R40+Delta!R40+Ember!R40+Falcon!R40+Granite!R40+Hollis!R40+SAFEREG!R40 -> 85188.2 | S40: =Alder!S40+Beacon!S40+Cobalt!S40+Delta!S40+Ember!S40+Falcon!S40+Granite!S40+Hollis!S40+SAFEREG!S40 -> 90743.6 | T40: =Alder!T40+Beacon!T40+Cobalt!T40+Delta!T40+Ember!T40+Falcon!T40+Granite!T40+Hollis!T40+SAFEREG!T40 -> 98182 | U40: =Alder!U40+Beacon!U40+Cobalt!U40+Delta!U40+Ember!U40+Falcon!U40+Granite!U40+Hollis!U40+SAFEREG!U40 -> 87470.4 | V40: =Alder!V40+Beacon!V40+Cobalt!V40+Delta!V40+Ember!V40+Falcon!V40+Granite!V40+Hollis!V40+SAFEREG!V40 -> 88474.9 | W40: =Alder!W40+Beacon!W40+Cobalt!W40+Delta!W40+Ember!W40+Falcon!W40+Granite!W40+Hollis!W40+SAFEREG!W40 -> 86267.1 | X40: =Alder!X40+Beacon!X40+Cobalt!X40+Delta!X40+Ember!X40+Falcon!X40+Granite!X40+Hollis!X40+SAFEREG!X40 -> 81103.4 | ... AB40: =Alder!AB40+Beacon!AB40+Cobalt!AB40+Delta!AB40+Ember!AB40+Falcon!AB40+Granite!AB40+Hollis!AB40+SAFEREG!AB40 -> 84145.9 | AC40: =AB40 -> 84145.9 | AE40: =Q40-C40 -> 0 | AF40: =R40-D40 -> 0 | AG40: =S40-E40 -> 0 | AH40: =T40-F40 -> 0 | AI40: =U40-G40 -> 0 | AJ40: =V40-H40 -> 0 | AK40: =W40-I40 -> 0 | AL40: =X40-J40 -> 0 | ... AP40: =AB40-N40 -> 0 | AQ40: =AP40 -> 0 | AS40: ='Safety-Adj'!C95 -> 0 | AT40: ='Safety-Adj'!D95 -> 0 | AU40: ='Safety-Adj'!E95 -> 0 | AV40: ='Safety-Adj'!F95 -> 0 | AW40: ='Safety-Adj'!G95 -> 0 | AX40: ='Safety-Adj'!H95 -> 0 | AY40: ='Safety-Adj'!I95 -> 0 | AZ40: ='Safety-Adj'!J95 -> 0 | ... BD40: ='Safety-Adj'!N95 -> -4000 | BE40: =BD40 -> -4000 | BG40: =C40+AE40+AS40 -> 85813.1 | BH40: =D40+AF40+AT40 -> 85188.2 | BI40: =E40+AG40+AU40 -> 90743.6 | BJ40: =F40+AH40+AV40 -> 98182 | BK40: =G40+AI40+AW40 -> 87470.4 | BL40: =H40+AJ40+AX40 -> 88474.9 | BM40: =I40+AK40+AY40 -> 86267.1 | BN40: =J40+AL40+AZ40 -> 81103.4 | ... BR40: =N40+AP40+BD40 -> 80145.9 | BS40: =BR40 -> 80145.9
B41: Trade Receivables | C41: =Alder!C41+Beacon!C41+Cobalt!C41+Delta!C41+Ember!C41+Falcon!C41+Granite!C41+Hollis!C41+SAFEREG!C41 -> 75494.8 | D41: =Alder!D41+Beacon!D41+Cobalt!D41+Delta!D41+Ember!D41+Falcon!D41+Granite!D41+Hollis!D41+SAFEREG!D41 -> 74367.2 | E41: =Alder!E41+Beacon!E41+Cobalt!E41+Delta!E41+Ember!E41+Falcon!E41+Granite!E41+Hollis!E41+SAFEREG!E41 -> 79758.9 | F41: =Alder!F41+Beacon!F41+Cobalt!F41+Delta!F41+Ember!F41+Falcon!F41+Granite!F41+Hollis!F41+SAFEREG!F41 -> 86270.8 | G41: =Alder!G41+Beacon!G41+Cobalt!G41+Delta!G41+Ember!G41+Falcon!G41+Granite!G41+Hollis!G41+SAFEREG!G41 -> 78614.2 | H41: =Alder!H41+Beacon!H41+Cobalt!H41+Delta!H41+Ember!H41+Falcon!H41+Granite!H41+Hollis!H41+SAFEREG!H41 -> 82088.2 | I41: =Alder!I41+Beacon!I41+Cobalt!I41+Delta!I41+Ember!I41+Falcon!I41+Granite!I41+Hollis!I41+SAFEREG!I41 -> 81637.3 | J41: =Alder!J41+Beacon!J41+Cobalt!J41+Delta!J41+Ember!J41+Falcon!J41+Granite!J41+Hollis!J41+SAFEREG!J41 -> 79900 | ... N41: =Alder!N41+Beacon!N41+Cobalt!N41+Delta!N41+Ember!N41+Falcon!N41+Granite!N41+Hollis!N41+SAFEREG!N41 -> 83847.7 | O41: =N41 -> 83847.7 | Q41: =Alder!Q41+Beacon!Q41+Cobalt!Q41+Delta!Q41+Ember!Q41+Falcon!Q41+Granite!Q41+Hollis!Q41+SAFEREG!Q41 -> 75494.8 | R41: =Alder!R41+Beacon!R41+Cobalt!R41+Delta!R41+Ember!R41+Falcon!R41+Granite!R41+Hollis!R41+SAFEREG!R41 -> 74367.2 | S41: =Alder!S41+Beacon!S41+Cobalt!S41+Delta!S41+Ember!S41+Falcon!S41+Granite!S41+Hollis!S41+SAFEREG!S41 -> 79758.9 | T41: =Alder!T41+Beacon!T41+Cobalt!T41+Delta!T41+Ember!T41+Falcon!T41+Granite!T41+Hollis!T41+SAFEREG!T41 -> 86270.8 | U41: =Alder!U41+Beacon!U41+Cobalt!U41+Delta!U41+Ember!U41+Falcon!U41+Granite!U41+Hollis!U41+SAFEREG!U41 -> 78614.2 | V41: =Alder!V41+Beacon!V41+Cobalt!V41+Delta!V41+Ember!V41+Falcon!V41+Granite!V41+Hollis!V41+SAFEREG!V41 -> 82088.2 | W41: =Alder!W41+Beacon!W41+Cobalt!W41+Delta!W41+Ember!W41+Falcon!W41+Granite!W41+Hollis!W41+SAFEREG!W41 -> 81637.3 | X41: =Alder!X41+Beacon!X41+Cobalt!X41+Delta!X41+Ember!X41+Falcon!X41+Granite!X41+Hollis!X41+SAFEREG!X41 -> 79900 | ... AB41: =Alder!AB41+Beacon!AB41+Cobalt!AB41+Delta!AB41+Ember!AB41+Falcon!AB41+Granite!AB41+Hollis!AB41+SAFEREG!AB41 -> 83847.7 | AC41: =AB41 -> 83847.7 | AE41: =Q41-C41 -> 0 | AF41: =R41-D41 -> 0 | AG41: =S41-E41 -> 0 | AH41: =T41-F41 -> 0 | AI41: =U41-G41 -> 0 | AJ41: =V41-H41 -> 0 | AK41: =W41-I41 -> 0 | AL41: =X41-J41 -> 0 | ... AP41: =AB41-N41 -> 0 | AQ41: =AP41 -> 0 | AS41: ='Safety-Adj'!C96 -> 0 | AT41: ='Safety-Adj'!D96 -> 0 | AU41: ='Safety-Adj'!E96 -> 0 | AV41: ='Safety-Adj'!F96 -> 0 | AW41: ='Safety-Adj'!G96 -> 0 | AX41: ='Safety-Adj'!H96 -> 0 | AY41: ='Safety-Adj'!I96 -> 0 | AZ41: ='Safety-Adj'!J96 -> 0 | ... BD41: ='Safety-Adj'!N96 -> 0 | BE41: =BD41 -> 0 | BG41: =C41+AE41+AS41 -> 75494.8 | BH41: =D41+AF41+AT41 -> 74367.2 | BI41: =E41+AG41+AU41 -> 79758.9 | BJ41: =F41+AH41+AV41 -> 86270.8 | BK41: =G41+AI41+AW41 -> 78614.2 | BL41: =H41+AJ41+AX41 -> 82088.2 | BM41: =I41+AK41+AY41 -> 81637.3 | BN41: =J41+AL41+AZ41 -> 79900 | ... BR41: =N41+AP41+BD41 -> 83847.7 | BS41: =BR41 -> 83847.7
B42: Other Receivables | C42: =Alder!C42+Beacon!C42+Cobalt!C42+Delta!C42+Ember!C42+Falcon!C42+Granite!C42+Hollis!C42+SAFEREG!C42 -> 771.6 | D42: =Alder!D42+Beacon!D42+Cobalt!D42+Delta!D42+Ember!D42+Falcon!D42+Granite!D42+Hollis!D42+SAFEREG!D42 -> 760.5 | E42: =Alder!E42+Beacon!E42+Cobalt!E42+Delta!E42+Ember!E42+Falcon!E42+Granite!E42+Hollis!E42+SAFEREG!E42 -> 813.8 | F42: =Alder!F42+Beacon!F42+Cobalt!F42+Delta!F42+Ember!F42+Falcon!F42+Granite!F42+Hollis!F42+SAFEREG!F42 -> 878.2 | G42: =Alder!G42+Beacon!G42+Cobalt!G42+Delta!G42+Ember!G42+Falcon!G42+Granite!G42+Hollis!G42+SAFEREG!G42 -> 802.4 | H42: =Alder!H42+Beacon!H42+Cobalt!H42+Delta!H42+Ember!H42+Falcon!H42+Granite!H42+Hollis!H42+SAFEREG!H42 -> 837 | I42: =Alder!I42+Beacon!I42+Cobalt!I42+Delta!I42+Ember!I42+Falcon!I42+Granite!I42+Hollis!I42+SAFEREG!I42 -> 832.4 | J42: =Alder!J42+Beacon!J42+Cobalt!J42+Delta!J42+Ember!J42+Falcon!J42+Granite!J42+Hollis!J42+SAFEREG!J42 -> 815.2 | ... N42: =Alder!N42+Beacon!N42+Cobalt!N42+Delta!N42+Ember!N42+Falcon!N42+Granite!N42+Hollis!N42+SAFEREG!N42 -> 854.2 | O42: =N42 -> 854.2 | Q42: =Alder!Q42+Beacon!Q42+Cobalt!Q42+Delta!Q42+Ember!Q42+Falcon!Q42+Granite!Q42+Hollis!Q42+SAFEREG!Q42 -> 771.6 | R42: =Alder!R42+Beacon!R42+Cobalt!R42+Delta!R42+Ember!R42+Falcon!R42+Granite!R42+Hollis!R42+SAFEREG!R42 -> 760.5 | S42: =Alder!S42+Beacon!S42+Cobalt!S42+Delta!S42+Ember!S42+Falcon!S42+Granite!S42+Hollis!S42+SAFEREG!S42 -> 813.8 | T42: =Alder!T42+Beacon!T42+Cobalt!T42+Delta!T42+Ember!T42+Falcon!T42+Granite!T42+Hollis!T42+SAFEREG!T42 -> 878.2 | U42: =Alder!U42+Beacon!U42+Cobalt!U42+Delta!U42+Ember!U42+Falcon!U42+Granite!U42+Hollis!U42+SAFEREG!U42 -> 802.4 | V42: =Alder!V42+Beacon!V42+Cobalt!V42+Delta!V42+Ember!V42+Falcon!V42+Granite!V42+Hollis!V42+SAFEREG!V42 -> 837 | W42: =Alder!W42+Beacon!W42+Cobalt!W42+Delta!W42+Ember!W42+Falcon!W42+Granite!W42+Hollis!W42+SAFEREG!W42 -> 832.4 | X42: =Alder!X42+Beacon!X42+Cobalt!X42+Delta!X42+Ember!X42+Falcon!X42+Granite!X42+Hollis!X42+SAFEREG!X42 -> 815.2 | ... AB42: =Alder!AB42+Beacon!AB42+Cobalt!AB42+Delta!AB42+Ember!AB42+Falcon!AB42+Granite!AB42+Hollis!AB42+SAFEREG!AB42 -> 854.2 | AC42: =AB42 -> 854.2 | AE42: =Q42-C42 -> 0 | AF42: =R42-D42 -> 0 | AG42: =S42-E42 -> 0 | AH42: =T42-F42 -> 0 | AI42: =U42-G42 -> 0 | AJ42: =V42-H42 -> 0 | AK42: =W42-I42 -> 0 | AL42: =X42-J42 -> 0 | ... AP42: =AB42-N42 -> 0 | AQ42: =AP42 -> 0 | AS42: ='Safety-Adj'!C97 -> 0 | AT42: ='Safety-Adj'!D97 -> 0 | AU42: ='Safety-Adj'!E97 -> 0 | AV42: ='Safety-Adj'!F97 -> 0 | AW42: ='Safety-Adj'!G97 -> 0 | AX42: ='Safety-Adj'!H97 -> 0 | AY42: ='Safety-Adj'!I97 -> 0 | AZ42: ='Safety-Adj'!J97 -> 0 | ... BD42: ='Safety-Adj'!N97 -> 0 | BE42: =BD42 -> 0 | BG42: =C42+AE42+AS42 -> 771.6 | BH42: =D42+AF42+AT42 -> 760.5 | BI42: =E42+AG42+AU42 -> 813.8 | BJ42: =F42+AH42+AV42 -> 878.2 | BK42: =G42+AI42+AW42 -> 802.4 | BL42: =H42+AJ42+AX42 -> 837 | BM42: =I42+AK42+AY42 -> 832.4 | BN42: =J42+AL42+AZ42 -> 815.2 | ... BR42: =N42+AP42+BD42 -> 854.2 | BS42: =BR42 -> 854.2
B43: Trade Payables | C43: =Alder!C43+Beacon!C43+Cobalt!C43+Delta!C43+Ember!C43+Falcon!C43+Granite!C43+Hollis!C43+SAFEREG!C43 -> -48792.2 | D43: =Alder!D43+Beacon!D43+Cobalt!D43+Delta!D43+Ember!D43+Falcon!D43+Granite!D43+Hollis!D43+SAFEREG!D43 -> -48143.7 | E43: =Alder!E43+Beacon!E43+Cobalt!E43+Delta!E43+Ember!E43+Falcon!E43+Granite!E43+Hollis!E43+SAFEREG!E43 -> -51673.8 | F43: =Alder!F43+Beacon!F43+Cobalt!F43+Delta!F43+Ember!F43+Falcon!F43+Granite!F43+Hollis!F43+SAFEREG!F43 -> -55817.4 | G43: =Alder!G43+Beacon!G43+Cobalt!G43+Delta!G43+Ember!G43+Falcon!G43+Granite!G43+Hollis!G43+SAFEREG!G43 -> -50866 | H43: =Alder!H43+Beacon!H43+Cobalt!H43+Delta!H43+Ember!H43+Falcon!H43+Granite!H43+Hollis!H43+SAFEREG!H43 -> -53518.3 | I43: =Alder!I43+Beacon!I43+Cobalt!I43+Delta!I43+Ember!I43+Falcon!I43+Granite!I43+Hollis!I43+SAFEREG!I43 -> -53247.7 | J43: =Alder!J43+Beacon!J43+Cobalt!J43+Delta!J43+Ember!J43+Falcon!J43+Granite!J43+Hollis!J43+SAFEREG!J43 -> -52148 | ... N43: =Alder!N43+Beacon!N43+Cobalt!N43+Delta!N43+Ember!N43+Falcon!N43+Granite!N43+Hollis!N43+SAFEREG!N43 -> -54847.8 | O43: =N43 -> -54847.8 | Q43: =Alder!Q43+Beacon!Q43+Cobalt!Q43+Delta!Q43+Ember!Q43+Falcon!Q43+Granite!Q43+Hollis!Q43+SAFEREG!Q43 -> -48792.2 | R43: =Alder!R43+Beacon!R43+Cobalt!R43+Delta!R43+Ember!R43+Falcon!R43+Granite!R43+Hollis!R43+SAFEREG!R43 -> -48143.7 | S43: =Alder!S43+Beacon!S43+Cobalt!S43+Delta!S43+Ember!S43+Falcon!S43+Granite!S43+Hollis!S43+SAFEREG!S43 -> -51673.8 | T43: =Alder!T43+Beacon!T43+Cobalt!T43+Delta!T43+Ember!T43+Falcon!T43+Granite!T43+Hollis!T43+SAFEREG!T43 -> -55817.4 | U43: =Alder!U43+Beacon!U43+Cobalt!U43+Delta!U43+Ember!U43+Falcon!U43+Granite!U43+Hollis!U43+SAFEREG!U43 -> -50866 | V43: =Alder!V43+Beacon!V43+Cobalt!V43+Delta!V43+Ember!V43+Falcon!V43+Granite!V43+Hollis!V43+SAFEREG!V43 -> -53518.3 | W43: =Alder!W43+Beacon!W43+Cobalt!W43+Delta!W43+Ember!W43+Falcon!W43+Granite!W43+Hollis!W43+SAFEREG!W43 -> -53247.7 | X43: =Alder!X43+Beacon!X43+Cobalt!X43+Delta!X43+Ember!X43+Falcon!X43+Granite!X43+Hollis!X43+SAFEREG!X43 -> -52148 | ... AB43: =Alder!AB43+Beacon!AB43+Cobalt!AB43+Delta!AB43+Ember!AB43+Falcon!AB43+Granite!AB43+Hollis!AB43+SAFEREG!AB43 -> -54847.8 | AC43: =AB43 -> -54847.8 | AE43: =Q43-C43 -> 0 | AF43: =R43-D43 -> 0 | AG43: =S43-E43 -> 0 | AH43: =T43-F43 -> 0 | AI43: =U43-G43 -> 0 | AJ43: =V43-H43 -> 0 | AK43: =W43-I43 -> 0 | AL43: =X43-J43 -> 0 | ... AP43: =AB43-N43 -> 0 | AQ43: =AP43 -> 0 | AS43: ='Safety-Adj'!C98 -> 0 | AT43: ='Safety-Adj'!D98 -> 0 | AU43: ='Safety-Adj'!E98 -> 0 | AV43: ='Safety-Adj'!F98 -> 0 | AW43: ='Safety-Adj'!G98 -> 0 | AX43: ='Safety-Adj'!H98 -> 0 | AY43: ='Safety-Adj'!I98 -> 0 | AZ43: ='Safety-Adj'!J98 -> 0 | ... BD43: ='Safety-Adj'!N98 -> 0 | BE43: =BD43 -> 0 | BG43: =C43+AE43+AS43 -> -48792.2 | BH43: =D43+AF43+AT43 -> -48143.7 | BI43: =E43+AG43+AU43 -> -51673.8 | BJ43: =F43+AH43+AV43 -> -55817.4 | BK43: =G43+AI43+AW43 -> -50866 | BL43: =H43+AJ43+AX43 -> -53518.3 | BM43: =I43+AK43+AY43 -> -53247.7 | BN43: =J43+AL43+AZ43 -> -52148 | ... BR43: =N43+AP43+BD43 -> -54847.8 | BS43: =BR43 -> -54847.8
B44: Other Payables | C44: =Alder!C44+Beacon!C44+Cobalt!C44+Delta!C44+Ember!C44+Falcon!C44+Granite!C44+Hollis!C44+SAFEREG!C44 -> -1673.5 | D44: =Alder!D44+Beacon!D44+Cobalt!D44+Delta!D44+Ember!D44+Falcon!D44+Granite!D44+Hollis!D44+SAFEREG!D44 -> -1650.9 | E44: =Alder!E44+Beacon!E44+Cobalt!E44+Delta!E44+Ember!E44+Falcon!E44+Granite!E44+Hollis!E44+SAFEREG!E44 -> -1757.8 | F44: =Alder!F44+Beacon!F44+Cobalt!F44+Delta!F44+Ember!F44+Falcon!F44+Granite!F44+Hollis!F44+SAFEREG!F44 -> -1886.4 | G44: =Alder!G44+Beacon!G44+Cobalt!G44+Delta!G44+Ember!G44+Falcon!G44+Granite!G44+Hollis!G44+SAFEREG!G44 -> -1734.8 | H44: =Alder!H44+Beacon!H44+Cobalt!H44+Delta!H44+Ember!H44+Falcon!H44+Granite!H44+Hollis!H44+SAFEREG!H44 -> -1803.7 | I44: =Alder!I44+Beacon!I44+Cobalt!I44+Delta!I44+Ember!I44+Falcon!I44+Granite!I44+Hollis!I44+SAFEREG!I44 -> -1794.7 | J44: =Alder!J44+Beacon!J44+Cobalt!J44+Delta!J44+Ember!J44+Falcon!J44+Granite!J44+Hollis!J44+SAFEREG!J44 -> -1760.5 | ... N44: =Alder!N44+Beacon!N44+Cobalt!N44+Delta!N44+Ember!N44+Falcon!N44+Granite!N44+Hollis!N44+SAFEREG!N44 -> -1838.4 | O44: =N44 -> -1838.4 | Q44: =Alder!Q44+Beacon!Q44+Cobalt!Q44+Delta!Q44+Ember!Q44+Falcon!Q44+Granite!Q44+Hollis!Q44+SAFEREG!Q44 -> -1673.5 | R44: =Alder!R44+Beacon!R44+Cobalt!R44+Delta!R44+Ember!R44+Falcon!R44+Granite!R44+Hollis!R44+SAFEREG!R44 -> -1650.9 | S44: =Alder!S44+Beacon!S44+Cobalt!S44+Delta!S44+Ember!S44+Falcon!S44+Granite!S44+Hollis!S44+SAFEREG!S44 -> -1757.8 | T44: =Alder!T44+Beacon!T44+Cobalt!T44+Delta!T44+Ember!T44+Falcon!T44+Granite!T44+Hollis!T44+SAFEREG!T44 -> -1886.4 | U44: =Alder!U44+Beacon!U44+Cobalt!U44+Delta!U44+Ember!U44+Falcon!U44+Granite!U44+Hollis!U44+SAFEREG!U44 -> -1734.8 | V44: =Alder!V44+Beacon!V44+Cobalt!V44+Delta!V44+Ember!V44+Falcon!V44+Granite!V44+Hollis!V44+SAFEREG!V44 -> -1803.7 | W44: =Alder!W44+Beacon!W44+Cobalt!W44+Delta!W44+Ember!W44+Falcon!W44+Granite!W44+Hollis!W44+SAFEREG!W44 -> -1794.7 | X44: =Alder!X44+Beacon!X44+Cobalt!X44+Delta!X44+Ember!X44+Falcon!X44+Granite!X44+Hollis!X44+SAFEREG!X44 -> -1760.5 | ... AB44: =Alder!AB44+Beacon!AB44+Cobalt!AB44+Delta!AB44+Ember!AB44+Falcon!AB44+Granite!AB44+Hollis!AB44+SAFEREG!AB44 -> -1838.4 | AC44: =AB44 -> -1838.4 | AE44: =Q44-C44 -> 0 | AF44: =R44-D44 -> 0 | AG44: =S44-E44 -> 0 | AH44: =T44-F44 -> 0 | AI44: =U44-G44 -> 0 | AJ44: =V44-H44 -> 0 | AK44: =W44-I44 -> 0 | AL44: =X44-J44 -> 0 | ... AP44: =AB44-N44 -> 0 | AQ44: =AP44 -> 0 | AS44: ='Safety-Adj'!C99 -> 0 | AT44: ='Safety-Adj'!D99 -> 0 | AU44: ='Safety-Adj'!E99 -> 0 | AV44: ='Safety-Adj'!F99 -> 0 | AW44: ='Safety-Adj'!G99 -> 0 | AX44: ='Safety-Adj'!H99 -> 0 | AY44: ='Safety-Adj'!I99 -> 0 | AZ44: ='Safety-Adj'!J99 -> 0 | ... BD44: ='Safety-Adj'!N99 -> 0 | BE44: =BD44 -> 0 | BG44: =C44+AE44+AS44 -> -1673.5 | BH44: =D44+AF44+AT44 -> -1650.9 | BI44: =E44+AG44+AU44 -> -1757.8 | BJ44: =F44+AH44+AV44 -> -1886.4 | BK44: =G44+AI44+AW44 -> -1734.8 | BL44: =H44+AJ44+AX44 -> -1803.7 | BM44: =I44+AK44+AY44 -> -1794.7 | BN44: =J44+AL44+AZ44 -> -1760.5 | ... BR44: =N44+AP44+BD44 -> -1838.4 | BS44: =BR44 -> -1838.4
B45: Total working capital | C45: =SUM(C40:C44) -> 111613.8 | D45: =SUM(D40:D44) -> 110521.3 | E45: =SUM(E40:E44) -> 117884.7 | F45: =SUM(F40:F44) -> 127627.2 | G45: =SUM(G40:G44) -> 114286.2 | H45: =SUM(H40:H44) -> 116078.1 | I45: =SUM(I40:I44) -> 113694.4 | J45: =SUM(J40:J44) -> 107910.1 | ... N45: =SUM(N40:N44) -> 112161.6 | O45: =N45 -> 112161.6 | Q45: =SUM(Q40:Q44) -> 111613.8 | R45: =SUM(R40:R44) -> 110521.3 | S45: =SUM(S40:S44) -> 117884.7 | T45: =SUM(T40:T44) -> 127627.2 | U45: =SUM(U40:U44) -> 114286.2 | V45: =SUM(V40:V44) -> 116078.1 | W45: =SUM(W40:W44) -> 113694.4 | X45: =SUM(X40:X44) -> 107910.1 | ... AB45: =SUM(AB40:AB44) -> 112161.6 | AC45: =AB45 -> 112161.6 | AE45: =SUM(AE40:AE44) -> 0 | AF45: =SUM(AF40:AF44) -> 0 | AG45: =SUM(AG40:AG44) -> 0 | AH45: =SUM(AH40:AH44) -> 0 | AI45: =SUM(AI40:AI44) -> 0 | AJ45: =SUM(AJ40:AJ44) -> 0 | AK45: =SUM(AK40:AK44) -> 0 | AL45: =SUM(AL40:AL44) -> 0 | ... AP45: =SUM(AP40:AP44) -> 0 | AQ45: =AP45 -> 0 | AS45: =SUM(AS40:AS44) -> 0 | AT45: =SUM(AT40:AT44) -> 0 | AU45: =SUM(AU40:AU44) -> 0 | AV45: =SUM(AV40:AV44) -> 0 | AW45: =SUM(AW40:AW44) -> 0 | AX45: =SUM(AX40:AX44) -> 0 | AY45: =SUM(AY40:AY44) -> 0 | AZ45: =SUM(AZ40:AZ44) -> 0 | ... BD45: =SUM(BD40:BD44) -> -4000 | BE45: =BD45 -> -4000 | BG45: =SUM(BG40:BG44) -> 111613.8 | BH45: =SUM(BH40:BH44) -> 110521.3 | BI45: =SUM(BI40:BI44) -> 117884.7 | BJ45: =SUM(BJ40:BJ44) -> 127627.2 | BK45: =SUM(BK40:BK44) -> 114286.2 | BL45: =SUM(BL40:BL44) -> 116078.1 | BM45: =SUM(BM40:BM44) -> 113694.4 | BN45: =SUM(BN40:BN44) -> 107910.1 | ... BR45: =SUM(BR40:BR44) -> 108161.6 | BS45: =BR45 -> 108161.6
B46: Working capital/sales (monthly) | C46: =IFERROR(C45/(C28*12),0) -> 0.18685751 | D46: =IFERROR(D45/(D28*12),0) -> 0.18783336 | E46: =IFERROR(E45/(E28*12),0) -> 0.18680403 | F46: =IFERROR(F45/(F28*12),0) -> 0.18697688 | G46: =IFERROR(G45/(G28*12),0) -> 0.18373928 | H46: =IFERROR(H45/(H28*12),0) -> 0.17872214 | I46: =IFERROR(I45/(I28*12),0) -> 0.17601921 | J46: =IFERROR(J45/(J28*12),0) -> 0.1706964 | ... N46: =IFERROR(N45/(N28*12),0) -> 0.1699752 | Q46: =IFERROR(Q45/(Q28*12),0) -> 0.18685751 | R46: =IFERROR(R45/(R28*12),0) -> 0.18783336 | S46: =IFERROR(S45/(S28*12),0) -> 0.18680403 | T46: =IFERROR(T45/(T28*12),0) -> 0.18697688 | U46: =IFERROR(U45/(U28*12),0) -> 0.18373928 | V46: =IFERROR(V45/(V28*12),0) -> 0.17872214 | W46: =IFERROR(W45/(W28*12),0) -> 0.17601921 | X46: =IFERROR(X45/(X28*12),0) -> 0.1706964 | ... AB46: =IFERROR(AB45/(AB28*12),0) -> 0.17011441 | AE46: =IFERROR(AE45/(AE28*12),0) -> 0 | AF46: =IFERROR(AF45/(AF28*12),0) -> 0 | AG46: =IFERROR(AG45/(AG28*12),0) -> 0 | AH46: =IFERROR(AH45/(AH28*12),0) -> 0 | AI46: =IFERROR(AI45/(AI28*12),0) -> 0 | AJ46: =IFERROR(AJ45/(AJ28*12),0) -> 0 | AK46: =IFERROR(AK45/(AK28*12),0) -> 0 | AL46: =IFERROR(AL45/(AL28*12),0) -> 0 | ... AP46: =IFERROR(AP45/(AP28*12),0) -> 0 | AS46: =IFERROR(AS45/(AS28*12),0) -> 0 | AT46: =IFERROR(AT45/(AT28*12),0) -> 0 | AU46: =IFERROR(AU45/(AU28*12),0) -> 0 | AV46: =IFERROR(AV45/(AV28*12),0) -> 0 | AW46: =IFERROR(AW45/(AW28*12),0) -> 0 | AX46: =IFERROR(AX45/(AX28*12),0) -> 0 | AY46: =IFERROR(AY45/(AY28*12),0) -> 0 | AZ46: =IFERROR(AZ45/(AZ28*12),0) -> 0 | ... BD46: =IFERROR(BD45/(BD28*12),0) -> -0.98039216 | BG46: =IFERROR(BG45/(BG28*12),0) -> 0.18685751 | BH46: =IFERROR(BH45/(BH28*12),0) -> 0.18783336 | BI46: =IFERROR(BI45/(BI28*12),0) -> 0.18680403 | BJ46: =IFERROR(BJ45/(BJ28*12),0) -> 0.18697688 | BK46: =IFERROR(BK45/(BK28*12),0) -> 0.18373928 | BL46: =IFERROR(BL45/(BL28*12),0) -> 0.17872214 | BM46: =IFERROR(BM45/(BM28*12),0) -> 0.17601921 | BN46: =IFERROR(BN45/(BN28*12),0) -> 0.1706964 | ... BR46: =IFERROR(BR45/(BR28*12),0) -> 0.16303875
B49: Budget 2026
C50: January | D50: February | E50: March | F50: April | G50: May | H50: June | I50: July | J50: August | K50: September | L50: October | M50: November | N50: December | O50: Full year
B51: Sales | C51: =Alder!C51+Beacon!C51+Cobalt!C51+Delta!C51+Ember!C51+Falcon!C51+Granite!C51+Hollis!C51+SAFEREG!C51 -> 49083 | D51: =Alder!D51+Beacon!D51+Cobalt!D51+Delta!D51+Ember!D51+Falcon!D51+Granite!D51+Hollis!D51+SAFEREG!D51 -> 48050 | E51: =Alder!E51+Beacon!E51+Cobalt!E51+Delta!E51+Ember!E51+Falcon!E51+Granite!E51+Hollis!E51+SAFEREG!E51 -> 51666.4 | F51: =Alder!F51+Beacon!F51+Cobalt!F51+Delta!F51+Ember!F51+Falcon!F51+Granite!F51+Hollis!F51+SAFEREG!F51 -> 55799.9 | G51: =Alder!G51+Beacon!G51+Cobalt!G51+Delta!G51+Ember!G51+Falcon!G51+Granite!G51+Hollis!G51+SAFEREG!G51 -> 50633.4 | H51: =Alder!H51+Beacon!H51+Cobalt!H51+Delta!H51+Ember!H51+Falcon!H51+Granite!H51+Hollis!H51+SAFEREG!H51 -> 53216.8 | I51: =Alder!I51+Beacon!I51+Cobalt!I51+Delta!I51+Ember!I51+Falcon!I51+Granite!I51+Hollis!I51+SAFEREG!I51 -> 52699.6 | J51: =Alder!J51+Beacon!J51+Cobalt!J51+Delta!J51+Ember!J51+Falcon!J51+Granite!J51+Hollis!J51+SAFEREG!J51 -> 51666.6 | ... N51: =Alder!N51+Beacon!N51+Cobalt!N51+Delta!N51+Ember!N51+Falcon!N51+Granite!N51+Hollis!N51+SAFEREG!N51 -> 53216.3 | O51: =SUM(C51:N51) -> 619998.1
B52: Gross Margin | C52: =Alder!C52+Beacon!C52+Cobalt!C52+Delta!C52+Ember!C52+Falcon!C52+Granite!C52+Hollis!C52+SAFEREG!C52 -> 15417.6 | D52: =Alder!D52+Beacon!D52+Cobalt!D52+Delta!D52+Ember!D52+Falcon!D52+Granite!D52+Hollis!D52+SAFEREG!D52 -> 15093.2 | E52: =Alder!E52+Beacon!E52+Cobalt!E52+Delta!E52+Ember!E52+Falcon!E52+Granite!E52+Hollis!E52+SAFEREG!E52 -> 16228.9 | F52: =Alder!F52+Beacon!F52+Cobalt!F52+Delta!F52+Ember!F52+Falcon!F52+Granite!F52+Hollis!F52+SAFEREG!F52 -> 17527.5 | G52: =Alder!G52+Beacon!G52+Cobalt!G52+Delta!G52+Ember!G52+Falcon!G52+Granite!G52+Hollis!G52+SAFEREG!G52 -> 15904.9 | H52: =Alder!H52+Beacon!H52+Cobalt!H52+Delta!H52+Ember!H52+Falcon!H52+Granite!H52+Hollis!H52+SAFEREG!H52 -> 16716.1 | I52: =Alder!I52+Beacon!I52+Cobalt!I52+Delta!I52+Ember!I52+Falcon!I52+Granite!I52+Hollis!I52+SAFEREG!I52 -> 16553.3 | J52: =Alder!J52+Beacon!J52+Cobalt!J52+Delta!J52+Ember!J52+Falcon!J52+Granite!J52+Hollis!J52+SAFEREG!J52 -> 16229.1 | ... N52: =Alder!N52+Beacon!N52+Cobalt!N52+Delta!N52+Ember!N52+Falcon!N52+Granite!N52+Hollis!N52+SAFEREG!N52 -> 16715.6 | O52: =SUM(C52:N52) -> 194749.5
B53: Op Costs | C53: =Alder!C53+Beacon!C53+Cobalt!C53+Delta!C53+Ember!C53+Falcon!C53+Granite!C53+Hollis!C53+SAFEREG!C53 -> -10679.1 | D53: =Alder!D53+Beacon!D53+Cobalt!D53+Delta!D53+Ember!D53+Falcon!D53+Granite!D53+Hollis!D53+SAFEREG!D53 -> -10462 | E53: =Alder!E53+Beacon!E53+Cobalt!E53+Delta!E53+Ember!E53+Falcon!E53+Granite!E53+Hollis!E53+SAFEREG!E53 -> -11225.6 | F53: =Alder!F53+Beacon!F53+Cobalt!F53+Delta!F53+Ember!F53+Falcon!F53+Granite!F53+Hollis!F53+SAFEREG!F53 -> -12101.3 | G53: =Alder!G53+Beacon!G53+Cobalt!G53+Delta!G53+Ember!G53+Falcon!G53+Granite!G53+Hollis!G53+SAFEREG!G53 -> -11011.9 | H53: =Alder!H53+Beacon!H53+Cobalt!H53+Delta!H53+Ember!H53+Falcon!H53+Granite!H53+Hollis!H53+SAFEREG!H53 -> -11552.8 | I53: =Alder!I53+Beacon!I53+Cobalt!I53+Delta!I53+Ember!I53+Falcon!I53+Granite!I53+Hollis!I53+SAFEREG!I53 -> -11445 | J53: =Alder!J53+Beacon!J53+Cobalt!J53+Delta!J53+Ember!J53+Falcon!J53+Granite!J53+Hollis!J53+SAFEREG!J53 -> -11226.9 | ... N53: =Alder!N53+Beacon!N53+Cobalt!N53+Delta!N53+Ember!N53+Falcon!N53+Granite!N53+Hollis!N53+SAFEREG!N53 -> -11557.4 | O53: =SUM(C53:N53) -> -134726.4
B54: PBITA | C54: =C52+C53 -> 4738.5 | D54: =D52+D53 -> 4631.2 | E54: =E52+E53 -> 5003.3 | F54: =F52+F53 -> 5426.2 | G54: =G52+G53 -> 4893 | H54: =H52+H53 -> 5163.3 | I54: =I52+I53 -> 5108.3 | J54: =J52+J53 -> 5002.2 | ... N54: =N52+N53 -> 5158.2 | O54: =SUM(C54:N54) -> 60023.1
B55: Net Inventory | C55: =Alder!C55+Beacon!C55+Cobalt!C55+Delta!C55+Ember!C55+Falcon!C55+Granite!C55+Hollis!C55+SAFEREG!C55 -> 84927.3 | D55: =Alder!D55+Beacon!D55+Cobalt!D55+Delta!D55+Ember!D55+Falcon!D55+Granite!D55+Hollis!D55+SAFEREG!D55 -> 83666.2 | E55: =Alder!E55+Beacon!E55+Cobalt!E55+Delta!E55+Ember!E55+Falcon!E55+Granite!E55+Hollis!E55+SAFEREG!E55 -> 89845.3 | F55: =Alder!F55+Beacon!F55+Cobalt!F55+Delta!F55+Ember!F55+Falcon!F55+Granite!F55+Hollis!F55+SAFEREG!F55 -> 96096.8 | G55: =Alder!G55+Beacon!G55+Cobalt!G55+Delta!G55+Ember!G55+Falcon!G55+Granite!G55+Hollis!G55+SAFEREG!G55 -> 87623.9 | H55: =Alder!H55+Beacon!H55+Cobalt!H55+Delta!H55+Ember!H55+Falcon!H55+Granite!H55+Hollis!H55+SAFEREG!H55 -> 92050.6 | I55: =Alder!I55+Beacon!I55+Cobalt!I55+Delta!I55+Ember!I55+Falcon!I55+Granite!I55+Hollis!I55+SAFEREG!I55 -> 91390.2 | J55: =Alder!J55+Beacon!J55+Cobalt!J55+Delta!J55+Ember!J55+Falcon!J55+Granite!J55+Hollis!J55+SAFEREG!J55 -> 90209.5 | ... N55: =Alder!N55+Beacon!N55+Cobalt!N55+Delta!N55+Ember!N55+Falcon!N55+Granite!N55+Hollis!N55+SAFEREG!N55 -> 91808.2 | O55: =N55 -> 91808.2
B56: Trade Receivables | C56: =Alder!C56+Beacon!C56+Cobalt!C56+Delta!C56+Ember!C56+Falcon!C56+Granite!C56+Hollis!C56+SAFEREG!C56 -> 73624.5 | D56: =Alder!D56+Beacon!D56+Cobalt!D56+Delta!D56+Ember!D56+Falcon!D56+Granite!D56+Hollis!D56+SAFEREG!D56 -> 72074.9 | E56: =Alder!E56+Beacon!E56+Cobalt!E56+Delta!E56+Ember!E56+Falcon!E56+Granite!E56+Hollis!E56+SAFEREG!E56 -> 77499.6 | F56: =Alder!F56+Beacon!F56+Cobalt!F56+Delta!F56+Ember!F56+Falcon!F56+Granite!F56+Hollis!F56+SAFEREG!F56 -> 83700 | G56: =Alder!G56+Beacon!G56+Cobalt!G56+Delta!G56+Ember!G56+Falcon!G56+Granite!G56+Hollis!G56+SAFEREG!G56 -> 75950.1 | H56: =Alder!H56+Beacon!H56+Cobalt!H56+Delta!H56+Ember!H56+Falcon!H56+Granite!H56+Hollis!H56+SAFEREG!H56 -> 79825.3 | I56: =Alder!I56+Beacon!I56+Cobalt!I56+Delta!I56+Ember!I56+Falcon!I56+Granite!I56+Hollis!I56+SAFEREG!I56 -> 79049.5 | J56: =Alder!J56+Beacon!J56+Cobalt!J56+Delta!J56+Ember!J56+Falcon!J56+Granite!J56+Hollis!J56+SAFEREG!J56 -> 77500 | ... N56: =Alder!N56+Beacon!N56+Cobalt!N56+Delta!N56+Ember!N56+Falcon!N56+Granite!N56+Hollis!N56+SAFEREG!N56 -> 79824.6 | O56: =N56 -> 79824.6
B57: Other Receivables | C57: =Alder!C57+Beacon!C57+Cobalt!C57+Delta!C57+Ember!C57+Falcon!C57+Granite!C57+Hollis!C57+SAFEREG!C57 -> 761.1 | D57: =Alder!D57+Beacon!D57+Cobalt!D57+Delta!D57+Ember!D57+Falcon!D57+Granite!D57+Hollis!D57+SAFEREG!D57 -> 745.8 | E57: =Alder!E57+Beacon!E57+Cobalt!E57+Delta!E57+Ember!E57+Falcon!E57+Granite!E57+Hollis!E57+SAFEREG!E57 -> 799.8 | F57: =Alder!F57+Beacon!F57+Cobalt!F57+Delta!F57+Ember!F57+Falcon!F57+Granite!F57+Hollis!F57+SAFEREG!F57 -> 862.1 | G57: =Alder!G57+Beacon!G57+Cobalt!G57+Delta!G57+Ember!G57+Falcon!G57+Granite!G57+Hollis!G57+SAFEREG!G57 -> 784.6 | H57: =Alder!H57+Beacon!H57+Cobalt!H57+Delta!H57+Ember!H57+Falcon!H57+Granite!H57+Hollis!H57+SAFEREG!H57 -> 823.1 | I57: =Alder!I57+Beacon!I57+Cobalt!I57+Delta!I57+Ember!I57+Falcon!I57+Granite!I57+Hollis!I57+SAFEREG!I57 -> 815.4 | J57: =Alder!J57+Beacon!J57+Cobalt!J57+Delta!J57+Ember!J57+Falcon!J57+Granite!J57+Hollis!J57+SAFEREG!J57 -> 800 | ... N57: =Alder!N57+Beacon!N57+Cobalt!N57+Delta!N57+Ember!N57+Falcon!N57+Granite!N57+Hollis!N57+SAFEREG!N57 -> 823.1 | O57: =N57 -> 823.1
B58: Trade Payables | C58: =Alder!C58+Beacon!C58+Cobalt!C58+Delta!C58+Ember!C58+Falcon!C58+Granite!C58+Hollis!C58+SAFEREG!C58 -> -47131.5 | D58: =Alder!D58+Beacon!D58+Cobalt!D58+Delta!D58+Ember!D58+Falcon!D58+Granite!D58+Hollis!D58+SAFEREG!D58 -> -46139.6 | E58: =Alder!E58+Beacon!E58+Cobalt!E58+Delta!E58+Ember!E58+Falcon!E58+Granite!E58+Hollis!E58+SAFEREG!E58 -> -49612.4 | F58: =Alder!F58+Beacon!F58+Cobalt!F58+Delta!F58+Ember!F58+Falcon!F58+Granite!F58+Hollis!F58+SAFEREG!F58 -> -53581.4 | G58: =Alder!G58+Beacon!G58+Cobalt!G58+Delta!G58+Ember!G58+Falcon!G58+Granite!G58+Hollis!G58+SAFEREG!G58 -> -48619.8 | H58: =Alder!H58+Beacon!H58+Cobalt!H58+Delta!H58+Ember!H58+Falcon!H58+Granite!H58+Hollis!H58+SAFEREG!H58 -> -51101 | I58: =Alder!I58+Beacon!I58+Cobalt!I58+Delta!I58+Ember!I58+Falcon!I58+Granite!I58+Hollis!I58+SAFEREG!I58 -> -50604.7 | J58: =Alder!J58+Beacon!J58+Cobalt!J58+Delta!J58+Ember!J58+Falcon!J58+Granite!J58+Hollis!J58+SAFEREG!J58 -> -49612.5 | ... N58: =Alder!N58+Beacon!N58+Cobalt!N58+Delta!N58+Ember!N58+Falcon!N58+Granite!N58+Hollis!N58+SAFEREG!N58 -> -51100.8 | O58: =N58 -> -51100.8
B59: Other Payables | C59: =Alder!C59+Beacon!C59+Cobalt!C59+Delta!C59+Ember!C59+Falcon!C59+Granite!C59+Hollis!C59+SAFEREG!C59 -> -1652.4 | D59: =Alder!D59+Beacon!D59+Cobalt!D59+Delta!D59+Ember!D59+Falcon!D59+Granite!D59+Hollis!D59+SAFEREG!D59 -> -1621.6 | E59: =Alder!E59+Beacon!E59+Cobalt!E59+Delta!E59+Ember!E59+Falcon!E59+Granite!E59+Hollis!E59+SAFEREG!E59 -> -1730 | F59: =Alder!F59+Beacon!F59+Cobalt!F59+Delta!F59+Ember!F59+Falcon!F59+Granite!F59+Hollis!F59+SAFEREG!F59 -> -1854 | G59: =Alder!G59+Beacon!G59+Cobalt!G59+Delta!G59+Ember!G59+Falcon!G59+Granite!G59+Hollis!G59+SAFEREG!G59 -> -1699.1 | H59: =Alder!H59+Beacon!H59+Cobalt!H59+Delta!H59+Ember!H59+Falcon!H59+Granite!H59+Hollis!H59+SAFEREG!H59 -> -1776.6 | I59: =Alder!I59+Beacon!I59+Cobalt!I59+Delta!I59+Ember!I59+Falcon!I59+Granite!I59+Hollis!I59+SAFEREG!I59 -> -1761.1 | J59: =Alder!J59+Beacon!J59+Cobalt!J59+Delta!J59+Ember!J59+Falcon!J59+Granite!J59+Hollis!J59+SAFEREG!J59 -> -1730 | ... N59: =Alder!N59+Beacon!N59+Cobalt!N59+Delta!N59+Ember!N59+Falcon!N59+Granite!N59+Hollis!N59+SAFEREG!N59 -> -1776.5 | O59: =N59 -> -1776.5
B60: Total working capital | C60: =SUM(C55:C59) -> 110529 | D60: =SUM(D55:D59) -> 108725.7 | E60: =SUM(E55:E59) -> 116802.3 | F60: =SUM(F55:F59) -> 125223.5 | G60: =SUM(G55:G59) -> 114039.7 | H60: =SUM(H55:H59) -> 119821.4 | I60: =SUM(I55:I59) -> 118889.3 | J60: =SUM(J55:J59) -> 117167 | ... N60: =SUM(N55:N59) -> 119578.6 | O60: =N60 -> 119578.6
B62: 2025 Actual
C63: January | D63: February | E63: March | F63: April | G63: May | H63: June | I63: July | J63: August | K63: September | L63: October | M63: November | N63: December | O63: Full year
B64: Sales | C64: =Alder!C64+Beacon!C64+Cobalt!C64+Delta!C64+Ember!C64+Falcon!C64+Granite!C64+Hollis!C64+SAFEREG!C64 -> 46990.7 | D64: =Alder!D64+Beacon!D64+Cobalt!D64+Delta!D64+Ember!D64+Falcon!D64+Granite!D64+Hollis!D64+SAFEREG!D64 -> 45717.1 | E64: =Alder!E64+Beacon!E64+Cobalt!E64+Delta!E64+Ember!E64+Falcon!E64+Granite!E64+Hollis!E64+SAFEREG!E64 -> 49328.6 | F64: =Alder!F64+Beacon!F64+Cobalt!F64+Delta!F64+Ember!F64+Falcon!F64+Granite!F64+Hollis!F64+SAFEREG!F64 -> 53313.8 | G64: =Alder!G64+Beacon!G64+Cobalt!G64+Delta!G64+Ember!G64+Falcon!G64+Granite!G64+Hollis!G64+SAFEREG!G64 -> 48140.4 | H64: =Alder!H64+Beacon!H64+Cobalt!H64+Delta!H64+Ember!H64+Falcon!H64+Granite!H64+Hollis!H64+SAFEREG!H64 -> 50828.2 | I64: =Alder!I64+Beacon!I64+Cobalt!I64+Delta!I64+Ember!I64+Falcon!I64+Granite!I64+Hollis!I64+SAFEREG!I64 -> 50581.7 | J64: =Alder!J64+Beacon!J64+Cobalt!J64+Delta!J64+Ember!J64+Falcon!J64+Granite!J64+Hollis!J64+SAFEREG!J64 -> 48966.9 | ... N64: =Alder!N64+Beacon!N64+Cobalt!N64+Delta!N64+Ember!N64+Falcon!N64+Granite!N64+Hollis!N64+SAFEREG!N64 -> 50915.4 | O64: =SUM(C64:N64) -> 591912.4
B65: Gross Margin | C65: =Alder!C65+Beacon!C65+Cobalt!C65+Delta!C65+Ember!C65+Falcon!C65+Granite!C65+Hollis!C65+SAFEREG!C65 -> 14798.8 | D65: =Alder!D65+Beacon!D65+Cobalt!D65+Delta!D65+Ember!D65+Falcon!D65+Granite!D65+Hollis!D65+SAFEREG!D65 -> 14364.4 | E65: =Alder!E65+Beacon!E65+Cobalt!E65+Delta!E65+Ember!E65+Falcon!E65+Granite!E65+Hollis!E65+SAFEREG!E65 -> 15557.9 | F65: =Alder!F65+Beacon!F65+Cobalt!F65+Delta!F65+Ember!F65+Falcon!F65+Granite!F65+Hollis!F65+SAFEREG!F65 -> 16673 | G65: =Alder!G65+Beacon!G65+Cobalt!G65+Delta!G65+Ember!G65+Falcon!G65+Granite!G65+Hollis!G65+SAFEREG!G65 -> 15143.6 | H65: =Alder!H65+Beacon!H65+Cobalt!H65+Delta!H65+Ember!H65+Falcon!H65+Granite!H65+Hollis!H65+SAFEREG!H65 -> 15955.1 | I65: =Alder!I65+Beacon!I65+Cobalt!I65+Delta!I65+Ember!I65+Falcon!I65+Granite!I65+Hollis!I65+SAFEREG!I65 -> 15818.6 | J65: =Alder!J65+Beacon!J65+Cobalt!J65+Delta!J65+Ember!J65+Falcon!J65+Granite!J65+Hollis!J65+SAFEREG!J65 -> 15395.6 | ... N65: =Alder!N65+Beacon!N65+Cobalt!N65+Delta!N65+Ember!N65+Falcon!N65+Granite!N65+Hollis!N65+SAFEREG!N65 -> 15989.5 | O65: =SUM(C65:N65) -> 185980.2
B66: Op Costs | C66: =Alder!C66+Beacon!C66+Cobalt!C66+Delta!C66+Ember!C66+Falcon!C66+Granite!C66+Hollis!C66+SAFEREG!C66 -> -10367.8 | D66: =Alder!D66+Beacon!D66+Cobalt!D66+Delta!D66+Ember!D66+Falcon!D66+Granite!D66+Hollis!D66+SAFEREG!D66 -> -10166 | E66: =Alder!E66+Beacon!E66+Cobalt!E66+Delta!E66+Ember!E66+Falcon!E66+Granite!E66+Hollis!E66+SAFEREG!E66 -> -10887 | F66: =Alder!F66+Beacon!F66+Cobalt!F66+Delta!F66+Ember!F66+Falcon!F66+Granite!F66+Hollis!F66+SAFEREG!F66 -> -11714.8 | G66: =Alder!G66+Beacon!G66+Cobalt!G66+Delta!G66+Ember!G66+Falcon!G66+Granite!G66+Hollis!G66+SAFEREG!G66 -> -10661.2 | H66: =Alder!H66+Beacon!H66+Cobalt!H66+Delta!H66+Ember!H66+Falcon!H66+Granite!H66+Hollis!H66+SAFEREG!H66 -> -11249.1 | I66: =Alder!I66+Beacon!I66+Cobalt!I66+Delta!I66+Ember!I66+Falcon!I66+Granite!I66+Hollis!I66+SAFEREG!I66 -> -11144.5 | J66: =Alder!J66+Beacon!J66+Cobalt!J66+Delta!J66+Ember!J66+Falcon!J66+Granite!J66+Hollis!J66+SAFEREG!J66 -> -10886.8 | ... N66: =Alder!N66+Beacon!N66+Cobalt!N66+Delta!N66+Ember!N66+Falcon!N66+Granite!N66+Hollis!N66+SAFEREG!N66 -> -11218.2 | O66: =SUM(C66:N66) -> -130781
B67: PBITA | C67: =C65+C66 -> 4431 | D67: =D65+D66 -> 4198.4 | E67: =E65+E66 -> 4670.9 | F67: =F65+F66 -> 4958.2 | G67: =G65+G66 -> 4482.4 | H67: =H65+H66 -> 4706 | I67: =I65+I66 -> 4674.1 | J67: =J65+J66 -> 4508.8 | ... N67: =N65+N66 -> 4771.3 | O67: =SUM(C67:N67) -> 55199.2
B68: Net Inventory | C68: =Alder!C68+Beacon!C68+Cobalt!C68+Delta!C68+Ember!C68+Falcon!C68+Granite!C68+Hollis!C68+SAFEREG!C68 -> 90725.6 | D68: =Alder!D68+Beacon!D68+Cobalt!D68+Delta!D68+Ember!D68+Falcon!D68+Granite!D68+Hollis!D68+SAFEREG!D68 -> 87368.7 | E68: =Alder!E68+Beacon!E68+Cobalt!E68+Delta!E68+Ember!E68+Falcon!E68+Granite!E68+Hollis!E68+SAFEREG!E68 -> 94392.3 | F68: =Alder!F68+Beacon!F68+Cobalt!F68+Delta!F68+Ember!F68+Falcon!F68+Granite!F68+Hollis!F68+SAFEREG!F68 -> 102158.8 | G68: =Alder!G68+Beacon!G68+Cobalt!G68+Delta!G68+Ember!G68+Falcon!G68+Granite!G68+Hollis!G68+SAFEREG!G68 -> 92328.8 | H68: =Alder!H68+Beacon!H68+Cobalt!H68+Delta!H68+Ember!H68+Falcon!H68+Granite!H68+Hollis!H68+SAFEREG!H68 -> 98237.9 | I68: =Alder!I68+Beacon!I68+Cobalt!I68+Delta!I68+Ember!I68+Falcon!I68+Granite!I68+Hollis!I68+SAFEREG!I68 -> 98353.2 | J68: =Alder!J68+Beacon!J68+Cobalt!J68+Delta!J68+Ember!J68+Falcon!J68+Granite!J68+Hollis!J68+SAFEREG!J68 -> 93929 | ... N68: =Alder!N68+Beacon!N68+Cobalt!N68+Delta!N68+Ember!N68+Falcon!N68+Granite!N68+Hollis!N68+SAFEREG!N68 -> 98217.3 | O68: =N68 -> 98217.3
B69: Trade Receivables | C69: =Alder!C69+Beacon!C69+Cobalt!C69+Delta!C69+Ember!C69+Falcon!C69+Granite!C69+Hollis!C69+SAFEREG!C69 -> 72052.5 | D69: =Alder!D69+Beacon!D69+Cobalt!D69+Delta!D69+Ember!D69+Falcon!D69+Granite!D69+Hollis!D69+SAFEREG!D69 -> 70099.6 | E69: =Alder!E69+Beacon!E69+Cobalt!E69+Delta!E69+Ember!E69+Falcon!E69+Granite!E69+Hollis!E69+SAFEREG!E69 -> 75637.2 | F69: =Alder!F69+Beacon!F69+Cobalt!F69+Delta!F69+Ember!F69+Falcon!F69+Granite!F69+Hollis!F69+SAFEREG!F69 -> 81747.7 | G69: =Alder!G69+Beacon!G69+Cobalt!G69+Delta!G69+Ember!G69+Falcon!G69+Granite!G69+Hollis!G69+SAFEREG!G69 -> 73815.3 | H69: =Alder!H69+Beacon!H69+Cobalt!H69+Delta!H69+Ember!H69+Falcon!H69+Granite!H69+Hollis!H69+SAFEREG!H69 -> 77936.6 | I69: =Alder!I69+Beacon!I69+Cobalt!I69+Delta!I69+Ember!I69+Falcon!I69+Granite!I69+Hollis!I69+SAFEREG!I69 -> 77558.6 | J69: =Alder!J69+Beacon!J69+Cobalt!J69+Delta!J69+Ember!J69+Falcon!J69+Granite!J69+Hollis!J69+SAFEREG!J69 -> 75082.6 | ... N69: =Alder!N69+Beacon!N69+Cobalt!N69+Delta!N69+Ember!N69+Falcon!N69+Granite!N69+Hollis!N69+SAFEREG!N69 -> 78070.3 | O69: =N69 -> 78070.3
B70: Other Receivables | C70: =Alder!C70+Beacon!C70+Cobalt!C70+Delta!C70+Ember!C70+Falcon!C70+Granite!C70+Hollis!C70+SAFEREG!C70 -> 730 | D70: =Alder!D70+Beacon!D70+Cobalt!D70+Delta!D70+Ember!D70+Falcon!D70+Granite!D70+Hollis!D70+SAFEREG!D70 -> 710.8 | E70: =Alder!E70+Beacon!E70+Cobalt!E70+Delta!E70+Ember!E70+Falcon!E70+Granite!E70+Hollis!E70+SAFEREG!E70 -> 764.9 | F70: =Alder!F70+Beacon!F70+Cobalt!F70+Delta!F70+Ember!F70+Falcon!F70+Granite!F70+Hollis!F70+SAFEREG!F70 -> 824.9 | G70: =Alder!G70+Beacon!G70+Cobalt!G70+Delta!G70+Ember!G70+Falcon!G70+Granite!G70+Hollis!G70+SAFEREG!G70 -> 747.1 | H70: =Alder!H70+Beacon!H70+Cobalt!H70+Delta!H70+Ember!H70+Falcon!H70+Granite!H70+Hollis!H70+SAFEREG!H70 -> 787.4 | I70: =Alder!I70+Beacon!I70+Cobalt!I70+Delta!I70+Ember!I70+Falcon!I70+Granite!I70+Hollis!I70+SAFEREG!I70 -> 783.6 | J70: =Alder!J70+Beacon!J70+Cobalt!J70+Delta!J70+Ember!J70+Falcon!J70+Granite!J70+Hollis!J70+SAFEREG!J70 -> 759.6 | ... N70: =Alder!N70+Beacon!N70+Cobalt!N70+Delta!N70+Ember!N70+Falcon!N70+Granite!N70+Hollis!N70+SAFEREG!N70 -> 788.8 | O70: =N70 -> 788.8
B71: Trade Payables | C71: =Alder!C71+Beacon!C71+Cobalt!C71+Delta!C71+Ember!C71+Falcon!C71+Granite!C71+Hollis!C71+SAFEREG!C71 -> -43995.6 | D71: =Alder!D71+Beacon!D71+Cobalt!D71+Delta!D71+Ember!D71+Falcon!D71+Granite!D71+Hollis!D71+SAFEREG!D71 -> -42848.8 | E71: =Alder!E71+Beacon!E71+Cobalt!E71+Delta!E71+Ember!E71+Falcon!E71+Granite!E71+Hollis!E71+SAFEREG!E71 -> -46153.1 | F71: =Alder!F71+Beacon!F71+Cobalt!F71+Delta!F71+Ember!F71+Falcon!F71+Granite!F71+Hollis!F71+SAFEREG!F71 -> -50075.9 | G71: =Alder!G71+Beacon!G71+Cobalt!G71+Delta!G71+Ember!G71+Falcon!G71+Granite!G71+Hollis!G71+SAFEREG!G71 -> -45095.6 | H71: =Alder!H71+Beacon!H71+Cobalt!H71+Delta!H71+Ember!H71+Falcon!H71+Granite!H71+Hollis!H71+SAFEREG!H71 -> -47659.9 | I71: =Alder!I71+Beacon!I71+Cobalt!I71+Delta!I71+Ember!I71+Falcon!I71+Granite!I71+Hollis!I71+SAFEREG!I71 -> -47509.5 | J71: =Alder!J71+Beacon!J71+Cobalt!J71+Delta!J71+Ember!J71+Falcon!J71+Granite!J71+Hollis!J71+SAFEREG!J71 -> -45880.9 | ... N71: =Alder!N71+Beacon!N71+Cobalt!N71+Delta!N71+Ember!N71+Falcon!N71+Granite!N71+Hollis!N71+SAFEREG!N71 -> -47732 | O71: =N71 -> -47732
B72: Other Payables | C72: =Alder!C72+Beacon!C72+Cobalt!C72+Delta!C72+Ember!C72+Falcon!C72+Granite!C72+Hollis!C72+SAFEREG!C72 -> -1589.8 | D72: =Alder!D72+Beacon!D72+Cobalt!D72+Delta!D72+Ember!D72+Falcon!D72+Granite!D72+Hollis!D72+SAFEREG!D72 -> -1551.5 | E72: =Alder!E72+Beacon!E72+Cobalt!E72+Delta!E72+Ember!E72+Falcon!E72+Granite!E72+Hollis!E72+SAFEREG!E72 -> -1659.8 | F72: =Alder!F72+Beacon!F72+Cobalt!F72+Delta!F72+Ember!F72+Falcon!F72+Granite!F72+Hollis!F72+SAFEREG!F72 -> -1779.4 | G72: =Alder!G72+Beacon!G72+Cobalt!G72+Delta!G72+Ember!G72+Falcon!G72+Granite!G72+Hollis!G72+SAFEREG!G72 -> -1624.2 | H72: =Alder!H72+Beacon!H72+Cobalt!H72+Delta!H72+Ember!H72+Falcon!H72+Granite!H72+Hollis!H72+SAFEREG!H72 -> -1704.9 | I72: =Alder!I72+Beacon!I72+Cobalt!I72+Delta!I72+Ember!I72+Falcon!I72+Granite!I72+Hollis!I72+SAFEREG!I72 -> -1697.4 | J72: =Alder!J72+Beacon!J72+Cobalt!J72+Delta!J72+Ember!J72+Falcon!J72+Granite!J72+Hollis!J72+SAFEREG!J72 -> -1649 | ... N72: =Alder!N72+Beacon!N72+Cobalt!N72+Delta!N72+Ember!N72+Falcon!N72+Granite!N72+Hollis!N72+SAFEREG!N72 -> -1707.4 | O72: =N72 -> -1707.4
B73: Total working capital | C73: =SUM(C68:C72) -> 117922.7 | D73: =SUM(D68:D72) -> 113778.8 | E73: =SUM(E68:E72) -> 122981.5 | F73: =SUM(F68:F72) -> 132876.1 | G73: =SUM(G68:G72) -> 120171.4 | H73: =SUM(H68:H72) -> 127597.1 | I73: =SUM(I68:I72) -> 127488.5 | J73: =SUM(J68:J72) -> 122241.3 | ... N73: =SUM(N68:N72) -> 127637 | O73: =N73 -> 127637

Sheet Alder-Var
A1: Current ME | B1: P09 | D1: Alder Gloves
A2: Next ME | B2: P10 | D2: TRAINING DATA ONLY - Zava Safety and all business names and numbers are fictitious. Layout mirrors a typical HFM / Cognos reporting pack.
C4: FCAST10
C5: Through Sep | F5: Rest of Year | I5: Full Year
B6: Favorable / (Unfavorable) | C6: Actual vs. FCAST09 | D6: Actual vs. Bud | E6: Actual vs. PY | F6: FCAST10 vs. FCAST09 | G6: FCAST10 vs. Bud | H6: FCAST10 vs. PY | I6: FCAST10 vs. FCAST09 | J6: FCAST10 vs. Bud | K6: FCAST10 vs. PY
B8: Sales | C8: =Alder!BU28 -> 0 | D8: =Alder!BV28 -> 4321.5 | E8: =Alder!BW28 -> 9085.9 | F8: =Alder!BY28 -> -600 | G8: =Alder!BZ28 -> 890 | H8: =Alder!CA28 -> 2526.4 | I8: =Alder!CC28 -> -600 | J8: =Alder!CD28 -> 5211.5 | K8: =Alder!CE28 -> 11612.3
B10: Gross Margin | C10: =Alder!BU29 -> -160 | D10: =Alder!BV29 -> -475.7 | E10: =Alder!BW29 -> 123.5 | F10: =Alder!BY29 -> -420 | G10: =Alder!BZ29 -> -1101 | H10: =Alder!CA29 -> -909.6 | I10: =Alder!CC29 -> -580 | J10: =Alder!CD29 -> -1576.7 | K10: =Alder!CE29 -> -786.1
B12: Op Costs | C12: =Alder!BU30 -> 240 | D12: =Alder!BV30 -> -174.7 | E12: =Alder!BW30 -> -899.6 | F12: =Alder!BY30 -> 60 | G12: =Alder!BZ30 -> -77.2 | H12: =Alder!CA30 -> -330.8 | I12: =Alder!CC30 -> 300 | J12: =Alder!CD30 -> -251.9 | K12: =Alder!CE30 -> -1230.4
B14: PBITA | C14: =Alder!BU31 -> 80 | D14: =Alder!BV31 -> -650.4 | E14: =Alder!BW31 -> -776.1 | F14: =Alder!BY31 -> -360 | G14: =Alder!BZ31 -> -1178.2 | H14: =Alder!CA31 -> -1240.4 | I14: =Alder!CC31 -> -280 | J14: =Alder!CD31 -> -1828.6 | K14: =Alder!CE31 -> -2016.5
B17: Commentary (business controller):

Sheet Alder-Adj
A1: Index | C1: 21 | D1: 20 | E1: 22 | F1: 22 | G1: 20 | H1: 22 | I1: 22 | J1: 21 | K1: 21 | L1: 22 | M1: 19 | N1: 22 | O1: =SUM(C1:N1) -> 254
B2: Section 1: Adjustments tied to individual events (i.e., new customer, modified sales contract, new/lost customer):
B3: TRAINING DATA ONLY - Zava Safety and all business names and numbers are fictitious. Layout mirrors a typical HFM / Cognos reporting pack.
C4: January | D4: February | E4: March | F4: April | G4: May | H4: June | I4: July | J4: August | K4: September | L4: October | M4: November | N4: December | O4: Total Adj
B5: Sales
B6: Insert Adj. 1 | C6: 0 | D6: 0 | E6: 0 | F6: 0 | G6: 0 | H6: 0 | I6: 0 | J6: 0 | K6: 0 | L6: -200 | M6: -200 | N6: -200 | O6: =SUM(C6:N6) -> -600
B7: Insert Adj. 2 | C7: 0 | D7: 0 | E7: 0 | F7: 0 | G7: 0 | H7: 0 | I7: 0 | J7: 0 | K7: 0 | L7: 0 | M7: 0 | N7: 0 | O7: =SUM(C7:N7) -> 0
B8: Insert Adj. 3 | C8: 0 | D8: 0 | E8: 0 | F8: 0 | G8: 0 | H8: 0 | I8: 0 | J8: 0 | K8: 0 | L8: 0 | M8: 0 | N8: 0 | O8: =SUM(C8:N8) -> 0
B9: Insert Adj. 4 | C9: 0 | D9: 0 | E9: 0 | F9: 0 | G9: 0 | H9: 0 | I9: 0 | J9: 0 | K9: 0 | L9: 0 | M9: 0 | N9: 0 | O9: =SUM(C9:N9) -> 0
B10: Insert Adj. 5 | C10: 0 | D10: 0 | E10: 0 | F10: 0 | G10: 0 | H10: 0 | I10: 0 | J10: 0 | K10: 0 | L10: 0 | M10: 0 | N10: 0 | O10: =SUM(C10:N10) -> 0
B11: Insert Adj. 6 | C11: 0 | D11: 0 | E11: 0 | F11: 0 | G11: 0 | H11: 0 | I11: 0 | J11: 0 | K11: 0 | L11: 0 | M11: 0 | N11: 0 | O11: =SUM(C11:N11) -> 0
B12: Insert Adj. 7 | C12: 0 | D12: 0 | E12: 0 | F12: 0 | G12: 0 | H12: 0 | I12: 0 | J12: 0 | K12: 0 | L12: 0 | M12: 0 | N12: 0 | O12: =SUM(C12:N12) -> 0
B13: Insert Adj. 8 | C13: 0 | D13: 0 | E13: 0 | F13: 0 | G13: 0 | H13: 0 | I13: 0 | J13: 0 | K13: 0 | L13: 0 | M13: 0 | N13: 0 | O13: =SUM(C13:N13) -> 0
B14: Total Sales | C14: =SUM(C6:C13) -> 0 | D14: =SUM(D6:D13) -> 0 | E14: =SUM(E6:E13) -> 0 | F14: =SUM(F6:F13) -> 0 | G14: =SUM(G6:G13) -> 0 | H14: =SUM(H6:H13) -> 0 | I14: =SUM(I6:I13) -> 0 | J14: =SUM(J6:J13) -> 0 | ... O14: =SUM(O6:O13) -> -600
B16: Gross Margin (%)
B17: =B6 -> Insert Adj. 1 | C17: =IFERROR(C28/C6,0) -> 0 | D17: =IFERROR(D28/D6,0) -> 0 | E17: =IFERROR(E28/E6,0) -> 0 | F17: =IFERROR(F28/F6,0) -> 0 | G17: =IFERROR(G28/G6,0) -> 0 | H17: =IFERROR(H28/H6,0) -> 0 | I17: =IFERROR(I28/I6,0) -> 0 | J17: =IFERROR(J28/J6,0) -> 0 | ... O17: =IFERROR(O28/O6,0) -> 0.96666667
B18: =B7 -> Insert Adj. 2 | C18: =IFERROR(C29/C7,0) -> 0 | D18: =IFERROR(D29/D7,0) -> 0 | E18: =IFERROR(E29/E7,0) -> 0 | F18: =IFERROR(F29/F7,0) -> 0 | G18: =IFERROR(G29/G7,0) -> 0 | H18: =IFERROR(H29/H7,0) -> 0 | I18: =IFERROR(I29/I7,0) -> 0 | J18: =IFERROR(J29/J7,0) -> 0 | ... O18: =IFERROR(O29/O7,0) -> 0
B19: =B8 -> Insert Adj. 3 | C19: =IFERROR(C30/C8,0) -> 0 | D19: =IFERROR(D30/D8,0) -> 0 | E19: =IFERROR(E30/E8,0) -> 0 | F19: =IFERROR(F30/F8,0) -> 0 | G19: =IFERROR(G30/G8,0) -> 0 | H19: =IFERROR(H30/H8,0) -> 0 | I19: =IFERROR(I30/I8,0) -> 0 | J19: =IFERROR(J30/J8,0) -> 0 | ... O19: =IFERROR(O30/O8,0) -> 0
B20: =B9 -> Insert Adj. 4 | C20: =IFERROR(C31/C9,0) -> 0 | D20: =IFERROR(D31/D9,0) -> 0 | E20: =IFERROR(E31/E9,0) -> 0 | F20: =IFERROR(F31/F9,0) -> 0 | G20: =IFERROR(G31/G9,0) -> 0 | H20: =IFERROR(H31/H9,0) -> 0 | I20: =IFERROR(I31/I9,0) -> 0 | J20: =IFERROR(J31/J9,0) -> 0 | ... O20: =IFERROR(O31/O9,0) -> 0
B21: =B10 -> Insert Adj. 5 | C21: =IFERROR(C32/C10,0) -> 0 | D21: =IFERROR(D32/D10,0) -> 0 | E21: =IFERROR(E32/E10,0) -> 0 | F21: =IFERROR(F32/F10,0) -> 0 | G21: =IFERROR(G32/G10,0) -> 0 | H21: =IFERROR(H32/H10,0) -> 0 | I21: =IFERROR(I32/I10,0) -> 0 | J21: =IFERROR(J32/J10,0) -> 0 | ... O21: =IFERROR(O32/O10,0) -> 0
B22: =B11 -> Insert Adj. 6 | C22: =IFERROR(C33/C11,0) -> 0 | D22: =IFERROR(D33/D11,0) -> 0 | E22: =IFERROR(E33/E11,0) -> 0 | F22: =IFERROR(F33/F11,0) -> 0 | G22: =IFERROR(G33/G11,0) -> 0 | H22: =IFERROR(H33/H11,0) -> 0 | I22: =IFERROR(I33/I11,0) -> 0 | J22: =IFERROR(J33/J11,0) -> 0 | ... O22: =IFERROR(O33/O11,0) -> 0
B23: =B12 -> Insert Adj. 7 | C23: =IFERROR(C34/C12,0) -> 0 | D23: =IFERROR(D34/D12,0) -> 0 | E23: =IFERROR(E34/E12,0) -> 0 | F23: =IFERROR(F34/F12,0) -> 0 | G23: =IFERROR(G34/G12,0) -> 0 | H23: =IFERROR(H34/H12,0) -> 0 | I23: =IFERROR(I34/I12,0) -> 0 | J23: =IFERROR(J34/J12,0) -> 0 | ... O23: =IFERROR(O34/O12,0) -> 0
B24: =B13 -> Insert Adj. 8 | C24: =IFERROR(C35/C13,0) -> 0 | D24: =IFERROR(D35/D13,0) -> 0 | E24: =IFERROR(E35/E13,0) -> 0 | F24: =IFERROR(F35/F13,0) -> 0 | G24: =IFERROR(G35/G13,0) -> 0 | H24: =IFERROR(H35/H13,0) -> 0 | I24: =IFERROR(I35/I13,0) -> 0 | J24: =IFERROR(J35/J13,0) -> 0 | ... O24: =IFERROR(O35/O13,0) -> 0
B25: Total Gross Margin (%) | C25: =IFERROR(C36/C14,0) -> 0 | D25: =IFERROR(D36/D14,0) -> 0 | E25: =IFERROR(E36/E14,0) -> 0 | F25: =IFERROR(F36/F14,0) -> 0 | G25: =IFERROR(G36/G14,0) -> 0 | H25: =IFERROR(H36/H14,0) -> 0 | I25: =IFERROR(I36/I14,0) -> 0 | J25: =IFERROR(J36/J14,0) -> 0 | ... O25: =IFERROR(O36/O14,0) -> 0.96666667
B27: Gross Margin ($)
B28: Insert Adj. 1 | C28: 0 | D28: 0 | E28: 0 | F28: 0 | G28: 0 | H28: 0 | I28: 0 | J28: 0 | K28: -160 | L28: -140 | M28: -140 | N28: -140 | O28: =SUM(C28:N28) -> -580
B29: Insert Adj. 2 | C29: 0 | D29: 0 | E29: 0 | F29: 0 | G29: 0 | H29: 0 | I29: 0 | J29: 0 | K29: 0 | L29: 0 | M29: 0 | N29: 0 | O29: =SUM(C29:N29) -> 0
B30: Insert Adj. 3 | C30: 0 | D30: 0 | E30: 0 | F30: 0 | G30: 0 | H30: 0 | I30: 0 | J30: 0 | K30: 0 | L30: 0 | M30: 0 | N30: 0 | O30: =SUM(C30:N30) -> 0
B31: Insert Adj. 4 | C31: 0 | D31: 0 | E31: 0 | F31: 0 | G31: 0 | H31: 0 | I31: 0 | J31: 0 | K31: 0 | L31: 0 | M31: 0 | N31: 0 | O31: =SUM(C31:N31) -> 0
B32: Insert Adj. 5 | C32: 0 | D32: 0 | E32: 0 | F32: 0 | G32: 0 | H32: 0 | I32: 0 | J32: 0 | K32: 0 | L32: 0 | M32: 0 | N32: 0 | O32: =SUM(C32:N32) -> 0
B33: Insert Adj. 6 | C33: 0 | D33: 0 | E33: 0 | F33: 0 | G33: 0 | H33: 0 | I33: 0 | J33: 0 | K33: 0 | L33: 0 | M33: 0 | N33: 0 | O33: =SUM(C33:N33) -> 0
B34: Insert Adj. 7 | C34: 0 | D34: 0 | E34: 0 | F34: 0 | G34: 0 | H34: 0 | I34: 0 | J34: 0 | K34: 0 | L34: 0 | M34: 0 | N34: 0 | O34: =SUM(C34:N34) -> 0
B35: Insert Adj. 8 | C35: 0 | D35: 0 | E35: 0 | F35: 0 | G35: 0 | H35: 0 | I35: 0 | J35: 0 | K35: 0 | L35: 0 | M35: 0 | N35: 0 | O35: =SUM(C35:N35) -> 0
B36: Total Gross Margin ($) | C36: =SUM(C28:C35) -> 0 | D36: =SUM(D28:D35) -> 0 | E36: =SUM(E28:E35) -> 0 | F36: =SUM(F28:F35) -> 0 | G36: =SUM(G28:G35) -> 0 | H36: =SUM(H28:H35) -> 0 | I36: =SUM(I28:I35) -> 0 | J36: =SUM(J28:J35) -> 0 | ... O36: =SUM(O28:O35) -> -580
B38: Op Costs (%)
B39: =B6 -> Insert Adj. 1 | C39: =IFERROR(C50/C6,0) -> 0 | D39: =IFERROR(D50/D6,0) -> 0 | E39: =IFERROR(E50/E6,0) -> 0 | F39: =IFERROR(F50/F6,0) -> 0 | G39: =IFERROR(G50/G6,0) -> 0 | H39: =IFERROR(H50/H6,0) -> 0 | I39: =IFERROR(I50/I6,0) -> 0 | J39: =IFERROR(J50/J6,0) -> 0 | ... O39: =IFERROR(O50/O6,0) -> -0.13333333
B40: =B7 -> Insert Adj. 2 | C40: =IFERROR(C51/C7,0) -> 0 | D40: =IFERROR(D51/D7,0) -> 0 | E40: =IFERROR(E51/E7,0) -> 0 | F40: =IFERROR(F51/F7,0) -> 0 | G40: =IFERROR(G51/G7,0) -> 0 | H40: =IFERROR(H51/H7,0) -> 0 | I40: =IFERROR(I51/I7,0) -> 0 | J40: =IFERROR(J51/J7,0) -> 0 | ... O40: =IFERROR(O51/O7,0) -> 0
B41: =B8 -> Insert Adj. 3 | C41: =IFERROR(C52/C8,0) -> 0 | D41: =IFERROR(D52/D8,0) -> 0 | E41: =IFERROR(E52/E8,0) -> 0 | F41: =IFERROR(F52/F8,0) -> 0 | G41: =IFERROR(G52/G8,0) -> 0 | H41: =IFERROR(H52/H8,0) -> 0 | I41: =IFERROR(I52/I8,0) -> 0 | J41: =IFERROR(J52/J8,0) -> 0 | ... O41: =IFERROR(O52/O8,0) -> 0
B42: =B9 -> Insert Adj. 4 | C42: =IFERROR(C53/C9,0) -> 0 | D42: =IFERROR(D53/D9,0) -> 0 | E42: =IFERROR(E53/E9,0) -> 0 | F42: =IFERROR(F53/F9,0) -> 0 | G42: =IFERROR(G53/G9,0) -> 0 | H42: =IFERROR(H53/H9,0) -> 0 | I42: =IFERROR(I53/I9,0) -> 0 | J42: =IFERROR(J53/J9,0) -> 0 | ... O42: =IFERROR(O53/O9,0) -> 0
B43: =B10 -> Insert Adj. 5 | C43: =IFERROR(C54/C10,0) -> 0 | D43: =IFERROR(D54/D10,0) -> 0 | E43: =IFERROR(E54/E10,0) -> 0 | F43: =IFERROR(F54/F10,0) -> 0 | G43: =IFERROR(G54/G10,0) -> 0 | H43: =IFERROR(H54/H10,0) -> 0 | I43: =IFERROR(I54/I10,0) -> 0 | J43: =IFERROR(J54/J10,0) -> 0 | ... O43: =IFERROR(O54/O10,0) -> 0
B44: =B11 -> Insert Adj. 6 | C44: =IFERROR(C55/C11,0) -> 0 | D44: =IFERROR(D55/D11,0) -> 0 | E44: =IFERROR(E55/E11,0) -> 0 | F44: =IFERROR(F55/F11,0) -> 0 | G44: =IFERROR(G55/G11,0) -> 0 | H44: =IFERROR(H55/H11,0) -> 0 | I44: =IFERROR(I55/I11,0) -> 0 | J44: =IFERROR(J55/J11,0) -> 0 | ... O44: =IFERROR(O55/O11,0) -> 0
B45: =B12 -> Insert Adj. 7 | C45: =IFERROR(C56/C12,0) -> 0 | D45: =IFERROR(D56/D12,0) -> 0 | E45: =IFERROR(E56/E12,0) -> 0 | F45: =IFERROR(F56/F12,0) -> 0 | G45: =IFERROR(G56/G12,0) -> 0 | H45: =IFERROR(H56/H12,0) -> 0 | I45: =IFERROR(I56/I12,0) -> 0 | J45: =IFERROR(J56/J12,0) -> 0 | ... O45: =IFERROR(O56/O12,0) -> 0
B46: =B13 -> Insert Adj. 8 | C46: =IFERROR(C57/C13,0) -> 0 | D46: =IFERROR(D57/D13,0) -> 0 | E46: =IFERROR(E57/E13,0) -> 0 | F46: =IFERROR(F57/F13,0) -> 0 | G46: =IFERROR(G57/G13,0) -> 0 | H46: =IFERROR(H57/H13,0) -> 0 | I46: =IFERROR(I57/I13,0) -> 0 | J46: =IFERROR(J57/J13,0) -> 0 | ... O46: =IFERROR(O57/O13,0) -> 0
B47: Total Op Costs (%) | C47: =IFERROR(C58/C14,0) -> 0 | D47: =IFERROR(D58/D14,0) -> 0 | E47: =IFERROR(E58/E14,0) -> 0 | F47: =IFERROR(F58/F14,0) -> 0 | G47: =IFERROR(G58/G14,0) -> 0 | H47: =IFERROR(H58/H14,0) -> 0 | I47: =IFERROR(I58/I14,0) -> 0 | J47: =IFERROR(J58/J14,0) -> 0 | ... O47: =IFERROR(O58/O14,0) -> 0.5
B49: Op Costs ($)
B50: Insert Adj. 1 | C50: 0 | D50: 0 | E50: 0 | F50: 0 | G50: 0 | H50: 0 | I50: 0 | J50: 0 | K50: 140 | L50: -20 | M50: -20 | N50: -20 | O50: =SUM(C50:N50) -> 80
B51: Insert Adj. 2 | C51: 0 | D51: 0 | E51: 0 | F51: 0 | G51: 0 | H51: 0 | I51: 0 | J51: 0 | K51: -380 | L51: 0 | M51: 0 | N51: 0 | O51: =SUM(C51:N51) -> -380
B52: Insert Adj. 3 | C52: 0 | D52: 0 | E52: 0 | F52: 0 | G52: 0 | H52: 0 | I52: 0 | J52: 0 | K52: 0 | L52: 0 | M52: 0 | N52: 0 | O52: =SUM(C52:N52) -> 0
B53: Insert Adj. 4 | C53: 0 | D53: 0 | E53: 0 | F53: 0 | G53: 0 | H53: 0 | I53: 0 | J53: 0 | K53: 0 | L53: 0 | M53: 0 | N53: 0 | O53: =SUM(C53:N53) -> 0
B54: Insert Adj. 5 | C54: 0 | D54: 0 | E54: 0 | F54: 0 | G54: 0 | H54: 0 | I54: 0 | J54: 0 | K54: 0 | L54: 0 | M54: 0 | N54: 0 | O54: =SUM(C54:N54) -> 0
B55: Insert Adj. 6 | C55: 0 | D55: 0 | E55: 0 | F55: 0 | G55: 0 | H55: 0 | I55: 0 | J55: 0 | K55: 0 | L55: 0 | M55: 0 | N55: 0 | O55: =SUM(C55:N55) -> 0
B56: Insert Adj. 7 | C56: 0 | D56: 0 | E56: 0 | F56: 0 | G56: 0 | H56: 0 | I56: 0 | J56: 0 | K56: 0 | L56: 0 | M56: 0 | N56: 0 | O56: =SUM(C56:N56) -> 0
B57: Insert Adj. 8 | C57: 0 | D57: 0 | E57: 0 | F57: 0 | G57: 0 | H57: 0 | I57: 0 | J57: 0 | K57: 0 | L57: 0 | M57: 0 | N57: 0 | O57: =SUM(C57:N57) -> 0
B58: Total Op Costs ($) | C58: =SUM(C50:C57) -> 0 | D58: =SUM(D50:D57) -> 0 | E58: =SUM(E50:E57) -> 0 | F58: =SUM(F50:F57) -> 0 | G58: =SUM(G50:G57) -> 0 | H58: =SUM(H50:H57) -> 0 | I58: =SUM(I50:I57) -> 0 | J58: =SUM(J50:J57) -> 0 | ... O58: =SUM(O50:O57) -> -300
B60: PBITA
B61: =B6 -> Insert Adj. 1 | C61: =C28-C50 -> 0 | D61: =D28-D50 -> 0 | E61: =E28-E50 -> 0 | F61: =F28-F50 -> 0 | G61: =G28-G50 -> 0 | H61: =H28-H50 -> 0 | I61: =I28-I50 -> 0 | J61: =J28-J50 -> 0 | ... N61: =N28-N50 -> -120 | O61: =SUM(C61:N61) -> -660
B62: =B7 -> Insert Adj. 2 | C62: =C29-C51 -> 0 | D62: =D29-D51 -> 0 | E62: =E29-E51 -> 0 | F62: =F29-F51 -> 0 | G62: =G29-G51 -> 0 | H62: =H29-H51 -> 0 | I62: =I29-I51 -> 0 | J62: =J29-J51 -> 0 | ... N62: =N29-N51 -> 0 | O62: =SUM(C62:N62) -> 380
B63: =B8 -> Insert Adj. 3 | C63: =C30-C52 -> 0 | D63: =D30-D52 -> 0 | E63: =E30-E52 -> 0 | F63: =F30-F52 -> 0 | G63: =G30-G52 -> 0 | H63: =H30-H52 -> 0 | I63: =I30-I52 -> 0 | J63: =J30-J52 -> 0 | ... N63: =N30-N52 -> 0 | O63: =SUM(C63:N63) -> 0
B64: =B9 -> Insert Adj. 4 | C64: =C31-C53 -> 0 | D64: =D31-D53 -> 0 | E64: =E31-E53 -> 0 | F64: =F31-F53 -> 0 | G64: =G31-G53 -> 0 | H64: =H31-H53 -> 0 | I64: =I31-I53 -> 0 | J64: =J31-J53 -> 0 | ... N64: =N31-N53 -> 0 | O64: =SUM(C64:N64) -> 0
B65: =B10 -> Insert Adj. 5 | C65: =C32-C54 -> 0 | D65: =D32-D54 -> 0 | E65: =E32-E54 -> 0 | F65: =F32-F54 -> 0 | G65: =G32-G54 -> 0 | H65: =H32-H54 -> 0 | I65: =I32-I54 -> 0 | J65: =J32-J54 -> 0 | ... N65: =N32-N54 -> 0 | O65: =SUM(C65:N65) -> 0
B66: =B11 -> Insert Adj. 6 | C66: =C33-C55 -> 0 | D66: =D33-D55 -> 0 | E66: =E33-E55 -> 0 | F66: =F33-F55 -> 0 | G66: =G33-G55 -> 0 | H66: =H33-H55 -> 0 | I66: =I33-I55 -> 0 | J66: =J33-J55 -> 0 | ... N66: =N33-N55 -> 0 | O66: =SUM(C66:N66) -> 0
B67: =B12 -> Insert Adj. 7 | C67: =C34-C56 -> 0 | D67: =D34-D56 -> 0 | E67: =E34-E56 -> 0 | F67: =F34-F56 -> 0 | G67: =G34-G56 -> 0 | H67: =H34-H56 -> 0 | I67: =I34-I56 -> 0 | J67: =J34-J56 -> 0 | ... N67: =N34-N56 -> 0 | O67: =SUM(C67:N67) -> 0
B68: =B13 -> Insert Adj. 8 | C68: =C35-C57 -> 0 | D68: =D35-D57 -> 0 | E68: =E35-E57 -> 0 | F68: =F35-F57 -> 0 | G68: =G35-G57 -> 0 | H68: =H35-H57 -> 0 | I68: =I35-I57 -> 0 | J68: =J35-J57 -> 0 | ... N68: =N35-N57 -> 0 | O68: =SUM(C68:N68) -> 0
B69: Total PBITA | C69: =SUM(C61:C68) -> 0 | D69: =SUM(D61:D68) -> 0 | E69: =SUM(E61:E68) -> 0 | F69: =SUM(F61:F68) -> 0 | G69: =SUM(G61:G68) -> 0 | H69: =SUM(H61:H68) -> 0 | I69: =SUM(I61:I68) -> 0 | J69: =SUM(J61:J68) -> 0 | ... O69: =SUM(O61:O68) -> -280
B71: Section 2: General adjustments in Gross Margin or Opex % of Sales that are not tied to individual events (i.e., employee turnover):
C73: January | D73: February | E73: March | F73: April | G73: May | H73: June | I73: July | J73: August | K73: September | L73: October | M73: November | N73: December | O73: Total Adj
B74: Gross Margin
B75: Gross Margin - Previous FCAST | C75: =Alder!C35 -> 0.26461929 | D75: =Alder!D35 -> 0.26197322 | E75: =Alder!E35 -> 0.2614399 | F75: =Alder!F35 -> 0.26262086 | G75: =Alder!G35 -> 0.26195599 | H75: =Alder!H35 -> 0.24014859 | I75: =Alder!I35 -> 0.24061322 | J75: =Alder!J35 -> 0.23877304 | ... N75: =Alder!N35 -> 0.23942871 | O75: N/A
B76: New Adjustments (%) | C76: None | D76: None | E76: None | F76: None | G76: None | H76: None | I76: None | J76: None | K76: None | L76: None | M76: None | N76: None
B77: New Adjustments ($) | C77: =IF(C76="None",0,(((Alder!C28*(C75+C76))-Alder!C29))) -> 0 | D77: =IF(D76="None",0,(((Alder!D28*(D75+D76))-Alder!D29))) -> 0 | E77: =IF(E76="None",0,(((Alder!E28*(E75+E76))-Alder!E29))) -> 0 | F77: =IF(F76="None",0,(((Alder!F28*(F75+F76))-Alder!F29))) -> 0 | G77: =IF(G76="None",0,(((Alder!G28*(G75+G76))-Alder!G29))) -> 0 | H77: =IF(H76="None",0,(((Alder!H28*(H75+H76))-Alder!H29))) -> 0 | I77: =IF(I76="None",0,(((Alder!I28*(I75+I76))-Alder!I29))) -> 0 | J77: =IF(J76="None",0,(((Alder!J28*(J75+J76))-Alder!J29))) -> 0 | ... N77: =IF(N76="None",0,(((Alder!N28*(N75+N76))-Alder!N29))) -> 0 | O77: =SUM(C77:N77) -> 0
B78: Gross Margin - Current FCAST | C78: =SUM(C75:C76) -> 0.26461929 | D78: =SUM(D75:D76) -> 0.26197322 | E78: =SUM(E75:E76) -> 0.2614399 | F78: =SUM(F75:F76) -> 0.26262086 | G78: =SUM(G75:G76) -> 0.26195599 | H78: =SUM(H75:H76) -> 0.24014859 | I78: =SUM(I75:I76) -> 0.24061322 | J78: =SUM(J75:J76) -> 0.23877304 | ... N78: =SUM(N75:N76) -> 0.23942871 | O78: N/A
B81: Op Costs
B82: Op Costs - Previous FCAST | C82: =Alder!C36 -> -0.20042529 | D82: =Alder!D36 -> -0.19913491 | E82: =Alder!E36 -> -0.19549268 | F82: =Alder!F36 -> -0.19898676 | G82: =Alder!G36 -> -0.20072718 | H82: =Alder!H36 -> -0.19957265 | I82: =Alder!I36 -> -0.2007327 | J82: =Alder!J36 -> -0.19965129 | ... N82: =Alder!N36 -> -0.1975202 | O82: N/A
B83: New Adjustments (%) | C83: None | D83: None | E83: None | F83: None | G83: None | H83: None | I83: None | J83: None | K83: None | L83: None | M83: None | N83: None
B84: New Adjustments ($) | C84: =-IF(C83="None",0,(((Alder!C28*-(C82+C83))-Alder!C30))) -> 0 | D84: =-IF(D83="None",0,(((Alder!D28*-(D82+D83))-Alder!D30))) -> 0 | E84: =-IF(E83="None",0,(((Alder!E28*-(E82+E83))-Alder!E30))) -> 0 | F84: =-IF(F83="None",0,(((Alder!F28*-(F82+F83))-Alder!F30))) -> 0 | G84: =-IF(G83="None",0,(((Alder!G28*-(G82+G83))-Alder!G30))) -> 0 | H84: =-IF(H83="None",0,(((Alder!H28*-(H82+H83))-Alder!H30))) -> 0 | I84: =-IF(I83="None",0,(((Alder!I28*-(I82+I83))-Alder!I30))) -> 0 | J84: =-IF(J83="None",0,(((Alder!J28*-(J82+J83))-Alder!J30))) -> 0 | ... N84: =-IF(N83="None",0,(((Alder!N28*-(N82+N83))-Alder!N30))) -> 0 | O84: =SUM(C84:N84) -> 0
B85: Op Costs - Current FCAST | C85: =SUM(C82:C83) -> -0.20042529 | D85: =SUM(D82:D83) -> -0.19913491 | E85: =SUM(E82:E83) -> -0.19549268 | F85: =SUM(F82:F83) -> -0.19898676 | G85: =SUM(G82:G83) -> -0.20072718 | H85: =SUM(H82:H83) -> -0.19957265 | I85: =SUM(I82:I83) -> -0.2007327 | J85: =SUM(J82:J83) -> -0.19965129 | ... N85: =SUM(N82:N83) -> -0.1975202 | O85: N/A
B87: Section 3: Working Capital Adjustments
C89: January | D89: February | E89: March | F89: April | G89: May | H89: June | I89: July | J89: August | K89: September | L89: October | M89: November | N89: December | O89: Total Adj
A90: 2090 | B90: Net Inventory | C90: 0 | D90: 0 | E90: 0 | F90: 0 | G90: 0 | H90: 0 | I90: 0 | J90: 0 | K90: 0 | L90: -1200 | M90: -2000 | N90: -2500
A91: 2135 | B91: Trade Receivables | C91: 0 | D91: 0 | E91: 0 | F91: 0 | G91: 0 | H91: 0 | I91: 0 | J91: 0 | K91: 0 | L91: 0 | M91: 0 | N91: 0
A92: 2175 | B92: Other Receivables | C92: 0 | D92: 0 | E92: 0 | F92: 0 | G92: 0 | H92: 0 | I92: 0 | J92: 0 | K92: 0 | L92: 0 | M92: 0 | N92: 0
A93: 2140 | B93: Trade Payables | C93: 0 | D93: 0 | E93: 0 | F93: 0 | G93: 0 | H93: 0 | I93: 0 | J93: 0 | K93: 0 | L93: 0 | M93: 0 | N93: 0
A94: 2180 | B94: Other Payables | C94: 0 | D94: 0 | E94: 0 | F94: 0 | G94: 0 | H94: 0 | I94: 0 | J94: 0 | K94: 0 | L94: 0 | M94: 0 | N94: 0
A95: 2185 | B95: Total Working Capital | C95: =SUM(C90:C94) -> 0 | D95: =SUM(D90:D94) -> 0 | E95: =SUM(E90:E94) -> 0 | F95: =SUM(F90:F94) -> 0 | G95: =SUM(G90:G94) -> 0 | H95: =SUM(H90:H94) -> 0 | I95: =SUM(I90:I94) -> 0 | J95: =SUM(J90:J94) -> 0 | ... N95: =SUM(N90:N94) -> -2500
B97: NOTE: A positive number within the working capital adjustments section indicates a DR (i.e., increase to asset / decrease to liability). A negative number indicates a CR.

Sheet Alder
C1: Actual | D1: Actual | E1: Actual | F1: Actual | G1: Actual | H1: Actual | I1: Actual | J1: Actual | K1: FCAST09 | L1: FCAST09 | M1: FCAST09 | N1: FCAST09
B2: Scenario# | C2: Actual | D2: Actual | E2: Actual | F2: Actual | G2: Actual | H2: Actual | I2: Actual | J2: Actual | K2: Actual | L2: Actual | M2: Actual | N2: Actual
B5: Year# | C5: 2026 | D5: 2026 | E5: 2026 | F5: 2026 | G5: 2026 | H5: 2026 | I5: 2026 | J5: 2026 | K5: 2026 | L5: 2026 | M5: 2026 | N5: 2026
B8: Period# | C8: P01 | D8: P02 | E8: P03 | F8: P04 | G8: P05 | H8: P06 | I8: P07 | J8: P08 | K8: P09 | L8: P10 | M8: P11 | N8: P12
B9: Account#
B10: ICP#
B11: Custom1# | C11: TotalC1 | D11: TotalC1 | E11: TotalC1 | F11: TotalC1 | G11: TotalC1 | H11: TotalC1 | I11: TotalC1 | J11: TotalC1 | K11: TotalC1 | L11: TotalC1 | M11: TotalC1 | N11: TotalC1
B12: Custom2# | C12: TotalC2 | D12: TotalC2 | E12: TotalC2 | F12: TotalC2 | G12: TotalC2 | H12: TotalC2 | I12: TotalC2 | J12: TotalC2 | K12: TotalC2 | L12: TotalC2 | M12: TotalC2 | N12: TotalC2
B13: Custom3#
B14: Custom4#
B18: View# | C18: Periodic | D18: Periodic | E18: Periodic | F18: Periodic | G18: Periodic | H18: Periodic | I18: Periodic | J18: Periodic | K18: Periodic | L18: Periodic | M18: Periodic | N18: Periodic
B19: Value# | C19: USD Total | D19: USD Total | E19: USD Total | F19: USD Total | G19: USD Total | H19: USD Total | I19: USD Total | J19: USD Total | K19: USD Total | L19: USD Total | M19: USD Total | N19: USD Total
B21: TRAINING DATA ONLY - Zava Safety and all business names and numbers are fictitious. Layout mirrors a typical HFM / Cognos reporting pack.
B22: ALDER_DISP
B23: Alder Gloves | BU23: FCAST10 - Variance ($) - Favorable / (Unfavorable)
C24: FCAST09 as Reported | Q24: FCAST09 at New Fx Rates | AE24: Fx Changes | AS24: Operational Adjustments | BG24: FCAST10 | BU24: Through Sep | BY24: Rest of Year | CC24: Full Year
C25: Actual | D25: Actual | E25: Actual | F25: Actual | G25: Actual | H25: Actual | I25: Actual | J25: Actual | K25: FCAST09 | L25: FCAST09 | M25: FCAST09 | N25: FCAST09 | O25: Forecast | Q25: Actual | R25: Actual | S25: Actual | T25: Actual | U25: Actual | V25: Actual | W25: Actual | X25: Actual | Y25: FCAST09 | Z25: FCAST09 | AA25: FCAST09 | AB25: FCAST09 | AC25: Forecast | BG25: Actual | BH25: Actual | BI25: Actual | BJ25: Actual | BK25: Actual | BL25: Actual | BM25: Actual | BN25: Actual | BO25: Actual | BP25: FCAST10 | BQ25: FCAST10 | BR25: FCAST10 | BS25: Forecast
B26: Description: | C26: January | D26: February | E26: March | F26: April | G26: May | H26: June | I26: July | J26: August | K26: September | L26: October | M26: November | N26: December | O26: Full year | Q26: January | R26: February | S26: March | T26: April | U26: May | V26: June | W26: July | X26: August | Y26: September | Z26: October | AA26: November | AB26: December | AC26: Full year | AE26: January | AF26: February | AG26: March | AH26: April | AI26: May | AJ26: June | AK26: July | AL26: August | AM26: September | AN26: October | AO26: November | AP26: December | AQ26: Full year | AS26: January | AT26: February | AU26: March | AV26: April | AW26: May | AX26: June | AY26: July | AZ26: August | BA26: September | BB26: October | BC26: November | BD26: December | BE26: Full year | BG26: January | BH26: February | BI26: March | BJ26: April | BK26: May | BL26: June | BM26: July | BN26: August | BO26: September | BP26: October | BQ26: November | BR26: December | BS26: Full year | BU26: Actual vs. FCAST09 | BV26: Actual vs. Bud | BW26: Actual vs. PY | BY26: FCAST10 vs. FCAST09 | BZ26: FCAST10 vs. Bud | CA26: FCAST10 vs. PY | CC26: FCAST10 vs. FCAST09 | CD26: FCAST10 vs. Bud | CE26: FCAST10 vs. PY
B28: Sales | C28: 12227 | D28: 12137.5 | E28: 13112 | F28: 14014.5 | G28: 12734.2 | H28: 13244.3 | I28: 13156.8 | J28: 12962.1 | K28: 12857.9 | L28: 13505.7 | M28: 12317.9 | N28: 13541.4 | O28: =SUM(C28:N28) -> 155811.3 | Q28: 12227 | R28: 12137.5 | S28: 13112 | T28: 14014.5 | U28: 12734.2 | V28: 13244.3 | W28: 13156.8 | X28: 12962.1 | Y28: 12857.9 | Z28: 13505.7 | AA28: 12317.9 | AB28: 13541.4 | AC28: =SUM(Q28:AB28) -> 155811.3 | AE28: =Q28-C28 -> 0 | AF28: =R28-D28 -> 0 | AG28: =S28-E28 -> 0 | AH28: =T28-F28 -> 0 | AI28: =U28-G28 -> 0 | AJ28: =V28-H28 -> 0 | AK28: =W28-I28 -> 0 | AL28: =X28-J28 -> 0 | ... AP28: =AB28-N28 -> 0 | AQ28: =SUM(AE28:AP28) -> 0 | AS28: ='Alder-Adj'!C14 -> 0 | AT28: ='Alder-Adj'!D14 -> 0 | AU28: ='Alder-Adj'!E14 -> 0 | AV28: ='Alder-Adj'!F14 -> 0 | AW28: ='Alder-Adj'!G14 -> 0 | AX28: ='Alder-Adj'!H14 -> 0 | AY28: ='Alder-Adj'!I14 -> 0 | AZ28: ='Alder-Adj'!J14 -> 0 | ... BD28: ='Alder-Adj'!N14 -> -200 | BE28: =SUM(AS28:BD28) -> -600 | BG28: =C28+AE28+AS28 -> 12227 | BH28: =D28+AF28+AT28 -> 12137.5 | BI28: =E28+AG28+AU28 -> 13112 | BJ28: =F28+AH28+AV28 -> 14014.5 | BK28: =G28+AI28+AW28 -> 12734.2 | BL28: =H28+AJ28+AX28 -> 13244.3 | BM28: =I28+AK28+AY28 -> 13156.8 | BN28: =J28+AL28+AZ28 -> 12962.1 | ... BR28: =N28+AP28+BD28 -> 13341.4 | BS28: =SUM(BG28:BR28) -> 155211.3 | BU28: =SUM(BG28:BO28)-SUM(C28:K28) -> 0 | BV28: =SUM(BG28:BO28)-SUM(C51:K51) -> 4321.5 | BW28: =SUM(BG28:BO28)-SUM(C64:K64) -> 9085.9 | BY28: =SUM(BP28:BR28)-SUM(L28:N28) -> -600 | BZ28: =SUM(BP28:BR28)-SUM(L51:N51) -> 890 | CA28: =SUM(BP28:BR28)-SUM(L64:N64) -> 2526.4 | CC28: =BS28-O28 -> -600 | CD28: =BS28-O51 -> 5211.5 | CE28: =BS28-O64 -> 11612.3
B29: Gross Margin | C29: 3235.5 | D29: 3179.7 | E29: 3428 | F29: 3680.5 | G29: 3335.8 | H29: 3180.6 | I29: 3165.7 | J29: 3095 | K29: 3096.5 | L29: 3179.7 | M29: 2934 | N29: 3242.2 | O29: =SUM(C29:N29) -> 38753.2 | Q29: 3235.5 | R29: 3179.7 | S29: 3428 | T29: 3680.5 | U29: 3335.8 | V29: 3180.6 | W29: 3165.7 | X29: 3095 | Y29: 3096.5 | Z29: 3179.7 | AA29: 2934 | AB29: 3242.2 | AC29: =SUM(Q29:AB29) -> 38753.2 | AE29: =Q29-C29 -> 0 | AF29: =R29-D29 -> 0 | AG29: =S29-E29 -> 0 | AH29: =T29-F29 -> 0 | AI29: =U29-G29 -> 0 | AJ29: =V29-H29 -> 0 | AK29: =W29-I29 -> 0 | AL29: =X29-J29 -> 0 | ... AP29: =AB29-N29 -> 0 | AQ29: =SUM(AE29:AP29) -> 0 | AS29: ='Alder-Adj'!C36+'Alder-Adj'!C77 -> 0 | AT29: ='Alder-Adj'!D36+'Alder-Adj'!D77 -> 0 | AU29: ='Alder-Adj'!E36+'Alder-Adj'!E77 -> 0 | AV29: ='Alder-Adj'!F36+'Alder-Adj'!F77 -> 0 | AW29: ='Alder-Adj'!G36+'Alder-Adj'!G77 -> 0 | AX29: ='Alder-Adj'!H36+'Alder-Adj'!H77 -> 0 | AY29: ='Alder-Adj'!I36+'Alder-Adj'!I77 -> 0 | AZ29: ='Alder-Adj'!J36+'Alder-Adj'!J77 -> 0 | ... BD29: ='Alder-Adj'!N36+'Alder-Adj'!N77 -> -140 | BE29: =SUM(AS29:BD29) -> -580 | BG29: =C29+AE29+AS29 -> 3235.5 | BH29: =D29+AF29+AT29 -> 3179.7 | BI29: =E29+AG29+AU29 -> 3428 | BJ29: =F29+AH29+AV29 -> 3680.5 | BK29: =G29+AI29+AW29 -> 3335.8 | BL29: =H29+AJ29+AX29 -> 3180.6 | BM29: =I29+AK29+AY29 -> 3165.7 | BN29: =J29+AL29+AZ29 -> 3095 | ... BR29: =N29+AP29+BD29 -> 3102.2 | BS29: =SUM(BG29:BR29) -> 38173.2 | BU29: =SUM(BG29:BO29)-SUM(C29:K29) -> -160 | BV29: =SUM(BG29:BO29)-SUM(C52:K52) -> -475.7 | BW29: =SUM(BG29:BO29)-SUM(C65:K65) -> 123.5 | BY29: =SUM(BP29:BR29)-SUM(L29:N29) -> -420 | BZ29: =SUM(BP29:BR29)-SUM(L52:N52) -> -1101 | CA29: =SUM(BP29:BR29)-SUM(L65:N65) -> -909.6 | CC29: =BS29-O29 -> -580 | CD29: =BS29-O52 -> -1576.7 | CE29: =BS29-O65 -> -786.1
B30: Op Costs | C30: -2450.6 | D30: -2417 | E30: -2563.3 | F30: -2788.7 | G30: -2556.1 | H30: -2643.2 | I30: -2641 | J30: -2587.9 | K30: -2529.2 | L30: -2703 | M30: -2448.8 | N30: -2674.7 | O30: =SUM(C30:N30) -> -31003.5 | Q30: -2450.6 | R30: -2417 | S30: -2563.3 | T30: -2788.7 | U30: -2556.1 | V30: -2643.2 | W30: -2641 | X30: -2587.9 | Y30: -2529.2 | Z30: -2703 | AA30: -2448.8 | AB30: -2674.7 | AC30: =SUM(Q30:AB30) -> -31003.5 | AE30: =Q30-C30 -> 0 | AF30: =R30-D30 -> 0 | AG30: =S30-E30 -> 0 | AH30: =T30-F30 -> 0 | AI30: =U30-G30 -> 0 | AJ30: =V30-H30 -> 0 | AK30: =W30-I30 -> 0 | AL30: =X30-J30 -> 0 | ... AP30: =AB30-N30 -> 0 | AQ30: =SUM(AE30:AP30) -> 0 | AS30: =-'Alder-Adj'!C58-'Alder-Adj'!C84 -> 0 | AT30: =-'Alder-Adj'!D58-'Alder-Adj'!D84 -> 0 | AU30: =-'Alder-Adj'!E58-'Alder-Adj'!E84 -> 0 | AV30: =-'Alder-Adj'!F58-'Alder-Adj'!F84 -> 0 | AW30: =-'Alder-Adj'!G58-'Alder-Adj'!G84 -> 0 | AX30: =-'Alder-Adj'!H58-'Alder-Adj'!H84 -> 0 | AY30: =-'Alder-Adj'!I58-'Alder-Adj'!I84 -> 0 | AZ30: =-'Alder-Adj'!J58-'Alder-Adj'!J84 -> 0 | ... BD30: =-'Alder-Adj'!N58-'Alder-Adj'!N84 -> 20 | BE30: =SUM(AS30:BD30) -> 300 | BG30: =C30+AE30+AS30 -> -2450.6 | BH30: =D30+AF30+AT30 -> -2417 | BI30: =E30+AG30+AU30 -> -2563.3 | BJ30: =F30+AH30+AV30 -> -2788.7 | BK30: =G30+AI30+AW30 -> -2556.1 | BL30: =H30+AJ30+AX30 -> -2643.2 | BM30: =I30+AK30+AY30 -> -2641 | BN30: =J30+AL30+AZ30 -> -2587.9 | ... BR30: =N30+AP30+BD30 -> -2654.7 | BS30: =SUM(BG30:BR30) -> -30703.5 | BU30: =SUM(BG30:BO30)-SUM(C30:K30) -> 240 | BV30: =SUM(BG30:BO30)-SUM(C53:K53) -> -174.7 | BW30: =SUM(BG30:BO30)-SUM(C66:K66) -> -899.6 | BY30: =SUM(BP30:BR30)-SUM(L30:N30) -> 60 | BZ30: =SUM(BP30:BR30)-SUM(L53:N53) -> -77.2 | CA30: =SUM(BP30:BR30)-SUM(L66:N66) -> -330.8 | CC30: =BS30-O30 -> 300 | CD30: =BS30-O53 -> -251.9 | CE30: =BS30-O66 -> -1230.4
B31: PBITA | C31: =C29+C30 -> 784.9 | D31: =D29+D30 -> 762.7 | E31: =E29+E30 -> 864.7 | F31: =F29+F30 -> 891.8 | G31: =G29+G30 -> 779.7 | H31: =H29+H30 -> 537.4 | I31: =I29+I30 -> 524.7 | J31: =J29+J30 -> 507.1 | ... N31: =N29+N30 -> 567.5 | O31: =SUM(C31:N31) -> 7749.7 | Q31: =Q29+Q30 -> 784.9 | R31: =R29+R30 -> 762.7 | S31: =S29+S30 -> 864.7 | T31: =T29+T30 -> 891.8 | U31: =U29+U30 -> 779.7 | V31: =V29+V30 -> 537.4 | W31: =W29+W30 -> 524.7 | X31: =X29+X30 -> 507.1 | ... AB31: =AB29+AB30 -> 567.5 | AC31: =SUM(Q31:AB31) -> 7749.7 | AE31: =AE29+AE30 -> 0 | AF31: =AF29+AF30 -> 0 | AG31: =AG29+AG30 -> 0 | AH31: =AH29+AH30 -> 0 | AI31: =AI29+AI30 -> 0 | AJ31: =AJ29+AJ30 -> 0 | AK31: =AK29+AK30 -> 0 | AL31: =AL29+AL30 -> 0 | ... AP31: =AP29+AP30 -> 0 | AQ31: =SUM(AE31:AP31) -> 0 | AS31: =AS29+AS30 -> 0 | AT31: =AT29+AT30 -> 0 | AU31: =AU29+AU30 -> 0 | AV31: =AV29+AV30 -> 0 | AW31: =AW29+AW30 -> 0 | AX31: =AX29+AX30 -> 0 | AY31: =AY29+AY30 -> 0 | AZ31: =AZ29+AZ30 -> 0 | ... BD31: =BD29+BD30 -> -120 | BE31: =SUM(AS31:BD31) -> -280 | BG31: =BG29+BG30 -> 784.9 | BH31: =BH29+BH30 -> 762.7 | BI31: =BI29+BI30 -> 864.7 | BJ31: =BJ29+BJ30 -> 891.8 | BK31: =BK29+BK30 -> 779.7 | BL31: =BL29+BL30 -> 537.4 | BM31: =BM29+BM30 -> 524.7 | BN31: =BN29+BN30 -> 507.1 | ... BR31: =BR29+BR30 -> 447.5 | BS31: =SUM(BG31:BR31) -> 7469.7 | BU31: =SUM(BG31:BO31)-SUM(C31:K31) -> 80 | BV31: =SUM(BG31:BO31)-SUM(C54:K54) -> -650.4 | BW31: =SUM(BG31:BO31)-SUM(C67:K67) -> -776.1 | BY31: =SUM(BP31:BR31)-SUM(L31:N31) -> -360 | BZ31: =SUM(BP31:BR31)-SUM(L54:N54) -> -1178.2 | CA31: =SUM(BP31:BR31)-SUM(L67:N67) -> -1240.4 | CC31: =BS31-O31 -> -280 | CD31: =BS31-O54 -> -1828.6 | CE31: =BS31-O67 -> -2016.5
B35: GM % | C35: =IFERROR(C29/C28,0) -> 0.26461929 | D35: =IFERROR(D29/D28,0) -> 0.26197322 | E35: =IFERROR(E29/E28,0) -> 0.2614399 | F35: =IFERROR(F29/F28,0) -> 0.26262086 | G35: =IFERROR(G29/G28,0) -> 0.26195599 | H35: =IFERROR(H29/H28,0) -> 0.24014859 | I35: =IFERROR(I29/I28,0) -> 0.24061322 | J35: =IFERROR(J29/J28,0) -> 0.23877304 | ... O35: =IFERROR(O29/O28,0) -> 0.2487188 | Q35: =IFERROR(Q29/Q28,0) -> 0.26461929 | R35: =IFERROR(R29/R28,0) -> 0.26197322 | S35: =IFERROR(S29/S28,0) -> 0.2614399 | T35: =IFERROR(T29/T28,0) -> 0.26262086 | U35: =IFERROR(U29/U28,0) -> 0.26195599 | V35: =IFERROR(V29/V28,0) -> 0.24014859 | W35: =IFERROR(W29/W28,0) -> 0.24061322 | X35: =IFERROR(X29/X28,0) -> 0.23877304 | ... AC35: =IFERROR(AC29/AC28,0) -> 0.2487188 | AE35: =IFERROR(AE29/AE28,0) -> 0 | AF35: =IFERROR(AF29/AF28,0) -> 0 | AG35: =IFERROR(AG29/AG28,0) -> 0 | AH35: =IFERROR(AH29/AH28,0) -> 0 | AI35: =IFERROR(AI29/AI28,0) -> 0 | AJ35: =IFERROR(AJ29/AJ28,0) -> 0 | AK35: =IFERROR(AK29/AK28,0) -> 0 | AL35: =IFERROR(AL29/AL28,0) -> 0 | ... AQ35: =IFERROR(AQ29/AQ28,0) -> 0 | AS35: =IFERROR(AS29/AS28,0) -> 0 | AT35: =IFERROR(AT29/AT28,0) -> 0 | AU35: =IFERROR(AU29/AU28,0) -> 0 | AV35: =IFERROR(AV29/AV28,0) -> 0 | AW35: =IFERROR(AW29/AW28,0) -> 0 | AX35: =IFERROR(AX29/AX28,0) -> 0 | AY35: =IFERROR(AY29/AY28,0) -> 0 | AZ35: =IFERROR(AZ29/AZ28,0) -> 0 | ... BE35: =IFERROR(BE29/BE28,0) -> 0.96666667 | BG35: =IFERROR(BG29/BG28,0) -> 0.26461929 | BH35: =IFERROR(BH29/BH28,0) -> 0.26197322 | BI35: =IFERROR(BI29/BI28,0) -> 0.2614399 | BJ35: =IFERROR(BJ29/BJ28,0) -> 0.26262086 | BK35: =IFERROR(BK29/BK28,0) -> 0.26195599 | BL35: =IFERROR(BL29/BL28,0) -> 0.24014859 | BM35: =IFERROR(BM29/BM28,0) -> 0.24061322 | BN35: =IFERROR(BN29/BN28,0) -> 0.23877304 | ... BS35: =IFERROR(BS29/BS28,0) -> 0.24594343
B36: Op Cost % | C36: =IFERROR(C30/C28,0) -> -0.20042529 | D36: =IFERROR(D30/D28,0) -> -0.19913491 | E36: =IFERROR(E30/E28,0) -> -0.19549268 | F36: =IFERROR(F30/F28,0) -> -0.19898676 | G36: =IFERROR(G30/G28,0) -> -0.20072718 | H36: =IFERROR(H30/H28,0) -> -0.19957265 | I36: =IFERROR(I30/I28,0) -> -0.2007327 | J36: =IFERROR(J30/J28,0) -> -0.19965129 | ... O36: =IFERROR(O30/O28,0) -> -0.19898108 | Q36: =IFERROR(Q30/Q28,0) -> -0.20042529 | R36: =IFERROR(R30/R28,0) -> -0.19913491 | S36: =IFERROR(S30/S28,0) -> -0.19549268 | T36: =IFERROR(T30/T28,0) -> -0.19898676 | U36: =IFERROR(U30/U28,0) -> -0.20072718 | V36: =IFERROR(V30/V28,0) -> -0.19957265 | W36: =IFERROR(W30/W28,0) -> -0.2007327 | X36: =IFERROR(X30/X28,0) -> -0.19965129 | ... AC36: =IFERROR(AC30/AC28,0) -> -0.19898108 | AE36: =IFERROR(AE30/AE28,0) -> 0 | AF36: =IFERROR(AF30/AF28,0) -> 0 | AG36: =IFERROR(AG30/AG28,0) -> 0 | AH36: =IFERROR(AH30/AH28,0) -> 0 | AI36: =IFERROR(AI30/AI28,0) -> 0 | AJ36: =IFERROR(AJ30/AJ28,0) -> 0 | AK36: =IFERROR(AK30/AK28,0) -> 0 | AL36: =IFERROR(AL30/AL28,0) -> 0 | ... AQ36: =IFERROR(AQ30/AQ28,0) -> 0 | AS36: =IFERROR(AS30/AS28,0) -> 0 | AT36: =IFERROR(AT30/AT28,0) -> 0 | AU36: =IFERROR(AU30/AU28,0) -> 0 | AV36: =IFERROR(AV30/AV28,0) -> 0 | AW36: =IFERROR(AW30/AW28,0) -> 0 | AX36: =IFERROR(AX30/AX28,0) -> 0 | AY36: =IFERROR(AY30/AY28,0) -> 0 | AZ36: =IFERROR(AZ30/AZ28,0) -> 0 | ... BE36: =IFERROR(BE30/BE28,0) -> -0.5 | BG36: =IFERROR(BG30/BG28,0) -> -0.20042529 | BH36: =IFERROR(BH30/BH28,0) -> -0.19913491 | BI36: =IFERROR(BI30/BI28,0) -> -0.19549268 | BJ36: =IFERROR(BJ30/BJ28,0) -> -0.19898676 | BK36: =IFERROR(BK30/BK28,0) -> -0.20072718 | BL36: =IFERROR(BL30/BL28,0) -> -0.19957265 | BM36: =IFERROR(BM30/BM28,0) -> -0.2007327 | BN36: =IFERROR(BN30/BN28,0) -> -0.19965129 | ... BS36: =IFERROR(BS30/BS28,0) -> -0.19781743
B37: PBITA % | C37: =IFERROR(C31/C28,0) -> 0.064193997 | D37: =IFERROR(D31/D28,0) -> 0.062838311 | E37: =IFERROR(E31/E28,0) -> 0.065947224 | F37: =IFERROR(F31/F28,0) -> 0.063634093 | G37: =IFERROR(G31/G28,0) -> 0.061228817 | H37: =IFERROR(H31/H28,0) -> 0.040575946 | I37: =IFERROR(I31/I28,0) -> 0.039880518 | J37: =IFERROR(J31/J28,0) -> 0.039121747 | ... O37: =IFERROR(O31/O28,0) -> 0.049737728 | Q37: =IFERROR(Q31/Q28,0) -> 0.064193997 | R37: =IFERROR(R31/R28,0) -> 0.062838311 | S37: =IFERROR(S31/S28,0) -> 0.065947224 | T37: =IFERROR(T31/T28,0) -> 0.063634093 | U37: =IFERROR(U31/U28,0) -> 0.061228817 | V37: =IFERROR(V31/V28,0) -> 0.040575946 | W37: =IFERROR(W31/W28,0) -> 0.039880518 | X37: =IFERROR(X31/X28,0) -> 0.039121747 | ... AC37: =IFERROR(AC31/AC28,0) -> 0.049737728 | AE37: =IFERROR(AE31/AE28,0) -> 0 | AF37: =IFERROR(AF31/AF28,0) -> 0 | AG37: =IFERROR(AG31/AG28,0) -> 0 | AH37: =IFERROR(AH31/AH28,0) -> 0 | AI37: =IFERROR(AI31/AI28,0) -> 0 | AJ37: =IFERROR(AJ31/AJ28,0) -> 0 | AK37: =IFERROR(AK31/AK28,0) -> 0 | AL37: =IFERROR(AL31/AL28,0) -> 0 | ... AQ37: =IFERROR(AQ31/AQ28,0) -> 0 | AS37: =IFERROR(AS31/AS28,0) -> 0 | AT37: =IFERROR(AT31/AT28,0) -> 0 | AU37: =IFERROR(AU31/AU28,0) -> 0 | AV37: =IFERROR(AV31/AV28,0) -> 0 | AW37: =IFERROR(AW31/AW28,0) -> 0 | AX37: =IFERROR(AX31/AX28,0) -> 0 | AY37: =IFERROR(AY31/AY28,0) -> 0 | AZ37: =IFERROR(AZ31/AZ28,0) -> 0 | ... BE37: =IFERROR(BE31/BE28,0) -> 0.46666667 | BG37: =IFERROR(BG31/BG28,0) -> 0.064193997 | BH37: =IFERROR(BH31/BH28,0) -> 0.062838311 | BI37: =IFERROR(BI31/BI28,0) -> 0.065947224 | BJ37: =IFERROR(BJ31/BJ28,0) -> 0.063634093 | BK37: =IFERROR(BK31/BK28,0) -> 0.061228817 | BL37: =IFERROR(BL31/BL28,0) -> 0.040575946 | BM37: =IFERROR(BM31/BM28,0) -> 0.039880518 | BN37: =IFERROR(BN31/BN28,0) -> 0.039121747 | ... BS37: =IFERROR(BS31/BS28,0) -> 0.048126006
B38: Sales/Day | C38: =IFERROR(C28/21,0) -> 582.2381 | D38: =IFERROR(D28/20,0) -> 606.875 | E38: =IFERROR(E28/22,0) -> 596 | F38: =IFERROR(F28/22,0) -> 637.02273 | G38: =IFERROR(G28/20,0) -> 636.71 | H38: =IFERROR(H28/22,0) -> 602.01364 | I38: =IFERROR(I28/22,0) -> 598.03636 | J38: =IFERROR(J28/21,0) -> 617.24286 | K38: =IFERROR(K28/21,0) -> 612.28095 | L38: =IFERROR(L28/22,0) -> 613.89545 | M38: =IFERROR(M28/19,0) -> 648.31053 | N38: =IFERROR(N28/22,0) -> 615.51818 | O38: =IFERROR(O28/254,0) -> 613.43031 | Q38: =IFERROR(Q28/21,0) -> 582.2381 | R38: =IFERROR(R28/20,0) -> 606.875 | S38: =IFERROR(S28/22,0) -> 596 | T38: =IFERROR(T28/22,0) -> 637.02273 | U38: =IFERROR(U28/20,0) -> 636.71 | V38: =IFERROR(V28/22,0) -> 602.01364 | W38: =IFERROR(W28/22,0) -> 598.03636 | X38: =IFERROR(X28/21,0) -> 617.24286 | Y38: =IFERROR(Y28/21,0) -> 612.28095 | Z38: =IFERROR(Z28/22,0) -> 613.89545 | AA38: =IFERROR(AA28/19,0) -> 648.31053 | AB38: =IFERROR(AB28/22,0) -> 615.51818 | AC38: =IFERROR(AC28/254,0) -> 613.43031 | AE38: =IFERROR(AE28/21,0) -> 0 | AF38: =IFERROR(AF28/20,0) -> 0 | AG38: =IFERROR(AG28/22,0) -> 0 | AH38: =IFERROR(AH28/22,0) -> 0 | AI38: =IFERROR(AI28/20,0) -> 0 | AJ38: =IFERROR(AJ28/22,0) -> 0 | AK38: =IFERROR(AK28/22,0) -> 0 | AL38: =IFERROR(AL28/21,0) -> 0 | AM38: =IFERROR(AM28/21,0) -> 0 | AN38: =IFERROR(AN28/22,0) -> 0 | AO38: =IFERROR(AO28/19,0) -> 0 | AP38: =IFERROR(AP28/22,0) -> 0 | AQ38: =IFERROR(AQ28/254,0) -> 0 | AS38: =IFERROR(AS28/21,0) -> 0 | AT38: =IFERROR(AT28/20,0) -> 0 | AU38: =IFERROR(AU28/22,0) -> 0 | AV38: =IFERROR(AV28/22,0) -> 0 | AW38: =IFERROR(AW28/20,0) -> 0 | AX38: =IFERROR(AX28/22,0) -> 0 | AY38: =IFERROR(AY28/22,0) -> 0 | AZ38: =IFERROR(AZ28/21,0) -> 0 | BA38: =IFERROR(BA28/21,0) -> 0 | BB38: =IFERROR(BB28/22,0) -> -9.0909091 | BC38: =IFERROR(BC28/19,0) -> -10.526316 | BD38: =IFERROR(BD28/22,0) -> -9.0909091 | BE38: =IFERROR(BE28/254,0) -> -2.3622047 | BG38: =IFERROR(BG28/21,0) -> 582.2381 | BH38: =IFERROR(BH28/20,0) -> 606.875 | BI38: =IFERROR(BI28/22,0) -> 596 | BJ38: =IFERROR(BJ28/22,0) -> 637.02273 | BK38: =IFERROR(BK28/20,0) -> 636.71 | BL38: =IFERROR(BL28/22,0) -> 602.01364 | BM38: =IFERROR(BM28/22,0) -> 598.03636 | BN38: =IFERROR(BN28/21,0) -> 617.24286 | BO38: =IFERROR(BO28/21,0) -> 612.28095 | BP38: =IFERROR(BP28/22,0) -> 604.80455 | BQ38: =IFERROR(BQ28/19,0) -> 637.78421 | BR38: =IFERROR(BR28/22,0) -> 606.42727 | BS38: =IFERROR(BS28/254,0) -> 611.06811
B40: Net Inventory | C40: 22505.5 | D40: 22640.4 | E40: 24132.9 | F40: 25725.7 | G40: 22899.8 | H40: 23548.3 | I40: 23519.2 | J40: 22081.9 | K40: 21834.7 | L40: 22410.7 | M40: 20565.5 | N40: 22179.7 | O40: =N40 -> 22179.7 | Q40: 22505.5 | R40: 22640.4 | S40: 24132.9 | T40: 25725.7 | U40: 22899.8 | V40: 23548.3 | W40: 23519.2 | X40: 22081.9 | Y40: 21834.7 | Z40: 22410.7 | AA40: 20565.5 | AB40: 22179.7 | AC40: =AB40 -> 22179.7 | AE40: =Q40-C40 -> 0 | AF40: =R40-D40 -> 0 | AG40: =S40-E40 -> 0 | AH40: =T40-F40 -> 0 | AI40: =U40-G40 -> 0 | AJ40: =V40-H40 -> 0 | AK40: =W40-I40 -> 0 | AL40: =X40-J40 -> 0 | ... AP40: =AB40-N40 -> 0 | AQ40: =AP40 -> 0 | AS40: ='Alder-Adj'!C90 -> 0 | AT40: ='Alder-Adj'!D90 -> 0 | AU40: ='Alder-Adj'!E90 -> 0 | AV40: ='Alder-Adj'!F90 -> 0 | AW40: ='Alder-Adj'!G90 -> 0 | AX40: ='Alder-Adj'!H90 -> 0 | AY40: ='Alder-Adj'!I90 -> 0 | AZ40: ='Alder-Adj'!J90 -> 0 | ... BD40: ='Alder-Adj'!N90 -> -2500 | BE40: =BD40 -> -2500 | BG40: =C40+AE40+AS40 -> 22505.5 | BH40: =D40+AF40+AT40 -> 22640.4 | BI40: =E40+AG40+AU40 -> 24132.9 | BJ40: =F40+AH40+AV40 -> 25725.7 | BK40: =G40+AI40+AW40 -> 22899.8 | BL40: =H40+AJ40+AX40 -> 23548.3 | BM40: =I40+AK40+AY40 -> 23519.2 | BN40: =J40+AL40+AZ40 -> 22081.9 | ... BR40: =N40+AP40+BD40 -> 19679.7 | BS40: =BR40 -> 19679.7
B41: Trade Receivables | C41: 18544.3 | D41: 18408.5 | E41: 19886.5 | F41: 21255.3 | G41: 19313.5 | H41: 20087.2 | I41: 19954.5 | J41: 19659.2 | K41: 19501.1 | L41: 20180.3 | M41: 18378.8 | N41: 20234.5 | O41: =N41 -> 20234.5 | Q41: 18544.3 | R41: 18408.5 | S41: 19886.5 | T41: 21255.3 | U41: 19313.5 | V41: 20087.2 | W41: 19954.5 | X41: 19659.2 | Y41: 19501.1 | Z41: 20180.3 | AA41: 18378.8 | AB41: 20234.5 | AC41: =AB41 -> 20234.5 | AE41: =Q41-C41 -> 0 | AF41: =R41-D41 -> 0 | AG41: =S41-E41 -> 0 | AH41: =T41-F41 -> 0 | AI41: =U41-G41 -> 0 | AJ41: =V41-H41 -> 0 | AK41: =W41-I41 -> 0 | AL41: =X41-J41 -> 0 | ... AP41: =AB41-N41 -> 0 | AQ41: =AP41 -> 0 | AS41: ='Alder-Adj'!C91 -> 0 | AT41: ='Alder-Adj'!D91 -> 0 | AU41: ='Alder-Adj'!E91 -> 0 | AV41: ='Alder-Adj'!F91 -> 0 | AW41: ='Alder-Adj'!G91 -> 0 | AX41: ='Alder-Adj'!H91 -> 0 | AY41: ='Alder-Adj'!I91 -> 0 | AZ41: ='Alder-Adj'!J91 -> 0 | ... BD41: ='Alder-Adj'!N91 -> 0 | BE41: =BD41 -> 0 | BG41: =C41+AE41+AS41 -> 18544.3 | BH41: =D41+AF41+AT41 -> 18408.5 | BI41: =E41+AG41+AU41 -> 19886.5 | BJ41: =F41+AH41+AV41 -> 21255.3 | BK41: =G41+AI41+AW41 -> 19313.5 | BL41: =H41+AJ41+AX41 -> 20087.2 | BM41: =I41+AK41+AY41 -> 19954.5 | BN41: =J41+AL41+AZ41 -> 19659.2 | ... BR41: =N41+AP41+BD41 -> 20234.5 | BS41: =BR41 -> 20234.5
B42: Other Receivables | C42: 183.4 | D42: 182.1 | E42: 196.7 | F42: 210.2 | G42: 191 | H42: 198.7 | I42: 197.4 | J42: 194.4 | K42: 192.9 | L42: 199.6 | M42: 181.8 | N42: 200.1 | O42: =N42 -> 200.1 | Q42: 183.4 | R42: 182.1 | S42: 196.7 | T42: 210.2 | U42: 191 | V42: 198.7 | W42: 197.4 | X42: 194.4 | Y42: 192.9 | Z42: 199.6 | AA42: 181.8 | AB42: 200.1 | AC42: =AB42 -> 200.1 | AE42: =Q42-C42 -> 0 | AF42: =R42-D42 -> 0 | AG42: =S42-E42 -> 0 | AH42: =T42-F42 -> 0 | AI42: =U42-G42 -> 0 | AJ42: =V42-H42 -> 0 | AK42: =W42-I42 -> 0 | AL42: =X42-J42 -> 0 | ... AP42: =AB42-N42 -> 0 | AQ42: =AP42 -> 0 | AS42: ='Alder-Adj'!C92 -> 0 | AT42: ='Alder-Adj'!D92 -> 0 | AU42: ='Alder-Adj'!E92 -> 0 | AV42: ='Alder-Adj'!F92 -> 0 | AW42: ='Alder-Adj'!G92 -> 0 | AX42: ='Alder-Adj'!H92 -> 0 | AY42: ='Alder-Adj'!I92 -> 0 | AZ42: ='Alder-Adj'!J92 -> 0 | ... BD42: ='Alder-Adj'!N92 -> 0 | BE42: =BD42 -> 0 | BG42: =C42+AE42+AS42 -> 183.4 | BH42: =D42+AF42+AT42 -> 182.1 | BI42: =E42+AG42+AU42 -> 196.7 | BJ42: =F42+AH42+AV42 -> 210.2 | BK42: =G42+AI42+AW42 -> 191 | BL42: =H42+AJ42+AX42 -> 198.7 | BM42: =I42+AK42+AY42 -> 197.4 | BN42: =J42+AL42+AZ42 -> 194.4 | ... BR42: =N42+AP42+BD42 -> 200.1 | BS42: =BR42 -> 200.1
B43: Trade Payables | C43: -12887.8 | D43: -12839.5 | E43: -13880.4 | F43: -14812.1 | G43: -13471 | H43: -14424.6 | I43: -14320.6 | J43: -14142.8 | K43: -14220.7 | L43: -14714.6 | M43: -13364.3 | N43: -14676.2 | O43: =N43 -> -14676.2 | Q43: -12887.8 | R43: -12839.5 | S43: -13880.4 | T43: -14812.1 | U43: -13471 | V43: -14424.6 | W43: -14320.6 | X43: -14142.8 | Y43: -14220.7 | Z43: -14714.6 | AA43: -13364.3 | AB43: -14676.2 | AC43: =AB43 -> -14676.2 | AE43: =Q43-C43 -> 0 | AF43: =R43-D43 -> 0 | AG43: =S43-E43 -> 0 | AH43: =T43-F43 -> 0 | AI43: =U43-G43 -> 0 | AJ43: =V43-H43 -> 0 | AK43: =W43-I43 -> 0 | AL43: =X43-J43 -> 0 | ... AP43: =AB43-N43 -> 0 | AQ43: =AP43 -> 0 | AS43: ='Alder-Adj'!C93 -> 0 | AT43: ='Alder-Adj'!D93 -> 0 | AU43: ='Alder-Adj'!E93 -> 0 | AV43: ='Alder-Adj'!F93 -> 0 | AW43: ='Alder-Adj'!G93 -> 0 | AX43: ='Alder-Adj'!H93 -> 0 | AY43: ='Alder-Adj'!I93 -> 0 | AZ43: ='Alder-Adj'!J93 -> 0 | ... BD43: ='Alder-Adj'!N93 -> 0 | BE43: =BD43 -> 0 | BG43: =C43+AE43+AS43 -> -12887.8 | BH43: =D43+AF43+AT43 -> -12839.5 | BI43: =E43+AG43+AU43 -> -13880.4 | BJ43: =F43+AH43+AV43 -> -14812.1 | BK43: =G43+AI43+AW43 -> -13471 | BL43: =H43+AJ43+AX43 -> -14424.6 | BM43: =I43+AK43+AY43 -> -14320.6 | BN43: =J43+AL43+AZ43 -> -14142.8 | ... BR43: =N43+AP43+BD43 -> -14676.2 | BS43: =BR43 -> -14676.2
B44: Other Payables | C44: -366.8 | D44: -364.1 | E44: -393.4 | F44: -420.4 | G44: -382 | H44: -397.3 | I44: -394.7 | J44: -388.9 | K44: -385.7 | L44: -399.2 | M44: -363.5 | N44: -400.2 | O44: =N44 -> -400.2 | Q44: -366.8 | R44: -364.1 | S44: -393.4 | T44: -420.4 | U44: -382 | V44: -397.3 | W44: -394.7 | X44: -388.9 | Y44: -385.7 | Z44: -399.2 | AA44: -363.5 | AB44: -400.2 | AC44: =AB44 -> -400.2 | AE44: =Q44-C44 -> 0 | AF44: =R44-D44 -> 0 | AG44: =S44-E44 -> 0 | AH44: =T44-F44 -> 0 | AI44: =U44-G44 -> 0 | AJ44: =V44-H44 -> 0 | AK44: =W44-I44 -> 0 | AL44: =X44-J44 -> 0 | ... AP44: =AB44-N44 -> 0 | AQ44: =AP44 -> 0 | AS44: ='Alder-Adj'!C94 -> 0 | AT44: ='Alder-Adj'!D94 -> 0 | AU44: ='Alder-Adj'!E94 -> 0 | AV44: ='Alder-Adj'!F94 -> 0 | AW44: ='Alder-Adj'!G94 -> 0 | AX44: ='Alder-Adj'!H94 -> 0 | AY44: ='Alder-Adj'!I94 -> 0 | AZ44: ='Alder-Adj'!J94 -> 0 | ... BD44: ='Alder-Adj'!N94 -> 0 | BE44: =BD44 -> 0 | BG44: =C44+AE44+AS44 -> -366.8 | BH44: =D44+AF44+AT44 -> -364.1 | BI44: =E44+AG44+AU44 -> -393.4 | BJ44: =F44+AH44+AV44 -> -420.4 | BK44: =G44+AI44+AW44 -> -382 | BL44: =H44+AJ44+AX44 -> -397.3 | BM44: =I44+AK44+AY44 -> -394.7 | BN44: =J44+AL44+AZ44 -> -388.9 | ... BR44: =N44+AP44+BD44 -> -400.2 | BS44: =BR44 -> -400.2
B45: Total working capital | C45: =SUM(C40:C44) -> 27978.6 | D45: =SUM(D40:D44) -> 28027.4 | E45: =SUM(E40:E44) -> 29942.3 | F45: =SUM(F40:F44) -> 31958.7 | G45: =SUM(G40:G44) -> 28551.3 | H45: =SUM(H40:H44) -> 29012.3 | I45: =SUM(I40:I44) -> 28955.8 | J45: =SUM(J40:J44) -> 27403.8 | ... N45: =SUM(N40:N44) -> 27537.9 | O45: =N45 -> 27537.9 | Q45: =SUM(Q40:Q44) -> 27978.6 | R45: =SUM(R40:R44) -> 28027.4 | S45: =SUM(S40:S44) -> 29942.3 | T45: =SUM(T40:T44) -> 31958.7 | U45: =SUM(U40:U44) -> 28551.3 | V45: =SUM(V40:V44) -> 29012.3 | W45: =SUM(W40:W44) -> 28955.8 | X45: =SUM(X40:X44) -> 27403.8 | ... AB45: =SUM(AB40:AB44) -> 27537.9 | AC45: =AB45 -> 27537.9 | AE45: =SUM(AE40:AE44) -> 0 | AF45: =SUM(AF40:AF44) -> 0 | AG45: =SUM(AG40:AG44) -> 0 | AH45: =SUM(AH40:AH44) -> 0 | AI45: =SUM(AI40:AI44) -> 0 | AJ45: =SUM(AJ40:AJ44) -> 0 | AK45: =SUM(AK40:AK44) -> 0 | AL45: =SUM(AL40:AL44) -> 0 | ... AP45: =SUM(AP40:AP44) -> 0 | AQ45: =AP45 -> 0 | AS45: =SUM(AS40:AS44) -> 0 | AT45: =SUM(AT40:AT44) -> 0 | AU45: =SUM(AU40:AU44) -> 0 | AV45: =SUM(AV40:AV44) -> 0 | AW45: =SUM(AW40:AW44) -> 0 | AX45: =SUM(AX40:AX44) -> 0 | AY45: =SUM(AY40:AY44) -> 0 | AZ45: =SUM(AZ40:AZ44) -> 0 | ... BD45: =SUM(BD40:BD44) -> -2500 | BE45: =BD45 -> -2500 | BG45: =SUM(BG40:BG44) -> 27978.6 | BH45: =SUM(BH40:BH44) -> 28027.4 | BI45: =SUM(BI40:BI44) -> 29942.3 | BJ45: =SUM(BJ40:BJ44) -> 31958.7 | BK45: =SUM(BK40:BK44) -> 28551.3 | BL45: =SUM(BL40:BL44) -> 29012.3 | BM45: =SUM(BM40:BM44) -> 28955.8 | BN45: =SUM(BN40:BN44) -> 27403.8 | ... BR45: =SUM(BR40:BR44) -> 25037.9 | BS45: =BR45 -> 25037.9
B46: Working capital/sales (monthly) | C46: =IFERROR(C45/(C28*12),0) -> 0.19068864 | D46: =IFERROR(D45/(D28*12),0) -> 0.1924298 | E46: =IFERROR(E45/(E28*12),0) -> 0.19029833 | F46: =IFERROR(F45/(F28*12),0) -> 0.19003354 | G46: =IFERROR(G45/(G28*12),0) -> 0.18684134 | H46: =IFERROR(H45/(H28*12),0) -> 0.18254582 | I46: =IFERROR(I45/(I28*12),0) -> 0.18340199 | J46: =IFERROR(J45/(J28*12),0) -> 0.17617901 | ... N46: =IFERROR(N45/(N28*12),0) -> 0.16946734 | Q46: =IFERROR(Q45/(Q28*12),0) -> 0.19068864 | R46: =IFERROR(R45/(R28*12),0) -> 0.1924298 | S46: =IFERROR(S45/(S28*12),0) -> 0.19029833 | T46: =IFERROR(T45/(T28*12),0) -> 0.19003354 | U46: =IFERROR(U45/(U28*12),0) -> 0.18684134 | V46: =IFERROR(V45/(V28*12),0) -> 0.18254582 | W46: =IFERROR(W45/(W28*12),0) -> 0.18340199 | X46: =IFERROR(X45/(X28*12),0) -> 0.17617901 | ... AB46: =IFERROR(AB45/(AB28*12),0) -> 0.16946734 | AE46: =IFERROR(AE45/(AE28*12),0) -> 0 | AF46: =IFERROR(AF45/(AF28*12),0) -> 0 | AG46: =IFERROR(AG45/(AG28*12),0) -> 0 | AH46: =IFERROR(AH45/(AH28*12),0) -> 0 | AI46: =IFERROR(AI45/(AI28*12),0) -> 0 | AJ46: =IFERROR(AJ45/(AJ28*12),0) -> 0 | AK46: =IFERROR(AK45/(AK28*12),0) -> 0 | AL46: =IFERROR(AL45/(AL28*12),0) -> 0 | ... AP46: =IFERROR(AP45/(AP28*12),0) -> 0 | AS46: =IFERROR(AS45/(AS28*12),0) -> 0 | AT46: =IFERROR(AT45/(AT28*12),0) -> 0 | AU46: =IFERROR(AU45/(AU28*12),0) -> 0 | AV46: =IFERROR(AV45/(AV28*12),0) -> 0 | AW46: =IFERROR(AW45/(AW28*12),0) -> 0 | AX46: =IFERROR(AX45/(AX28*12),0) -> 0 | AY46: =IFERROR(AY45/(AY28*12),0) -> 0 | AZ46: =IFERROR(AZ45/(AZ28*12),0) -> 0 | ... BD46: =IFERROR(BD45/(BD28*12),0) -> 1.0416667 | BG46: =IFERROR(BG45/(BG28*12),0) -> 0.19068864 | BH46: =IFERROR(BH45/(BH28*12),0) -> 0.1924298 | BI46: =IFERROR(BI45/(BI28*12),0) -> 0.19029833 | BJ46: =IFERROR(BJ45/(BJ28*12),0) -> 0.19003354 | BK46: =IFERROR(BK45/(BK28*12),0) -> 0.18684134 | BL46: =IFERROR(BL45/(BL28*12),0) -> 0.18254582 | BM46: =IFERROR(BM45/(BM28*12),0) -> 0.18340199 | BN46: =IFERROR(BN45/(BN28*12),0) -> 0.17617901 | ... BR46: =IFERROR(BR45/(BR28*12),0) -> 0.15639226
B49: Budget 2026
C50: January | D50: February | E50: March | F50: April | G50: May | H50: June | I50: July | J50: August | K50: September | L50: October | M50: November | N50: December | O50: Full year
B51: Sales | C51: 11875 | D51: 11625 | E51: 12499.9 | F51: 13500 | G51: 12250 | H51: 12875 | I51: 12749.9 | J51: 12500 | K51: 12250 | L51: 13125 | M51: 11875 | N51: 12875 | O51: =SUM(C51:N51) -> 149999.8
B52: Gross Margin | C52: 3146.9 | D52: 3080.6 | E52: 3312.4 | F52: 3577.5 | G52: 3246.3 | H52: 3411.8 | I52: 3378.7 | J52: 3312.5 | K52: 3246.3 | L52: 3478.1 | M52: 3146.9 | N52: 3411.9 | O52: =SUM(C52:N52) -> 39749.9
B53: Op Costs | C53: -2410.7 | D53: -2360.1 | E53: -2537.5 | F53: -2740.6 | G53: -2486.9 | H53: -2613.6 | I53: -2588.5 | J53: -2537.5 | K53: -2486.9 | L53: -2665 | M53: -2410.7 | N53: -2613.6 | O53: =SUM(C53:N53) -> -30451.6
B54: PBITA | C54: =C52+C53 -> 736.2 | D54: =D52+D53 -> 720.5 | E54: =E52+E53 -> 774.9 | F54: =F52+F53 -> 836.9 | G54: =G52+G53 -> 759.4 | H54: =H52+H53 -> 798.2 | I54: =I52+I53 -> 790.2 | J54: =J52+J53 -> 775 | ... N54: =N52+N53 -> 798.3 | O54: =SUM(C54:N54) -> 9298.3
B55: Net Inventory | C55: 22047.2 | D55: 21955.7 | E55: 23058 | F55: 24932.8 | G55: 23042.6 | H55: 23739.7 | I55: 23671.2 | J55: 23554.5 | K55: 23081.5 | L55: 24442.9 | M55: 22079.5 | N55: 23926.4 | O55: =N55 -> 23926.4
B56: Trade Receivables | C56: 17812.5 | D56: 17437.5 | E56: 18749.8 | F56: 20250 | G56: 18375 | H56: 19312.5 | I56: 19124.8 | J56: 18750 | K56: 18375 | L56: 19687.5 | M56: 17812.5 | N56: 19312.5 | O56: =N56 -> 19312.5
B57: Other Receivables | C57: 178.1 | D57: 174.4 | E57: 187.5 | F57: 202.5 | G57: 183.8 | H57: 193.1 | I57: 191.2 | J57: 187.5 | K57: 183.8 | L57: 196.9 | M57: 178.1 | N57: 193.1 | O57: =N57 -> 193.1
B58: Trade Payables | C58: -12219.3 | D58: -11962.2 | E58: -12862.5 | F58: -13891.5 | G58: -12605.2 | H58: -13248.5 | I58: -13119.7 | J58: -12862.5 | K58: -12605.2 | L58: -13505.7 | M58: -12219.3 | N58: -13248.3 | O58: =N58 -> -13248.3
B59: Other Payables | C59: -356.2 | D59: -348.8 | E59: -375 | F59: -405 | G59: -367.5 | H59: -386.2 | I59: -382.5 | J59: -375 | K59: -367.5 | L59: -393.8 | M59: -356.2 | N59: -386.2 | O59: =N59 -> -386.2
B60: Total working capital | C60: =SUM(C55:C59) -> 27462.3 | D60: =SUM(D55:D59) -> 27256.6 | E60: =SUM(E55:E59) -> 28757.8 | F60: =SUM(F55:F59) -> 31088.8 | G60: =SUM(G55:G59) -> 28628.7 | H60: =SUM(H55:H59) -> 29610.6 | I60: =SUM(I55:I59) -> 29485 | J60: =SUM(J55:J59) -> 29254.5 | ... N60: =SUM(N55:N59) -> 29797.5 | O60: =N60 -> 29797.5
B62: 2025 Actual
C63: January | D63: February | E63: March | F63: April | G63: May | H63: June | I63: July | J63: August | K63: September | L63: October | M63: November | N63: December | O63: Full year
B64: Sales | C64: 11439 | D64: 10950.3 | E64: 12000.4 | F64: 13070.6 | G64: 11619.2 | H64: 12276.2 | I64: 12248.2 | J64: 11977.4 | K64: 11779.1 | L64: 12655.3 | M64: 11249.6 | N64: 12333.7 | O64: =SUM(C64:N64) -> 143599
B65: Gross Margin | C65: 3138 | D65: 2951.8 | E65: 3289.7 | F65: 3505.6 | G65: 3133.5 | H65: 3336.8 | I65: 3286.2 | J65: 3254.9 | K65: 3217.3 | L65: 3430.6 | M65: 3051.7 | N65: 3363.2 | O65: =SUM(C65:N65) -> 38959.3
B66: Op Costs | C66: -2332.3 | D66: -2272.6 | E66: -2462.4 | F66: -2662.1 | G66: -2405.3 | H66: -2536.4 | I66: -2516.1 | J66: -2441.4 | K66: -2408.8 | L66: -2580.1 | M66: -2335.8 | N66: -2519.8 | O66: =SUM(C66:N66) -> -29473.1
B67: PBITA | C67: =C65+C66 -> 805.7 | D67: =D65+D66 -> 679.2 | E67: =E65+E66 -> 827.3 | F67: =F65+F66 -> 843.5 | G67: =G65+G66 -> 728.2 | H67: =H65+H66 -> 800.4 | I67: =I65+I66 -> 770.1 | J67: =J65+J66 -> 813.5 | ... N67: =N65+N66 -> 843.4 | O67: =SUM(C67:N67) -> 9486.2
B68: Net Inventory | C68: 23602.6 | D68: 22384 | E68: 24068.8 | F68: 26337.6 | G68: 23549.9 | H68: 24811.8 | I68: 25484.9 | J68: 24062.8 | K68: 23908.1 | L68: 26061.1 | M68: 23195.6 | N68: 25323.4 | O68: =N68 -> 25323.4
B69: Trade Receivables | C69: 17539.8 | D69: 16790.5 | E69: 18400.6 | F69: 20041.6 | G69: 17816.1 | H69: 18823.5 | I69: 18780.6 | J69: 18365.3 | K69: 18061.3 | L69: 19404.8 | M69: 17249.4 | N69: 18911.7 | O69: =N69 -> 18911.7
B70: Other Receivables | C70: 171.6 | D70: 164.3 | E70: 180 | F70: 196.1 | G70: 174.3 | H70: 184.1 | I70: 183.7 | J70: 179.7 | K70: 176.7 | L70: 189.8 | M70: 168.7 | N70: 185 | O70: =N70 -> 185
B71: Trade Payables | C71: -11344.7 | D71: -10931.3 | E71: -11904.6 | F71: -13072.2 | G71: -11597.1 | H71: -12217.2 | I71: -12248.1 | J71: -11920.8 | K71: -11701.1 | L71: -12607.1 | M71: -11203.8 | N71: -12259.7 | O71: =N71 -> -12259.7
B72: Other Payables | C72: -343.2 | D72: -328.5 | E72: -360 | F72: -392.1 | G72: -348.6 | H72: -368.3 | I72: -367.4 | J72: -359.3 | K72: -353.4 | L72: -379.7 | M72: -337.5 | N72: -370 | O72: =N72 -> -370
B73: Total working capital | C73: =SUM(C68:C72) -> 29626.1 | D73: =SUM(D68:D72) -> 28079 | E73: =SUM(E68:E72) -> 30384.8 | F73: =SUM(F68:F72) -> 33111 | G73: =SUM(G68:G72) -> 29594.6 | H73: =SUM(H68:H72) -> 31233.9 | I73: =SUM(I68:I72) -> 31833.7 | J73: =SUM(J68:J72) -> 30327.7 | ... N73: =SUM(N68:N72) -> 31790.4 | O73: =N73 -> 31790.4

Sheet Beacon-Var
A1: Current ME | B1: P09 | D1: Beacon Hi-Vis
A2: Next ME | B2: P10 | D2: TRAINING DATA ONLY - Zava Safety and all business names and numbers are fictitious. Layout mirrors a typical HFM / Cognos reporting pack.
C4: FCAST10
C5: Through Sep | F5: Rest of Year | I5: Full Year
B6: Favorable / (Unfavorable) | C6: Actual vs. FCAST09 | D6: Actual vs. Bud | E6: Actual vs. PY | F6: FCAST10 vs. FCAST09 | G6: FCAST10 vs. Bud | H6: FCAST10 vs. PY | I6: FCAST10 vs. FCAST09 | J6: FCAST10 vs. Bud | K6: FCAST10 vs. PY
B8: Sales | C8: =Beacon!BU28 -> 150 | D8: =Beacon!BV28 -> 3250.8 | E8: =Beacon!BW28 -> 6179 | F8: =Beacon!BY28 -> 750 | G8: =Beacon!BZ28 -> 2417 | H8: =Beacon!CA28 -> 3639.3 | I8: =Beacon!CC28 -> 900 | J8: =Beacon!CD28 -> 5667.8 | K8: =Beacon!CE28 -> 9818.3
B10: Gross Margin | C10: =Beacon!BU29 -> 60 | D10: =Beacon!BV29 -> 2370.9 | E10: =Beacon!BW29 -> 3866.8 | F10: =Beacon!BY29 -> 290 | G10: =Beacon!BZ29 -> 1301.7 | H10: =Beacon!CA29 -> 1877.3 | I10: =Beacon!CC29 -> 350 | J10: =Beacon!CD29 -> 3672.6 | K10: =Beacon!CE29 -> 5744.1
B12: Op Costs | C12: =Beacon!BU30 -> -76 | D12: =Beacon!BV30 -> -434.8 | E12: =Beacon!BW30 -> -863.9 | F12: =Beacon!BY30 -> -30 | G12: =Beacon!BZ30 -> -233 | H12: =Beacon!CA30 -> -364.9 | I12: =Beacon!CC30 -> -106 | J12: =Beacon!CD30 -> -667.8 | K12: =Beacon!CE30 -> -1228.8
B14: PBITA | C14: =Beacon!BU31 -> -16 | D14: =Beacon!BV31 -> 1936.1 | E14: =Beacon!BW31 -> 3002.9 | F14: =Beacon!BY31 -> 260 | G14: =Beacon!BZ31 -> 1068.7 | H14: =Beacon!CA31 -> 1512.4 | I14: =Beacon!CC31 -> 244 | J14: =Beacon!CD31 -> 3004.8 | K14: =Beacon!CE31 -> 4515.3
B17: Commentary (business controller):

Sheet Beacon-Adj
A1: Index | C1: 21 | D1: 20 | E1: 22 | F1: 22 | G1: 20 | H1: 22 | I1: 22 | J1: 21 | K1: 21 | L1: 22 | M1: 19 | N1: 22 | O1: =SUM(C1:N1) -> 254
B2: Section 1: Adjustments tied to individual events (i.e., new customer, modified sales contract, new/lost customer):
B3: TRAINING DATA ONLY - Zava Safety and all business names and numbers are fictitious. Layout mirrors a typical HFM / Cognos reporting pack.
C4: January | D4: February | E4: March | F4: April | G4: May | H4: June | I4: July | J4: August | K4: September | L4: October | M4: November | N4: December | O4: Total Adj
B5: Sales
B6: DOT highway program orders - surveyor vests | C6: 0 | D6: 0 | E6: 0 | F6: 0 | G6: 0 | H6: 0 | I6: 0 | J6: 0 | K6: 150 | L6: 250 | M6: 300 | N6: 200 | O6: =SUM(C6:N6) -> 900
B7: Insert Adj. 2 | C7: 0 | D7: 0 | E7: 0 | F7: 0 | G7: 0 | H7: 0 | I7: 0 | J7: 0 | K7: 0 | L7: 0 | M7: 0 | N7: 0 | O7: =SUM(C7:N7) -> 0
B8: Insert Adj. 3 | C8: 0 | D8: 0 | E8: 0 | F8: 0 | G8: 0 | H8: 0 | I8: 0 | J8: 0 | K8: 0 | L8: 0 | M8: 0 | N8: 0 | O8: =SUM(C8:N8) -> 0
B9: Insert Adj. 4 | C9: 0 | D9: 0 | E9: 0 | F9: 0 | G9: 0 | H9: 0 | I9: 0 | J9: 0 | K9: 0 | L9: 0 | M9: 0 | N9: 0 | O9: =SUM(C9:N9) -> 0
B10: Insert Adj. 5 | C10: 0 | D10: 0 | E10: 0 | F10: 0 | G10: 0 | H10: 0 | I10: 0 | J10: 0 | K10: 0 | L10: 0 | M10: 0 | N10: 0 | O10: =SUM(C10:N10) -> 0
B11: Insert Adj. 6 | C11: 0 | D11: 0 | E11: 0 | F11: 0 | G11: 0 | H11: 0 | I11: 0 | J11: 0 | K11: 0 | L11: 0 | M11: 0 | N11: 0 | O11: =SUM(C11:N11) -> 0
B12: Insert Adj. 7 | C12: 0 | D12: 0 | E12: 0 | F12: 0 | G12: 0 | H12: 0 | I12: 0 | J12: 0 | K12: 0 | L12: 0 | M12: 0 | N12: 0 | O12: =SUM(C12:N12) -> 0
B13: Insert Adj. 8 | C13: 0 | D13: 0 | E13: 0 | F13: 0 | G13: 0 | H13: 0 | I13: 0 | J13: 0 | K13: 0 | L13: 0 | M13: 0 | N13: 0 | O13: =SUM(C13:N13) -> 0
B14: Total Sales | C14: =SUM(C6:C13) -> 0 | D14: =SUM(D6:D13) -> 0 | E14: =SUM(E6:E13) -> 0 | F14: =SUM(F6:F13) -> 0 | G14: =SUM(G6:G13) -> 0 | H14: =SUM(H6:H13) -> 0 | I14: =SUM(I6:I13) -> 0 | J14: =SUM(J6:J13) -> 0 | ... O14: =SUM(O6:O13) -> 900
B16: Gross Margin (%)
B17: =B6 -> DOT highway program orders - surveyor vests | C17: =IFERROR(C28/C6,0) -> 0 | D17: =IFERROR(D28/D6,0) -> 0 | E17: =IFERROR(E28/E6,0) -> 0 | F17: =IFERROR(F28/F6,0) -> 0 | G17: =IFERROR(G28/G6,0) -> 0 | H17: =IFERROR(H28/H6,0) -> 0 | I17: =IFERROR(I28/I6,0) -> 0 | J17: =IFERROR(J28/J6,0) -> 0 | ... O17: =IFERROR(O28/O6,0) -> 0.38888889
B18: =B7 -> Insert Adj. 2 | C18: =IFERROR(C29/C7,0) -> 0 | D18: =IFERROR(D29/D7,0) -> 0 | E18: =IFERROR(E29/E7,0) -> 0 | F18: =IFERROR(F29/F7,0) -> 0 | G18: =IFERROR(G29/G7,0) -> 0 | H18: =IFERROR(H29/H7,0) -> 0 | I18: =IFERROR(I29/I7,0) -> 0 | J18: =IFERROR(J29/J7,0) -> 0 | ... O18: =IFERROR(O29/O7,0) -> 0
B19: =B8 -> Insert Adj. 3 | C19: =IFERROR(C30/C8,0) -> 0 | D19: =IFERROR(D30/D8,0) -> 0 | E19: =IFERROR(E30/E8,0) -> 0 | F19: =IFERROR(F30/F8,0) -> 0 | G19: =IFERROR(G30/G8,0) -> 0 | H19: =IFERROR(H30/H8,0) -> 0 | I19: =IFERROR(I30/I8,0) -> 0 | J19: =IFERROR(J30/J8,0) -> 0 | ... O19: =IFERROR(O30/O8,0) -> 0
B20: =B9 -> Insert Adj. 4 | C20: =IFERROR(C31/C9,0) -> 0 | D20: =IFERROR(D31/D9,0) -> 0 | E20: =IFERROR(E31/E9,0) -> 0 | F20: =IFERROR(F31/F9,0) -> 0 | G20: =IFERROR(G31/G9,0) -> 0 | H20: =IFERROR(H31/H9,0) -> 0 | I20: =IFERROR(I31/I9,0) -> 0 | J20: =IFERROR(J31/J9,0) -> 0 | ... O20: =IFERROR(O31/O9,0) -> 0
B21: =B10 -> Insert Adj. 5 | C21: =IFERROR(C32/C10,0) -> 0 | D21: =IFERROR(D32/D10,0) -> 0 | E21: =IFERROR(E32/E10,0) -> 0 | F21: =IFERROR(F32/F10,0) -> 0 | G21: =IFERROR(G32/G10,0) -> 0 | H21: =IFERROR(H32/H10,0) -> 0 | I21: =IFERROR(I32/I10,0) -> 0 | J21: =IFERROR(J32/J10,0) -> 0 | ... O21: =IFERROR(O32/O10,0) -> 0
B22: =B11 -> Insert Adj. 6 | C22: =IFERROR(C33/C11,0) -> 0 | D22: =IFERROR(D33/D11,0) -> 0 | E22: =IFERROR(E33/E11,0) -> 0 | F22: =IFERROR(F33/F11,0) -> 0 | G22: =IFERROR(G33/G11,0) -> 0 | H22: =IFERROR(H33/H11,0) -> 0 | I22: =IFERROR(I33/I11,0) -> 0 | J22: =IFERROR(J33/J11,0) -> 0 | ... O22: =IFERROR(O33/O11,0) -> 0
B23: =B12 -> Insert Adj. 7 | C23: =IFERROR(C34/C12,0) -> 0 | D23: =IFERROR(D34/D12,0) -> 0 | E23: =IFERROR(E34/E12,0) -> 0 | F23: =IFERROR(F34/F12,0) -> 0 | G23: =IFERROR(G34/G12,0) -> 0 | H23: =IFERROR(H34/H12,0) -> 0 | I23: =IFERROR(I34/I12,0) -> 0 | J23: =IFERROR(J34/J12,0) -> 0 | ... O23: =IFERROR(O34/O12,0) -> 0
B24: =B13 -> Insert Adj. 8 | C24: =IFERROR(C35/C13,0) -> 0 | D24: =IFERROR(D35/D13,0) -> 0 | E24: =IFERROR(E35/E13,0) -> 0 | F24: =IFERROR(F35/F13,0) -> 0 | G24: =IFERROR(G35/G13,0) -> 0 | H24: =IFERROR(H35/H13,0) -> 0 | I24: =IFERROR(I35/I13,0) -> 0 | J24: =IFERROR(J35/J13,0) -> 0 | ... O24: =IFERROR(O35/O13,0) -> 0
B25: Total Gross Margin (%) | C25: =IFERROR(C36/C14,0) -> 0 | D25: =IFERROR(D36/D14,0) -> 0 | E25: =IFERROR(E36/E14,0) -> 0 | F25: =IFERROR(F36/F14,0) -> 0 | G25: =IFERROR(G36/G14,0) -> 0 | H25: =IFERROR(H36/H14,0) -> 0 | I25: =IFERROR(I36/I14,0) -> 0 | J25: =IFERROR(J36/J14,0) -> 0 | ... O25: =IFERROR(O36/O14,0) -> 0.38888889
B27: Gross Margin ($)
B28: DOT highway program orders - surveyor vests | C28: 0 | D28: 0 | E28: 0 | F28: 0 | G28: 0 | H28: 0 | I28: 0 | J28: 0 | K28: 60 | L28: 95 | M28: 115 | N28: 80 | O28: =SUM(C28:N28) -> 350
B29: Insert Adj. 2 | C29: 0 | D29: 0 | E29: 0 | F29: 0 | G29: 0 | H29: 0 | I29: 0 | J29: 0 | K29: 0 | L29: 0 | M29: 0 | N29: 0 | O29: =SUM(C29:N29) -> 0
B30: Insert Adj. 3 | C30: 0 | D30: 0 | E30: 0 | F30: 0 | G30: 0 | H30: 0 | I30: 0 | J30: 0 | K30: 0 | L30: 0 | M30: 0 | N30: 0 | O30: =SUM(C30:N30) -> 0
B31: Insert Adj. 4 | C31: 0 | D31: 0 | E31: 0 | F31: 0 | G31: 0 | H31: 0 | I31: 0 | J31: 0 | K31: 0 | L31: 0 | M31: 0 | N31: 0 | O31: =SUM(C31:N31) -> 0
B32: Insert Adj. 5 | C32: 0 | D32: 0 | E32: 0 | F32: 0 | G32: 0 | H32: 0 | I32: 0 | J32: 0 | K32: 0 | L32: 0 | M32: 0 | N32: 0 | O32: =SUM(C32:N32) -> 0
B33: Insert Adj. 6 | C33: 0 | D33: 0 | E33: 0 | F33: 0 | G33: 0 | H33: 0 | I33: 0 | J33: 0 | K33: 0 | L33: 0 | M33: 0 | N33: 0 | O33: =SUM(C33:N33) -> 0
B34: Insert Adj. 7 | C34: 0 | D34: 0 | E34: 0 | F34: 0 | G34: 0 | H34: 0 | I34: 0 | J34: 0 | K34: 0 | L34: 0 | M34: 0 | N34: 0 | O34: =SUM(C34:N34) -> 0
B35: Insert Adj. 8 | C35: 0 | D35: 0 | E35: 0 | F35: 0 | G35: 0 | H35: 0 | I35: 0 | J35: 0 | K35: 0 | L35: 0 | M35: 0 | N35: 0 | O35: =SUM(C35:N35) -> 0
B36: Total Gross Margin ($) | C36: =SUM(C28:C35) -> 0 | D36: =SUM(D28:D35) -> 0 | E36: =SUM(E28:E35) -> 0 | F36: =SUM(F28:F35) -> 0 | G36: =SUM(G28:G35) -> 0 | H36: =SUM(H28:H35) -> 0 | I36: =SUM(I28:I35) -> 0 | J36: =SUM(J28:J35) -> 0 | ... O36: =SUM(O28:O35) -> 350
B38: Op Costs (%)
B39: =B6 -> DOT highway program orders - surveyor vests | C39: =IFERROR(C50/C6,0) -> 0 | D39: =IFERROR(D50/D6,0) -> 0 | E39: =IFERROR(E50/E6,0) -> 0 | F39: =IFERROR(F50/F6,0) -> 0 | G39: =IFERROR(G50/G6,0) -> 0 | H39: =IFERROR(H50/H6,0) -> 0 | I39: =IFERROR(I50/I6,0) -> 0 | J39: =IFERROR(J50/J6,0) -> 0 | ... O39: =IFERROR(O50/O6,0) -> 0.04
B40: =B7 -> Insert Adj. 2 | C40: =IFERROR(C51/C7,0) -> 0 | D40: =IFERROR(D51/D7,0) -> 0 | E40: =IFERROR(E51/E7,0) -> 0 | F40: =IFERROR(F51/F7,0) -> 0 | G40: =IFERROR(G51/G7,0) -> 0 | H40: =IFERROR(H51/H7,0) -> 0 | I40: =IFERROR(I51/I7,0) -> 0 | J40: =IFERROR(J51/J7,0) -> 0 | ... O40: =IFERROR(O51/O7,0) -> 0
B41: =B8 -> Insert Adj. 3 | C41: =IFERROR(C52/C8,0) -> 0 | D41: =IFERROR(D52/D8,0) -> 0 | E41: =IFERROR(E52/E8,0) -> 0 | F41: =IFERROR(F52/F8,0) -> 0 | G41: =IFERROR(G52/G8,0) -> 0 | H41: =IFERROR(H52/H8,0) -> 0 | I41: =IFERROR(I52/I8,0) -> 0 | J41: =IFERROR(J52/J8,0) -> 0 | ... O41: =IFERROR(O52/O8,0) -> 0
B42: =B9 -> Insert Adj. 4 | C42: =IFERROR(C53/C9,0) -> 0 | D42: =IFERROR(D53/D9,0) -> 0 | E42: =IFERROR(E53/E9,0) -> 0 | F42: =IFERROR(F53/F9,0) -> 0 | G42: =IFERROR(G53/G9,0) -> 0 | H42: =IFERROR(H53/H9,0) -> 0 | I42: =IFERROR(I53/I9,0) -> 0 | J42: =IFERROR(J53/J9,0) -> 0 | ... O42: =IFERROR(O53/O9,0) -> 0
B43: =B10 -> Insert Adj. 5 | C43: =IFERROR(C54/C10,0) -> 0 | D43: =IFERROR(D54/D10,0) -> 0 | E43: =IFERROR(E54/E10,0) -> 0 | F43: =IFERROR(F54/F10,0) -> 0 | G43: =IFERROR(G54/G10,0) -> 0 | H43: =IFERROR(H54/H10,0) -> 0 | I43: =IFERROR(I54/I10,0) -> 0 | J43: =IFERROR(J54/J10,0) -> 0 | ... O43: =IFERROR(O54/O10,0) -> 0
B44: =B11 -> Insert Adj. 6 | C44: =IFERROR(C55/C11,0) -> 0 | D44: =IFERROR(D55/D11,0) -> 0 | E44: =IFERROR(E55/E11,0) -> 0 | F44: =IFERROR(F55/F11,0) -> 0 | G44: =IFERROR(G55/G11,0) -> 0 | H44: =IFERROR(H55/H11,0) -> 0 | I44: =IFERROR(I55/I11,0) -> 0 | J44: =IFERROR(J55/J11,0) -> 0 | ... O44: =IFERROR(O55/O11,0) -> 0
B45: =B12 -> Insert Adj. 7 | C45: =IFERROR(C56/C12,0) -> 0 | D45: =IFERROR(D56/D12,0) -> 0 | E45: =IFERROR(E56/E12,0) -> 0 | F45: =IFERROR(F56/F12,0) -> 0 | G45: =IFERROR(G56/G12,0) -> 0 | H45: =IFERROR(H56/H12,0) -> 0 | I45: =IFERROR(I56/I12,0) -> 0 | J45: =IFERROR(J56/J12,0) -> 0 | ... O45: =IFERROR(O56/O12,0) -> 0
B46: =B13 -> Insert Adj. 8 | C46: =IFERROR(C57/C13,0) -> 0 | D46: =IFERROR(D57/D13,0) -> 0 | E46: =IFERROR(E57/E13,0) -> 0 | F46: =IFERROR(F57/F13,0) -> 0 | G46: =IFERROR(G57/G13,0) -> 0 | H46: =IFERROR(H57/H13,0) -> 0 | I46: =IFERROR(I57/I13,0) -> 0 | J46: =IFERROR(J57/J13,0) -> 0 | ... O46: =IFERROR(O57/O13,0) -> 0
B47: Total Op Costs (%) | C47: =IFERROR(C58/C14,0) -> 0 | D47: =IFERROR(D58/D14,0) -> 0 | E47: =IFERROR(E58/E14,0) -> 0 | F47: =IFERROR(F58/F14,0) -> 0 | G47: =IFERROR(G58/G14,0) -> 0 | H47: =IFERROR(H58/H14,0) -> 0 | I47: =IFERROR(I58/I14,0) -> 0 | J47: =IFERROR(J58/J14,0) -> 0 | ... O47: =IFERROR(O58/O14,0) -> 0.11777778
B49: Op Costs ($)
B50: Commission on DOT program | C50: 0 | D50: 0 | E50: 0 | F50: 0 | G50: 0 | H50: 0 | I50: 0 | J50: 0 | K50: 6 | L50: 10 | M50: 12 | N50: 8 | O50: =SUM(C50:N50) -> 36
B51: Bonus accrual true-up | C51: 0 | D51: 0 | E51: 0 | F51: 0 | G51: 0 | H51: 0 | I51: 0 | J51: 0 | K51: 70 | L51: 0 | M51: 0 | N51: 0 | O51: =SUM(C51:N51) -> 70
B52: Insert Adj. 3 | C52: 0 | D52: 0 | E52: 0 | F52: 0 | G52: 0 | H52: 0 | I52: 0 | J52: 0 | K52: 0 | L52: 0 | M52: 0 | N52: 0 | O52: =SUM(C52:N52) -> 0
B53: Insert Adj. 4 | C53: 0 | D53: 0 | E53: 0 | F53: 0 | G53: 0 | H53: 0 | I53: 0 | J53: 0 | K53: 0 | L53: 0 | M53: 0 | N53: 0 | O53: =SUM(C53:N53) -> 0
B54: Insert Adj. 5 | C54: 0 | D54: 0 | E54: 0 | F54: 0 | G54: 0 | H54: 0 | I54: 0 | J54: 0 | K54: 0 | L54: 0 | M54: 0 | N54: 0 | O54: =SUM(C54:N54) -> 0
B55: Insert Adj. 6 | C55: 0 | D55: 0 | E55: 0 | F55: 0 | G55: 0 | H55: 0 | I55: 0 | J55: 0 | K55: 0 | L55: 0 | M55: 0 | N55: 0 | O55: =SUM(C55:N55) -> 0
B56: Insert Adj. 7 | C56: 0 | D56: 0 | E56: 0 | F56: 0 | G56: 0 | H56: 0 | I56: 0 | J56: 0 | K56: 0 | L56: 0 | M56: 0 | N56: 0 | O56: =SUM(C56:N56) -> 0
B57: Insert Adj. 8 | C57: 0 | D57: 0 | E57: 0 | F57: 0 | G57: 0 | H57: 0 | I57: 0 | J57: 0 | K57: 0 | L57: 0 | M57: 0 | N57: 0 | O57: =SUM(C57:N57) -> 0
B58: Total Op Costs ($) | C58: =SUM(C50:C57) -> 0 | D58: =SUM(D50:D57) -> 0 | E58: =SUM(E50:E57) -> 0 | F58: =SUM(F50:F57) -> 0 | G58: =SUM(G50:G57) -> 0 | H58: =SUM(H50:H57) -> 0 | I58: =SUM(I50:I57) -> 0 | J58: =SUM(J50:J57) -> 0 | ... O58: =SUM(O50:O57) -> 106
B60: PBITA
B61: =B6 -> DOT highway program orders - surveyor vests | C61: =C28-C50 -> 0 | D61: =D28-D50 -> 0 | E61: =E28-E50 -> 0 | F61: =F28-F50 -> 0 | G61: =G28-G50 -> 0 | H61: =H28-H50 -> 0 | I61: =I28-I50 -> 0 | J61: =J28-J50 -> 0 | ... N61: =N28-N50 -> 72 | O61: =SUM(C61:N61) -> 314
B62: =B7 -> Insert Adj. 2 | C62: =C29-C51 -> 0 | D62: =D29-D51 -> 0 | E62: =E29-E51 -> 0 | F62: =F29-F51 -> 0 | G62: =G29-G51 -> 0 | H62: =H29-H51 -> 0 | I62: =I29-I51 -> 0 | J62: =J29-J51 -> 0 | ... N62: =N29-N51 -> 0 | O62: =SUM(C62:N62) -> -70
B63: =B8 -> Insert Adj. 3 | C63: =C30-C52 -> 0 | D63: =D30-D52 -> 0 | E63: =E30-E52 -> 0 | F63: =F30-F52 -> 0 | G63: =G30-G52 -> 0 | H63: =H30-H52 -> 0 | I63: =I30-I52 -> 0 | J63: =J30-J52 -> 0 | ... N63: =N30-N52 -> 0 | O63: =SUM(C63:N63) -> 0
B64: =B9 -> Insert Adj. 4 | C64: =C31-C53 -> 0 | D64: =D31-D53 -> 0 | E64: =E31-E53 -> 0 | F64: =F31-F53 -> 0 | G64: =G31-G53 -> 0 | H64: =H31-H53 -> 0 | I64: =I31-I53 -> 0 | J64: =J31-J53 -> 0 | ... N64: =N31-N53 -> 0 | O64: =SUM(C64:N64) -> 0
B65: =B10 -> Insert Adj. 5 | C65: =C32-C54 -> 0 | D65: =D32-D54 -> 0 | E65: =E32-E54 -> 0 | F65: =F32-F54 -> 0 | G65: =G32-G54 -> 0 | H65: =H32-H54 -> 0 | I65: =I32-I54 -> 0 | J65: =J32-J54 -> 0 | ... N65: =N32-N54 -> 0 | O65: =SUM(C65:N65) -> 0
B66: =B11 -> Insert Adj. 6 | C66: =C33-C55 -> 0 | D66: =D33-D55 -> 0 | E66: =E33-E55 -> 0 | F66: =F33-F55 -> 0 | G66: =G33-G55 -> 0 | H66: =H33-H55 -> 0 | I66: =I33-I55 -> 0 | J66: =J33-J55 -> 0 | ... N66: =N33-N55 -> 0 | O66: =SUM(C66:N66) -> 0
B67: =B12 -> Insert Adj. 7 | C67: =C34-C56 -> 0 | D67: =D34-D56 -> 0 | E67: =E34-E56 -> 0 | F67: =F34-F56 -> 0 | G67: =G34-G56 -> 0 | H67: =H34-H56 -> 0 | I67: =I34-I56 -> 0 | J67: =J34-J56 -> 0 | ... N67: =N34-N56 -> 0 | O67: =SUM(C67:N67) -> 0
B68: =B13 -> Insert Adj. 8 | C68: =C35-C57 -> 0 | D68: =D35-D57 -> 0 | E68: =E35-E57 -> 0 | F68: =F35-F57 -> 0 | G68: =G35-G57 -> 0 | H68: =H35-H57 -> 0 | I68: =I35-I57 -> 0 | J68: =J35-J57 -> 0 | ... N68: =N35-N57 -> 0 | O68: =SUM(C68:N68) -> 0
B69: Total PBITA | C69: =SUM(C61:C68) -> 0 | D69: =SUM(D61:D68) -> 0 | E69: =SUM(E61:E68) -> 0 | F69: =SUM(F61:F68) -> 0 | G69: =SUM(G61:G68) -> 0 | H69: =SUM(H61:H68) -> 0 | I69: =SUM(I61:I68) -> 0 | J69: =SUM(J61:J68) -> 0 | ... O69: =SUM(O61:O68) -> 244
B71: Section 2: General adjustments in Gross Margin or Opex % of Sales that are not tied to individual events (i.e., employee turnover):
C73: January | D73: February | E73: March | F73: April | G73: May | H73: June | I73: July | J73: August | K73: September | L73: October | M73: November | N73: December | O73: Total Adj
B74: Gross Margin
B75: Gross Margin - Previous FCAST | C75: =Beacon!C35 -> 0.40707473 | D75: =Beacon!D35 -> 0.40452114 | E75: =Beacon!E35 -> 0.40263232 | F75: =Beacon!F35 -> 0.40540621 | G75: =Beacon!G35 -> 0.40782724 | H75: =Beacon!H35 -> 0.40601749 | I75: =Beacon!I35 -> 0.40736037 | J75: =Beacon!J35 -> 0.40264448 | ... N75: =Beacon!N35 -> 0.40299068 | O75: N/A
B76: New Adjustments (%) | C76: None | D76: None | E76: None | F76: None | G76: None | H76: None | I76: None | J76: None | K76: None | L76: None | M76: None | N76: None
B77: New Adjustments ($) | C77: =IF(C76="None",0,(((Beacon!C28*(C75+C76))-Beacon!C29))) -> 0 | D77: =IF(D76="None",0,(((Beacon!D28*(D75+D76))-Beacon!D29))) -> 0 | E77: =IF(E76="None",0,(((Beacon!E28*(E75+E76))-Beacon!E29))) -> 0 | F77: =IF(F76="None",0,(((Beacon!F28*(F75+F76))-Beacon!F29))) -> 0 | G77: =IF(G76="None",0,(((Beacon!G28*(G75+G76))-Beacon!G29))) -> 0 | H77: =IF(H76="None",0,(((Beacon!H28*(H75+H76))-Beacon!H29))) -> 0 | I77: =IF(I76="None",0,(((Beacon!I28*(I75+I76))-Beacon!I29))) -> 0 | J77: =IF(J76="None",0,(((Beacon!J28*(J75+J76))-Beacon!J29))) -> 0 | ... N77: =IF(N76="None",0,(((Beacon!N28*(N75+N76))-Beacon!N29))) -> 0 | O77: =SUM(C77:N77) -> 0
B78: Gross Margin - Current FCAST | C78: =SUM(C75:C76) -> 0.40707473 | D78: =SUM(D75:D76) -> 0.40452114 | E78: =SUM(E75:E76) -> 0.40263232 | F78: =SUM(F75:F76) -> 0.40540621 | G78: =SUM(G75:G76) -> 0.40782724 | H78: =SUM(H75:H76) -> 0.40601749 | I78: =SUM(I75:I76) -> 0.40736037 | J78: =SUM(J75:J76) -> 0.40264448 | ... N78: =SUM(N75:N76) -> 0.40299068 | O78: N/A
B81: Op Costs
B82: Op Costs - Previous FCAST | C82: =Beacon!C36 -> -0.22336119 | D82: =Beacon!D36 -> -0.22234268 | E82: =Beacon!E36 -> -0.22490145 | F82: =Beacon!F36 -> -0.21948153 | G82: =Beacon!G36 -> -0.22134701 | H82: =Beacon!H36 -> -0.2200407 | I82: =Beacon!I36 -> -0.22339885 | J82: =Beacon!J36 -> -0.22102809 | ... N82: =Beacon!N36 -> -0.21655382 | O82: N/A
B83: New Adjustments (%) | C83: None | D83: None | E83: None | F83: None | G83: None | H83: None | I83: None | J83: None | K83: None | L83: None | M83: None | N83: None
B84: New Adjustments ($) | C84: =-IF(C83="None",0,(((Beacon!C28*-(C82+C83))-Beacon!C30))) -> 0 | D84: =-IF(D83="None",0,(((Beacon!D28*-(D82+D83))-Beacon!D30))) -> 0 | E84: =-IF(E83="None",0,(((Beacon!E28*-(E82+E83))-Beacon!E30))) -> 0 | F84: =-IF(F83="None",0,(((Beacon!F28*-(F82+F83))-Beacon!F30))) -> 0 | G84: =-IF(G83="None",0,(((Beacon!G28*-(G82+G83))-Beacon!G30))) -> 0 | H84: =-IF(H83="None",0,(((Beacon!H28*-(H82+H83))-Beacon!H30))) -> 0 | I84: =-IF(I83="None",0,(((Beacon!I28*-(I82+I83))-Beacon!I30))) -> 0 | J84: =-IF(J83="None",0,(((Beacon!J28*-(J82+J83))-Beacon!J30))) -> 0 | ... N84: =-IF(N83="None",0,(((Beacon!N28*-(N82+N83))-Beacon!N30))) -> 0 | O84: =SUM(C84:N84) -> 0
B85: Op Costs - Current FCAST | C85: =SUM(C82:C83) -> -0.22336119 | D85: =SUM(D82:D83) -> -0.22234268 | E85: =SUM(E82:E83) -> -0.22490145 | F85: =SUM(F82:F83) -> -0.21948153 | G85: =SUM(G82:G83) -> -0.22134701 | H85: =SUM(H82:H83) -> -0.2200407 | I85: =SUM(I82:I83) -> -0.22339885 | J85: =SUM(J82:J83) -> -0.22102809 | ... N85: =SUM(N82:N83) -> -0.21655382 | O85: N/A
B87: Section 3: Working Capital Adjustments
C89: January | D89: February | E89: March | F89: April | G89: May | H89: June | I89: July | J89: August | K89: September | L89: October | M89: November | N89: December | O89: Total Adj
A90: 2090 | B90: Net Inventory | C90: 0 | D90: 0 | E90: 0 | F90: 0 | G90: 0 | H90: 0 | I90: 0 | J90: 0 | K90: 0 | L90: 0 | M90: 0 | N90: 0
A91: 2135 | B91: Trade Receivables | C91: 0 | D91: 0 | E91: 0 | F91: 0 | G91: 0 | H91: 0 | I91: 0 | J91: 0 | K91: 0 | L91: 0 | M91: 0 | N91: 0
A92: 2175 | B92: Other Receivables | C92: 0 | D92: 0 | E92: 0 | F92: 0 | G92: 0 | H92: 0 | I92: 0 | J92: 0 | K92: 0 | L92: 0 | M92: 0 | N92: 0
A93: 2140 | B93: Trade Payables | C93: 0 | D93: 0 | E93: 0 | F93: 0 | G93: 0 | H93: 0 | I93: 0 | J93: 0 | K93: 0 | L93: 0 | M93: 0 | N93: 0
A94: 2180 | B94: Other Payables | C94: 0 | D94: 0 | E94: 0 | F94: 0 | G94: 0 | H94: 0 | I94: 0 | J94: 0 | K94: 0 | L94: 0 | M94: 0 | N94: 0
A95: 2185 | B95: Total Working Capital | C95: =SUM(C90:C94) -> 0 | D95: =SUM(D90:D94) -> 0 | E95: =SUM(E90:E94) -> 0 | F95: =SUM(F90:F94) -> 0 | G95: =SUM(G90:G94) -> 0 | H95: =SUM(H90:H94) -> 0 | I95: =SUM(I90:I94) -> 0 | J95: =SUM(J90:J94) -> 0 | ... N95: =SUM(N90:N94) -> 0
B97: NOTE: A positive number within the working capital adjustments section indicates a DR (i.e., increase to asset / decrease to liability). A negative number indicates a CR.

Sheet Beacon
C1: Actual | D1: Actual | E1: Actual | F1: Actual | G1: Actual | H1: Actual | I1: Actual | J1: Actual | K1: FCAST09 | L1: FCAST09 | M1: FCAST09 | N1: FCAST09
B2: Scenario# | C2: Actual | D2: Actual | E2: Actual | F2: Actual | G2: Actual | H2: Actual | I2: Actual | J2: Actual | K2: Actual | L2: Actual | M2: Actual | N2: Actual
B5: Year# | C5: 2026 | D5: 2026 | E5: 2026 | F5: 2026 | G5: 2026 | H5: 2026 | I5: 2026 | J5: 2026 | K5: 2026 | L5: 2026 | M5: 2026 | N5: 2026
B8: Period# | C8: P01 | D8: P02 | E8: P03 | F8: P04 | G8: P05 | H8: P06 | I8: P07 | J8: P08 | K8: P09 | L8: P10 | M8: P11 | N8: P12
B9: Account#
B10: ICP#
B11: Custom1# | C11: TotalC1 | D11: TotalC1 | E11: TotalC1 | F11: TotalC1 | G11: TotalC1 | H11: TotalC1 | I11: TotalC1 | J11: TotalC1 | K11: TotalC1 | L11: TotalC1 | M11: TotalC1 | N11: TotalC1
B12: Custom2# | C12: TotalC2 | D12: TotalC2 | E12: TotalC2 | F12: TotalC2 | G12: TotalC2 | H12: TotalC2 | I12: TotalC2 | J12: TotalC2 | K12: TotalC2 | L12: TotalC2 | M12: TotalC2 | N12: TotalC2
B13: Custom3#
B14: Custom4#
B18: View# | C18: Periodic | D18: Periodic | E18: Periodic | F18: Periodic | G18: Periodic | H18: Periodic | I18: Periodic | J18: Periodic | K18: Periodic | L18: Periodic | M18: Periodic | N18: Periodic
B19: Value# | C19: USD Total | D19: USD Total | E19: USD Total | F19: USD Total | G19: USD Total | H19: USD Total | I19: USD Total | J19: USD Total | K19: USD Total | L19: USD Total | M19: USD Total | N19: USD Total
B21: TRAINING DATA ONLY - Zava Safety and all business names and numbers are fictitious. Layout mirrors a typical HFM / Cognos reporting pack.
B22: BEACON_DISP
B23: Beacon Hi-Vis | BU23: FCAST10 - Variance ($) - Favorable / (Unfavorable)
C24: FCAST09 as Reported | Q24: FCAST09 at New Fx Rates | AE24: Fx Changes | AS24: Operational Adjustments | BG24: FCAST10 | BU24: Through Sep | BY24: Rest of Year | CC24: Full Year
C25: Actual | D25: Actual | E25: Actual | F25: Actual | G25: Actual | H25: Actual | I25: Actual | J25: Actual | K25: FCAST09 | L25: FCAST09 | M25: FCAST09 | N25: FCAST09 | O25: Forecast | Q25: Actual | R25: Actual | S25: Actual | T25: Actual | U25: Actual | V25: Actual | W25: Actual | X25: Actual | Y25: FCAST09 | Z25: FCAST09 | AA25: FCAST09 | AB25: FCAST09 | AC25: Forecast | BG25: Actual | BH25: Actual | BI25: Actual | BJ25: Actual | BK25: Actual | BL25: Actual | BM25: Actual | BN25: Actual | BO25: Actual | BP25: FCAST10 | BQ25: FCAST10 | BR25: FCAST10 | BS25: Forecast
B26: Description: | C26: January | D26: February | E26: March | F26: April | G26: May | H26: June | I26: July | J26: August | K26: September | L26: October | M26: November | N26: December | O26: Full year | Q26: January | R26: February | S26: March | T26: April | U26: May | V26: June | W26: July | X26: August | Y26: September | Z26: October | AA26: November | AB26: December | AC26: Full year | AE26: January | AF26: February | AG26: March | AH26: April | AI26: May | AJ26: June | AK26: July | AL26: August | AM26: September | AN26: October | AO26: November | AP26: December | AQ26: Full year | AS26: January | AT26: February | AU26: March | AV26: April | AW26: May | AX26: June | AY26: July | AZ26: August | BA26: September | BB26: October | BC26: November | BD26: December | BE26: Full year | BG26: January | BH26: February | BI26: March | BJ26: April | BK26: May | BL26: June | BM26: July | BN26: August | BO26: September | BP26: October | BQ26: November | BR26: December | BS26: Full year | BU26: Actual vs. FCAST09 | BV26: Actual vs. Bud | BW26: Actual vs. PY | BY26: FCAST10 vs. FCAST09 | BZ26: FCAST10 vs. Bud | CA26: FCAST10 vs. PY | CC26: FCAST10 vs. FCAST09 | CD26: FCAST10 vs. Bud | CE26: FCAST10 vs. PY
B28: Sales | C28: 5755.7 | D28: 5626.9 | E28: 6063.1 | F28: 6681.2 | G28: 6043 | H28: 6437.9 | I28: 6298.6 | J28: 6262.1 | K28: 6257.1 | L28: 6639.3 | M28: 6041.9 | N28: 6660.7 | O28: =SUM(C28:N28) -> 74767.5 | Q28: 5755.7 | R28: 5626.9 | S28: 6063.1 | T28: 6681.2 | U28: 6043 | V28: 6437.9 | W28: 6298.6 | X28: 6262.1 | Y28: 6257.1 | Z28: 6639.3 | AA28: 6041.9 | AB28: 6660.7 | AC28: =SUM(Q28:AB28) -> 74767.5 | AE28: =Q28-C28 -> 0 | AF28: =R28-D28 -> 0 | AG28: =S28-E28 -> 0 | AH28: =T28-F28 -> 0 | AI28: =U28-G28 -> 0 | AJ28: =V28-H28 -> 0 | AK28: =W28-I28 -> 0 | AL28: =X28-J28 -> 0 | ... AP28: =AB28-N28 -> 0 | AQ28: =SUM(AE28:AP28) -> 0 | AS28: ='Beacon-Adj'!C14 -> 0 | AT28: ='Beacon-Adj'!D14 -> 0 | AU28: ='Beacon-Adj'!E14 -> 0 | AV28: ='Beacon-Adj'!F14 -> 0 | AW28: ='Beacon-Adj'!G14 -> 0 | AX28: ='Beacon-Adj'!H14 -> 0 | AY28: ='Beacon-Adj'!I14 -> 0 | AZ28: ='Beacon-Adj'!J14 -> 0 | ... BD28: ='Beacon-Adj'!N14 -> 200 | BE28: =SUM(AS28:BD28) -> 900 | BG28: =C28+AE28+AS28 -> 5755.7 | BH28: =D28+AF28+AT28 -> 5626.9 | BI28: =E28+AG28+AU28 -> 6063.1 | BJ28: =F28+AH28+AV28 -> 6681.2 | BK28: =G28+AI28+AW28 -> 6043 | BL28: =H28+AJ28+AX28 -> 6437.9 | BM28: =I28+AK28+AY28 -> 6298.6 | BN28: =J28+AL28+AZ28 -> 6262.1 | ... BR28: =N28+AP28+BD28 -> 6860.7 | BS28: =SUM(BG28:BR28) -> 75667.5 | BU28: =SUM(BG28:BO28)-SUM(C28:K28) -> 150 | BV28: =SUM(BG28:BO28)-SUM(C51:K51) -> 3250.8 | BW28: =SUM(BG28:BO28)-SUM(C64:K64) -> 6179 | BY28: =SUM(BP28:BR28)-SUM(L28:N28) -> 750 | BZ28: =SUM(BP28:BR28)-SUM(L51:N51) -> 2417 | CA28: =SUM(BP28:BR28)-SUM(L64:N64) -> 3639.3 | CC28: =BS28-O28 -> 900 | CD28: =BS28-O51 -> 5667.8 | CE28: =BS28-O64 -> 9818.3
B29: Gross Margin | C29: 2343 | D29: 2276.2 | E29: 2441.2 | F29: 2708.6 | G29: 2464.5 | H29: 2613.9 | I29: 2565.8 | J29: 2521.4 | K29: 2521.4 | L29: 2695.6 | M29: 2436.7 | N29: 2684.2 | O29: =SUM(C29:N29) -> 30272.5 | Q29: 2343 | R29: 2276.2 | S29: 2441.2 | T29: 2708.6 | U29: 2464.5 | V29: 2613.9 | W29: 2565.8 | X29: 2521.4 | Y29: 2521.4 | Z29: 2695.6 | AA29: 2436.7 | AB29: 2684.2 | AC29: =SUM(Q29:AB29) -> 30272.5 | AE29: =Q29-C29 -> 0 | AF29: =R29-D29 -> 0 | AG29: =S29-E29 -> 0 | AH29: =T29-F29 -> 0 | AI29: =U29-G29 -> 0 | AJ29: =V29-H29 -> 0 | AK29: =W29-I29 -> 0 | AL29: =X29-J29 -> 0 | ... AP29: =AB29-N29 -> 0 | AQ29: =SUM(AE29:AP29) -> 0 | AS29: ='Beacon-Adj'!C36+'Beacon-Adj'!C77 -> 0 | AT29: ='Beacon-Adj'!D36+'Beacon-Adj'!D77 -> 0 | AU29: ='Beacon-Adj'!E36+'Beacon-Adj'!E77 -> 0 | AV29: ='Beacon-Adj'!F36+'Beacon-Adj'!F77 -> 0 | AW29: ='Beacon-Adj'!G36+'Beacon-Adj'!G77 -> 0 | AX29: ='Beacon-Adj'!H36+'Beacon-Adj'!H77 -> 0 | AY29: ='Beacon-Adj'!I36+'Beacon-Adj'!I77 -> 0 | AZ29: ='Beacon-Adj'!J36+'Beacon-Adj'!J77 -> 0 | ... BD29: ='Beacon-Adj'!N36+'Beacon-Adj'!N77 -> 80 | BE29: =SUM(AS29:BD29) -> 350 | BG29: =C29+AE29+AS29 -> 2343 | BH29: =D29+AF29+AT29 -> 2276.2 | BI29: =E29+AG29+AU29 -> 2441.2 | BJ29: =F29+AH29+AV29 -> 2708.6 | BK29: =G29+AI29+AW29 -> 2464.5 | BL29: =H29+AJ29+AX29 -> 2613.9 | BM29: =I29+AK29+AY29 -> 2565.8 | BN29: =J29+AL29+AZ29 -> 2521.4 | ... BR29: =N29+AP29+BD29 -> 2764.2 | BS29: =SUM(BG29:BR29) -> 30622.5 | BU29: =SUM(BG29:BO29)-SUM(C29:K29) -> 60 | BV29: =SUM(BG29:BO29)-SUM(C52:K52) -> 2370.9 | BW29: =SUM(BG29:BO29)-SUM(C65:K65) -> 3866.8 | BY29: =SUM(BP29:BR29)-SUM(L29:N29) -> 290 | BZ29: =SUM(BP29:BR29)-SUM(L52:N52) -> 1301.7 | CA29: =SUM(BP29:BR29)-SUM(L65:N65) -> 1877.3 | CC29: =BS29-O29 -> 350 | CD29: =BS29-O52 -> 3672.6 | CE29: =BS29-O65 -> 5744.1
B30: Op Costs | C30: -1285.6 | D30: -1251.1 | E30: -1363.6 | F30: -1466.4 | G30: -1337.6 | H30: -1416.6 | I30: -1407.1 | J30: -1384.1 | K30: -1376.3 | L30: -1466.8 | M30: -1323.1 | N30: -1442.4 | O30: =SUM(C30:N30) -> -16520.7 | Q30: -1285.6 | R30: -1251.1 | S30: -1363.6 | T30: -1466.4 | U30: -1337.6 | V30: -1416.6 | W30: -1407.1 | X30: -1384.1 | Y30: -1376.3 | Z30: -1466.8 | AA30: -1323.1 | AB30: -1442.4 | AC30: =SUM(Q30:AB30) -> -16520.7 | AE30: =Q30-C30 -> 0 | AF30: =R30-D30 -> 0 | AG30: =S30-E30 -> 0 | AH30: =T30-F30 -> 0 | AI30: =U30-G30 -> 0 | AJ30: =V30-H30 -> 0 | AK30: =W30-I30 -> 0 | AL30: =X30-J30 -> 0 | ... AP30: =AB30-N30 -> 0 | AQ30: =SUM(AE30:AP30) -> 0 | AS30: =-'Beacon-Adj'!C58-'Beacon-Adj'!C84 -> 0 | AT30: =-'Beacon-Adj'!D58-'Beacon-Adj'!D84 -> 0 | AU30: =-'Beacon-Adj'!E58-'Beacon-Adj'!E84 -> 0 | AV30: =-'Beacon-Adj'!F58-'Beacon-Adj'!F84 -> 0 | AW30: =-'Beacon-Adj'!G58-'Beacon-Adj'!G84 -> 0 | AX30: =-'Beacon-Adj'!H58-'Beacon-Adj'!H84 -> 0 | AY30: =-'Beacon-Adj'!I58-'Beacon-Adj'!I84 -> 0 | AZ30: =-'Beacon-Adj'!J58-'Beacon-Adj'!J84 -> 0 | ... BD30: =-'Beacon-Adj'!N58-'Beacon-Adj'!N84 -> -8 | BE30: =SUM(AS30:BD30) -> -106 | BG30: =C30+AE30+AS30 -> -1285.6 | BH30: =D30+AF30+AT30 -> -1251.1 | BI30: =E30+AG30+AU30 -> -1363.6 | BJ30: =F30+AH30+AV30 -> -1466.4 | BK30: =G30+AI30+AW30 -> -1337.6 | BL30: =H30+AJ30+AX30 -> -1416.6 | BM30: =I30+AK30+AY30 -> -1407.1 | BN30: =J30+AL30+AZ30 -> -1384.1 | ... BR30: =N30+AP30+BD30 -> -1450.4 | BS30: =SUM(BG30:BR30) -> -16626.7 | BU30: =SUM(BG30:BO30)-SUM(C30:K30) -> -76 | BV30: =SUM(BG30:BO30)-SUM(C53:K53) -> -434.8 | BW30: =SUM(BG30:BO30)-SUM(C66:K66) -> -863.9 | BY30: =SUM(BP30:BR30)-SUM(L30:N30) -> -30 | BZ30: =SUM(BP30:BR30)-SUM(L53:N53) -> -233 | CA30: =SUM(BP30:BR30)-SUM(L66:N66) -> -364.9 | CC30: =BS30-O30 -> -106 | CD30: =BS30-O53 -> -667.8 | CE30: =BS30-O66 -> -1228.8
B31: PBITA | C31: =C29+C30 -> 1057.4 | D31: =D29+D30 -> 1025.1 | E31: =E29+E30 -> 1077.6 | F31: =F29+F30 -> 1242.2 | G31: =G29+G30 -> 1126.9 | H31: =H29+H30 -> 1197.3 | I31: =I29+I30 -> 1158.7 | J31: =J29+J30 -> 1137.3 | ... N31: =N29+N30 -> 1241.8 | O31: =SUM(C31:N31) -> 13751.8 | Q31: =Q29+Q30 -> 1057.4 | R31: =R29+R30 -> 1025.1 | S31: =S29+S30 -> 1077.6 | T31: =T29+T30 -> 1242.2 | U31: =U29+U30 -> 1126.9 | V31: =V29+V30 -> 1197.3 | W31: =W29+W30 -> 1158.7 | X31: =X29+X30 -> 1137.3 | ... AB31: =AB29+AB30 -> 1241.8 | AC31: =SUM(Q31:AB31) -> 13751.8 | AE31: =AE29+AE30 -> 0 | AF31: =AF29+AF30 -> 0 | AG31: =AG29+AG30 -> 0 | AH31: =AH29+AH30 -> 0 | AI31: =AI29+AI30 -> 0 | AJ31: =AJ29+AJ30 -> 0 | AK31: =AK29+AK30 -> 0 | AL31: =AL29+AL30 -> 0 | ... AP31: =AP29+AP30 -> 0 | AQ31: =SUM(AE31:AP31) -> 0 | AS31: =AS29+AS30 -> 0 | AT31: =AT29+AT30 -> 0 | AU31: =AU29+AU30 -> 0 | AV31: =AV29+AV30 -> 0 | AW31: =AW29+AW30 -> 0 | AX31: =AX29+AX30 -> 0 | AY31: =AY29+AY30 -> 0 | AZ31: =AZ29+AZ30 -> 0 | ... BD31: =BD29+BD30 -> 72 | BE31: =SUM(AS31:BD31) -> 244 | BG31: =BG29+BG30 -> 1057.4 | BH31: =BH29+BH30 -> 1025.1 | BI31: =BI29+BI30 -> 1077.6 | BJ31: =BJ29+BJ30 -> 1242.2 | BK31: =BK29+BK30 -> 1126.9 | BL31: =BL29+BL30 -> 1197.3 | BM31: =BM29+BM30 -> 1158.7 | BN31: =BN29+BN30 -> 1137.3 | ... BR31: =BR29+BR30 -> 1313.8 | BS31: =SUM(BG31:BR31) -> 13995.8 | BU31: =SUM(BG31:BO31)-SUM(C31:K31) -> -16 | BV31: =SUM(BG31:BO31)-SUM(C54:K54) -> 1936.1 | BW31: =SUM(BG31:BO31)-SUM(C67:K67) -> 3002.9 | BY31: =SUM(BP31:BR31)-SUM(L31:N31) -> 260 | BZ31: =SUM(BP31:BR31)-SUM(L54:N54) -> 1068.7 | CA31: =SUM(BP31:BR31)-SUM(L67:N67) -> 1512.4 | CC31: =BS31-O31 -> 244 | CD31: =BS31-O54 -> 3004.8 | CE31: =BS31-O67 -> 4515.3
